Workbook

Sheet Page de garde
A1: Page de garde
B5: REPUBLIQUE | I5: DU SENEGAL
B7: MINISTERE | I7: DES FINANCES ET DU BUDGET
B9: DIRECTION | I9: DIRECTION GENERALE DES IMPÔTS ET DES DOMAINES
B17: CENTRE DE DEPOT : | V17: xxxx
A23: ETATS FINANCIERS NORMALISES
A24: SYSTÈME COMPTABLE (SYSCOHADA)
B27: EXERCICE CLOS LE :
A30: DESIGNATION DE L'ENTREPRISE
C35: DENOMINATION SOCIALE :
C36: (ou nom et prénoms de l'exploitant)
C41: SIGLE USUEL :
C46: ADRESSE COMPLETE :
C51: N° D'IDENTIFICATION FISCALE :
C55: SYSTEME NORMAL
C59: Documents déposés | V59: Réservé à la Direction Générale des Impôts
C62: Fiche d'identification et renseignements divers | S62: X | V62: Date de dépôt
C64: Bilan | S64: X
C66: Compte de résultat | S66: X | V66: Nom de l'agent de DGI ayant réceptionné le dépôt
C68: Tableau des flux de trésorerie | S68: X
C70: Notes annexes | S70: X | V70: Signature de l'agent et cachet du service
C72: Nombre de pages déposées par exemplaire
C73: Nombre d'exemplaires déposés

Sheet Fiche de renseignement R1
A1: Fiche R1
I4: Dénomination sociale de l’entreprise | J4: =+'Page de garde'!L35 -> 0
I7: Adresse de l'entreprise | J7: ='Page de garde'!J46 -> 0 | AC7: Sigle usuel | AD7: =+'Page de garde'!H41 -> 0
I10: N° d'identification fiscale | J10: ='Page de garde'!N51 -> 0 | U10: Exercice clos le | V10: =+'Page de garde'!M27 -> 0 | AG10: Durée (en mois) | AH10: 12
B13: ZA | E13: EXERCICE COMPTABLE | W13: DU | Y13: 43466 | AF13: AU | AH13: 43830
B16: ZB | E16: DATE D'ARRETE EFFECTIF DES COMPTES | U16: =+V10 -> 0
B20: ZC | E20: EXERCICE PRECEDENT CLOS LE | Q20: 44196 | AK20: DUREE EXERCICE PRECEDENT EN MOIS : | AL20: 12
B24: ZD | F24: SN | I24: SN-DKR-2007-X XXXXX | W24: XX
F25: Greffe | I25: N° registre du Commerce | W25: N° répertoire des entreprises
B28: ZE | G28: XXX
G29: N° de caisse sociale | S29: N° Code importateur | AE29: Code activité principale
B32: ZF | D32: =+J4 -> 0 | AE32: =+AD7 -> 0
D33: Désignation de l'entreprise | AE33: Sigle
B36: ZG | G36: XXXXXXX | Q36: XXX | Y36: 3 | AA36: 4 | AE36: Dakar
G37: N° de téléphone | Q37: email | Y37: Code | AA37: Boîte postale | AE37: Ville
B40: ZH | D40: XXX
D41: Adresse géographique complète (Immeuble, rue, quartier, ville, pays)
B44: ZI | D44: XX
D45: Désignation précise de l'activité principale exercée par l'entreprise
D48: xxxxxx
D49: Nom, adresse et qualité de personne à contacter en cas de demande d'informations complémentaires
D52: XXXXXXXXXXXX
D53: Nom du professionnel salarié de l'entreprise ou Nom, adresse et téléphone du cabinet comptable ou du professionnel INSCRIT A L'ORDRE NATIONAL DES EXPERTS COMPTABLES ET DES COMPTABLES AGREES ayant établi les états financiers.
D56: XXXXXXXXXXX
D57: Noms et adresses du ou des commissaires au comptes
E64: Non assujettie | K64: Non (refus) | O64: Oui avec réserves | S64: X | T64: Oui sans réserves | Z64: Non assujettie | AG64: Non | AK64: X | AL64: Oui
C66: Etats financiers certifiés (cocher la case) | X66: Etats financiers approuvés par l'Assemblée Générale (cocher la case)
T69: Domiciliations bancaires
D70: Nom du signataire des états financiers | T70: Banque | AD70: Numéro de compte
T71: UBA | AD71: 93ODD
D73: Qualité du signataire des états financiers
D76: Date de signature
D83: Signature

Sheet BAL N
A1: N° Comptes | B1: Libellés | C1: S 1 Débit | D1: S 1 Crédit | E1: Mouv Débit | F1: Mouv Crédit | G1: S 2 Débit | H1: S 2 Crédit | I1: Ext 2 | J1: Ext 3 | K1: Ext 4 | L1: Ext 5 | M1: Ext 1
A2: 1013000 | B2: K souscri, appelé versé, non amorti | D2: 500000 | H2: 500000 | I2: =LEFT(A2,2) | J2: =LEFT(A2,3) | K2: =LEFT(A2,4) | L2: =LEFT(A2,5) | M2: =LEFT(A2,1)
A3: 111000 | B3: RESERVE LEGALE | D3: 100000 | H3: 100000 | I3: =LEFT(A3,2) | J3: =LEFT(A3,3) | K3: =LEFT(A3,4) | L3: =LEFT(A3,5) | M3: =LEFT(A3,1)
A4: 118000 | B4: Autres Réserves | D4: 11482807 | F4: 583865 | H4: 12066672 | I4: =LEFT(A4,2) | J4: =LEFT(A4,3) | K4: =LEFT(A4,4) | L4: =LEFT(A4,5) | M4: =LEFT(A4,1)
A5: 131000 | B5: RESULTAT NET : BENEFICE | D5: 583865 | E5: 583865 | I5: =LEFT(A5,2) | J5: =LEFT(A5,3) | K5: =LEFT(A5,4) | L5: =LEFT(A5,5) | M5: =LEFT(A5,1)
A6: 234000 | B6: INSTALLATIONS TECHNIQUES | C6: 160271186 | G6: 160271186 | I6: =LEFT(A6,2) | J6: =LEFT(A6,3) | K6: =LEFT(A6,4) | L6: =LEFT(A6,5) | M6: =LEFT(A6,1)
A7: 244100 | B7: MATERIEL DE BUREAU | C7: 2415000 | G7: 2415000 | I7: =LEFT(A7,2) | J7: =LEFT(A7,3) | K7: =LEFT(A7,4) | L7: =LEFT(A7,5) | M7: =LEFT(A7,1)
A8: 244200 | B8: Matériel et mobilier informatique | C8: 1538547 | G8: 1538547 | I8: =LEFT(A8,2) | J8: =LEFT(A8,3) | K8: =LEFT(A8,4) | L8: =LEFT(A8,5) | M8: =LEFT(A8,1)
A9: 244400 | B9: MOBILIER DE BUREAU | C9: 3601695 | G9: 3601695 | I9: =LEFT(A9,2) | J9: =LEFT(A9,3) | K9: =LEFT(A9,4) | L9: =LEFT(A9,5) | M9: =LEFT(A9,1)
A10: 283410 | B10: AMORT AMENAG & INST TECH SOL PROPRE | D10: 123093728 | F10: 33317458 | H10: 156411186 | I10: =LEFT(A10,2) | J10: =LEFT(A10,3) | K10: =LEFT(A10,4) | L10: =LEFT(A10,5) | M10: =LEFT(A10,1)
A11: 284420 | B11: AMORT MATERIEL INFORMAIQUE | D11: 928070 | F11: 395608 | H11: 1323678 | I11: =LEFT(A11,2) | J11: =LEFT(A11,3) | K11: =LEFT(A11,4) | L11: =LEFT(A11,5) | M11: =LEFT(A11,1)
A12: 284440 | B12: AMORT MOBILIER DE BUREAU | D12: 3054906 | F12: 1320594 | H12: 4375500 | I12: =LEFT(A12,2) | J12: =LEFT(A12,3) | K12: =LEFT(A12,4) | L12: =LEFT(A12,5) | M12: =LEFT(A12,1)
A13: 311100 | B13: MARCHANDISES | C13: 2500000 | E13: 2980700 | F13: 2500000 | G13: 2980700 | I13: =LEFT(A13,2) | J13: =LEFT(A13,3) | K13: =LEFT(A13,4) | L13: =LEFT(A13,5) | M13: =LEFT(A13,1)
A14: 401100 | B14: Fournisseurs | D14: 11377437 | E14: 107400631 | F14: 104261071 | H14: 8237877 | I14: =LEFT(A14,2) | J14: =LEFT(A14,3) | K14: =LEFT(A14,4) | L14: =LEFT(A14,5) | M14: =LEFT(A14,1)
A15: 411100 | B15: Clients | E15: 147229638 | F15: 147229638 | I15: =LEFT(A15,2) | J15: =LEFT(A15,3) | K15: =LEFT(A15,4) | L15: =LEFT(A15,5) | M15: =LEFT(A15,1)
A16: 422000 | B16: PERSONNEL REMUNERATIONS DUE | D16: 980000 | E16: 10160000 | F16: 9960000 | H16: 780000 | I16: =LEFT(A16,2) | J16: =LEFT(A16,3) | K16: =LEFT(A16,4) | L16: =LEFT(A16,5) | M16: =LEFT(A16,1)
A17: 431100 | B17: PRESTATIONS FAMILIALES | D17: 61740 | F17: 224910 | H17: 286650 | I17: =LEFT(A17,2) | J17: =LEFT(A17,3) | K17: =LEFT(A17,4) | L17: =LEFT(A17,5) | M17: =LEFT(A17,1)
A18: 431200 | B18: ACCIDENTS DE TRAVAIL | D18: 27720 | F18: 96390 | H18: 124110 | I18: =LEFT(A18,2) | J18: =LEFT(A18,3) | K18: =LEFT(A18,4) | L18: =LEFT(A18,5) | M18: =LEFT(A18,1)
A19: 431300 | B19: CAISSE DE RETRAITE OBLIGATOIRE | D19: 419953 | F19: 1493616 | H19: 1913569 | I19: =LEFT(A19,2) | J19: =LEFT(A19,3) | K19: =LEFT(A19,4) | L19: =LEFT(A19,5) | M19: =LEFT(A19,1)
A20: 441000 | B20: ETAT IMPOT SUR LES BENEFICES | D20: 5463975 | F20: 623854 | H20: 6087829 | I20: =LEFT(A20,2) | J20: =LEFT(A20,3) | K20: =LEFT(A20,4) | L20: =LEFT(A20,5) | M20: =LEFT(A20,1)
A21: 442200 | B21: IMPOTS ET TAXES SUR LES COLLECT PUB | D21: 3713622 | F21: 1575000 | H21: 5288622 | I21: =LEFT(A21,2) | J21: =LEFT(A21,3) | K21: =LEFT(A21,4) | L21: =LEFT(A21,5) | M21: =LEFT(A21,1)
A22: 443100 | B22: T.V.A. facturée sur ventes | E22: 22458759 | F22: 22458759 | I22: =LEFT(A22,2) | J22: =LEFT(A22,3) | K22: =LEFT(A22,4) | L22: =LEFT(A22,5) | M22: =LEFT(A22,1)
A23: 444100 | B23: État, T.V.A. due | D23: 3083795 | E23: 10754807 | F23: 8964438 | H23: 1293426 | I23: =LEFT(A23,2) | J23: =LEFT(A23,3) | K23: =LEFT(A23,4) | L23: =LEFT(A23,5) | M23: =LEFT(A23,1)
A24: 445200 | B24: T.V.A. récupérable sur achats | E24: 13522401 | F24: 13522401 | I24: =LEFT(A24,2) | J24: =LEFT(A24,3) | K24: =LEFT(A24,4) | L24: =LEFT(A24,5) | M24: =LEFT(A24,1)
A25: 447100 | B25: Impôt Général sur le revenu | D25: 20150 | E25: 449500 | F25: 500500 | H25: 71150 | I25: =LEFT(A25,2) | J25: =LEFT(A25,3) | K25: =LEFT(A25,4) | L25: =LEFT(A25,5) | M25: =LEFT(A25,1)
A26: 447200 | B26: IMPOT SUR SALAIRES | C26: 4498 | E26: 1605500 | F26: 1125900 | G26: 484098 | I26: =LEFT(A26,2) | J26: =LEFT(A26,3) | K26: =LEFT(A26,4) | L26: =LEFT(A26,5) | M26: =LEFT(A26,1)
A27: 447300 | B27: Contribution nationale | D27: 4000 | E27: 32500 | F27: 24300 | G27: 4200 | I27: =LEFT(A27,2) | J27: =LEFT(A27,3) | K27: =LEFT(A27,4) | L27: =LEFT(A27,5) | M27: =LEFT(A27,1)
A28: 447400 | B28: Contribution nationale de solidari | D28: 52807 | E28: 411112 | F28: 320073 | G28: 38232 | I28: =LEFT(A28,2) | J28: =LEFT(A28,3) | K28: =LEFT(A28,4) | L28: =LEFT(A28,5) | M28: =LEFT(A28,1)
A29: 447800 | B29: ETAT BRS | E29: 1575000 | F29: 1575000 | I29: =LEFT(A29,2) | J29: =LEFT(A29,3) | K29: =LEFT(A29,4) | L29: =LEFT(A29,5) | M29: =LEFT(A29,1)
A30: 462001 | B30: MATHAR MBOUP | D30: 4500000 | E30: 2500000 | H30: 2000000 | I30: =LEFT(A30,2) | J30: =LEFT(A30,3) | K30: =LEFT(A30,4) | L30: =LEFT(A30,5) | M30: =LEFT(A30,1)
A31: 462002 | B31: OTTAVI CARLO | D31: 10624330 | E31: 5000000 | H31: 5624330 | I31: =LEFT(A31,2) | J31: =LEFT(A31,3) | K31: =LEFT(A31,4) | L31: =LEFT(A31,5) | M31: =LEFT(A31,1)
A32: 521001 | B32: UBA | C32: 255614 | E32: 73657643 | F32: 69967213 | G32: 3946044 | I32: =LEFT(A32,2) | J32: =LEFT(A32,3) | K32: =LEFT(A32,4) | L32: =LEFT(A32,5) | M32: =LEFT(A32,1)
A33: 521002 | B33: BOA | C33: 4455707 | E33: 26035783 | F33: 28421751 | G33: 2069739 | I33: =LEFT(A33,2) | J33: =LEFT(A33,3) | K33: =LEFT(A33,4) | L33: =LEFT(A33,5) | M33: =LEFT(A33,1)
A34: 571000 | B34: CAISSE | C34: 5030658 | E34: 52397912 | F34: 49362829 | G34: 8065741 | I34: =LEFT(A34,2) | J34: =LEFT(A34,3) | K34: =LEFT(A34,4) | L34: =LEFT(A34,5) | M34: =LEFT(A34,1)
A35: 585000 | B35: VIREMENTS DE FONDS | E35: 4850000 | F35: 4850000 | I35: =LEFT(A35,2) | J35: =LEFT(A35,3) | K35: =LEFT(A35,4) | L35: =LEFT(A35,5) | M35: =LEFT(A35,1)
A36: 601100 | B36: ACHAT DE MARCHANDISES | E36: 54529241 | F36: 155999 | G36: 54373242 | I36: =LEFT(A36,2) | J36: =LEFT(A36,3) | K36: =LEFT(A36,4) | L36: =LEFT(A36,5) | M36: =LEFT(A36,1)
A37: 603100 | B37: VARIATION DES STOCKS DE MARCHANDISE | E37: 2500000 | F37: 2980700 | H37: 480700 | I37: =LEFT(A37,2) | J37: =LEFT(A37,3) | K37: =LEFT(A37,4) | L37: =LEFT(A37,5) | M37: =LEFT(A37,1)
A38: 605200 | B38: Fournitures non stockab - Electrici | E38: 5157737 | G38: 5157737 | I38: =LEFT(A38,2) | J38: =LEFT(A38,3) | K38: =LEFT(A38,4) | L38: =LEFT(A38,5) | M38: =LEFT(A38,1)
A39: 605300 | B39: Fourn non soctk. Autre énergies | E39: 574500 | G39: 574500 | I39: =LEFT(A39,2) | J39: =LEFT(A39,3) | K39: =LEFT(A39,4) | L39: =LEFT(A39,5) | M39: =LEFT(A39,1)
A40: 605700 | B40: Achats d'études et presta de servic | E40: 4900000 | G40: 4900000 | I40: =LEFT(A40,2) | J40: =LEFT(A40,3) | K40: =LEFT(A40,4) | L40: =LEFT(A40,5) | M40: =LEFT(A40,1)
A41: 622000 | B41: LOCATION ET CHARGES LOCATIVES | E41: 8750000 | G41: 8750000 | I41: =LEFT(A41,2) | J41: =LEFT(A41,3) | K41: =LEFT(A41,4) | L41: =LEFT(A41,5) | M41: =LEFT(A41,1)
A42: 622200 | B42: Location de bâtiments | E42: 1750000 | G42: 1750000 | I42: =LEFT(A42,2) | J42: =LEFT(A42,3) | K42: =LEFT(A42,4) | L42: =LEFT(A42,5) | M42: =LEFT(A42,1)
A43: 622800 | B43: Locations et chargs locativ diverse | E43: 222000 | G43: 222000 | I43: =LEFT(A43,2) | J43: =LEFT(A43,3) | K43: =LEFT(A43,4) | L43: =LEFT(A43,5) | M43: =LEFT(A43,1)
A44: 624100 | B44: Entretien & Réparation biens Immobi | E44: 1893330 | G44: 1893330 | I44: =LEFT(A44,2) | J44: =LEFT(A44,3) | K44: =LEFT(A44,4) | L44: =LEFT(A44,5) | M44: =LEFT(A44,1)
A45: 624200 | B45: Entretien et réparat biens mobilier | E45: 2640000 | G45: 2640000 | I45: =LEFT(A45,2) | J45: =LEFT(A45,3) | K45: =LEFT(A45,4) | L45: =LEFT(A45,5) | M45: =LEFT(A45,1)
A46: 631800 | B46: Autres frais bancaires | E46: 3003414 | F46: 11700 | G46: 2991714 | I46: =LEFT(A46,2) | J46: =LEFT(A46,3) | K46: =LEFT(A46,4) | L46: =LEFT(A46,5) | M46: =LEFT(A46,1)
A47: 637000 | B47: RENUMERATION PERSONNEL EXTERIEUR | E47: 10510500 | G47: 10510500 | I47: =LEFT(A47,2) | J47: =LEFT(A47,3) | K47: =LEFT(A47,4) | L47: =LEFT(A47,5) | M47: =LEFT(A47,1)
A48: 641100 | B48: IMPOT FONCIERS ET TAXES ANNEXES | E48: 1575000 | G48: 1575000 | I48: =LEFT(A48,2) | J48: =LEFT(A48,3) | K48: =LEFT(A48,4) | L48: =LEFT(A48,5) | M48: =LEFT(A48,1)
A49: 641200 | B49: Patentes, licences et taxes annexes | E49: 1575000 | G49: 1575000 | I49: =LEFT(A49,2) | J49: =LEFT(A49,3) | K49: =LEFT(A49,4) | L49: =LEFT(A49,5) | M49: =LEFT(A49,1)
A50: 641300 | B50: Taxes sur appointements et salaires | E50: 320073 | G50: 320073 | I50: =LEFT(A50,2) | J50: =LEFT(A50,3) | K50: =LEFT(A50,4) | L50: =LEFT(A50,5) | M50: =LEFT(A50,1)
A51: 6418100 | B51: TOM 3.8% | E51: 378000 | G51: 378000 | I51: =LEFT(A51,2) | J51: =LEFT(A51,3) | K51: =LEFT(A51,4) | L51: =LEFT(A51,5) | M51: =LEFT(A51,1)
A52: 646000 | B52: DROITS D'ENREGISTREMENT | E52: 155862 | G52: 155862 | I52: =LEFT(A52,2) | J52: =LEFT(A52,3) | K52: =LEFT(A52,4) | L52: =LEFT(A52,5) | M52: =LEFT(A52,1)
A53: 647100 | B53: Pénaltés d'assiettes, impôt | E53: 217016 | G53: 217016 | I53: =LEFT(A53,2) | J53: =LEFT(A53,3) | K53: =LEFT(A53,4) | L53: =LEFT(A53,5) | M53: =LEFT(A53,1)
A54: 658800 | B54: AUTRES CHARGES DIVERSES | E54: 150000 | G54: 150000 | I54: =LEFT(A54,2) | J54: =LEFT(A54,3) | K54: =LEFT(A54,4) | L54: =LEFT(A54,5) | M54: =LEFT(A54,1)
A55: 661100 | B55: APPOINTEMENTS SALAIRES ET COMMISSIO | E55: 8413083 | G55: 8413083 | I55: =LEFT(A55,2) | J55: =LEFT(A55,3) | K55: =LEFT(A55,4) | L55: =LEFT(A55,5) | M55: =LEFT(A55,1)
A56: 662100 | B56: Salaires personnes non national | E56: 2233692 | G56: 2233692 | I56: =LEFT(A56,2) | J56: =LEFT(A56,3) | K56: =LEFT(A56,4) | L56: =LEFT(A56,5) | M56: =LEFT(A56,1)
A57: 663800 | B57: AUTRES IMDEMNITES ET AVANTAGES DIVE | E57: 1060800 | G57: 1060800 | I57: =LEFT(A57,2) | J57: =LEFT(A57,3) | K57: =LEFT(A57,4) | L57: =LEFT(A57,5) | M57: =LEFT(A57,1)
A58: 664100 | B58: CHARGES SOCIALES SUR REMUNERATION D | E58: 954021 | G58: 954021 | I58: =LEFT(A58,2) | J58: =LEFT(A58,3) | K58: =LEFT(A58,4) | L58: =LEFT(A58,5) | M58: =LEFT(A58,1)
... A60: 681300 | B60: DOTATION AMORTISSEMENT IMMOB CORPOR | E60: 34638052 | G60: 34638052 | I60: =LEFT(A60,2) | J60: =LEFT(A60,3) | K60: =LEFT(A60,4) | L60: =LEFT(A60,5) | M60: =LEFT(A60,1)
A61: 701100 | B61: VENTES DE MARCHANDISES | F61: 124770879 | H61: 124770879 | I61: =LEFT(A61,2) | J61: =LEFT(A61,3) | K61: =LEFT(A61,4) | L61: =LEFT(A61,5) | M61: =LEFT(A61,1)
A62: 895000 | B62: IMPOT MINIMUM FORFAITAIRE IMF | E62: 623854 | G62: 623854 | I62: =LEFT(A62,2) | J62: =LEFT(A62,3) | K62: =LEFT(A62,4) | L62: =LEFT(A62,5) | M62: =LEFT(A62,1)
I63: =LEFT(A63,2) | J63: =LEFT(A63,3) | K63: =LEFT(A63,4) | L63: =LEFT(A63,5) | M63: =LEFT(A63,1)
I64: =LEFT(A64,2) | J64: =LEFT(A64,3) | K64: =LEFT(A64,4) | L64: =LEFT(A64,5) | M64: =LEFT(A64,1)
I65: =LEFT(A65,2) | J65: =LEFT(A65,3) | K65: =LEFT(A65,4) | L65: =LEFT(A65,5) | M65: =LEFT(A65,1)
I66: =LEFT(A66,2) | J66: =LEFT(A66,3) | K66: =LEFT(A66,4) | L66: =LEFT(A66,5) | M66: =LEFT(A66,1)
I67: =LEFT(A67,2) | J67: =LEFT(A67,3) | K67: =LEFT(A67,4) | L67: =LEFT(A67,5) | M67: =LEFT(A67,1)
I68: =LEFT(A68,2) | J68: =LEFT(A68,3) | K68: =LEFT(A68,4) | L68: =LEFT(A68,5) | M68: =LEFT(A68,1)
I69: =LEFT(A69,2) | J69: =LEFT(A69,3) | K69: =LEFT(A69,4) | L69: =LEFT(A69,5) | M69: =LEFT(A69,1)
I70: =LEFT(A70,2) | J70: =LEFT(A70,3) | K70: =LEFT(A70,4) | L70: =LEFT(A70,5) | M70: =LEFT(A70,1)
I71: =LEFT(A71,2) | J71: =LEFT(A71,3) | K71: =LEFT(A71,4) | L71: =LEFT(A71,5) | M71: =LEFT(A71,1)
I72: =LEFT(A72,2) | J72: =LEFT(A72,3) | K72: =LEFT(A72,4) | L72: =LEFT(A72,5) | M72: =LEFT(A72,1)
I73: =LEFT(A73,2) | J73: =LEFT(A73,3) | K73: =LEFT(A73,4) | L73: =LEFT(A73,5) | M73: =LEFT(A73,1)
I74: =LEFT(A74,2) | J74: =LEFT(A74,3) | K74: =LEFT(A74,4) | L74: =LEFT(A74,5) | M74: =LEFT(A74,1)
... I300: =LEFT(A300,2) | J300: =LEFT(A300,3) | K300: =LEFT(A300,4) | L300: =LEFT(A300,5) | M300: =LEFT(A300,1)
J301: =LEFT(A301,3) | K301: =LEFT(A301,4) | L301: =LEFT(A301,5) | M301: =LEFT(A301,1)
J302: =LEFT(A302,3) | K302: =LEFT(A302,4) | L302: =LEFT(A302,5) | M302: =LEFT(A302,1)
J303: =LEFT(A303,3) | K303: =LEFT(A303,4) | L303: =LEFT(A303,5) | M303: =LEFT(A303,1)
J304: =LEFT(A304,3) | K304: =LEFT(A304,4) | L304: =LEFT(A304,5) | M304: =LEFT(A304,1)
J305: =LEFT(A305,3) | K305: =LEFT(A305,4) | L305: =LEFT(A305,5) | M305: =LEFT(A305,1)
J306: =LEFT(A306,3) | K306: =LEFT(A306,4) | L306: =LEFT(A306,5) | M306: =LEFT(A306,1)
J307: =LEFT(A307,3) | K307: =LEFT(A307,4) | L307: =LEFT(A307,5) | M307: =LEFT(A307,1)
J308: =LEFT(A308,3) | K308: =LEFT(A308,4) | L308: =LEFT(A308,5) | M308: =LEFT(A308,1)
J309: =LEFT(A309,3) | K309: =LEFT(A309,4) | L309: =LEFT(A309,5) | M309: =LEFT(A309,1)
J310: =LEFT(A310,3) | K310: =LEFT(A310,4) | L310: =LEFT(A310,5) | M310: =LEFT(A310,1)
J311: =LEFT(A311,3) | K311: =LEFT(A311,4) | L311: =LEFT(A311,5) | M311: =LEFT(A311,1)
J312: =LEFT(A312,3) | K312: =LEFT(A312,4) | L312: =LEFT(A312,5) | M312: =LEFT(A312,1)
... J325: =LEFT(A325,3) | K325: =LEFT(A325,4) | L325: =LEFT(A325,5) | M325: =LEFT(A325,1)

Sheet BAL N-1
A1: N° Comptes | B1: Libellés | C1: S 1 Débit | D1: S 1 Crédit | E1: Mouv Débit | F1: Mouv Crédit | G1: S 2 Débit | H1: S 2 Crédit | I1: Ext 2 | J1: Ext 3 | K1: Ext 4 | L1: Ext 5 | M1: Ext 1
A2: 1013000 | B2: K souscri, appelé versé, non amorti | D2: 500000 | H2: 500000 | I2: =LEFT(A2,2) | J2: =LEFT(A2,3) | K2: =LEFT(A2,4) | L2: =LEFT(A2,5) | M2: =LEFT(A2,1)
A3: 111000 | B3: RESERVE LEGALE | D3: 100000 | H3: 100000 | I3: =LEFT(A3,2) | J3: =LEFT(A3,3) | K3: =LEFT(A3,4) | L3: =LEFT(A3,5) | M3: =LEFT(A3,1)
A4: 118000 | B4: Autres Réserves | D4: 4604302 | F4: 6878505 | H4: 11482807 | I4: =LEFT(A4,2) | J4: =LEFT(A4,3) | K4: =LEFT(A4,4) | L4: =LEFT(A4,5) | M4: =LEFT(A4,1)
A5: 131000 | B5: RESULTAT NET : BENEFICE | D5: 6878505 | E5: 6878505 | I5: =LEFT(A5,2) | J5: =LEFT(A5,3) | K5: =LEFT(A5,4) | L5: =LEFT(A5,5) | M5: =LEFT(A5,1)
A6: 234000 | B6: INSTALLATIONS TECHNIQUES | C6: 160271186 | G6: 160271186 | I6: =LEFT(A6,2) | J6: =LEFT(A6,3) | K6: =LEFT(A6,4) | L6: =LEFT(A6,5) | M6: =LEFT(A6,1)
A7: 244100 | B7: MATERIEL DE BUREAU | C7: 2415000 | G7: 2415000 | I7: =LEFT(A7,2) | J7: =LEFT(A7,3) | K7: =LEFT(A7,4) | L7: =LEFT(A7,5) | M7: =LEFT(A7,1)
A8: 244200 | B8: Matériel et mobilier informatique | C8: 1538547 | G8: 1538547 | I8: =LEFT(A8,2) | J8: =LEFT(A8,3) | K8: =LEFT(A8,4) | L8: =LEFT(A8,5) | M8: =LEFT(A8,1)
A9: 244400 | B9: MOBILIER DE BUREAU | C9: 3601695 | G9: 3601695 | I9: =LEFT(A9,2) | J9: =LEFT(A9,3) | K9: =LEFT(A9,4) | L9: =LEFT(A9,5) | M9: =LEFT(A9,1)
A10: 283410 | B10: AMORT AMENAG & INST TECH SOL PROPRE | D10: 70204237 | F10: 52889491 | H10: 123093728 | I10: =LEFT(A10,2) | J10: =LEFT(A10,3) | K10: =LEFT(A10,4) | L10: =LEFT(A10,5) | M10: =LEFT(A10,1)
A11: 284420 | B11: AMORT MATERIEL INFORMAIQUE | D11: 491256 | F11: 436814 | H11: 928070 | I11: =LEFT(A11,2) | J11: =LEFT(A11,3) | K11: =LEFT(A11,4) | L11: =LEFT(A11,5) | M11: =LEFT(A11,1)
A12: 284440 | B12: AMORT MOBILIER DE BUREAU | D12: 1610991 | F12: 1443915 | H12: 3054906 | I12: =LEFT(A12,2) | J12: =LEFT(A12,3) | K12: =LEFT(A12,4) | L12: =LEFT(A12,5) | M12: =LEFT(A12,1)
A13: 311100 | B13: MARCHANDISES | C13: 1800000 | E13: 2500000 | F13: 1800000 | G13: 2500000 | I13: =LEFT(A13,2) | J13: =LEFT(A13,3) | K13: =LEFT(A13,4) | L13: =LEFT(A13,5) | M13: =LEFT(A13,1)
A14: 401100 | B14: Fournisseurs | C14: 112000 | D14: 3101723 | E14: 216195687 | F14: 224583401 | H14: 11377437 | I14: =LEFT(A14,2) | J14: =LEFT(A14,3) | K14: =LEFT(A14,4) | L14: =LEFT(A14,5) | M14: =LEFT(A14,1)
A15: 411100 | B15: Clients | E15: 307818915 | F15: 307818915 | I15: =LEFT(A15,2) | J15: =LEFT(A15,3) | K15: =LEFT(A15,4) | L15: =LEFT(A15,5) | M15: =LEFT(A15,1)
A16: 422000 | B16: PERSONNEL REMUNERATIONS DUE | D16: 1110000 | E16: 13210000 | F16: 13080000 | H16: 980000 | I16: =LEFT(A16,2) | J16: =LEFT(A16,3) | K16: =LEFT(A16,4) | L16: =LEFT(A16,5) | M16: =LEFT(A16,1)
A17: 431100 | B17: PRESTATIONS FAMILIALES | D17: 88200 | E17: 317520 | F17: 291060 | H17: 61740 | I17: =LEFT(A17,2) | J17: =LEFT(A17,3) | K17: =LEFT(A17,4) | L17: =LEFT(A17,5) | M17: =LEFT(A17,1)
A18: 431200 | B18: ACCIDENTS DE TRAVAIL | D18: 12600 | E18: 109620 | F18: 124740 | H18: 27720 | I18: =LEFT(A18,2) | J18: =LEFT(A18,3) | K18: =LEFT(A18,4) | L18: =LEFT(A18,5) | M18: =LEFT(A18,1)
A19: 431300 | B19: CAISSE DE RETRAITE OBLIGATOIRE | D19: 527791 | E19: 2073396 | F19: 1965558 | H19: 419953 | I19: =LEFT(A19,2) | J19: =LEFT(A19,3) | K19: =LEFT(A19,4) | L19: =LEFT(A19,5) | M19: =LEFT(A19,1)
A20: 441000 | B20: ETAT IMPOT SUR LES BENEFICES | D20: 4963975 | F20: 500000 | H20: 5463975 | I20: =LEFT(A20,2) | J20: =LEFT(A20,3) | K20: =LEFT(A20,4) | L20: =LEFT(A20,5) | M20: =LEFT(A20,1)
A21: 442200 | B21: IMPOTS ET TAXES SUR LES COLLECT PUB | D21: 2081922 | F21: 1631700 | H21: 3713622 | I21: =LEFT(A21,2) | J21: =LEFT(A21,3) | K21: =LEFT(A21,4) | L21: =LEFT(A21,5) | M21: =LEFT(A21,1)
A22: 443100 | B22: T.V.A. facturée sur ventes | E22: 46955429 | F22: 46955429 | I22: =LEFT(A22,2) | J22: =LEFT(A22,3) | K22: =LEFT(A22,4) | L22: =LEFT(A22,5) | M22: =LEFT(A22,1)
A23: 444100 | B23: État, T.V.A. due | E23: 15872155 | F23: 18955950 | H23: 3083795 | I23: =LEFT(A23,2) | J23: =LEFT(A23,3) | K23: =LEFT(A23,4) | L23: =LEFT(A23,5) | M23: =LEFT(A23,1)
A24: 444900 | B24: État, crédit de T.V.A. à reporter | C24: 150242 | E24: 1327632 | F24: 1477874 | I24: =LEFT(A24,2) | J24: =LEFT(A24,3) | K24: =LEFT(A24,4) | L24: =LEFT(A24,5) | M24: =LEFT(A24,1)
A25: 445200 | B25: T.V.A. récupérable sur achats | E25: 28484122 | F25: 28484122 | I25: =LEFT(A25,2) | J25: =LEFT(A25,3) | K25: =LEFT(A25,4) | L25: =LEFT(A25,5) | M25: =LEFT(A25,1)
A26: 447100 | B26: Impôt Général sur le revenu | D26: 47710 | E26: 226960 | F26: 199400 | H26: 20150 | I26: =LEFT(A26,2) | J26: =LEFT(A26,3) | K26: =LEFT(A26,4) | L26: =LEFT(A26,5) | M26: =LEFT(A26,1)
A27: 447200 | B27: IMPOT SUR SALAIRES | C27: 26120 | E27: 1463978 | F27: 1485600 | G27: 4498 | I27: =LEFT(A27,2) | J27: =LEFT(A27,3) | K27: =LEFT(A27,4) | L27: =LEFT(A27,5) | M27: =LEFT(A27,1)
A28: 447300 | B28: Contribution nationale | C28: 400 | E28: 27400 | F28: 31800 | H28: 4000 | I28: =LEFT(A28,2) | J28: =LEFT(A28,3) | K28: =LEFT(A28,4) | L28: =LEFT(A28,5) | M28: =LEFT(A28,1)
A29: 447400 | B29: Contribution nationale de solidari | C29: 18065 | E29: 350328 | F29: 421200 | H29: 52807 | I29: =LEFT(A29,2) | J29: =LEFT(A29,3) | K29: =LEFT(A29,4) | L29: =LEFT(A29,5) | M29: =LEFT(A29,1)
A30: 462001 | B30: MATHAR MBOUP | D30: 35500000 | E30: 31000000 | H30: 4500000 | I30: =LEFT(A30,2) | J30: =LEFT(A30,3) | K30: =LEFT(A30,4) | L30: =LEFT(A30,5) | M30: =LEFT(A30,1)
A31: 462002 | B31: OTTAVI CARLO | D31: 41824330 | E31: 31200000 | H31: 10624330 | I31: =LEFT(A31,2) | J31: =LEFT(A31,3) | K31: =LEFT(A31,4) | L31: =LEFT(A31,5) | M31: =LEFT(A31,1)
A32: 521001 | B32: UBA | C32: 435541 | E32: 95618375 | F32: 95798302 | G32: 255614 | I32: =LEFT(A32,2) | J32: =LEFT(A32,3) | K32: =LEFT(A32,4) | L32: =LEFT(A32,5) | M32: =LEFT(A32,1)
A33: 521002 | B33: BOA | C33: 2764611 | E33: 81638267 | F33: 79947171 | G33: 4455707 | I33: =LEFT(A33,2) | J33: =LEFT(A33,3) | K33: =LEFT(A33,4) | L33: =LEFT(A33,5) | M33: =LEFT(A33,1)
A34: 571000 | B34: CAISSE | C34: 514135 | E34: 136741708 | F34: 132225185 | G34: 5030658 | I34: =LEFT(A34,2) | J34: =LEFT(A34,3) | K34: =LEFT(A34,4) | L34: =LEFT(A34,5) | M34: =LEFT(A34,1)
A35: 601100 | B35: ACHAT DE MARCHANDISES | E35: 130065506 | F35: 3527137 | G35: 126538369 | I35: =LEFT(A35,2) | J35: =LEFT(A35,3) | K35: =LEFT(A35,4) | L35: =LEFT(A35,5) | M35: =LEFT(A35,1)
A36: 603100 | B36: VARIATION DES STOCKS DE MARCHANDISE | E36: 1800000 | F36: 2500000 | H36: 700000 | I36: =LEFT(A36,2) | J36: =LEFT(A36,3) | K36: =LEFT(A36,4) | L36: =LEFT(A36,5) | M36: =LEFT(A36,1)
A37: 605000 | B37: AUTRES ACHATS | E37: 5674578 | G37: 5674578 | I37: =LEFT(A37,2) | J37: =LEFT(A37,3) | K37: =LEFT(A37,4) | L37: =LEFT(A37,5) | M37: =LEFT(A37,1)
A38: 605200 | B38: Fournitures non stockab - Electrici | E38: 1241709 | G38: 1241709 | I38: =LEFT(A38,2) | J38: =LEFT(A38,3) | K38: =LEFT(A38,4) | L38: =LEFT(A38,5) | M38: =LEFT(A38,1)
A39: 605300 | B39: Fourn non soctk. Autre énergies | E39: 6409141 | G39: 6409141 | I39: =LEFT(A39,2) | J39: =LEFT(A39,3) | K39: =LEFT(A39,4) | L39: =LEFT(A39,5) | M39: =LEFT(A39,1)
A40: 605700 | B40: Achats d'études et presta de servic | E40: 7290000 | G40: 7290000 | I40: =LEFT(A40,2) | J40: =LEFT(A40,3) | K40: =LEFT(A40,4) | L40: =LEFT(A40,5) | M40: =LEFT(A40,1)
A41: 605800 | B41: Achats de travaux, matériels et équ | E41: 2500000 | G41: 2500000 | I41: =LEFT(A41,2) | J41: =LEFT(A41,3) | K41: =LEFT(A41,4) | L41: =LEFT(A41,5) | M41: =LEFT(A41,1)
A42: 613000 | B42: TRANSPORT POUR LE COMPTE DE TIERS | E42: 1260000 | G42: 1260000 | I42: =LEFT(A42,2) | J42: =LEFT(A42,3) | K42: =LEFT(A42,4) | L42: =LEFT(A42,5) | M42: =LEFT(A42,1)
A43: 622200 | B43: Location de bâtiments | E43: 10500000 | G43: 10500000 | I43: =LEFT(A43,2) | J43: =LEFT(A43,3) | K43: =LEFT(A43,4) | L43: =LEFT(A43,5) | M43: =LEFT(A43,1)
A44: 624200 | B44: Entretien et réparat biens mobilier | E44: 4683870 | G44: 4683870 | I44: =LEFT(A44,2) | J44: =LEFT(A44,3) | K44: =LEFT(A44,4) | L44: =LEFT(A44,5) | M44: =LEFT(A44,1)
A45: 627000 | B45: PUBLICITE, PUBLICATION, RELATION PU | E45: 10500000 | F45: 330792 | G45: 10169208 | I45: =LEFT(A45,2) | J45: =LEFT(A45,3) | K45: =LEFT(A45,4) | L45: =LEFT(A45,5) | M45: =LEFT(A45,1)
A46: 631800 | B46: Autres frais bancaires | E46: 3772008 | F46: 41553 | G46: 3730455 | I46: =LEFT(A46,2) | J46: =LEFT(A46,3) | K46: =LEFT(A46,4) | L46: =LEFT(A46,5) | M46: =LEFT(A46,1)
A47: 637000 | B47: RENUMERATION PERSONNEL EXTERIEUR | E47: 3988000 | G47: 3988000 | I47: =LEFT(A47,2) | J47: =LEFT(A47,3) | K47: =LEFT(A47,4) | L47: =LEFT(A47,5) | M47: =LEFT(A47,1)
A48: 641200 | B48: Patentes, licences et taxes annexes | E48: 1731700 | G48: 1731700 | I48: =LEFT(A48,2) | J48: =LEFT(A48,3) | K48: =LEFT(A48,4) | L48: =LEFT(A48,5) | M48: =LEFT(A48,1)
A49: 641300 | B49: Taxes sur appointements et salaires | E49: 33564 | G49: 33564 | I49: =LEFT(A49,2) | J49: =LEFT(A49,3) | K49: =LEFT(A49,4) | L49: =LEFT(A49,5) | M49: =LEFT(A49,1)
A50: 6418100 | B50: TOM 3.8% | E50: 378000 | G50: 378000 | I50: =LEFT(A50,2) | J50: =LEFT(A50,3) | K50: =LEFT(A50,4) | L50: =LEFT(A50,5) | M50: =LEFT(A50,1)
A51: 646000 | B51: DROITS D'ENREGISTREMENT | E51: 210000 | G51: 210000 | I51: =LEFT(A51,2) | J51: =LEFT(A51,3) | K51: =LEFT(A51,4) | L51: =LEFT(A51,5) | M51: =LEFT(A51,1)
A52: 646200 | B52: Droits de timbre | E52: 12000 | G52: 12000 | I52: =LEFT(A52,2) | J52: =LEFT(A52,3) | K52: =LEFT(A52,4) | L52: =LEFT(A52,5) | M52: =LEFT(A52,1)
A53: 647100 | B53: Pénaltés d'assiettes, impôt | E53: 52000 | G53: 52000 | I53: =LEFT(A53,2) | J53: =LEFT(A53,3) | K53: =LEFT(A53,4) | L53: =LEFT(A53,5) | M53: =LEFT(A53,1)
A54: 658200 | B54: DONS | E54: 500000 | G54: 500000 | I54: =LEFT(A54,2) | J54: =LEFT(A54,3) | K54: =LEFT(A54,4) | L54: =LEFT(A54,5) | M54: =LEFT(A54,1)
A55: 658800 | B55: AUTRES CHARGES DIVERSES | E55: 1440413 | G55: 1440413 | I55: =LEFT(A55,2) | J55: =LEFT(A55,3) | K55: =LEFT(A55,4) | L55: =LEFT(A55,5) | M55: =LEFT(A55,1)
A56: 661100 | B56: APPOINTEMENTS SALAIRES ET COMMISSIO | E56: 11777130 | G56: 11777130 | I56: =LEFT(A56,2) | J56: =LEFT(A56,3) | K56: =LEFT(A56,4) | L56: =LEFT(A56,5) | M56: =LEFT(A56,1)
A57: 662100 | B57: Salaires personnes non national | E57: 2233692 | G57: 2233692 | I57: =LEFT(A57,2) | J57: =LEFT(A57,3) | K57: =LEFT(A57,4) | L57: =LEFT(A57,5) | M57: =LEFT(A57,1)
A58: 663800 | B58: AUTRES IMDEMNITES ET AVANTAGES DIVE | E58: 1372800 | G58: 1372800 | I58: =LEFT(A58,2) | J58: =LEFT(A58,3) | K58: =LEFT(A58,4) | L58: =LEFT(A58,5) | M58: =LEFT(A58,1)
... A61: 681300 | B61: DOTATION AMORTISSEMENT IMMOB CORPOR | E61: 54770220 | G61: 54770220 | I61: =LEFT(A61,2) | J61: =LEFT(A61,3) | K61: =LEFT(A61,4) | L61: =LEFT(A61,5) | M61: =LEFT(A61,1)
A62: 701100 | B62: VENTES DE MARCHANDISES | F62: 260863486 | H62: 260863486 | I62: =LEFT(A62,2) | J62: =LEFT(A62,3) | K62: =LEFT(A62,4) | L62: =LEFT(A62,5) | M62: =LEFT(A62,1)
A63: 891000 | B63: IMPÖT SUR LES SOCIETES | E63: 500000 | G63: 500000 | I63: =LEFT(A63,2) | J63: =LEFT(A63,3) | K63: =LEFT(A63,4) | L63: =LEFT(A63,5) | M63: =LEFT(A63,1)
I64: =LEFT(A64,2) | J64: =LEFT(A64,3) | K64: =LEFT(A64,4) | L64: =LEFT(A64,5) | M64: =LEFT(A64,1)
I65: =LEFT(A65,2) | J65: =LEFT(A65,3) | K65: =LEFT(A65,4) | L65: =LEFT(A65,5) | M65: =LEFT(A65,1)
I66: =LEFT(A66,2) | J66: =LEFT(A66,3) | K66: =LEFT(A66,4) | L66: =LEFT(A66,5) | M66: =LEFT(A66,1)
I67: =LEFT(A67,2) | J67: =LEFT(A67,3) | K67: =LEFT(A67,4) | L67: =LEFT(A67,5) | M67: =LEFT(A67,1)
I68: =LEFT(A68,2) | J68: =LEFT(A68,3) | K68: =LEFT(A68,4) | L68: =LEFT(A68,5) | M68: =LEFT(A68,1)
I69: =LEFT(A69,2) | J69: =LEFT(A69,3) | K69: =LEFT(A69,4) | L69: =LEFT(A69,5) | M69: =LEFT(A69,1)
I70: =LEFT(A70,2) | J70: =LEFT(A70,3) | K70: =LEFT(A70,4) | L70: =LEFT(A70,5) | M70: =LEFT(A70,1)
I71: =LEFT(A71,2) | J71: =LEFT(A71,3) | K71: =LEFT(A71,4) | L71: =LEFT(A71,5) | M71: =LEFT(A71,1)
I72: =LEFT(A72,2) | J72: =LEFT(A72,3) | K72: =LEFT(A72,4) | L72: =LEFT(A72,5) | M72: =LEFT(A72,1)
I73: =LEFT(A73,2) | J73: =LEFT(A73,3) | K73: =LEFT(A73,4) | L73: =LEFT(A73,5) | M73: =LEFT(A73,1)
I74: =LEFT(A74,2) | J74: =LEFT(A74,3) | K74: =LEFT(A74,4) | L74: =LEFT(A74,5) | M74: =LEFT(A74,1)
I75: =LEFT(A75,2) | J75: =LEFT(A75,3) | K75: =LEFT(A75,4) | L75: =LEFT(A75,5) | M75: =LEFT(A75,1)
... I300: =LEFT(A300,2) | J300: =LEFT(A300,3) | K300: =LEFT(A300,4) | L300: =LEFT(A300,5) | M300: =LEFT(A300,1)
J301: =LEFT(A301,3) | K301: =LEFT(A301,4) | L301: =LEFT(A301,5) | M301: =LEFT(A301,1)
J302: =LEFT(A302,3) | K302: =LEFT(A302,4) | L302: =LEFT(A302,5) | M302: =LEFT(A302,1)
J303: =LEFT(A303,3) | K303: =LEFT(A303,4) | L303: =LEFT(A303,5) | M303: =LEFT(A303,1)
J304: =LEFT(A304,3) | K304: =LEFT(A304,4) | L304: =LEFT(A304,5) | M304: =LEFT(A304,1)
J305: =LEFT(A305,3) | K305: =LEFT(A305,4) | L305: =LEFT(A305,5) | M305: =LEFT(A305,1)
J306: =LEFT(A306,3) | K306: =LEFT(A306,4) | L306: =LEFT(A306,5) | M306: =LEFT(A306,1)
J307: =LEFT(A307,3) | K307: =LEFT(A307,4) | L307: =LEFT(A307,5) | M307: =LEFT(A307,1)
J308: =LEFT(A308,3) | K308: =LEFT(A308,4) | L308: =LEFT(A308,5) | M308: =LEFT(A308,1)
J309: =LEFT(A309,3) | K309: =LEFT(A309,4) | L309: =LEFT(A309,5) | M309: =LEFT(A309,1)
J310: =LEFT(A310,3) | K310: =LEFT(A310,4) | L310: =LEFT(A310,5) | M310: =LEFT(A310,1)
J311: =LEFT(A311,3) | K311: =LEFT(A311,4) | L311: =LEFT(A311,5) | M311: =LEFT(A311,1)
J312: =LEFT(A312,3) | K312: =LEFT(A312,4) | L312: =LEFT(A312,5) | M312: =LEFT(A312,1)
... J325: =LEFT(A325,3) | K325: =LEFT(A325,4) | L325: =LEFT(A325,5) | M325: =LEFT(A325,1)

Sheet Activités de l'entreprise R2
A1: Fiche R2
B4: Désignation de l'entreprise : | C4: ='Fiche de renseignement R1'!$J$4 -> 0
B5: Adresse de l'entreprise :
B6: ='Fiche de renseignement R1'!J7 -> 0 | L6: Sigle usuel : | M6: ='Fiche de renseignement R1'!AD7 -> 0
B7: N° d'identification : | L7: Exercice clos le :
B8: =+'Fiche de renseignement R1'!J10 -> 0 | K8: ='Fiche de renseignement R1'!V10 -> 0 | M8: Durée (en mois) | N8: ='Fiche de renseignement R1'!AH10 -> 12
A10: FICHE D'IDENTIFICATION ET RENSEIGNEMENTS DIVERS 2
L12: Contrôle de l'entreprise (cocher la case)
A14: ZK | B14: Forme juridique (1) | F14: 0 | G14: 2 | K14: ZQ | L14: Entreprise sous contrôle public
A16: ZL | B16: Régime fiscal (1) | F16: 2 | K16: ZR | L16: Entreprise sous contrôle privé national | Q16: X
A18: ZM | B18: Pays du siège social (1) | F18: 0 | G18: 7 | K18: ZS | L18: Entreprise sous contrôle privé étranger
A20: ZN | B20: Nbre d'établissements dans le pays | F20: 0 | G20: 1
A22: ZO | B22: Nbre d'établissements hors du pays | F22: 0 | G22: 0
B23: pour lesquels une comptabilité distincte est tenue
A25: ZP | B25: 1ère année exercice dans le pays | E25: 2 | F25: 0 | G25: 0 | H25: 1
A28: ACTIVITE DE L'ENTREPRISE
B30: DESIGNATION DE L'ACTIVITE (2) | C30: Code nomenclature d'activité (1) | K30: Valeur Ajoutée (VA) HT/ Chiffre d'affaire | M30: % activité dans le CA HT ou la VA
B33: TRAITEMENT ET EXPORTATION DE PRODUITS HALIEUTIQUES | D33: 3 | E33: 0 | F33: 0 | G33: 0 | H33: 2 | I33: 0 | L33: =IFERROR(VLOOKUP("702200",'BAL N'!A:H,8,FALSE),IFERROR(VLOOKUP(702200,'BAL N'!A:H,8,FALSE),0)) -> 0 | M33: =IFERROR(+L33/$L$59,0) -> 0
M36: =IFERROR(+L36/$L$59,0) -> 0
M39: =IFERROR(+L39/$L$59,0) -> 0
M42: =IFERROR(+L42/$L$59,0) -> 0
M45: =IFERROR(+L45/$L$59,0) -> 0
M48: =IFERROR(+L48/$L$59,0) -> 0
M51: =IFERROR(+L51/$L$59,0) -> 0
M54: =IFERROR(+L54/$L$59,0) -> 0
B57: Divers
I59: TOTAL | L59: =SUM(L32:L56) -> 0 | M59: =SUM(M32:M57) -> 0
B62: (1) Se réréfer aux tables des codes
B63: (2) Lister de manière précise les activités dans l'ordre décroissant du CAHT, ou de la valeur ajoutée (V.A.)
B64: (3) Rayer la mention inutile (utiliser de préférence la V.A.)

Sheet Dirigeants R3
A1: Fiche R3
A3: Désignation de l'entreprise | B3: ='Fiche de renseignement R1'!$J$4 -> 0
A4: Adresse de l'entreprise | B4: ='Activités de l''entreprise R2'!B6 -> 0 | D4: Sigle usuel | E4: ='Activités de l''entreprise R2'!M6 -> 0
A5: N° d'identification fiscale | B5: ='Activités de l''entreprise R2'!B8 -> 0 | C5: Exercice clos le | D5: ='Activités de l''entreprise R2'!K8 -> 0 | E5: Durée (en mois) | F5: ='Activités de l''entreprise R2'!N8 -> 12
A7: FICHE D'IDENTIFICATION ET RENSEIGNEMENTS DIVERS 3
A9: DIRIGEANTS (1)
A11: Nom | B11: Prénoms | C11: Qualité | D11: N° d'identification fiscale | E11: Adressse (BP, ville, pays)
A12: HDH | B12: HDDH | C12: HH | D12: DHD | E12: DHHH
A27: (1) Dirigeants = Président Directeur Général, Directeur Général, Adminsitrateur Général, Gérant, Autres.
A29: MEMBRES DU CONSEIL D'ADMINISTRATION
A31: Nom | B31: Prénoms | C31: Qualité | E31: Adressse (BP, ville, pays)

Sheet Tableau des Notes R4
A1: FICHE R4
A2: Désignation entité : | B2: ='Fiche de renseignement R1'!$J$4 -> 0 | D2: Excercice clos le : | E2: =+'Fiche de renseignement R1'!$V$10 -> 0
A3: Numéro d'identification : | B3: =+'Fiche de renseignement R1'!$J$10 -> 0 | D3: Durée en mois : | E3: =+'Fiche de renseignement R1'!$AH$10 -> 12
A6: FICHE RECAPITULATIVE DES NOTES ANNEXES PRESENTEES
A8: NOTES | B8: INTITULES | C8: A | E8: N/A
A9: NOTE 1 | B9: DETTES GARANTIES PAR DES SURETES REELLES
A10: NOTE 2 | B10: INFORMATIONS OBLIGATOIRES
A11: NOTE 3A | B11: IMMOBILISATION BRUTE
A12: NOTE 3B | B12: BIENS PRIS EN LOCATION ACQUISITION
A13: NOTE 3C | B13: IMMOBILISATIONS : AMORTISSEMENTS
A14: NOTE 3D | B14: IMMOBILISATIONS : PLUS-VALUES ET MOINS VALUES DE CESSION
A15: NOTE 3E | B15: INFORMATIONS SUR LES REEVALUATIONS EFFECTUEES PAR L'ENTITE
A16: NOTE 4 | B16: IMMOBILISATIONS FINANCIERES
A17: NOTE 5 | B17: ACTIF CIRCULANT HAO
A18: NOTE 6 | B18: STOCKS ET ENCOURS
A19: NOTE 7 | B19: CLIENTS PRODUITS A RECEVOIR
A20: NOTE 8 | B20: AUTRES CREANCES
... A54: NOTE 36 | B54: TABLES DES CODES

Sheet BILAN PAYSAGE
A1: BILAN PAYSAGE
A3: Désignation entité : | D3: ='Fiche de renseignement R1'!$J$4 -> 0 | I3: Excercice clos le : | J3: =+'Fiche de renseignement R1'!$V$10 -> 0
A4: Numéro d'identification : | D4: =+'Fiche de renseignement R1'!$J$10 -> 0 | I4: Durée en mois : | J4: =+'Fiche de renseignement R1'!$AH$10 -> 12
A6: REF | B6: ACTIF | C6: Note | D6: =IFERROR("Exercice au 31/12/"&YEAR('Fiche de renseignement R1'!V10),"Exercice au 31/12/N") -> Exercice au 31/12/1900 | G6: =IFERROR("Exercice au 31/12/"&YEAR('Fiche de renseignement R1'!Q20),"Exercice au 31/12/N-1") -> Exercice au 31/12/2020 | H6: REF | I6: PASSIF | J6: Note | K6: =IFERROR("Exercice au 31/12/"&YEAR('Fiche de renseignement R1'!V10),"Exercice au 31/12/N") -> Exercice au 31/12/1900 | L6: =IFERROR("Exercice au 31/12/"&YEAR('Fiche de renseignement R1'!Q20),"Exercice au 31/12/N-1") -> Exercice au 31/12/2020
D7: Brut | E7: Amorts et Dépréc. | F7: Net | G7: Net | K7: Net | L7: Net
A8: AD | B8: IMMOBILISATIONS INCORPORELLES | C8: 3 | D8: =+D9+D10+D11+D12 -> 0 | E8: =+E9+E10+E11+E12 -> 0 | F8: =+F9+F10+F11+F12 -> 0 | G8: =+G9+G10+G11+G12 -> 0 | H8: CA | I8: CAPITAL | J8: 13 | K8: =+SUMIF('BAL N'!J:J,"=101",'BAL N'!H:H)+SUMIF('BAL N'!J:J,"=102",'BAL N'!H:H)+SUMIF('BAL N'!J:J,"=103",'BAL N'!H:H)+SUMIF('BAL N'!J:J,"=104",'BAL N'!H:H) -> 0 | L8: =+SUMIF('BAL N'!J:J,"=101",'BAL N'!D:D)+SUMIF('BAL N'!J:J,"=102",'BAL N'!D:D)+SUMIF('BAL N'!J:J,"=103",'BAL N'!D:D)+SUMIF('BAL N'!J:J,"=104",'BAL N'!D:D) -> 0
A9: AE | B9: Frais de développement et de prospection | D9: =+SUMIF('BAL N'!J:J,"=211",'BAL N'!G:G)+SUMIF('BAL N'!K:K,"=2181",'BAL N'!G:G)+SUMIF('BAL N'!K:K,"=2191",'BAL N'!G:G) -> 0 | E9: =+SUMIF('BAL N'!K:K,"=2811",'BAL N'!H:H)+SUMIF('BAL N'!L:L,"=28181",'BAL N'!H:H)+SUMIF('BAL N'!L:L,"=28191",'BAL N'!H:H)+SUMIF('BAL N'!K:K,"=2911",'BAL N'!H:H)+SUMIF('BAL N'!K:K,"=2918",'BAL N'!H:H)+SUMIF('BAL N'!K:K,"=2919",'BAL N'!H:H) -> 0 | F9: =+D9-E9 -> 0 | G9: =+SUMIF('BAL N'!J:J,"=211",'BAL N'!C:C)+SUMIF('BAL N'!K:K,"=2181",'BAL N'!C:C)+SUMIF('BAL N'!K:K,"=2191",'BAL N'!C:C)-(SUMIF('BAL N'!K:K,"=2811",'BAL N'!D:D)+SUMIF('BAL N'!L:L,"=28181",'BAL N'!D:D)+SUMIF('BAL N'!L:L,"=28191",'BAL N'!D:D)+SUMIF('BAL N'!K:K,"=2911",'BAL N'!D:D)+SUMIF('BAL N'!K:K,"=2918",'BAL N'!D:D)+SUMIF('BAL N'!K:K,"=2919",'BAL N'!D:D)) -> 0 | H9: CB | I9: Apporteurs capital non appelé | J9: 13 | K9: =+SUMIF('BAL N'!J:J,"=109",'BAL N'!H:H) -> 0 | L9: =+SUMIF('BAL N'!J:J,"=109",'BAL N'!D:D) -> 0
A10: AF | B10: Brevets, licences, logiciels et droits similaires | D10: =+SUMIF('BAL N'!J:J,"=212",'BAL N'!G:G)+SUMIF('BAL N'!J:J,"=213",'BAL N'!G:G)+SUMIF('BAL N'!J:J,"=214",'BAL N'!G:G)+SUMIF('BAL N'!K:K,"=2193",'BAL N'!G:G) -> 0 | E10: =+SUMIF('BAL N'!K:K,"=2812",'BAL N'!H:H)+SUMIF('BAL N'!K:K,"=2813",'BAL N'!H:H)+SUMIF('BAL N'!K:K,"=2814",'BAL N'!H:H)+SUMIF('BAL N'!K:K,"=2912",'BAL N'!H:H)+SUMIF('BAL N'!K:K,"=2913",'BAL N'!H:H)+SUMIF('BAL N'!K:K,"=2914",'BAL N'!H:H)+SUMIF('BAL N'!K:K,"=2919",'BAL N'!H:H) -> 0 | F10: =+D10-E10 -> 0 | G10: =+SUMIF('BAL N'!J:J,"=212",'BAL N'!C:C)+SUMIF('BAL N'!J:J,"=213",'BAL N'!C:C)+SUMIF('BAL N'!J:J,"=214",'BAL N'!C:C)+SUMIF('BAL N'!K:K,"=2193",'BAL N'!C:C)-(SUMIF('BAL N'!K:K,"=2811",'BAL N'!D:D)+SUMIF('BAL N'!K:K,"=2812",'BAL N'!D:D)+SUMIF('BAL N'!K:K,"=2813",'BAL N'!D:D)+SUMIF('BAL N'!K:K,"=2814",'BAL N'!D:D)+SUMIF('BAL N'!L:L,"=28181",'BAL N'!D:D)+SUMIF('BAL N'!L:L,"=28191",'BAL N'!D:D)+SUMIF('BAL N'!K:K,"=2911",'BAL N'!D:D)+SUMIF('BAL N'!K:K,"=2912",'BAL N'!D:D)+SUMIF('BAL N'!K:K,"=2913",'BAL N'!D:D)+SUMIF('BAL N'!K:K,"=2914",'BAL N'!D:D)+SUMIF('BAL N'!K:K,"=2918",'BAL N'!D:D)+SUMIF('BAL N'!K:K,"=2919",'BAL N'!D:D)) -> 0 | H10: CD | I10: Primes liées au capital social | J10: 14 | K10: =+SUMIF('BAL N'!J:J,"=105",'BAL N'!H:H) -> 0 | L10: =+SUMIF('BAL N'!J:J,"=105",'BAL N'!D:D) -> 0
A11: AG | B11: Fonds commercial et droit au bail | D11: =+SUMIF('BAL N'!J:J,"=215",'BAL N'!G:G)+SUMIF('BAL N'!J:J,"=216",'BAL N'!G:G) -> 0 | E11: =+SUMIF('BAL N'!K:K,"=2815",'BAL N'!H:H)+SUMIF('BAL N'!K:K,"=2816",'BAL N'!H:H)+SUMIF('BAL N'!K:K,"=2915",'BAL N'!H:H)+SUMIF('BAL N'!K:K,"=2916",'BAL N'!H:H) -> 0 | F11: =+D11-E11 -> 0 | G11: =+SUMIF('BAL N'!J:J,"=215",'BAL N'!C:C)+SUMIF('BAL N'!J:J,"=216",'BAL N'!C:C)-(SUMIF('BAL N'!K:K,"=2815",'BAL N'!D:D)+SUMIF('BAL N'!K:K,"=2816",'BAL N'!D:D)+SUMIF('BAL N'!K:K,"=2915",'BAL N'!D:D)+SUMIF('BAL N'!K:K,"=2916",'BAL N'!D:D)) -> 0 | H11: CE | I11: Ecarts de réévaluation | J11: 3e | K11: =+SUMIF('BAL N'!J:J,"=106",'BAL N'!H:H) -> 0 | L11: =+SUMIF('BAL N'!J:J,"=106",'BAL N'!D:D) -> 0
A12: AH | B12: Autres immobilisations incorporelles | D12: =+SUMIF('BAL N'!J:J,"=217",'BAL N'!G:G)+SUMIF('BAL N'!J:J,"=218",'BAL N'!G:G)-SUMIF('BAL N'!K:K,"=2181",'BAL N'!G:G)+SUMIF('BAL N'!K:K,"=2198",'BAL N'!G:G) -> 0 | E12: =+SUMIF('BAL N'!K:K,"=2817",'BAL N'!H:H)+SUMIF('BAL N'!K:K,"=2818",'BAL N'!H:H)+SUMIF('BAL N'!K:K,"=2917",'BAL N'!H:H)+SUMIF('BAL N'!K:K,"=2918",'BAL N'!H:H)+SUMIF('BAL N'!K:K,"=2919",'BAL N'!H:H) -> 0 | F12: =+D12-E12 -> 0 | G12: =+SUMIF('BAL N'!J:J,"=217",'BAL N'!C:C)+SUMIF('BAL N'!J:J,"=218",'BAL N'!C:C)-SUMIF('BAL N'!K:K,"=2181",'BAL N'!C:C)+SUMIF('BAL N'!K:K,"=2198",'BAL N'!C:C)-(SUMIF('BAL N'!K:K,"=2817",'BAL N'!D:D)+SUMIF('BAL N'!K:K,"=2818",'BAL N'!D:D)+SUMIF('BAL N'!K:K,"=2917",'BAL N'!D:D)+SUMIF('BAL N'!K:K,"=2918",'BAL N'!D:D)+SUMIF('BAL N'!K:K,"=2919",'BAL N'!D:D)) -> 0 | H12: CF | I12: Réserves indisponibles | J12: 14 | K12: =+SUMIF('BAL N'!J:J,"=111",'BAL N'!H:H)+SUMIF('BAL N'!J:J,"=112",'BAL N'!H:H)+SUMIF('BAL N'!J:J,"=113",'BAL N'!H:H) -> 0 | L12: =+SUMIF('BAL N'!J:J,"=111",'BAL N'!D:D)+SUMIF('BAL N'!J:J,"=112",'BAL N'!D:D)+SUMIF('BAL N'!J:J,"=113",'BAL N'!D:D) -> 0
A13: AI | B13: IMMOBILISATIONS CORPORELLES | C13: 3 | D13: =SUM(D14:D19) -> 0 | E13: =SUM(E14:E19) -> 0 | F13: =SUM(F14:F19) -> 0 | G13: =SUM(G14:G19) -> 0 | H13: CG | I13: Réserves libres | J13: 14 | K13: =+SUMIF('BAL N'!J:J,"=118",'BAL N'!H:H) -> 0 | L13: =+SUMIF('BAL N'!J:J,"=118",'BAL N'!D:D) -> 0
A14: AJ | B14: Terrains (1) (1) dont placement en net ………../………… | D14: =+SUMIF('BAL N'!I:I,"=22",'BAL N'!G:G) -> 0 | E14: =+SUMIF('BAL N'!J:J,"=282",'BAL N'!H:H)+SUMIF('BAL N'!J:J,"=292",'BAL N'!H:H) -> 0 | F14: =+D14-E14 -> 0 | G14: =+SUMIF('BAL N'!I:I,"=22",'BAL N'!C:C)-(SUMIF('BAL N'!J:J,"=282",'BAL N'!D:D)+SUMIF('BAL N'!J:J,"=292",'BAL N'!D:D)) -> 0 | H14: CH | I14: Report à nouveau (+ ou -) | J14: 14 | K14: =+SUMIF('BAL N'!I:I,"=12",'BAL N'!H:H)-SUMIF('BAL N'!I:I,"=12",'BAL N'!G:G) -> 0 | L14: =+SUMIF('BAL N'!I:I,"=13",'BAL N'!D:D)-SUMIF('BAL N'!I:I,"=13",'BAL N'!C:C) -> 0
A15: AK | B15: Bâtiments (1) dont placement en net ………../………… | D15: =+SUMIF('BAL N'!J:J,"=231",'BAL N'!G:G)+SUMIF('BAL N'!J:J,"=232",'BAL N'!G:G)+SUMIF('BAL N'!J:J,"=233",'BAL N'!G:G)+SUMIF('BAL N'!J:J,"=237",'BAL N'!G:G)+SUMIF('BAL N'!K:K,"=2391",'BAL N'!G:G) -> 0 | E15: =+SUMIF('BAL N'!K:K,"=2831",'BAL N'!H:H)+SUMIF('BAL N'!K:K,"=2832",'BAL N'!H:H)+SUMIF('BAL N'!K:K,"=2833",'BAL N'!H:H)+SUMIF('BAL N'!K:K,"=2837",'BAL N'!H:H)+SUMIF('BAL N'!K:K,"=2931",'BAL N'!H:H)+SUMIF('BAL N'!K:K,"=2932",'BAL N'!H:H)+SUMIF('BAL N'!K:K,"=2933",'BAL N'!H:H)+SUMIF('BAL N'!K:K,"=2937",'BAL N'!H:H)+SUMIF('BAL N'!K:K,"=2939",'BAL N'!H:H) -> 0 | F15: =+D15-E15 -> 0 | G15: =+SUMIF('BAL N'!J:J,"=231",'BAL N'!C:C)+SUMIF('BAL N'!J:J,"=232",'BAL N'!C:C)+SUMIF('BAL N'!J:J,"=233",'BAL N'!C:C)+SUMIF('BAL N'!J:J,"=237",'BAL N'!C:C)++SUMIF('BAL N'!J:J,"=239",'BAL N'!C:C)-SUMIF('BAL N'!J:J,"=238",'BAL N'!D:D)-(SUMIF('BAL N'!K:K,"=2831",'BAL N'!D:D)+SUMIF('BAL N'!K:K,"=2832",'BAL N'!D:D)+SUMIF('BAL N'!K:K,"=2833",'BAL N'!D:D)+SUMIF('BAL N'!K:K,"=2837",'BAL N'!D:D)+SUMIF('BAL N'!K:K,"=2931",'BAL N'!D:D)+SUMIF('BAL N'!K:K,"=2932",'BAL N'!D:D)+SUMIF('BAL N'!K:K,"=2933",'BAL N'!D:D)+SUMIF('BAL N'!K:K,"=2937",'BAL N'!D:D)+SUMIF('BAL N'!K:K,"=2939",'BAL N'!D:D)) -> 0 | H15: CJ | I15: Résutat net de l'exercice (bénéfice + ou perte -) | K15: =+SUMIF('BAL N'!M:M,"=7",'BAL N'!H:H)+SUMIF('BAL N'!M:M,"=8",'BAL N'!H:H)-SUMIF('BAL N'!M:M,"=6",'BAL N'!G:G)-SUMIF('BAL N'!M:M,"=8",'BAL N'!G:G)+SUMIF('BAL N'!J:J,"=603",'BAL N'!H:H) -> 0 | L15: =-SUMIF('BAL N'!J:J,"=131",'BAL N'!C:C)+SUMIF('BAL N'!J:J,"=131",'BAL N'!D:D) -> 0
A16: AL | B16: Aménagements, agencements et installations | D16: =+SUMIF('BAL N'!J:J,"=234",'BAL N'!G:G)+SUMIF('BAL N'!J:J,"=235",'BAL N'!G:G)+SUMIF('BAL N'!J:J,"=238",'BAL N'!G:G)+SUMIF('BAL N'!J:J,"=239",'BAL N'!G:G) -> 0 | E16: =+SUMIF('BAL N'!K:K,"=2834",'BAL N'!H:H)+SUMIF('BAL N'!K:K,"=2835",'BAL N'!H:H)+SUMIF('BAL N'!K:K,"=2838",'BAL N'!H:H)+SUMIF('BAL N'!K:K,"=2934",'BAL N'!H:H)+SUMIF('BAL N'!K:K,"=2935",'BAL N'!H:H)+SUMIF('BAL N'!K:K,"=2938",'BAL N'!H:H)+SUMIF('BAL N'!K:K,"=2939",'BAL N'!H:H) -> 0 | F16: =+D16-E16 -> 0 | G16: =+SUMIF('BAL N'!J:J,"=234",'BAL N'!C:C)+SUMIF('BAL N'!J:J,"=235",'BAL N'!C:C)+SUMIF('BAL N'!J:J,"=238",'BAL N'!C:C)+SUMIF('BAL N'!K:K,"=2392",'BAL N'!C:C)+SUMIF('BAL N'!K:K,"=2393",'BAL N'!C:C)-(+SUMIF('BAL N'!K:K,"=2834",'BAL N'!D:D)+SUMIF('BAL N'!K:K,"=2835",'BAL N'!D:D)+SUMIF('BAL N'!K:K,"=2838",'BAL N'!D:D)+SUMIF('BAL N'!K:K,"=2934",'BAL N'!D:D)+SUMIF('BAL N'!K:K,"=2935",'BAL N'!D:D)+SUMIF('BAL N'!K:K,"=2938",'BAL N'!D:D)+SUMIF('BAL N'!K:K,"=2939",'BAL N'!D:D)) -> 0 | H16: CL | I16: Subventions d'investissement | J16: 15 | K16: =+SUMIF('BAL N'!I:I,"=14",'BAL N'!H:H) -> 0 | L16: =+SUMIF('BAL N'!I:I,"=14",'BAL N'!D:D) -> 0
A17: AM | B17: Matériel, mobilier et actifs biologiques | D17: =+SUMIF('BAL N'!I:I,"=24",'BAL N'!G:G)-SUMIF('BAL N'!J:J,"=245",'BAL N'!G:G)-SUMIF('BAL N'!K:K,"=2495",'BAL N'!G:G) -> 0 | E17: =+SUMIF('BAL N'!J:J,"=284",'BAL N'!H:H)-SUMIF('BAL N'!K:K,"=2845",'BAL N'!H:H)+SUMIF('BAL N'!J:J,"=294",'BAL N'!H:H)-SUMIF('BAL N'!K:K,"=2945",'BAL N'!H:H)-SUMIF('BAL N'!K:K,"=2949",'BAL N'!H:H) -> 0 | F17: =+D17-E17 -> 0 | G17: =+SUMIF('BAL N'!I:I,"=24",'BAL N'!C:C)-SUMIF('BAL N'!J:J,"=245",'BAL N'!C:C)-SUMIF('BAL N'!J:J,"=2495",'BAL N'!C:C)-(SUMIF('BAL N'!J:J,"=284",'BAL N'!D:D)-SUMIF('BAL N'!K:K,"=2845",'BAL N'!D:D)+SUMIF('BAL N'!J:J,"=294",'BAL N'!D:D)-SUMIF('BAL N'!K:K,"=2945",'BAL N'!D:D)-SUMIF('BAL N'!K:K,"=2949",'BAL N'!D:D)) -> 0 | H17: CM | I17: Provisions réglementées et fonds assimilés | J17: 15 | K17: =+SUMIF('BAL N'!I:I,"=15",'BAL N'!H:H) -> 0 | L17: =+SUMIF('BAL N'!I:I,"=15",'BAL N'!D:D) -> 0
A18: AN | B18: Matériel de transport | D18: =+SUMIF('BAL N'!J:J,"=245",'BAL N'!G:G)+SUMIF('BAL N'!K:K,"=2495",'BAL N'!G:G) -> 0 | E18: =+SUMIF('BAL N'!K:K,"=2845",'BAL N'!H:H)+SUMIF('BAL N'!K:K,"=2849",'BAL N'!H:H)+SUMIF('BAL N'!K:K,"=2945",'BAL N'!H:H) -> 0 | F18: =+D18-E18 -> 0 | G18: =+SUMIF('BAL N'!J:J,"=245",'BAL N'!C:C)+SUMIF('BAL N'!K:K,"=2495",'BAL N'!C:C)-(+SUMIF('BAL N'!K:K,"=2845",'BAL N'!D:D)+SUMIF('BAL N'!K:K,"=2849",'BAL N'!D:D)+SUMIF('BAL N'!K:K,"=2945",'BAL N'!D:D)) -> 0 | H18: CP | I18: TOTAL CAPITAUX PROPRES ET RESSOURCES ASSIMILEES | K18: =SUM(K8:K17) -> 0 | L18: =SUM(L8:L17) -> 0
A19: AP | B19: Avances & acomptes versés sur immobilisations | C19: 3 | D19: =+SUMIF('BAL N'!I:I,"=25",'BAL N'!G:G) -> 0 | E19: =+SUMIF('BAL N'!J:J,"=295",'BAL N'!H:H) -> 0 | F19: =+D19-E19 -> 0 | G19: =+SUMIF('BAL N'!I:I,"=25",'BAL N'!C:C)-SUMIF('BAL N'!J:J,"=295",'BAL N'!D:D) -> 0 | H19: DA | I19: Emprunts et dettes financières diverses | J19: 16 | K19: =+SUMIF('BAL N'!I:I,"=16",'BAL N'!H:H)+SUMIF('BAL N'!J:J,"=181",'BAL N'!H:H)+SUMIF('BAL N'!J:J,"=182",'BAL N'!H:H)+SUMIF('BAL N'!J:J,"=184",'BAL N'!H:H) -> 0 | L19: =+SUMIF('BAL N'!I:I,"=16",'BAL N'!D:D)+SUMIF('BAL N'!J:J,"=181",'BAL N'!D:D)+SUMIF('BAL N'!J:J,"=182",'BAL N'!D:D)+SUMIF('BAL N'!J:J,"=183",'BAL N'!D:D)+SUMIF('BAL N'!J:J,"=184",'BAL N'!D:D) -> 0
A20: AQ | B20: IMMOBILISATIONS FINANCIERES | C20: 4 | D20: =SUM(D21:D22) -> 0 | E20: =SUM(E21:E22) -> 0 | F20: =SUM(F21:F22) -> 0 | G20: =SUM(G21:G22) -> 0 | H20: DB | I20: Dettes de location acquisition | J20: 16 | K20: =+SUMIF('BAL N'!I:I,"=17",'BAL N'!H:H) -> 0 | L20: =+SUMIF('BAL N'!I:I,"=17",'BAL N'!D:D) -> 0
A21: AR | B21: Titres de participation | D21: =+SUMIF('BAL N'!I:I,"=26",'BAL N'!G:G) -> 0 | E21: =+SUMIF('BAL N'!J:J,"=296",'BAL N'!H:H) -> 0 | F21: =+D21-E21 -> 0 | G21: =+SUMIF('BAL N'!I:I,"=26",'BAL N'!C:C)-SUMIF('BAL N'!J:J,"=296",'BAL N'!D:D) -> 0 | H21: DC | I21: Provisions pour risques et charges | J21: 16 | K21: =+SUMIF('BAL N'!I:I,"=19",'BAL N'!H:H) -> 0 | L21: =+SUMIF('BAL N'!I:I,"=19",'BAL N'!D:D) -> 0
A22: AS | B22: Autres immobilisations financières | D22: =+SUMIF('BAL N'!I:I,"=27",'BAL N'!G:G) -> 0 | E22: =+SUMIF('BAL N'!J:J,"=297",'BAL N'!H:H) -> 0 | F22: =+D22-E22 -> 0 | G22: =+SUMIF('BAL N'!I:I,"=27",'BAL N'!C:C)-SUMIF('BAL N'!J:J,"=297",'BAL N'!D:D) -> 0 | H22: DD | I22: TOTAL DETTES FINANCIERES ET RESSOURCES ASSIMILEES | K22: =SUM(K19:K21) -> 0 | L22: =SUM(L19:L21) -> 0
A23: AZ | B23: TOTAL ACTIF IMMOBILISE | D23: =+D20+D13+D8 -> 0 | E23: =+E20+E13+E8 -> 0 | F23: =+F20+F13+F8 -> 0 | G23: =+G20+G13+G8 -> 0 | H23: DF | I23: TOTAL RESSOURCES STABLES
A24: BA | B24: ACTIF CIRCULANT H.A.O. | C24: 5 | D24: =+SUMIF('BAL N'!J:J,"=485",'BAL N'!G:G)+SUMIF('BAL N'!J:J,"=488",'BAL N'!G:G) -> 0 | E24: =+SUMIF('BAL N'!J:J,"=498",'BAL N'!H:H) -> 0 | F24: =+D24-E24 -> 0 | G24: =+SUMIF('BAL N'!J:J,"=485",'BAL N'!C:C)+SUMIF('BAL N'!J:J,"=488",'BAL N'!C:C)-SUMIF('BAL N'!J:J,"=498",'BAL N'!D:D) -> 0 | H24: DH | I24: Dettes circulantes HAO | J24: 5 | K24: =+SUMIF('BAL N'!J:J,"=481",'BAL N'!H:H)+SUMIF('BAL N'!J:J,"=482",'BAL N'!H:H)+SUMIF('BAL N'!J:J,"=484",'BAL N'!H:H)+SUMIF('BAL N'!K:K,"=4998",'BAL N'!H:H) -> 0 | L24: =+SUMIF('BAL N'!J:J,"=481",'BAL N'!D:D)+SUMIF('BAL N'!J:J,"=482",'BAL N'!D:D)+SUMIF('BAL N'!J:J,"=484",'BAL N'!D:D)+SUMIF('BAL N'!K:K,"=4998",'BAL N'!D:D) -> 0
A25: BB | B25: STOCKS ET ENCOURS | C25: 6 | D25: =+SUMIF('BAL N'!I:I,"=31",'BAL N'!G:G)+SUMIF('BAL N'!I:I,"=32",'BAL N'!G:G)+SUMIF('BAL N'!I:I,"=33",'BAL N'!G:G)+SUMIF('BAL N'!I:I,"=34",'BAL N'!G:G)+SUMIF('BAL N'!I:I,"=35",'BAL N'!G:G)+SUMIF('BAL N'!I:I,"=36",'BAL N'!G:G)+SUMIF('BAL N'!I:I,"=37",'BAL N'!G:G)+SUMIF('BAL N'!I:I,"=38",'BAL N'!G:G) -> 0 | E25: =+SUMIF('BAL N'!I:I,"=39",'BAL N'!H:H) -> 0 | F25: =+D25-E25 -> 0 | G25: =+SUMIF('BAL N'!I:I,"=31",'BAL N'!C:C)+SUMIF('BAL N'!I:I,"=32",'BAL N'!C:C)+SUMIF('BAL N'!I:I,"=33",'BAL N'!C:C)+SUMIF('BAL N'!I:I,"=34",'BAL N'!C:C)+SUMIF('BAL N'!I:I,"=35",'BAL N'!C:C)+SUMIF('BAL N'!I:I,"=36",'BAL N'!C:C)+SUMIF('BAL N'!I:I,"=37",'BAL N'!C:C)+SUMIF('BAL N'!I:I,"=38",'BAL N'!C:C)-SUMIF('BAL N'!I:I,"=39",'BAL N'!D:D) -> 0 | H25: DI | I25: Clients, avances reçues | J25: 7 | K25: =+SUMIF('BAL N'!J:J,"=419",'BAL N'!H:H) -> 0 | L25: =+SUMIF('BAL N'!J:J,"=419",'BAL N'!D:D) -> 0
A26: BG | B26: CREANCES ET EMPLOIS ASSIMILES | F26: =+D26-E26 -> 0 | H26: DJ | I26: Fournisseurs d'exploitation | J26: 17 | K26: =+SUMIF('BAL N'!I:I,"=40",'BAL N'!H:H)-SUMIF('BAL N'!J:J,"=409",'BAL N'!H:H) -> 0 | L26: =+SUMIF('BAL N'!J:J,"=401",'BAL N'!D:D)+SUMIF('BAL N'!J:J,"=402",'BAL N'!D:D)+SUMIF('BAL N'!J:J,"=408",'BAL N'!D:D)-SUMIF('BAL N'!J:J,"=401",'BAL N'!C:C) -> 0
A27: BH | B27: Fournisseurs, avances versées | C27: 17 | D27: =+SUMIF('BAL N'!I:I,"=40",'BAL N'!G:G)-SUMIF('BAL N'!J:J,"=490",'BAL N'!D:D) -> 0 | E27: =+SUMIF('BAL N'!J:J,"=490",'BAL N'!H:H) -> 0 | F27: =+D27-E27 -> 0 | G27: =+SUMIF('BAL N'!I:I,"=40",'BAL N'!C:C)-SUMIF('BAL N'!J:J,"=490",'BAL N'!D:D)-SUMIF('BAL N'!J:J,"409",'BAL N'!D:D) -> 0 | H27: DK | I27: Dettes fiscales et sociales | J27: 18 | K27: =+SUMIF('BAL N'!I:I,"=42",'BAL N'!H:H)+SUMIF('BAL N'!I:I,"=43",'BAL N'!H:H)+SUMIF('BAL N'!I:I,"=44",'BAL N'!H:H) -> 0 | L27: =+SUMIF('BAL N'!I:I,"=42",'BAL N'!D:D)-SUMIF('BAL N'!J:J,"=421",'BAL N'!D:D)+SUMIF('BAL N'!K:K,"=4287",'BAL N'!D:D)+SUMIF('BAL N'!I:I,"=43",'BAL N'!D:D)-SUMIF('BAL N'!K:K,"=4387",'BAL N'!D:D)+SUMIF('BAL N'!J:J,"=441",'BAL N'!D:D)+SUMIF('BAL N'!J:J,"=442",'BAL N'!D:D)+SUMIF('BAL N'!J:J,"=443",'BAL N'!D:D)+SUMIF('BAL N'!K:K,"=4441",'BAL N'!D:D)+SUMIF('BAL N'!J:J,"=446",'BAL N'!D:D)+SUMIF('BAL N'!J:J,"=447",'BAL N'!D:D)+SUMIF('BAL N'!K:K,"=4486",'BAL N'!D:D)+SUMIF('BAL N'!K:K,"=4494",'BAL N'!D:D) -> 0
A28: BI | B28: Clients | C28: 7 | D28: =+SUMIF('BAL N'!I:I,"=41",'BAL N'!G:G)-SUMIF('BAL N'!J:J,"=419",'BAL N'!G:G) -> 0 | E28: =+SUMIF('BAL N'!J:J,"=491",'BAL N'!H:H) -> 0 | F28: =+D28-E28 -> 0 | G28: =+SUMIF('BAL N'!I:I,"=41",'BAL N'!C:C)-SUMIF('BAL N'!J:J,"=491",'BAL N'!D:D)-SUMIF('BAL N'!J:J,"=411",'BAL N'!D:D) -> 0 | H28: DM | I28: Autres dettes | J28: 19 | K28: =+SUMIF('BAL N'!J:J,"=185",'BAL N'!H:H)+SUMIF('BAL N'!I:I,"=45",'BAL N'!H:H)+SUMIF('BAL N'!I:I,"=47",'BAL N'!H:H)+SUMIF('BAL N'!I:I,"=46",'BAL N'!H:H)-SUMIF('BAL N'!J:J,"=479",'BAL N'!H:H) -> 0 | L28: =+SUMIF('BAL N'!J:J,"=185",'BAL N'!D:D)+SUMIF('BAL N'!K:K,"=4712",'BAL N'!D:D)+SUMIF('BAL N'!J:J,"=472",'BAL N'!D:D)+SUMIF('BAL N'!J:J,"=477",'BAL N'!D:D)+SUMIF('BAL N'!I:I,"=46",'BAL N'!D:D)-SUMIF('BAL N'!J:J,"=4712",'BAL N'!C:C) -> 0
A29: BJ | B29: Autres créances | C29: 8 | D29: =SUMIF('BAL N'!J:J,"=185",'BAL N'!G:G)+SUMIF('BAL N'!I:I,"=42",'BAL N'!G:G)+SUMIF('BAL N'!I:I,"=43",'BAL N'!G:G)+SUMIF('BAL N'!I:I,"=44",'BAL N'!G:G)+SUMIF('BAL N'!I:I,"=45",'BAL N'!G:G)+SUMIF('BAL N'!I:I,"=46",'BAL N'!G:G)+SUMIF('BAL N'!I:I,"=47",'BAL N'!G:G)-SUMIF('BAL N'!J:J,"=478",'BAL N'!G:G) -> 0 | E29: =+SUMIF('BAL N'!J:J,"=492",'BAL N'!H:H)+SUMIF('BAL N'!J:J,"=493",'BAL N'!H:H)+SUMIF('BAL N'!J:J,"=494",'BAL N'!H:H)+SUMIF('BAL N'!J:J,"=495",'BAL N'!H:H)+SUMIF('BAL N'!J:J,"=496",'BAL N'!H:H)+SUMIF('BAL N'!J:J,"=497",'BAL N'!H:H) -> 0 | F29: =+D29-E29 -> 0 | G29: =+SUMIF('BAL N'!K:K,"=4287",'BAL N'!C:C)+SUMIF('BAL N'!K:K,"=4387",'BAL N'!C:C)+SUMIF('BAL N'!K:K,"=4449",'BAL N'!C:C)+SUMIF('BAL N'!J:J,"=421",'BAL N'!C:C)+SUMIF('BAL N'!J:J,"=445",'BAL N'!C:C)+SUMIF('BAL N'!K:K,"=4487",'BAL N'!C:C)+SUMIF('BAL N'!J:J,"=449",'BAL N'!C:C)+SUMIF('BAL N'!I:I,"=45",'BAL N'!C:C)+SUMIF('BAL N'!I:I,"=46",'BAL N'!C:C)+SUMIF('BAL N'!K:K,"=4711",'BAL N'!C:C)+SUMIF('BAL N'!J:J,"=475",'BAL N'!C:C)+SUMIF('BAL N'!J:J,"=476",'BAL N'!C:C)-(SUMIF('BAL N'!J:J,"=492",'BAL N'!D:D)+SUMIF('BAL N'!J:J,"=493",'BAL N'!D:D)+SUMIF('BAL N'!J:J,"=495",'BAL N'!D:D)+SUMIF('BAL N'!J:J,"=496",'BAL N'!D:D)+SUMIF('BAL N'!J:J,"=497",'BAL N'!D:D))-SUMIF('BAL N'!K:K,"=4711",'BAL N'!D:D) -> 0 | H29: DN | I29: Provisions pour risques à court terme | J29: 19 | K29: =+SUMIF('BAL N'!J:J,"=499",'BAL N'!H:H)+SUMIF('BAL N'!J:J,"=599",'BAL N'!H:H)-SUMIF('BAL N'!K:K,"=4998",'BAL N'!H:H) -> 0 | L29: =+SUMIF('BAL N'!J:J,"=499",'BAL N'!D:D)+SUMIF('BAL N'!J:J,"=599",'BAL N'!D:D)-SUMIF('BAL N'!K:K,"=4998",'BAL N'!D:D) -> 0
A30: BK | B30: TOTAL ACTIF CIRCULANT | D30: =SUM(D24:D29) -> 0 | E30: =SUM(E24:E29) -> 0 | F30: =SUM(F24:F29) -> 0 | G30: =SUM(G24:G29) -> 0 | H30: DP | I30: TOTAL PASSIF CIRCULANT | K30: =SUM(K24:K29) -> 0 | L30: =SUM(L24:L29) -> 0
A31: BQ | B31: Titres de placement | C31: 9 | D31: =+SUMIF('BAL N'!I:I,"=50",'BAL N'!G:G) -> 0 | E31: =+SUMIF('BAL N'!J:J,"=590",'BAL N'!H:H) -> 0 | F31: =+D31-E31 -> 0 | G31: =+SUMIF('BAL N'!I:I,"=59",'BAL N'!C:C)-SUMIF('BAL N'!J:J,"=590",'BAL N'!D:D) -> 0
A32: BR | B32: Valeurs à encaisser | C32: 10 | D32: =+SUMIF('BAL N'!I:I,"=51",'BAL N'!G:G) -> 0 | E32: =+SUMIF('BAL N'!J:J,"=591",'BAL N'!H:H) -> 0 | F32: =+D32-E32 -> 0 | G32: =+SUMIF('BAL N'!I:I,"=51",'BAL N'!C:C)-SUMIF('BAL N'!J:J,"=591",'BAL N'!D:D) -> 0 | H32: DQ | I32: Banques, crédits d'escompte | J32: 20 | K32: =+SUMIF('BAL N'!J:J,"=564",'BAL N'!H:H)+SUMIF('BAL N'!J:J,"=565",'BAL N'!H:H) -> 0 | L32: =+SUMIF('BAL N'!J:J,"=564",'BAL N'!D:D)+SUMIF('BAL N'!J:J,"=565",'BAL N'!D:D) -> 0
A33: BS | B33: Banques, chèques postaux, caisse et assimilés | C33: 11 | D33: =SUMIF('BAL N'!I:I,"=52",'BAL N'!G:G)+SUMIF('BAL N'!I:I,"=53",'BAL N'!G:G)+SUMIF('BAL N'!I:I,"=54",'BAL N'!G:G)+SUMIF('BAL N'!I:I,"=55",'BAL N'!G:G)+SUMIF('BAL N'!I:I,"=57",'BAL N'!G:G)+SUMIF('BAL N'!J:J,"=581",'BAL N'!G:G)+SUMIF('BAL N'!J:J,"=582",'BAL N'!G:G) -> 0 | E33: =+SUMIF('BAL N'!J:J,"=592",'BAL N'!H:H)+SUMIF('BAL N'!J:J,"=593",'BAL N'!H:H)+SUMIF('BAL N'!J:J,"=594",'BAL N'!H:H) -> 0 | F33: =+D33-E33 -> 0 | G33: =SUMIF('BAL N'!I:I,"=52",'BAL N'!C:C)+SUMIF('BAL N'!I:I,"=57",'BAL N'!C:C)+SUMIF('BAL N'!I:I,"=58",'BAL N'!C:C)+SUMIF('BAL N'!I:I,"=55",'BAL N'!C:C)+SUMIF('BAL N'!I:I,"=54",'BAL N'!C:C)+SUMIF('BAL N'!I:I,"=53",'BAL N'!C:C)-SUMIF('BAL N'!J:J,"=592",'BAL N'!D:D) -> 0 | H33: DR | I33: Banques, établissements financiers et crédits de trésorerie | J33: 20 | K33: =+SUMIF('BAL N'!I:I,"=52",'BAL N'!H:H)+SUMIF('BAL N'!I:I,"=53",'BAL N'!H:H)+SUMIF('BAL N'!J:J,"=561",'BAL N'!H:H)+SUMIF('BAL N'!J:J,"=566",'BAL N'!H:H) -> 0 | L33: =+SUMIF('BAL N'!I:I,"=52",'BAL N'!D:D)+SUMIF('BAL N'!J:J,"=561",'BAL N'!D:D)+SUMIF('BAL N'!J:J,"=566",'BAL N'!D:D) -> 0
A34: BT | B34: TOTAL TRESORERIE - ACTIF | D34: =SUM(D31:D33) -> 0 | E34: =SUM(E31:E33) -> 0 | F34: =SUM(F31:F33) -> 0 | G34: =SUM(G31:G33) -> 0 | H34: DT | I34: TOTAL TRESORERIE - PASSIF | K34: =+K32+K33 -> 0 | L34: =+L32+L33 -> 0
A35: BU | B35: Ecarts de conversion - Actif | C35: 12 | D35: =+SUMIF('BAL N'!J:J,"=478",'BAL N'!G:G) -> 0 | G35: =+SUMIF('BAL N'!J:J,"=478",'BAL N'!C:C) -> 0 | H35: DV | I35: Ecarts de conversion - Passif | J35: 12 | K35: =+SUMIF('BAL N'!J:J,"=479",'BAL N'!H:H) -> 0 | L35: =+SUMIF('BAL N'!J:J,"=479",'BAL N'!D:D) -> 0
A36: BZ | B36: TOTAL GENERAL | D36: =+D34+D30+D23 -> 0 | E36: =+E34+E30+E23 -> 0 | F36: =+F34+F30+F23 -> 0 | G36: =+G34+G30+G23 -> 0 | H36: DZ | I36: TOTAL GENERAL | K36: =+K34+K30+K22+K18 -> 0 | L36: =+L34+L30+L22+L18 -> 0

Sheet COMPTE DE RESULTAT
A1: COMPTE DE RESULTAT
A3: Désignation entité : | B3: ='Fiche de renseignement R1'!$J$4 -> 0 | D3: Excercice clos le : | E3: =+'Fiche de renseignement R1'!$V$10 -> 0
A4: Numéro d'identification : | B4: =+'Fiche de renseignement R1'!$J$10 -> 0 | D4: Durée en mois : | E4: =+'Fiche de renseignement R1'!$AH$10 -> 12
A6: REF | B6: LIBELLES | D6: NOTE | E6: =IFERROR("31/12/"&YEAR('Fiche de renseignement R1'!V10),"Exercice au 31/12/N") -> 31/12/1900 | F6: =IFERROR("31/12/"&YEAR('Fiche de renseignement R1'!Q20),"Exercice au 31/12/N-1") -> 31/12/2020
A7: TA | B7: Ventes de marchandises A | C7: + | D7: 21 | E7: =+SUMIF('BAL N'!J:J,"=701",'BAL N'!H:H) -> 0 | F7: =+SUMIF('BAL N-1'!J:J,"=701",'BAL N-1'!H:H) -> 0
A8: RA | B8: Achats de marchandises | C8: - | D8: 22 | E8: =+SUMIF('BAL N'!J:J,"=601",'BAL N'!G:G) -> 0 | F8: =+SUMIF('BAL N-1'!J:J,"=601",'BAL N-1'!G:G) -> 0
A9: RB | B9: Variation de stocks de marchandises | C9: -/+ | D9: 6 | E9: =-(+SUMIF('BAL N'!K:K,"=6031",'BAL N'!H:H)-SUMIF('BAL N'!K:K,"=6031",'BAL N'!G:G)) -> 0 | F9: =-(+SUMIF('BAL N-1'!K:K,"=6031",'BAL N-1'!H:H)-SUMIF('BAL N-1'!K:K,"=6031",'BAL N-1'!G:G)) -> 0
A10: XA | B10: MARGE BRUTE SUR MARCHANDISES (somme TA à RB) | E10: =+E14-E8-E9 -> 0 | F10: =+F14-F8-F9 -> 0
A11: TB | B11: Ventes de produits fabriqués B | C11: + | D11: 21 | E11: =+SUMIF('BAL N'!J:J,"=702",'BAL N'!H:H)+SUMIF('BAL N'!J:J,"=703",'BAL N'!H:H)+SUMIF('BAL N'!J:J,"=704",'BAL N'!H:H) -> 0 | F11: =+SUMIF('BAL N-1'!J:J,"=702",'BAL N-1'!H:H)+SUMIF('BAL N-1'!J:J,"=703",'BAL N-1'!H:H)+SUMIF('BAL N-1'!J:J,"=704",'BAL N-1'!H:H) -> 0
A12: TC | B12: Travaux, services vendus C | C12: + | D12: 21 | E12: =+SUMIF('BAL N'!J:J,"=705",'BAL N'!H:H)+SUMIF('BAL N'!J:J,"=706",'BAL N'!H:H) -> 0 | F12: =+SUMIF('BAL N-1'!J:J,"=705",'BAL N-1'!H:H)+SUMIF('BAL N-1'!J:J,"=706",'BAL N-1'!H:H) -> 0
A13: TD | B13: Produits accessoires D | C13: + | D13: 21 | E13: =+SUMIF('BAL N'!J:J,"=707",'BAL N'!H:H) -> 0 | F13: =+SUMIF('BAL N-1'!J:J,"=707",'BAL N-1'!H:H) -> 0
A14: XB | B14: CHIFFRE D'AFFAIRES (A + B + C + D) | E14: =+E7+E13+E12+E11 -> 0 | F14: =+F7+F13+F12+F11 -> 0
A15: TE | B15: Production stockée (ou destockage) | C15: -/+ | D15: 6 | E15: =+SUMIF('BAL N'!I:I,"=73",'BAL N'!H:H) -> 0 | F15: =+SUMIF('BAL N-1'!I:I,"=73",'BAL N-1'!H:H) -> 0
A16: TF | B16: Production immobilisée | D16: 21 | E16: =+SUMIF('BAL N'!I:I,"=72",'BAL N'!H:H) -> 0 | F16: =+SUMIF('BAL N-1'!I:I,"=72",'BAL N-1'!H:H) -> 0
A17: TG | B17: Subventions d'exploitation | D17: 21 | E17: =+SUMIF('BAL N'!I:I,"=71",'BAL N'!H:H) -> 0 | F17: =+SUMIF('BAL N-1'!I:I,"=71",'BAL N-1'!H:H) -> 0
A18: TH | B18: Autres produits | C18: + | D18: 21 | E18: =+SUMIF('BAL N'!I:I,"=75",'BAL N'!H:H) -> 0 | F18: =+SUMIF('BAL N-1'!I:I,"=75",'BAL N-1'!H:H) -> 0
A19: TI | B19: Transferts de charges d'exploitation | C19: + | D19: 12 | E19: =+SUMIF('BAL N'!J:J,"=781",'BAL N'!H:H) -> 0 | F19: =+SUMIF('BAL N-1'!J:J,"=781",'BAL N-1'!H:H) -> 0
A20: RC | B20: Achats de matières premières et fournitures liées | C20: - | D20: 22 | E20: =+SUMIF('BAL N'!J:J,"=602",'BAL N'!G:G) -> 0 | F20: =+SUMIF('BAL N-1'!J:J,"=602",'BAL N-1'!G:G) -> 0
A21: RD | B21: Variation de stocks de stocks de matières premières et fournitures liées | C21: -/+ | D21: 6 | E21: =-SUMIF('BAL N'!K:K,"=6032",'BAL N'!H:H)+SUMIF('BAL N'!K:K,"=6032",'BAL N'!G:G)-SUMIF('BAL N'!K:K,"=6034",'BAL N'!H:H)+SUMIF('BAL N'!K:K,"=6034",'BAL N'!G:G) -> 0 | F21: =-SUMIF('BAL N-1'!K:K,"=6032",'BAL N-1'!H:H)+SUMIF('BAL N-1'!K:K,"=6032",'BAL N-1'!G:G)-SUMIF('BAL N-1'!K:K,"=6034",'BAL N-1'!H:H)+SUMIF('BAL N-1'!K:K,"=6034",'BAL N-1'!G:G) -> 0
A22: RE | B22: Autres achats | C22: - | D22: 22 | E22: =+SUMIF('BAL N'!J:J,"=604",'BAL N'!G:G)+SUMIF('BAL N'!J:J,"=605",'BAL N'!G:G)+SUMIF('BAL N'!J:J,"=608",'BAL N'!G:G)+SUMIF('BAL N'!J:J,"=606",'BAL N'!G:G) -> 0 | F22: =+SUMIF('BAL N-1'!J:J,"=604",'BAL N-1'!G:G)+SUMIF('BAL N-1'!J:J,"=605",'BAL N-1'!G:G)+SUMIF('BAL N-1'!J:J,"=608",'BAL N-1'!G:G)+SUMIF('BAL N-1'!J:J,"=606",'BAL N-1'!G:G) -> 0
A23: RF | B23: Variation de stocks d'autres approvisionnements | C23: -/+ | D23: 6 | E23: =+SUMIF('BAL N'!K:K,"=6033",'BAL N'!H:H)-SUMIF('BAL N'!K:K,"=6033",'BAL N'!G:G) -> 0 | F23: =+SUMIF('BAL N-1'!K:K,"=6033",'BAL N-1'!H:H)-SUMIF('BAL N-1'!K:K,"=6033",'BAL N-1'!G:G) -> 0
A24: RG | B24: Transports | C24: - | D24: 23 | E24: =+SUMIF('BAL N'!I:I,"=61",'BAL N'!G:G) -> 0 | F24: =+SUMIF('BAL N-1'!I:I,"=61",'BAL N-1'!G:G) -> 0
A25: RH | B25: Services extérieurs | C25: - | D25: 24 | E25: =+SUMIF('BAL N'!I:I,"=62",'BAL N'!G:G)+SUMIF('BAL N'!I:I,"=63",'BAL N'!G:G) -> 0 | F25: =+SUMIF('BAL N-1'!I:I,"=62",'BAL N-1'!G:G)+SUMIF('BAL N-1'!I:I,"=63",'BAL N-1'!G:G) -> 0
A26: RI | B26: Impôts et taxes | C26: - | D26: 25 | E26: =+SUMIF('BAL N'!I:I,"=64",'BAL N'!G:G) -> 0 | F26: =+SUMIF('BAL N-1'!I:I,"=64",'BAL N-1'!G:G) -> 0
A27: RJ | B27: Autres charges | C27: - | D27: 26 | E27: =+SUMIF('BAL N'!I:I,"=65",'BAL N'!G:G) -> 0 | F27: =+SUMIF('BAL N-1'!I:I,"=65",'BAL N-1'!G:G) -> 0
A28: XC | B28: VALEUR AJOUTEE (XB + RA + RB) + (somme TE à RJ) | E28: =+E10+E15+E16+E17+E18+E19-E20-E21-E22-E23-E24-E25-E26-E27 -> 0 | F28: =+F10+F15+F16+F17+F18+F19-F20-F21-F22-F23-F24-F25-F26-F27 -> 0
A29: RK | B29: Charges de personnel | C29: - | D29: 27 | E29: =+SUMIF('BAL N'!I:I,"=66",'BAL N'!G:G) -> 0 | F29: =+SUMIF('BAL N-1'!I:I,"=66",'BAL N-1'!G:G) -> 0
A30: XD | B30: EXCEDENT BRUT D'EXPLOITATION (XC + RK) | E30: =+E28-E29 -> 0 | F30: =+F28-F29 -> 0
A31: TJ | B31: Reprises d'amortissements, provisions et dépréciations | C31: + | D31: 28 | E31: =+SUMIF('BAL N'!J:J,"=791",'BAL N'!H:H)+SUMIF('BAL N'!J:J,"=798",'BAL N'!H:H)+SUMIF('BAL N'!J:J,"=799",'BAL N'!H:H) -> 0 | F31: =+SUMIF('BAL N-1'!J:J,"=791",'BAL N-1'!H:H)+SUMIF('BAL N-1'!J:J,"=798",'BAL N-1'!H:H)+SUMIF('BAL N-1'!J:J,"=799",'BAL N-1'!H:H) -> 0
A32: RL | B32: Dotations aux amortissements, aux provisions et dépréciations | C32: - | D32: 3C & 28 | E32: =+SUMIF('BAL N'!J:J,"=681",'BAL N'!G:G)+SUMIF('BAL N'!J:J,"=691",'BAL N'!G:G) -> 0 | F32: =+SUMIF('BAL N-1'!J:J,"=681",'BAL N-1'!G:G)+SUMIF('BAL N-1'!J:J,"=691",'BAL N-1'!G:G) -> 0
A33: XE | B33: RESULTAT D'EXPLOITATION (XD + TJ + RL) | E33: =+E30+E31-E32 -> 0 | F33: =+F30+F31-F32 -> 0
A34: TK | B34: Revenus financiers et assimilés | C34: + | D34: 29 | E34: =+SUMIF('BAL N'!I:I,"=77",'BAL N'!H:H) -> 0 | F34: =+SUMIF('BAL N-1'!I:I,"=77",'BAL N-1'!H:H) -> 0
A35: TL | B35: Reprises de provisions et dépréciations financières | C35: + | D35: 28 | E35: =+SUMIF('BAL N'!J:J,"=797",'BAL N'!H:H) -> 0 | F35: =+SUMIF('BAL N-1'!J:J,"=797",'BAL N-1'!H:H) -> 0
A36: TM | B36: Tranferts de charges financières | C36: + | D36: 12 | E36: =+SUMIF('BAL N'!J:J,"=787",'BAL N'!H:H) -> 0 | F36: =+SUMIF('BAL N-1'!J:J,"=787",'BAL N-1'!H:H) -> 0
A37: RM | B37: Frais financiers et charges assimilées | C37: - | D37: 29 | E37: =+SUMIF('BAL N'!I:I,"=67",'BAL N'!G:G) -> 0 | F37: =+SUMIF('BAL N-1'!I:I,"=67",'BAL N-1'!G:G) -> 0
A38: RN | B38: Dotations aux provisions et aux dépréciations financières | C38: - | D38: 3C & 28 | E38: =SUMIF('BAL N'!J:J,"=697",'BAL N'!G:G) -> 0 | F38: =+SUMIF('BAL N-1'!J:J,"=697",'BAL N-1'!G:G) -> 0
A39: XF | B39: RESULTAT FINANCIER (somme TK à RN) | E39: =+E34+E35+E36-E37-E38 -> 0 | F39: =+F34+F35+F36-F37-F38 -> 0
A40: XG | B40: RESULTAT DES ACTIVITES ORDINAIRES (XE + XF) | E40: =+E33+E39 -> 0 | F40: =+F33+F39 -> 0
A41: TN | B41: Produits des cessions d'immobilisations | C41: + | D41: 3D | E41: =+SUMIF('BAL N'!I:I,"=82",'BAL N'!H:H) -> 0 | F41: =+SUMIF('BAL N-1'!I:I,"=82",'BAL N-1'!H:H) -> 0
A42: TO | B42: Autres produits H.A.O. | C42: + | D42: 30 | E42: =+SUMIF('BAL N'!I:I,"=84",'BAL N'!H:H)+SUMIF('BAL N'!I:I,"=86",'BAL N'!H:H)+SUMIF('BAL N'!I:I,"=88",'BAL N'!H:H) -> 0 | F42: =+SUMIF('BAL N-1'!I:I,"=84",'BAL N-1'!H:H)+SUMIF('BAL N-1'!I:I,"=86",'BAL N-1'!H:H) -> 0
A43: RO | B43: Valeurs comptables des cessions d'immobilisations | C43: - | D43: 3D | E43: =+SUMIF('BAL N'!I:I,"=81",'BAL N'!G:G) -> 0 | F43: =+SUMIF('BAL N-1'!I:I,"=81",'BAL N-1'!G:G) -> 0
A44: RP | B44: Autres charges H.A.O. | C44: - | D44: 30 | E44: =+SUMIF('BAL N'!I:I,"=83",'BAL N'!G:G)+SUMIF('BAL N'!I:I,"=85",'BAL N'!G:G) -> 0 | F44: =+SUMIF('BAL N-1'!I:I,"=83",'BAL N-1'!G:G)+SUMIF('BAL N-1'!I:I,"=85",'BAL N-1'!G:G) -> 0
A45: XH | B45: RESULTAT HORS ACTIVITES ORDINAIRES (somme TN à RP) | E45: =+E41+E42-E43-E44 -> 0 | F45: =+F41+F42-F43-F44 -> 0
A46: RQ | B46: Participation des travailleurs | C46: - | D46: 30 | E46: =+SUMIF('BAL N'!I:I,"=87",'BAL N'!G:G) -> 0 | F46: =+SUMIF('BAL N-1'!I:I,"=87",'BAL N-1'!G:G) -> 0
A47: RS | B47: Impôts sur le résultat | C47: - | E47: =+SUMIF('BAL N'!I:I,"=89",'BAL N'!G:G) -> 0 | F47: =+SUMIF('BAL N-1'!I:I,"=89",'BAL N-1'!G:G) -> 0
A48: XI | B48: RESULTAT NET (XG + XH + RQ + RS) | E48: =+E40+E45-E46-E47 -> 0 | F48: =+F40+F45-F46-F47 -> 0

Sheet FLUX DE TRESORERIE
A1: FLUX DE TRESORERIE
A3: Désignation entité : | B3: ='Fiche de renseignement R1'!$J$4 -> 0 | D3: Excercice clos le : | E3: =+'Fiche de renseignement R1'!$V$10 -> 0
A4: Numéro d'identification : | B4: =+'Fiche de renseignement R1'!$J$10 -> 0 | D4: Durée en mois : | E4: =+'Fiche de renseignement R1'!$AH$10 -> 12
A6: REF | B6: LIBELLES | D6: NOTE | E6: =IFERROR("31/12/"&YEAR('Fiche de renseignement R1'!V10),"Exercice au 31/12/N") -> 31/12/1900 | F6: =IFERROR("31/12/"&YEAR('Fiche de renseignement R1'!Q20),"Exercice au 31/12/N-1") -> 31/12/2020
A7: ZA | B7: Trésorerie nette au 1er janvier (Trésorerie actif N-1 - Trésorerie passif N-1) | C7: A | E7: ='BILAN PAYSAGE'!F34-'BILAN PAYSAGE'!K34 -> 0 | F7: -
B8: Flux de trésorerie provenant des activités opérationnelles
A9: FA | B9: Capacité d'Autofinancement Globale (CAFG) | E9: ='COMPTE DE RESULTAT'!E48+'COMPTE DE RESULTAT'!E32-'COMPTE DE RESULTAT'!E31-'COMPTE DE RESULTAT'!E45 -> 0 | F9: -
A10: FB | B10: - Variation d'actif circulant HAO (1)
A11: FC | B11: - Variation des stocks | E11: =+'BILAN PAYSAGE'!F25-'BILAN PAYSAGE'!G25 -> 0 | F11: -
A12: FD | B12: - Variation des créances | E12: =+('BILAN PAYSAGE'!F27-'BILAN PAYSAGE'!G27)+('BILAN PAYSAGE'!F28-'BILAN PAYSAGE'!G28)+('BILAN PAYSAGE'!F29-'BILAN PAYSAGE'!G29) -> 0 | F12: -
A13: FE | B13: + Variation du passif circulant (1) | E13: =+'BILAN PAYSAGE'!K30-'BILAN PAYSAGE'!L30 -> 0 | F13: -
B14: Variation du BF lié aux activités opérationnelles (FB + FC + FD + FE) : ……………………………………………..
A15: ZB | B15: Flux de trésorerie provenant des activités opérationnelles (somme FA à FE) | C15: B | E15: =+E9-E10-E11-E12+E13 -> 0 | F15: =IFERROR(+F9-F10-F11-F12+F13,0) -> 0
B16: Flux de trésorerie provenant des activités d'investissement
A17: FF | B17: - Décaissements liés aux acquisitions d'immobilisations incorporelles | E17: =+SUMIF('BAL N'!J:J,"=211",'BAL N'!E:E)+SUMIF('BAL N'!J:J,"=212",'BAL N'!E:E)+SUMIF('BAL N'!J:J,"=213",'BAL N'!E:E)+SUMIF('BAL N'!J:J,"=214",'BAL N'!E:E)+SUMIF('BAL N'!J:J,"=215",'BAL N'!E:E)+SUMIF('BAL N'!J:J,"=216",'BAL N'!E:E)+SUMIF('BAL N'!J:J,"=217",'BAL N'!E:E)+SUMIF('BAL N'!J:J,"=218",'BAL N'!E:E) -> 0 | F17: -
A18: FG | B18: - Décaissements liés aux acquisitions d'immobilisations corporelles | E18: =+SUMIF('BAL N'!I:I,"=22",'BAL N'!E:E)+SUMIF('BAL N'!I:I,"=23",'BAL N'!E:E)+SUMIF('BAL N'!I:I,"=24",'BAL N'!E:E) -> 0 | F18: -
A19: FH | B19: - Décaissements liés aux acquisitions d'immobilisations financières | E19: =(+SUMIF('BAL N'!I:I,"=25",'BAL N'!E:E)+SUMIF('BAL N'!I:I,"=26",'BAL N'!E:E)+SUMIF('BAL N'!I:I,"=27",'BAL N'!E:E)) -> 0 | F19: -
A20: FI | B20: + Encaissements liés aux cessions d'immobilisations incorporelles et corporelles | E20: =+SUMIF('BAL N'!I:I,"=82",'BAL N'!H:H) -> 0 | F20: -
A21: FJ | B21: + Encaissements liés aux cessions d'immobilisations financières
A22: ZC | B22: Flux de trésorerie provenant des activités d'investissement (somme FF à FJ) | C22: C | E22: =-E17-E18-E19+E20+E21 -> 0 | F22: =IFERROR(-F17-F18-F19+F20+F21,0) -> 0
B23: Flux de trésorerie provenant du financement par les capitaux propres
A24: FK | B24: + Augmentations de capital par apports nouveaux
A25: FL | B25: + Subventions d'investissements reçues | E25: =+SUMIF('BAL N'!I:I,"=14",'BAL N'!F:F) -> 0 | F25: -
A26: FM | B26: - Prélèvements sur le capital
A27: FN | B27: - Dividendes versés
A28: ZD | B28: Flux de trésorerie provenant des capitaux propres (somme FK à FN) | C28: D | E28: =+E24+E25-E26-E27 -> 0 | F28: =IFERROR(+F24+F25-F26-F27,0) -> 0
B29: Flux de trésorerie provenant du financement par les capitaux étrangers
A30: FO | B30: + Emprunts | E30: =+SUMIF('BAL N'!J:J,"=161",'BAL N'!F:F)+SUMIF('BAL N'!J:J,"=162",'BAL N'!F:F)+SUMIF('BAL N'!K:K,"=1661",'BAL N'!F:F)+SUMIF('BAL N'!K:K,"=1662",'BAL N'!F:F) -> 0 | F30: -
A31: FP | B31: + Autres dettes financières | E31: =+SUMIF('BAL N'!I:I,"=17",'BAL N'!H:H) -> 0 | F31: -
A32: FQ | B32: - Remboursements des emprunts et autres dettes financières | E32: =+SUMIF('BAL N'!I:I,"=16",'BAL N'!E:E)+SUMIF('BAL N'!I:I,"=17",'BAL N'!E:E)+SUMIF('BAL N'!I:I,"=18",'BAL N'!E:E) -> 0 | F32: -
A33: ZE | B33: Flux de trésorerie provenant des capitaux étrangers (somme FO à FQ) | C33: E | E33: =+E30+E31-E32 -> 0 | F33: =IFERROR(+F30+F31-F32,0) -> 0
A34: ZF | B34: Flux de trésorerie provenant des activités de financement (D + E) | C34: F | E34: =+E28+E33 -> 0 | F34: =+F28+F33 -> 0
A35: ZG | B35: VARIATION DE LA TRESORERIE NETTE DE LA PERIODE (B + C + F) | C35: G | E35: =+E34+E22+E15 -> 0 | F35: =IFERROR(+F34+F22+F15,0) -> 0
A36: ZH | B36: Trésorerie nette au 31 décembre (G + A) Contrôle : Trésorerie actif N - Trésorerie passif N | C36: H | E36: =+E35+E7 -> 0 | F36: =IFERROR(+F35+F7,0) -> 0
B37: Contrôle

Sheet Note 1
A1: NOTE 1 : DETTES GARANTIES PAR DES SURETES REELLES
A3: Désignation entité : | B3: ='Fiche de renseignement R1'!$J$4 -> 0 | D3: Excercice clos le : | E3: =+'Fiche de renseignement R1'!$V$10 -> 0
A4: Numéro d'identification : | B4: =+'Fiche de renseignement R1'!$J$10 -> 0 | D4: Durée en mois : | E4: =+'Fiche de renseignement R1'!$AH$10 -> 12
A7: LIBELLES | B7: Note | C7: Montant brut | D7: SURETES REELLES
D8: Hypothèques | E8: Nantissements | F8: Gages
F9: Autres
A10: Dettes financières et ressources assimilées :
A11: Emprunts obligataires convertibles | C11: =+SUMIF('BAL N'!K:K,"=1612",'BAL N'!H:H) -> 0
A12: Autres emprunts obligataires | C12: =+SUMIF('BAL N'!K:K,"=1618",'BAL N'!H:H) -> 0
A13: Emprunts et dettes des établissements de crédit | C13: =+SUMIF('BAL N'!J:J,"=162",'BAL N'!H:H) -> 0
A14: Autres dettes financières | C14: =+SUMIF('BAL N'!J:J,"=163",'BAL N'!H:H)+SUMIF('BAL N'!J:J,"=164",'BAL N'!H:H)+SUMIF('BAL N'!J:J,"=165",'BAL N'!H:H)+SUMIF('BAL N'!J:J,"=167",'BAL N'!H:H)+SUMIF('BAL N'!J:J,"=168",'BAL N'!H:H) -> 0
A15: SOUS TOTAL (1) | C15: =SUM(C11:C14) -> 0 | D15: =SUM(D11:D14) -> 0 | E15: =SUM(E11:E14) -> 0 | F15: =SUM(F11:F14) -> 0
A17: Dettes de location-acquisition :
A18: Dettes de crédit-bail immobilier | C18: =+SUMIF('BAL N'!J:J,"=172",'BAL N'!H:H) -> 0
A19: Dettes de crédit-bail mobilier | C19: =+SUMIF('BAL N'!J:J,"=173",'BAL N'!H:H) -> 0
A20: Dettes sur contrats de location-vente | C20: =+SUMIF('BAL N'!J:J,"=174",'BAL N'!H:H) -> 0
A21: Dettes sur contrats de location-acquisition | C21: =+SUMIF('BAL N'!J:J,"=176",'BAL N'!H:H) -> 0
A22: SOUS TOTAL (2) | C22: =SUM(C18:C21) -> 0 | D22: =SUM(D18:D21) -> 0 | E22: =SUM(E18:E21) -> 0 | F22: =SUM(F18:F21) -> 0
A24: Dettes du passif circulant :
A25: Fournisseurs et comptes rattachés | C25: =+SUMIF('BAL N'!I:I,"=40",'BAL N'!H:H)-SUMIF('BAL N'!J:J,"=409",'BAL N'!H:H) -> 0
A26: Clients | C26: =SUMIF('BAL N'!J:J,"=419",'BAL N'!H:H) -> 0
A27: Personnel | C27: =+SUMIF('BAL N'!I:I,"=42",'BAL N'!H:H) -> 0
A28: Sécurité sociale et organismes sociaux | C28: =+SUMIF('BAL N'!I:I,"=43",'BAL N'!H:H) -> 0
A29: Etat | C29: =+SUMIF('BAL N'!I:I,"=44",'BAL N'!H:H) -> 0
A30: Organismes internationaux | C30: =+SUMIF('BAL N'!I:I,"=45",'BAL N'!H:H) -> 0
A31: Associés et groupe | C31: =+SUMIF('BAL N'!I:I,"=46",'BAL N'!H:H) -> 0
A32: Créditeurs divers | C32: =+SUMIF('BAL N'!I:I,"=47",'BAL N'!H:H) -> 0
A33: SOUS TOTAL (3) | C33: =SUM(C25:C32) -> 0 | D33: =SUM(D25:D32) -> 0 | E33: =SUM(E25:E32) -> 0 | F33: =SUM(F25:F32) -> 0
A34: TOTAL (1) + (2) + (3) | C34: =+C15+C22+C33 -> 0 | D34: =+D15+D22+D33 -> 0 | E34: =+E15+E22+E33 -> 0 | F34: =+F15+F22+F33 -> 0
A35: ENGAGEMENTS FINANCIERS | E35: Engagements donnés | F35: Engagements reçus
A36: Engagements consentis à des entités liées
A37: Primes de remboursement non échus
A38: Avals, cautions, garanties
A39: Hypothèques, nantissements, gages, autres
A40: Effets escomptés non échus
A41: Créances commerciales et professionnelles cédées
A42: Abandons de créances conditionnels
A43: TOTAL | E43: =SUM(E36:E42) -> 0 | F43: =SUM(F36:F42) -> 0
A44: Commentaire :
A45: · Indiquer la raison d’être des suretés

Sheet Note 2
A1: NOTE 2 : INFORMATIONS OBLIGATOIRES
A3: Désignation entité : | B3: ='Fiche de renseignement R1'!$J$4 -> 0 | C3: Excercice clos le : | D3: =+'Note 1'!E3 -> 0
A4: Numéro d'identification : | B4: =+'Note 1'!B4 -> 0 | C4: Durée en mois : | D4: =+'Note 1'!E5 -> 0
A6: A - DECLARATION DE CONFORMITE AU SYSCOHADA
A7: Les états financiers sont établis en conformité avec le systéme comptable OHADA et l'acte uniforme relatif au droit comptable et à l'information financiére
A8: B - REGLES ET METHODES COMPTABLES
A9: Les états financiers ont été confectionnés dans le respect des postulats, des conventions et des régles d'évaluation édictés par le SYSCOHADA et l'Acte Uniforme
A10: C - DEROGATION AUX POSTULATS ET CONVENTIONS COMPTABLES
A11: Respect de tous les postulats et conventions comptables sans aucune dérogation
A12: D - INFORMATIONS COMPLEMENTAIRES RELATIVES AU BILAN, AU COMPTE DE RESULTAT ET AU TABLEAU DES FLUX DE TRESORERIE
A13: Pas d'informations complémentaires relatives aux autres états financiers

Sheet Note 3A
A1: NOTE 3A : IMMOBILISATION BRUTE
A3: Désignation entité : | B3: ='Fiche de renseignement R1'!$J$4 -> 0 | E3: Excercice clos le : | G3: =+'Note 1'!G3 -> 0
A4: Numéro d'identification : | B4: =+'Note 1'!B4 -> 0 | E4: Durée en mois : | G4: =+'Note 1'!E4 -> 12
A7: SITUATIONS ET MOUVEMENTS | B7: Montant brut à l'ouverture de l'exercice | C7: Acquisitions Apports Créations | D7: Virements de poste à poste | E7: Suite à une réévaluation pratiquée au cours de l'exercice | F7: Cessions Scissions Hors service | G7: Virements de poste à poste | H7: Montant brut à la clôture de l'exercice
A10: IMMOBILISATIONS INCORPORELLES
A11: Frais de développement et de prospection | B11: =+SUMIF('BAL N'!J:J,"=211",'BAL N'!G:G) -> 0 | H11: =+B11+C11+D11+E11-F11-G11 -> 0
A12: Brevets, licences, logiciels et droits similaires | B12: =+SUMIF('BAL N'!J:J,"=212",'BAL N'!G:G)+SUMIF('BAL N'!J:J,"=213",'BAL N'!G:G) -> 0 | H12: =+B12+C12+D12+E12-F12-G12 -> 0
A13: Fonds commercial et droit au bail | B13: =+SUMIF('BAL N'!J:J,"=215",'BAL N'!G:G) -> 0 | H13: =+B13+C13+D13+E13-F13-G13 -> 0
A14: Autres immobilisations incorporelles | B14: =+SUMIF('BAL N'!J:J,"=214",'BAL N'!G:G)+SUMIF('BAL N'!J:J,"=216",'BAL N'!G:G)+SUMIF('BAL N'!J:J,"=217",'BAL N'!G:G)+SUMIF('BAL N'!J:J,"=218",'BAL N'!G:G)+SUMIF('BAL N'!J:J,"=219",'BAL N'!G:G) -> 0 | H14: =+B14+C14+D14+E14-F14-G14 -> 0
A15: IMMOBILISATIONS CORPORELLES
A16: Terrains hors immeuble de placement | B16: =+SUMIF('BAL N'!I:I,"=22",'BAL N'!G:G)-SUMIF('BAL N'!J:J,"=228",'BAL N'!G:G) -> 0 | H16: =+B16+C16+D16+E16-F16-G16 -> 0
A17: Terrains immeuble de placement | B17: =+SUMIF('BAL N'!J:J,"=228",'BAL N'!G:G) -> 0 | H17: =+B17+C17+D17+E17-F17-G17 -> 0
A18: Bâtiments hors immeuble de placement | B18: =+SUMIF('BAL N'!I:I,"=23",'BAL N'!G:G)-SUMIF('BAL N'!K:K,"=2315",'BAL N'!G:G)-SUMIF('BAL N'!K:K,"=2325",'BAL N'!G:G) -> 0 | H18: =+B18+C18+D18+E18-F18-G18 -> 0
A19: Bâtiments immeuble de placement | B19: =+SUMIF('BAL N'!K:K,"=2315",'BAL N'!G:G)+SUMIF('BAL N'!K:K,"=2325",'BAL N'!G:G) -> 0 | H19: =+B19+C19+D19+E19-F19-G19 -> 0
A20: Aménagements, agencements et installations | B20: =+SUMIF('BAL N'!J:J,"=234",'BAL N'!G:G)+SUMIF('BAL N'!J:J,"=235",'BAL N'!G:G) -> 0 | H20: =+B20+C20+D20+E20-F20-G20 -> 0
A21: Matériel, mobilier et actifs biologiques | B21: =+SUMIF('BAL N'!I:I,"=24",'BAL N'!G:G)-SUMIF('BAL N'!J:J,"=245",'BAL N'!G:G) -> 0 | H21: =+B21+C21+D21+E21-F21-G21 -> 0
A22: Matériel de transport | B22: =+SUMIF('BAL N'!J:J,"=245",'BAL N'!G:G) -> 0 | H22: =+B22+C22+D22+E22-F22-G22 -> 0
A23: AVANCES ET ACOMPTES VERSES SUR IMMOBILISATIONS
A24: IMMOBILISATIONS FINANCIERES
A25: Titres de participation | B25: =+SUMIF('BAL N'!I:I,"=26",'BAL N'!G:G) -> 0 | H25: =+B25+C25+D25+E25-F25-G25 -> 0
A26: Autres immobilisations financières | B26: =+SUMIF('BAL N'!I:I,"=27",'BAL N'!G:G) -> 0 | H26: =+B26+C26+D26+E26-F26-G26 -> 0
A27: TOTAL GENERAL | B27: =SUM(B11:B26) -> 0 | C27: =SUM(C11:C26) -> 0 | D27: =SUM(D11:D26) -> 0 | E27: =SUM(E11:E26) -> 0 | F27: =SUM(F11:F26) -> 0 | G27: =SUM(G11:G26) -> 0 | H27: =SUM(H11:H26) -> 0
A28: Commentaire :
A29: · Toute variation significative doit être commentée
A30: · Détailler les éléments constitutifs du fonds commercial et indiquer la date d'acquisition
A31: · Pour l'immobilisation incorporelle relative à la concession faire un descriptif de l'accord
A32: · Indiquer :
A33: - la nature de la créance ;
A34: - la durée de la concession ;
A35: - l'échéance ;
A36: · Indiquer les créances du groupe avec nature et date d'échéance
A37: · Pour les banques, DAT indiquer le nom de labanque, le montant et la date d'échéance

Sheet Note 3B
A1: NOTE 3B : BIENS PRIS EN LOCATION ACQUISITION
A3: Désignation entité : | B3: ='Fiche de renseignement R1'!$J$4 -> 0 | G3: Excercice clos le : | H3: =+'Note 1'!E3 -> 0
A4: Numéro d'identification : | B4: =+'Note 1'!B4 -> 0 | G4: Durée en mois : | H4: =+'Note 1'!E4 -> 12
A6: SITUATIONS ET MOUVEMENTS | B6: NATURE DU CONTRAT (I; M; A) | C6: A | D6: AUGMENTATIONS B | G6: DIMINUTIONS C | I6: D = A +B - C
C7: Montant brut à l'ouverture de l'exercice | D7: Acquisitions Apports Créations | E7: Virements de poste à poste | F7: Suite à une réévaluation pratiquée au cours de l'exercice | G7: Cessions Scissions Hors service | H7: Virements de poste à poste | I7: Montant brut à l'ouverture de l'exercice
B8: [1]
A9: Brevets, licences, logiciels et droits similaires | I9: =SUM(B9:F9)-SUM(G9:H9) -> 0
A10: Fonds commercial et droit au bail | I10: =SUM(B10:F10)-SUM(G10:H10) -> 0
A11: Autres immobilisations incorporelles | I11: =SUM(B11:F11)-SUM(G11:H11) -> 0
A12: SOUS TOTAL : IMMOBILISATIONS INCORPORELLES | D12: =SUM(D9:D11) -> 0 | E12: =SUM(E9:E11) -> 0 | F12: =SUM(F9:F11) -> 0 | G12: =SUM(G9:G11) -> 0
A13: Terrains | I13: =SUM(B13:F13)-SUM(G13:H13) -> 0
A14: Bâtiments | I14: =SUM(B14:F14)-SUM(G14:H14) -> 0
A15: Aménagements, agencements et installations | I15: =SUM(B15:F15)-SUM(G15:H15) -> 0
A16: Matériel, mobilier et actifs biologiques | I16: =SUM(B16:F16)-SUM(G16:H16) -> 0
A17: Matériel de transport | I17: =SUM(B17:F17)-SUM(G17:H17) -> 0
A18: SOUS TOTAL : IMMOBILISATIONS CORPORELLES | C18: =SUM(C13:C17) -> 0 | I18: =SUM(I13:I17) -> 0
A20: TOTAL GENERAL | C20: =SUM(C9:C11)+SUM(C13:C17) -> 0 | D20: =SUM(D9:D11)+SUM(D13:D17) -> 0 | F20: =SUM(F9:F11)+SUM(F13:F17) -> 0 | G20: =SUM(G9:G11)+SUM(G13:G17) -> 0 | H20: =SUM(H9:H11)+SUM(H13:H17) -> 0 | I20: =SUM(I9:I11)+SUM(I13:I17) -> 0
A21: [1] I : crédit-bail immobilier; M : crédit-bail mobilier; A : autres contrats (dédoubler le poste si montants significatifs)
A22: Commentaire :
A23: · Indiquer la nature du bien, le nom du bailleur et la durée du bail

Sheet Note 3C
A1: NOTE 3C : IMMOBILISATIONS (AMORTISSEMENTS)
A3: Désignation entité : | B3: ='Fiche de renseignement R1'!$J$4 -> 0 | D3: Excercice clos le : | E3: =+'Note 1'!E3 -> 0
A4: Numéro d'identification : | B4: =+'Note 1'!B4 -> 0 | D4: Durée en mois : | E4: =+'Note 1'!E4 -> 12
A7: SITUATIONS ET MOUVEMENTS | B7: A | C7: B | D7: C | E7: D = A +B - C
B8: Amortissements cumulés à l'ouverture de l'exercice | C8: Augmentations : Dotations de l'exercice | D8: Diminutions : Amortissements relatifs aux éléments sortis de l'actif | E8: Cumul des amortissements à la clôture de l'exercice
A10: Frais de développement et de prospection | E10: =+B10+C10-D10 -> 0
A11: Brevets, licences, logiciels et droits similaires | B11: =+SUMIF('BAL N'!K:K,"=2811",'BAL N'!D:D) -> 0 | C11: =+SUMIF('BAL N'!K:K,"=2811",'BAL N'!F:F) -> 0 | D11: =+SUMIF('BAL N'!K:K,"=2811",'BAL N'!E:E) -> 0 | E11: =+B11+C11-D11 -> 0
A12: Fonds commercial et droit au bail | B12: =+SUMIF('BAL N'!K:K,"=2813",'BAL N'!D:D) -> 0 | C12: =+SUMIF('BAL N'!K:K,"=2813",'BAL N'!F:F) -> 0 | D12: =+SUMIF('BAL N'!K:K,"=2813",'BAL N'!E:E) -> 0 | E12: =+B12+C12-D12 -> 0
A13: Autres immobilisations incorporelles | B13: =+SUMIF('BAL N'!K:K,"=2815",'BAL N'!D:D) -> 0 | C13: =+SUMIF('BAL N'!K:K,"=2815",'BAL N'!F:F) -> 0 | D13: =+SUMIF('BAL N'!K:K,"=2815",'BAL N'!E:E) -> 0 | E13: =+B13+C13-D13 -> 0
A14: SOUS TOTAL : IMMOBILISATIONS INCORPORELLES | B14: =+SUMIF('BAL N'!K:K,"=2814",'BAL N'!D:D)+SUMIF('BAL N'!K:K,"=2816",'BAL N'!D:D)+SUMIF('BAL N'!K:K,"=2818",'BAL N'!D:D)+SUMIF('BAL N'!K:K,"=2817",'BAL N'!D:D) -> 0 | C14: =+SUMIF('BAL N'!K:K,"=2817",'BAL N'!F:F)+SUMIF('BAL N'!K:K,"=2814",'BAL N'!F:F)+SUMIF('BAL N'!K:K,"=2816",'BAL N'!F:F)+SUMIF('BAL N'!K:K,"=2817",'BAL N'!F:F)+SUMIF('BAL N'!K:K,"=2818",'BAL N'!F:F) -> 0 | D14: =+SUMIF('BAL N'!K:K,"=2814",'BAL N'!E:E)+SUMIF('BAL N'!K:K,"=2816",'BAL N'!E:E)++SUMIF('BAL N'!K:K,"=2817",'BAL N'!E:E)+SUMIF('BAL N'!K:K,"=2818",'BAL N'!E:E) -> 0 | E14: =+B14+C14-D14 -> 0
A15: Terrains hors immeuble de placement | B15: =+SUMIF('BAL N'!I:I,"=22",'BAL N'!G:G)-SUMIF('BAL N'!J:J,"=228",'BAL N'!G:G) -> 0 | C15: =+SUMIF('BAL N'!J:J,"=282",'BAL N'!F:F)-SUMIF('BAL N'!K:K,"=2828",'BAL N'!F:F) -> 0 | D15: =+SUMIF('BAL N'!J:J,"=282",'BAL N'!E:E)-SUMIF('BAL N'!K:K,"=2828",'BAL N'!E:E) -> 0 | E15: =+B15+C15-D15 -> 0
A16: Terrains immeuble de placement | B16: =+SUMIF('BAL N'!J:J,"=228",'BAL N'!G:G) -> 0 | C16: =+SUMIF('BAL N'!K:K,"=2828",'BAL N'!F:F) -> 0 | D16: =+SUMIF('BAL N'!K:K,"=2828",'BAL N'!E:E) -> 0 | E16: =+B16+C16-D16 -> 0
A17: Bâtiments hors immeuble de placement | B17: =+SUMIF('BAL N'!J:J,"=283",'BAL N'!D:D)-SUMIF('BAL N'!L:L,"=28315",'BAL N'!D:D)-SUMIF('BAL N'!L:L,"=28325",'BAL N'!D:D) -> 0 | C17: =+SUMIF('BAL N'!J:J,"=283",'BAL N'!F:F)-SUMIF('BAL N'!L:L,"=28315",'BAL N'!F:F)-SUMIF('BAL N'!L:L,"=28325",'BAL N'!F:F) -> 0 | D17: =+SUMIF('BAL N'!J:J,"=283",'BAL N'!E:E)-SUMIF('BAL N'!L:L,"=28315",'BAL N'!E:E)-SUMIF('BAL N'!L:L,"=28325",'BAL N'!E:E) -> 0 | E17: =+B17+C17-D17 -> 0
A18: Bâtiments immeuble de placement | B18: =+SUMIF('BAL N'!L:L,"=28315",'BAL N'!D:D)+SUMIF('BAL N'!L:L,"=28325",'BAL N'!D:D) -> 0 | C18: =+SUMIF('BAL N'!L:L,"=28315",'BAL N'!F:F)+SUMIF('BAL N'!L:L,"=28325",'BAL N'!F:F) -> 0 | D18: =+SUMIF('BAL N'!L:L,"=28315",'BAL N'!E:E)+SUMIF('BAL N'!L:L,"=28325",'BAL N'!E:E) -> 0 | E18: =+B18+C18-D18 -> 0
A19: Aménagements, agencements et installations | B19: =+SUMIF('BAL N'!K:K,"=2834",'BAL N'!D:D)+SUMIF('BAL N'!K:K,"=2835",'BAL N'!D:D) -> 0 | C19: =+SUMIF('BAL N'!K:K,"=2834",'BAL N'!F:F)+SUMIF('BAL N'!K:K,"=2835",'BAL N'!F:F) -> 0 | D19: =+SUMIF('BAL N'!K:K,"=2834",'BAL N'!E:E)+SUMIF('BAL N'!K:K,"=2835",'BAL N'!E:E) -> 0 | E19: =+B19+C19-D19 -> 0
A20: Matériel, mobilier et actifs biologiques | B20: =+SUMIF('BAL N'!J:J,"=284",'BAL N'!D:D)-SUMIF('BAL N'!K:K,"=2845",'BAL N'!D:D) -> 0 | C20: =+SUMIF('BAL N'!J:J,"=284",'BAL N'!F:F)-SUMIF('BAL N'!K:K,"=2845",'BAL N'!F:F) -> 0 | D20: =+SUMIF('BAL N'!J:J,"=284",'BAL N'!E:E)-SUMIF('BAL N'!K:K,"=2845",'BAL N'!E:E) -> 0 | E20: =+B20+C20-D20 -> 0
A21: Matériel de transport | B21: =+SUMIF('BAL N'!K:K,"=2845",'BAL N'!D:D) -> 0 | C21: =+SUMIF('BAL N'!K:K,"=2845",'BAL N'!F:F) -> 0 | D21: =+SUMIF('BAL N'!K:K,"=2845",'BAL N'!E:E) -> 0 | E21: =+B21+C21-D21 -> 0
A22: SOUS TOTAL : IMMOBILISATIONS CORPORELLES | B22: =SUM(B15:B21) -> 0 | C22: =SUM(C15:C21) -> 0 | D22: =SUM(D15:D21) -> 0 | E22: =+B22+C22-D22 -> 0
A24: TOTAL GENERAL | B24: =SUM(B14,B22) -> 0 | C24: =SUM(C14,C22) -> 0 | D24: =SUM(D14,D22) -> 0 | E24: =SUM(B24:D24) -> 0
A25: Commentaire :
A26: · Indiquer :
A27: - les modes d'amortissements utilisés : amortissement linéaire
A28: - la durée de vie ou les taux d'amortissements utilisés ;

Sheet Note 3D
A1: NOTE 3D : IMMOBILISATIONS (PLUS-VALUES ET MOINS VALUES DE CESSION)
A3: Désignation entité : | B3: ='Fiche de renseignement R1'!$J$4 -> 0 | D3: Excercice clos le : | E3: =+'Note 1'!E3 -> 0
A4: Numéro d'identification : | B4: =+'Note 1'!B4 -> 0 | D4: Durée en mois : | E4: =+'Note 1'!E4 -> 12
B7: MONTANT BRUT | C7: AMORTISSEMENTS | D7: VALEUR COMPTABLE NETTE | E7: PRIX DE CESSION | F7: PLUS VALUE OU MOINS VALUE
C8: PRATIQUES
B9: A | C9: B | D9: C = A - B | E9: D | F9: E = D - C
A10: Frais de développement et de prospection
A11: Brevets, licences, logiciels et droits similaires | D11: =+B11-C11 -> 0 | F11: =+E11-D11 -> 0
A12: Fonds commercial et droit au bail | D12: =+B12-C12 -> 0 | F12: =+E12-D12 -> 0
A13: Autres immobilisations incorporelles | D13: =+B13-C13 -> 0 | F13: =+E13-D13 -> 0
A14: SOUS TOTAL : IMMOBILISATIONS INCORPORELLES | B14: =SUM(B11:B13) -> 0 | C14: =SUM(C11:C13) -> 0 | D14: =+B14-C14 -> 0 | E14: =SUM(E11:E13) -> 0 | F14: =+E14-D14 -> 0
A15: Terrains
A16: Bâtiments
A17: Aménagements, agencements et installations
A18: Matériel, mobilier et actifs biologiques
A19: Matériel de transport
A20: SOUS TOTAL : IMMOBILISATIONS CORPORELLES | B20: =SUM(B15:B19) -> 0 | C20: =SUM(C21:C22) -> 0 | D20: =+B20-C20 -> 0 | E20: =SUM(E21:E22) -> 0 | F20: =+E20-D20 -> 0
A21: Titres de participation | D21: =+B21-C21 -> 0 | F21: =+E21-D21 -> 0
A22: Autres immobilisations financières | D22: =+B22-C22 -> 0 | F22: =+E22-D22 -> 0
A23: SOUS TOTAL : IMMOBILISATIONS FINANCIERES | B23: =SUM(B21:B22) -> 0 | C23: =SUM(C21:C22) -> 0 | D23: =+B23-C23 -> 0 | F23: =+E23-D23 -> 0
A25: TOTAL GENERAL | B25: =+B14+B20+B23 -> 0 | C25: =+C14+C20+C23 -> 0 | D25: =+B25-C25 -> 0 | F25: =+E25-D25 -> 0
A26: Commentaire :
A27: · Mentionner la justification de la cession ainsi que la date d'acquisition et la date de sortie

Sheet Note 3E
A1: NOTE 3E : INFORMATIONS SUR LES REEVALUATIONS EFFECTUEES PAR L'ENTITE
A3: Désignation entité : | B3: ='Fiche de renseignement R1'!$J$4 -> 0 | C3: Excercice clos le : | D3: =+'Note 1'!E3 -> 0
A4: Numéro d'identification : | B4: =+'Note 1'!B4 -> 0 | C4: Durée en mois : | D4: =+'Note 1'!E4 -> 12
A7: Nature et date des réévaluations :
A13: Eléments réévalués par postes du bilan | B13: Montants coûts historiques | C13: Amortissements supplémentaires
A22: Méthode de réévaluation utilisée :
A24: Traitement fiscal de l'écart de réévaluation
A25: et des amortissements supplémentaires :
A27: Montant de l'écart incorporé au capital :

Sheet Note 4
A1: NOTE 4 : IMMOBILISATIONS FINANCIERES
A3: Désignation entité : | B3: ='Fiche de renseignement R1'!$J$4 -> 0 | E3: Excercice clos le : | F3: =+'Note 1'!E3 -> 0
A4: Numéro d'identification : | B4: =+'Note 1'!B4 -> 0 | E4: Durée en mois : | F4: =+'Note 1'!E4 -> 12
A7: SITUATIONS ET MOUVEMENTS | B7: =IFERROR(YEAR('Fiche de renseignement R1'!V10),"Annee N") -> 1900 | C7: =IFERROR(YEAR('Fiche de renseignement R1'!Q20),"Annee N-1") -> 2020 | D7: Variation en % | E7: Créances à un an au plus | F7: Créances à plus d'un an et à deux ans au plus | G7: Créances à plus de deux ans
A9: Titres de participation | B9: =+SUMIF('BAL N'!I:I,"=26",'BAL N'!G:G) -> 0 | C9: =+SUMIF('BAL N'!I:I,"=26",'BAL N'!C:C) -> 0 | D9: =IFERROR((B9-C9)/B9,0) -> 0
A10: Prêts et créances | B10: =+SUMIF('BAL N'!J:J,"=271",'BAL N'!G:G) -> 0 | C10: =+SUMIF('BAL N'!I:I,"=271",'BAL N'!C:C) -> 0 | D10: =IFERROR((B10-C10)/B10,0) -> 0
A11: Prêt au personnel | B11: =+SUMIF('BAL N'!J:J,"=272",'BAL N'!G:G) -> 0 | C11: =+SUMIF('BAL N'!I:I,"=272",'BAL N'!C:C) -> 0 | D11: =IFERROR((B11-C11)/B11,0) -> 0
A12: Créances sur l'Etat | B12: =+SUMIF('BAL N'!J:J,"=273",'BAL N'!G:G) -> 0 | C12: =+SUMIF('BAL N'!I:I,"=273",'BAL N'!C:C) -> 0 | D12: =IFERROR((B12-C12)/B12,0) -> 0
A13: Titres immobilisés | B13: =+SUMIF('BAL N'!J:J,"=274",'BAL N'!G:G) -> 0 | C13: =+SUMIF('BAL N'!I:I,"=274",'BAL N'!C:C) -> 0 | D13: =IFERROR((B13-C13)/B13,0) -> 0
A14: Dépôts et cautionnements | B14: =+SUMIF('BAL N'!J:J,"=275",'BAL N'!G:G) -> 0 | C14: =+SUMIF('BAL N'!J:J,"=275",'BAL N'!C:C) -> 0 | D14: =IFERROR((B14-C14)/B14,0) -> 0
A15: Intérêts courus | B15: =+SUMIF('BAL N'!J:J,"=276",'BAL N'!G:G) -> 0 | C15: =+SUMIF('BAL N'!J:J,"=276",'BAL N'!C:C) -> 0 | D15: =IFERROR((B15-C15)/B15,0) -> 0
A16: TOTAL BRUT | B16: =SUM(B9:B15) -> 0 | C16: =SUM(C9:C15) -> 0 | D16: =IFERROR((B16-C16)/B16,0) -> 0
A17: Dépréciations titres de participation | B17: =+SUMIF('BAL N'!J:J,"=296",'BAL N'!H:H) -> 0 | C17: =+SUMIF('BAL N'!J:J,"=296",'BAL N'!D:D) -> 0 | D17: =IFERROR((B17-C17)/B17,0) -> 0
A18: Dépréciations autres immobilisations | B18: =+SUMIF('BAL N'!J:J,"=297",'BAL N'!H:H) -> 0 | C18: =+SUMIF('BAL N'!J:J,"=297",'BAL N'!D:D) -> 0 | D18: =IFERROR((B18-C18)/B18,0) -> 0
A19: TOTAL NET DE DEPRECIATION | B19: =SUM(B17:B18) -> 0 | C19: =SUM(C17:C18) -> 0 | D19: =IFERROR((B19-C19)/B19,0) -> 0
A21: Liste des filiales et participations :
A23: Dénomination sociale | B23: Localisation (ville/pays) | C23: Valeur d'acquisition | E23: % détenu | F23: Montant des capitaux propres filiale | G23: Résultat dernier exercice filiale
A32: Commentaire :
A33: · Justifier toute variation significative
A34: · Commenter toutes les créances anciennes
A35: · Pour les créances relatives à la concession, faire un descriptif de l'accord
A36: · Indiquer :
A37: - la nature de la créance ;
A38: - la durée de la concession ;
A39: - l'échéance ;
A40: · Indiquer le nombre et la date d'acquisition des actions ou parts propres
A41: · Dépréciation : indiquer les évènements et les circonstances qui ont motivé
A42: la dépréciation ou la reprise

Sheet Note 5
A1: NOTE 5 : ACTIF CIRCULANT HAO
A3: Désignation entité : | B3: ='Fiche de renseignement R1'!$J$4 -> 0 | E3: Excercice clos le : | F3: =+'Note 1'!E3 -> 0
A4: Numéro d'identification : | B4: =+'Note 1'!B4 -> 0 | E4: Durée en mois : | F4: =+'Note 1'!E4 -> 12
A6: ACTIF CIRCULANT HAO | P6: ACTIF CIRCULANT HAO | X6: ACTIF CIRCULANT HAO | AF6: ACTIF CIRCULANT HAO | AN6: ACTIF CIRCULANT HAO | AV6: ACTIF CIRCULANT HAO | BD6: ACTIF CIRCULANT HAO | BL6: ACTIF CIRCULANT HAO | BT6: ACTIF CIRCULANT HAO | CB6: ACTIF CIRCULANT HAO | CJ6: ACTIF CIRCULANT HAO | CR6: ACTIF CIRCULANT HAO | CZ6: ACTIF CIRCULANT HAO | DH6: ACTIF CIRCULANT HAO | DP6: ACTIF CIRCULANT HAO | DX6: ACTIF CIRCULANT HAO | EF6: ACTIF CIRCULANT HAO | EN6: ACTIF CIRCULANT HAO | EV6: ACTIF CIRCULANT HAO | FD6: ACTIF CIRCULANT HAO | FL6: ACTIF CIRCULANT HAO | FT6: ACTIF CIRCULANT HAO | GB6: ACTIF CIRCULANT HAO | GJ6: ACTIF CIRCULANT HAO | GR6: ACTIF CIRCULANT HAO | GZ6: ACTIF CIRCULANT HAO | HH6: ACTIF CIRCULANT HAO | HP6: ACTIF CIRCULANT HAO | HX6: ACTIF CIRCULANT HAO | IF6: ACTIF CIRCULANT HAO | IN6: ACTIF CIRCULANT HAO | IV6: ACTIF CIRCULANT HAO | JD6: ACTIF CIRCULANT HAO | JL6: ACTIF CIRCULANT HAO | JT6: ACTIF CIRCULANT HAO | KB6: ACTIF CIRCULANT HAO | KJ6: ACTIF CIRCULANT HAO | KR6: ACTIF CIRCULANT HAO | KZ6: ACTIF CIRCULANT HAO | LH6: ACTIF CIRCULANT HAO | LP6: ACTIF CIRCULANT HAO | LX6: ACTIF CIRCULANT HAO | MF6: ACTIF CIRCULANT HAO | MN6: ACTIF CIRCULANT HAO | MV6: ACTIF CIRCULANT HAO | ND6: ACTIF CIRCULANT HAO | NL6: ACTIF CIRCULANT HAO | NT6: ACTIF CIRCULANT HAO | OB6: ACTIF CIRCULANT HAO | OJ6: ACTIF CIRCULANT HAO | OR6: ACTIF CIRCULANT HAO | OZ6: ACTIF CIRCULANT HAO | PH6: ACTIF CIRCULANT HAO | PP6: ACTIF CIRCULANT HAO | PX6: ACTIF CIRCULANT HAO | QF6: ACTIF CIRCULANT HAO | QN6: ACTIF CIRCULANT HAO | QV6: ACTIF CIRCULANT HAO | RD6: ACTIF CIRCULANT HAO | RL6: ACTIF CIRCULANT HAO | RT6: ACTIF CIRCULANT HAO | SB6: ACTIF CIRCULANT HAO | SJ6: ACTIF CIRCULANT HAO | SR6: ACTIF CIRCULANT HAO | SZ6: ACTIF CIRCULANT HAO | TH6: ACTIF CIRCULANT HAO | TP6: ACTIF CIRCULANT HAO | TX6: ACTIF CIRCULANT HAO | UF6: ACTIF CIRCULANT HAO | UN6: ACTIF CIRCULANT HAO | UV6: ACTIF CIRCULANT HAO | VD6: ACTIF CIRCULANT HAO | VL6: ACTIF CIRCULANT HAO | VT6: ACTIF CIRCULANT HAO | WB6: ACTIF CIRCULANT HAO | WJ6: ACTIF CIRCULANT HAO | WR6: ACTIF CIRCULANT HAO | WZ6: ACTIF CIRCULANT HAO | XH6: ACTIF CIRCULANT HAO | XP6: ACTIF CIRCULANT HAO | XX6: ACTIF CIRCULANT HAO | YF6: ACTIF CIRCULANT HAO | YN6: ACTIF CIRCULANT HAO | YV6: ACTIF CIRCULANT HAO | ZD6: ACTIF CIRCULANT HAO | ZL6: ACTIF CIRCULANT HAO | ZT6: ACTIF CIRCULANT HAO | AAB6: ACTIF CIRCULANT HAO | AAJ6: ACTIF CIRCULANT HAO | AAR6: ACTIF CIRCULANT HAO | AAZ6: ACTIF CIRCULANT HAO | ABH6: ACTIF CIRCULANT HAO | ABP6: ACTIF CIRCULANT HAO | ABX6: ACTIF CIRCULANT HAO | ACF6: ACTIF CIRCULANT HAO | ACN6: ACTIF CIRCULANT HAO | ACV6: ACTIF CIRCULANT HAO | ADD6: ACTIF CIRCULANT HAO | ADL6: ACTIF CIRCULANT HAO | ADT6: ACTIF CIRCULANT HAO | AEB6: ACTIF CIRCULANT HAO | AEJ6: ACTIF CIRCULANT HAO | AER6: ACTIF CIRCULANT HAO | AEZ6: ACTIF CIRCULANT HAO | AFH6: ACTIF CIRCULANT HAO | AFP6: ACTIF CIRCULANT HAO | AFX6: ACTIF CIRCULANT HAO | AGF6: ACTIF CIRCULANT HAO | AGN6: ACTIF CIRCULANT HAO | AGV6: ACTIF CIRCULANT HAO | AHD6: ACTIF CIRCULANT HAO | AHL6: ACTIF CIRCULANT HAO | AHT6: ACTIF CIRCULANT HAO | AIB6: ACTIF CIRCULANT HAO | AIJ6: ACTIF CIRCULANT HAO | AIR6: ACTIF CIRCULANT HAO | AIZ6: ACTIF CIRCULANT HAO | AJH6: ACTIF CIRCULANT HAO | AJP6: ACTIF CIRCULANT HAO | AJX6: ACTIF CIRCULANT HAO | AKF6: ACTIF CIRCULANT HAO | AKN6: ACTIF CIRCULANT HAO | AKV6: ACTIF CIRCULANT HAO | ALD6: ACTIF CIRCULANT HAO | ALL6: ACTIF CIRCULANT HAO | ALT6: ACTIF CIRCULANT HAO | AMB6: ACTIF CIRCULANT HAO | AMJ6: ACTIF CIRCULANT HAO | AMR6: ACTIF CIRCULANT HAO | AMZ6: ACTIF CIRCULANT HAO | ANH6: ACTIF CIRCULANT HAO | ANP6: ACTIF CIRCULANT HAO | ANX6: ACTIF CIRCULANT HAO | AOF6: ACTIF CIRCULANT HAO | AON6: ACTIF CIRCULANT HAO | AOV6: ACTIF CIRCULANT HAO | APD6: ACTIF CIRCULANT HAO | APL6: ACTIF CIRCULANT HAO | APT6: ACTIF CIRCULANT HAO | AQB6: ACTIF CIRCULANT HAO | AQJ6: ACTIF CIRCULANT HAO | AQR6: ACTIF CIRCULANT HAO | AQZ6: ACTIF CIRCULANT HAO | ARH6: ACTIF CIRCULANT HAO | ARP6: ACTIF CIRCULANT HAO | ARX6: ACTIF CIRCULANT HAO | ASF6: ACTIF CIRCULANT HAO | ASN6: ACTIF CIRCULANT HAO | ASV6: ACTIF CIRCULANT HAO | ATD6: ACTIF CIRCULANT HAO | ATL6: ACTIF CIRCULANT HAO | ATT6: ACTIF CIRCULANT HAO | AUB6: ACTIF CIRCULANT HAO | AUJ6: ACTIF CIRCULANT HAO | AUR6: ACTIF CIRCULANT HAO | AUZ6: ACTIF CIRCULANT HAO | AVH6: ACTIF CIRCULANT HAO | AVP6: ACTIF CIRCULANT HAO | AVX6: ACTIF CIRCULANT HAO | AWF6: ACTIF CIRCULANT HAO | AWN6: ACTIF CIRCULANT HAO | AWV6: ACTIF CIRCULANT HAO | AXD6: ACTIF CIRCULANT HAO | AXL6: ACTIF CIRCULANT HAO | AXT6: ACTIF CIRCULANT HAO | AYB6: ACTIF CIRCULANT HAO | AYJ6: ACTIF CIRCULANT HAO | AYR6: ACTIF CIRCULANT HAO | AYZ6: ACTIF CIRCULANT HAO | AZH6: ACTIF CIRCULANT HAO | AZP6: ACTIF CIRCULANT HAO | AZX6: ACTIF CIRCULANT HAO | BAF6: ACTIF CIRCULANT HAO | BAN6: ACTIF CIRCULANT HAO | BAV6: ACTIF CIRCULANT HAO | BBD6: ACTIF CIRCULANT HAO | BBL6: ACTIF CIRCULANT HAO | BBT6: ACTIF CIRCULANT HAO | BCB6: ACTIF CIRCULANT HAO | BCJ6: ACTIF CIRCULANT HAO | BCR6: ACTIF CIRCULANT HAO | BCZ6: ACTIF CIRCULANT HAO | BDH6: ACTIF CIRCULANT HAO | BDP6: ACTIF CIRCULANT HAO | BDX6: ACTIF CIRCULANT HAO | BEF6: ACTIF CIRCULANT HAO | BEN6: ACTIF CIRCULANT HAO | BEV6: ACTIF CIRCULANT HAO | BFD6: ACTIF CIRCULANT HAO | BFL6: ACTIF CIRCULANT HAO | BFT6: ACTIF CIRCULANT HAO | BGB6: ACTIF CIRCULANT HAO | BGJ6: ACTIF CIRCULANT HAO | BGR6: ACTIF CIRCULANT HAO | BGZ6: ACTIF CIRCULANT HAO | BHH6: ACTIF CIRCULANT HAO | BHP6: ACTIF CIRCULANT HAO | BHX6: ACTIF CIRCULANT HAO | BIF6: ACTIF CIRCULANT HAO | BIN6: ACTIF CIRCULANT HAO | BIV6: ACTIF CIRCULANT HAO | BJD6: ACTIF CIRCULANT HAO | BJL6: ACTIF CIRCULANT HAO | BJT6: ACTIF CIRCULANT HAO | BKB6: ACTIF CIRCULANT HAO | BKJ6: ACTIF CIRCULANT HAO | BKR6: ACTIF CIRCULANT HAO | BKZ6: ACTIF CIRCULANT HAO | BLH6: ACTIF CIRCULANT HAO | BLP6: ACTIF CIRCULANT HAO | BLX6: ACTIF CIRCULANT HAO | BMF6: ACTIF CIRCULANT HAO | BMN6: ACTIF CIRCULANT HAO | BMV6: ACTIF CIRCULANT HAO | BND6: ACTIF CIRCULANT HAO | BNL6: ACTIF CIRCULANT HAO | BNT6: ACTIF CIRCULANT HAO | BOB6: ACTIF CIRCULANT HAO | BOJ6: ACTIF CIRCULANT HAO | BOR6: ACTIF CIRCULANT HAO | BOZ6: ACTIF CIRCULANT HAO | BPH6: ACTIF CIRCULANT HAO | BPP6: ACTIF CIRCULANT HAO | BPX6: ACTIF CIRCULANT HAO | BQF6: ACTIF CIRCULANT HAO | BQN6: ACTIF CIRCULANT HAO | BQV6: ACTIF CIRCULANT HAO | BRD6: ACTIF CIRCULANT HAO | BRL6: ACTIF CIRCULANT HAO | BRT6: ACTIF CIRCULANT HAO | BSB6: ACTIF CIRCULANT HAO | BSJ6: ACTIF CIRCULANT HAO | BSR6: ACTIF CIRCULANT HAO | BSZ6: ACTIF CIRCULANT HAO | BTH6: ACTIF CIRCULANT HAO | BTP6: ACTIF CIRCULANT HAO | BTX6: ACTIF CIRCULANT HAO | BUF6: ACTIF CIRCULANT HAO | BUN6: ACTIF CIRCULANT HAO | BUV6: ACTIF CIRCULANT HAO | BVD6: ACTIF CIRCULANT HAO | BVL6: ACTIF CIRCULANT HAO | BVT6: ACTIF CIRCULANT HAO | BWB6: ACTIF CIRCULANT HAO | BWJ6: ACTIF CIRCULANT HAO | BWR6: ACTIF CIRCULANT HAO | BWZ6: ACTIF CIRCULANT HAO | BXH6: ACTIF CIRCULANT HAO | BXP6: ACTIF CIRCULANT HAO | BXX6: ACTIF CIRCULANT HAO | BYF6: ACTIF CIRCULANT HAO | BYN6: ACTIF CIRCULANT HAO | BYV6: ACTIF CIRCULANT HAO | BZD6: ACTIF CIRCULANT HAO | BZL6: ACTIF CIRCULANT HAO | BZT6: ACTIF CIRCULANT HAO | CAB6: ACTIF CIRCULANT HAO | CAJ6: ACTIF CIRCULANT HAO | CAR6: ACTIF CIRCULANT HAO | CAZ6: ACTIF CIRCULANT HAO | CBH6: ACTIF CIRCULANT HAO | CBP6: ACTIF CIRCULANT HAO | CBX6: ACTIF CIRCULANT HAO | CCF6: ACTIF CIRCULANT HAO | CCN6: ACTIF CIRCULANT HAO | CCV6: ACTIF CIRCULANT HAO | CDD6: ACTIF CIRCULANT HAO | CDL6: ACTIF CIRCULANT HAO | CDT6: ACTIF CIRCULANT HAO | CEB6: ACTIF CIRCULANT HAO | CEJ6: ACTIF CIRCULANT HAO | CER6: ACTIF CIRCULANT HAO | CEZ6: ACTIF CIRCULANT HAO | CFH6: ACTIF CIRCULANT HAO | CFP6: ACTIF CIRCULANT HAO | CFX6: ACTIF CIRCULANT HAO | CGF6: ACTIF CIRCULANT HAO | CGN6: ACTIF CIRCULANT HAO | CGV6: ACTIF CIRCULANT HAO | CHD6: ACTIF CIRCULANT HAO | CHL6: ACTIF CIRCULANT HAO | CHT6: ACTIF CIRCULANT HAO | CIB6: ACTIF CIRCULANT HAO | CIJ6: ACTIF CIRCULANT HAO | CIR6: ACTIF CIRCULANT HAO | CIZ6: ACTIF CIRCULANT HAO | CJH6: ACTIF CIRCULANT HAO | CJP6: ACTIF CIRCULANT HAO | CJX6: ACTIF CIRCULANT HAO | CKF6: ACTIF CIRCULANT HAO | CKN6: ACTIF CIRCULANT HAO | CKV6: ACTIF CIRCULANT HAO | CLD6: ACTIF CIRCULANT HAO | CLL6: ACTIF CIRCULANT HAO | CLT6: ACTIF CIRCULANT HAO | CMB6: ACTIF CIRCULANT HAO | CMJ6: ACTIF CIRCULANT HAO | CMR6: ACTIF CIRCULANT HAO | CMZ6: ACTIF CIRCULANT HAO | CNH6: ACTIF CIRCULANT HAO | CNP6: ACTIF CIRCULANT HAO | CNX6: ACTIF CIRCULANT HAO | COF6: ACTIF CIRCULANT HAO | CON6: ACTIF CIRCULANT HAO | COV6: ACTIF CIRCULANT HAO | CPD6: ACTIF CIRCULANT HAO | CPL6: ACTIF CIRCULANT HAO | CPT6: ACTIF CIRCULANT HAO | CQB6: ACTIF CIRCULANT HAO | CQJ6: ACTIF CIRCULANT HAO | CQR6: ACTIF CIRCULANT HAO | CQZ6: ACTIF CIRCULANT HAO | CRH6: ACTIF CIRCULANT HAO | CRP6: ACTIF CIRCULANT HAO | CRX6: ACTIF CIRCULANT HAO | CSF6: ACTIF CIRCULANT HAO | CSN6: ACTIF CIRCULANT HAO | CSV6: ACTIF CIRCULANT HAO | CTD6: ACTIF CIRCULANT HAO | CTL6: ACTIF CIRCULANT HAO | CTT6: ACTIF CIRCULANT HAO | CUB6: ACTIF CIRCULANT HAO | CUJ6: ACTIF CIRCULANT HAO | CUR6: ACTIF CIRCULANT HAO | CUZ6: ACTIF CIRCULANT HAO | CVH6: ACTIF CIRCULANT HAO | CVP6: ACTIF CIRCULANT HAO | CVX6: ACTIF CIRCULANT HAO | CWF6: ACTIF CIRCULANT HAO | CWN6: ACTIF CIRCULANT HAO | CWV6: ACTIF CIRCULANT HAO | CXD6: ACTIF CIRCULANT HAO | CXL6: ACTIF CIRCULANT HAO | CXT6: ACTIF CIRCULANT HAO | CYB6: ACTIF CIRCULANT HAO | CYJ6: ACTIF CIRCULANT HAO | CYR6: ACTIF CIRCULANT HAO | CYZ6: ACTIF CIRCULANT HAO | CZH6: ACTIF CIRCULANT HAO | CZP6: ACTIF CIRCULANT HAO | CZX6: ACTIF CIRCULANT HAO | DAF6: ACTIF CIRCULANT HAO | DAN6: ACTIF CIRCULANT HAO | DAV6: ACTIF CIRCULANT HAO | DBD6: ACTIF CIRCULANT HAO | DBL6: ACTIF CIRCULANT HAO | DBT6: ACTIF CIRCULANT HAO | DCB6: ACTIF CIRCULANT HAO | DCJ6: ACTIF CIRCULANT HAO | DCR6: ACTIF CIRCULANT HAO | DCZ6: ACTIF CIRCULANT HAO | DDH6: ACTIF CIRCULANT HAO | DDP6: ACTIF CIRCULANT HAO | DDX6: ACTIF CIRCULANT HAO | DEF6: ACTIF CIRCULANT HAO | DEN6: ACTIF CIRCULANT HAO | DEV6: ACTIF CIRCULANT HAO | DFD6: ACTIF CIRCULANT HAO | DFL6: ACTIF CIRCULANT HAO | DFT6: ACTIF CIRCULANT HAO | DGB6: ACTIF CIRCULANT HAO | DGJ6: ACTIF CIRCULANT HAO | DGR6: ACTIF CIRCULANT HAO | DGZ6: ACTIF CIRCULANT HAO | DHH6: ACTIF CIRCULANT HAO | DHP6: ACTIF CIRCULANT HAO | DHX6: ACTIF CIRCULANT HAO | DIF6: ACTIF CIRCULANT HAO | DIN6: ACTIF CIRCULANT HAO | DIV6: ACTIF CIRCULANT HAO | DJD6: ACTIF CIRCULANT HAO | DJL6: ACTIF CIRCULANT HAO | DJT6: ACTIF CIRCULANT HAO | DKB6: ACTIF CIRCULANT HAO | DKJ6: ACTIF CIRCULANT HAO | DKR6: ACTIF CIRCULANT HAO | DKZ6: ACTIF CIRCULANT HAO | DLH6: ACTIF CIRCULANT HAO | DLP6: ACTIF CIRCULANT HAO | DLX6: ACTIF CIRCULANT HAO | DMF6: ACTIF CIRCULANT HAO | DMN6: ACTIF CIRCULANT HAO | DMV6: ACTIF CIRCULANT HAO | DND6: ACTIF CIRCULANT HAO | DNL6: ACTIF CIRCULANT HAO | DNT6: ACTIF CIRCULANT HAO | DOB6: ACTIF CIRCULANT HAO | DOJ6: ACTIF CIRCULANT HAO | DOR6: ACTIF CIRCULANT HAO | DOZ6: ACTIF CIRCULANT HAO | DPH6: ACTIF CIRCULANT HAO | DPP6: ACTIF CIRCULANT HAO | DPX6: ACTIF CIRCULANT HAO | DQF6: ACTIF CIRCULANT HAO | DQN6: ACTIF CIRCULANT HAO | DQV6: ACTIF CIRCULANT HAO | DRD6: ACTIF CIRCULANT HAO | DRL6: ACTIF CIRCULANT HAO | DRT6: ACTIF CIRCULANT HAO | DSB6: ACTIF CIRCULANT HAO | DSJ6: ACTIF CIRCULANT HAO | DSR6: ACTIF CIRCULANT HAO | DSZ6: ACTIF CIRCULANT HAO | DTH6: ACTIF CIRCULANT HAO | DTP6: ACTIF CIRCULANT HAO | DTX6: ACTIF CIRCULANT HAO | DUF6: ACTIF CIRCULANT HAO | DUN6: ACTIF CIRCULANT HAO | DUV6: ACTIF CIRCULANT HAO | DVD6: ACTIF CIRCULANT HAO | DVL6: ACTIF CIRCULANT HAO | DVT6: ACTIF CIRCULANT HAO | DWB6: ACTIF CIRCULANT HAO | DWJ6: ACTIF CIRCULANT HAO | DWR6: ACTIF CIRCULANT HAO | DWZ6: ACTIF CIRCULANT HAO | DXH6: ACTIF CIRCULANT HAO | DXP6: ACTIF CIRCULANT HAO | DXX6: ACTIF CIRCULANT HAO | DYF6: ACTIF CIRCULANT HAO | DYN6: ACTIF CIRCULANT HAO | DYV6: ACTIF CIRCULANT HAO | DZD6: ACTIF CIRCULANT HAO | DZL6: ACTIF CIRCULANT HAO | DZT6: ACTIF CIRCULANT HAO | EAB6: ACTIF CIRCULANT HAO | EAJ6: ACTIF CIRCULANT HAO | EAR6: ACTIF CIRCULANT HAO | EAZ6: ACTIF CIRCULANT HAO | EBH6: ACTIF CIRCULANT HAO | EBP6: ACTIF CIRCULANT HAO | EBX6: ACTIF CIRCULANT HAO | ECF6: ACTIF CIRCULANT HAO | ECN6: ACTIF CIRCULANT HAO | ECV6: ACTIF CIRCULANT HAO | EDD6: ACTIF CIRCULANT HAO | EDL6: ACTIF CIRCULANT HAO | EDT6: ACTIF CIRCULANT HAO | EEB6: ACTIF CIRCULANT HAO | EEJ6: ACTIF CIRCULANT HAO | EER6: ACTIF CIRCULANT HAO | EEZ6: ACTIF CIRCULANT HAO | EFH6: ACTIF CIRCULANT HAO | EFP6: ACTIF CIRCULANT HAO | EFX6: ACTIF CIRCULANT HAO | EGF6: ACTIF CIRCULANT HAO | EGN6: ACTIF CIRCULANT HAO | EGV6: ACTIF CIRCULANT HAO | EHD6: ACTIF CIRCULANT HAO | EHL6: ACTIF CIRCULANT HAO | EHT6: ACTIF CIRCULANT HAO | EIB6: ACTIF CIRCULANT HAO | EIJ6: ACTIF CIRCULANT HAO | EIR6: ACTIF CIRCULANT HAO | EIZ6: ACTIF CIRCULANT HAO | EJH6: ACTIF CIRCULANT HAO | EJP6: ACTIF CIRCULANT HAO | EJX6: ACTIF CIRCULANT HAO | EKF6: ACTIF CIRCULANT HAO | EKN6: ACTIF CIRCULANT HAO | EKV6: ACTIF CIRCULANT HAO | ELD6: ACTIF CIRCULANT HAO | ELL6: ACTIF CIRCULANT HAO | ELT6: ACTIF CIRCULANT HAO | EMB6: ACTIF CIRCULANT HAO | EMJ6: ACTIF CIRCULANT HAO | EMR6: ACTIF CIRCULANT HAO | EMZ6: ACTIF CIRCULANT HAO | ENH6: ACTIF CIRCULANT HAO | ENP6: ACTIF CIRCULANT HAO | ENX6: ACTIF CIRCULANT HAO | EOF6: ACTIF CIRCULANT HAO | EON6: ACTIF CIRCULANT HAO | EOV6: ACTIF CIRCULANT HAO | EPD6: ACTIF CIRCULANT HAO | EPL6: ACTIF CIRCULANT HAO | EPT6: ACTIF CIRCULANT HAO | EQB6: ACTIF CIRCULANT HAO | EQJ6: ACTIF CIRCULANT HAO | EQR6: ACTIF CIRCULANT HAO | EQZ6: ACTIF CIRCULANT HAO | ERH6: ACTIF CIRCULANT HAO | ERP6: ACTIF CIRCULANT HAO | ERX6: ACTIF CIRCULANT HAO | ESF6: ACTIF CIRCULANT HAO | ESN6: ACTIF CIRCULANT HAO | ESV6: ACTIF CIRCULANT HAO | ETD6: ACTIF CIRCULANT HAO | ETL6: ACTIF CIRCULANT HAO | ETT6: ACTIF CIRCULANT HAO | EUB6: ACTIF CIRCULANT HAO | EUJ6: ACTIF CIRCULANT HAO | EUR6: ACTIF CIRCULANT HAO | EUZ6: ACTIF CIRCULANT HAO | EVH6: ACTIF CIRCULANT HAO | EVP6: ACTIF CIRCULANT HAO | EVX6: ACTIF CIRCULANT HAO | EWF6: ACTIF CIRCULANT HAO | EWN6: ACTIF CIRCULANT HAO | EWV6: ACTIF CIRCULANT HAO | EXD6: ACTIF CIRCULANT HAO | EXL6: ACTIF CIRCULANT HAO | EXT6: ACTIF CIRCULANT HAO | EYB6: ACTIF CIRCULANT HAO | EYJ6: ACTIF CIRCULANT HAO | EYR6: ACTIF CIRCULANT HAO | EYZ6: ACTIF CIRCULANT HAO | EZH6: ACTIF CIRCULANT HAO | EZP6: ACTIF CIRCULANT HAO | EZX6: ACTIF CIRCULANT HAO | FAF6: ACTIF CIRCULANT HAO | FAN6: ACTIF CIRCULANT HAO | FAV6: ACTIF CIRCULANT HAO | FBD6: ACTIF CIRCULANT HAO | FBL6: ACTIF CIRCULANT HAO | FBT6: ACTIF CIRCULANT HAO | FCB6: ACTIF CIRCULANT HAO | FCJ6: ACTIF CIRCULANT HAO | FCR6: ACTIF CIRCULANT HAO | FCZ6: ACTIF CIRCULANT HAO | FDH6: ACTIF CIRCULANT HAO | FDP6: ACTIF CIRCULANT HAO | FDX6: ACTIF CIRCULANT HAO | FEF6: ACTIF CIRCULANT HAO | FEN6: ACTIF CIRCULANT HAO | FEV6: ACTIF CIRCULANT HAO | FFD6: ACTIF CIRCULANT HAO | FFL6: ACTIF CIRCULANT HAO | FFT6: ACTIF CIRCULANT HAO | FGB6: ACTIF CIRCULANT HAO | FGJ6: ACTIF CIRCULANT HAO | FGR6: ACTIF CIRCULANT HAO | FGZ6: ACTIF CIRCULANT HAO | FHH6: ACTIF CIRCULANT HAO | FHP6: ACTIF CIRCULANT HAO | FHX6: ACTIF CIRCULANT HAO | FIF6: ACTIF CIRCULANT HAO | FIN6: ACTIF CIRCULANT HAO | FIV6: ACTIF CIRCULANT HAO | FJD6: ACTIF CIRCULANT HAO | FJL6: ACTIF CIRCULANT HAO | FJT6: ACTIF CIRCULANT HAO | FKB6: ACTIF CIRCULANT HAO | FKJ6: ACTIF CIRCULANT HAO | FKR6: ACTIF CIRCULANT HAO | FKZ6: ACTIF CIRCULANT HAO | FLH6: ACTIF CIRCULANT HAO | FLP6: ACTIF CIRCULANT HAO | FLX6: ACTIF CIRCULANT HAO | FMF6: ACTIF CIRCULANT HAO | FMN6: ACTIF CIRCULANT HAO | FMV6: ACTIF CIRCULANT HAO | FND6: ACTIF CIRCULANT HAO | FNL6: ACTIF CIRCULANT HAO | FNT6: ACTIF CIRCULANT HAO | FOB6: ACTIF CIRCULANT HAO | FOJ6: ACTIF CIRCULANT HAO | FOR6: ACTIF CIRCULANT HAO | FOZ6: ACTIF CIRCULANT HAO | FPH6: ACTIF CIRCULANT HAO | FPP6: ACTIF CIRCULANT HAO | FPX6: ACTIF CIRCULANT HAO | FQF6: ACTIF CIRCULANT HAO | FQN6: ACTIF CIRCULANT HAO | FQV6: ACTIF CIRCULANT HAO | FRD6: ACTIF CIRCULANT HAO | FRL6: ACTIF CIRCULANT HAO | FRT6: ACTIF CIRCULANT HAO | FSB6: ACTIF CIRCULANT HAO | FSJ6: ACTIF CIRCULANT HAO | FSR6: ACTIF CIRCULANT HAO | FSZ6: ACTIF CIRCULANT HAO | FTH6: ACTIF CIRCULANT HAO | FTP6: ACTIF CIRCULANT HAO | FTX6: ACTIF CIRCULANT HAO | FUF6: ACTIF CIRCULANT HAO | FUN6: ACTIF CIRCULANT HAO | FUV6: ACTIF CIRCULANT HAO | FVD6: ACTIF CIRCULANT HAO | FVL6: ACTIF CIRCULANT HAO | FVT6: ACTIF CIRCULANT HAO | FWB6: ACTIF CIRCULANT HAO | FWJ6: ACTIF CIRCULANT HAO | FWR6: ACTIF CIRCULANT HAO | FWZ6: ACTIF CIRCULANT HAO | FXH6: ACTIF CIRCULANT HAO | FXP6: ACTIF CIRCULANT HAO | FXX6: ACTIF CIRCULANT HAO | FYF6: ACTIF CIRCULANT HAO | FYN6: ACTIF CIRCULANT HAO | FYV6: ACTIF CIRCULANT HAO | FZD6: ACTIF CIRCULANT HAO | FZL6: ACTIF CIRCULANT HAO | FZT6: ACTIF CIRCULANT HAO | GAB6: ACTIF CIRCULANT HAO | GAJ6: ACTIF CIRCULANT HAO | GAR6: ACTIF CIRCULANT HAO | GAZ6: ACTIF CIRCULANT HAO | GBH6: ACTIF CIRCULANT HAO | GBP6: ACTIF CIRCULANT HAO | GBX6: ACTIF CIRCULANT HAO | GCF6: ACTIF CIRCULANT HAO | GCN6: ACTIF CIRCULANT HAO | GCV6: ACTIF CIRCULANT HAO | GDD6: ACTIF CIRCULANT HAO | GDL6: ACTIF CIRCULANT HAO | GDT6: ACTIF CIRCULANT HAO | GEB6: ACTIF CIRCULANT HAO | GEJ6: ACTIF CIRCULANT HAO | GER6: ACTIF CIRCULANT HAO | GEZ6: ACTIF CIRCULANT HAO | GFH6: ACTIF CIRCULANT HAO | GFP6: ACTIF CIRCULANT HAO | GFX6: ACTIF CIRCULANT HAO | GGF6: ACTIF CIRCULANT HAO | GGN6: ACTIF CIRCULANT HAO | GGV6: ACTIF CIRCULANT HAO | GHD6: ACTIF CIRCULANT HAO | GHL6: ACTIF CIRCULANT HAO | GHT6: ACTIF CIRCULANT HAO | GIB6: ACTIF CIRCULANT HAO | GIJ6: ACTIF CIRCULANT HAO | GIR6: ACTIF CIRCULANT HAO | GIZ6: ACTIF CIRCULANT HAO | GJH6: ACTIF CIRCULANT HAO | GJP6: ACTIF CIRCULANT HAO | GJX6: ACTIF CIRCULANT HAO | GKF6: ACTIF CIRCULANT HAO | GKN6: ACTIF CIRCULANT HAO | GKV6: ACTIF CIRCULANT HAO | GLD6: ACTIF CIRCULANT HAO | GLL6: ACTIF CIRCULANT HAO | GLT6: ACTIF CIRCULANT HAO | GMB6: ACTIF CIRCULANT HAO | GMJ6: ACTIF CIRCULANT HAO | GMR6: ACTIF CIRCULANT HAO | GMZ6: ACTIF CIRCULANT HAO | GNH6: ACTIF CIRCULANT HAO | GNP6: ACTIF CIRCULANT HAO | GNX6: ACTIF CIRCULANT HAO | GOF6: ACTIF CIRCULANT HAO | GON6: ACTIF CIRCULANT HAO | GOV6: ACTIF CIRCULANT HAO | GPD6: ACTIF CIRCULANT HAO | GPL6: ACTIF CIRCULANT HAO | GPT6: ACTIF CIRCULANT HAO | GQB6: ACTIF CIRCULANT HAO | GQJ6: ACTIF CIRCULANT HAO | GQR6: ACTIF CIRCULANT HAO | GQZ6: ACTIF CIRCULANT HAO | GRH6: ACTIF CIRCULANT HAO | GRP6: ACTIF CIRCULANT HAO | GRX6: ACTIF CIRCULANT HAO | GSF6: ACTIF CIRCULANT HAO | GSN6: ACTIF CIRCULANT HAO | GSV6: ACTIF CIRCULANT HAO | GTD6: ACTIF CIRCULANT HAO | GTL6: ACTIF CIRCULANT HAO | GTT6: ACTIF CIRCULANT HAO | GUB6: ACTIF CIRCULANT HAO | GUJ6: ACTIF CIRCULANT HAO | GUR6: ACTIF CIRCULANT HAO | GUZ6: ACTIF CIRCULANT HAO | GVH6: ACTIF CIRCULANT HAO | GVP6: ACTIF CIRCULANT HAO | GVX6: ACTIF CIRCULANT HAO | GWF6: ACTIF CIRCULANT HAO | GWN6: ACTIF CIRCULANT HAO | GWV6: ACTIF CIRCULANT HAO | GXD6: ACTIF CIRCULANT HAO | GXL6: ACTIF CIRCULANT HAO | GXT6: ACTIF CIRCULANT HAO | GYB6: ACTIF CIRCULANT HAO | GYJ6: ACTIF CIRCULANT HAO | GYR6: ACTIF CIRCULANT HAO | GYZ6: ACTIF CIRCULANT HAO | GZH6: ACTIF CIRCULANT HAO | GZP6: ACTIF CIRCULANT HAO | GZX6: ACTIF CIRCULANT HAO | HAF6: ACTIF CIRCULANT HAO | HAN6: ACTIF CIRCULANT HAO | HAV6: ACTIF CIRCULANT HAO | HBD6: ACTIF CIRCULANT HAO | HBL6: ACTIF CIRCULANT HAO | HBT6: ACTIF CIRCULANT HAO | HCB6: ACTIF CIRCULANT HAO | HCJ6: ACTIF CIRCULANT HAO | HCR6: ACTIF CIRCULANT HAO | HCZ6: ACTIF CIRCULANT HAO | HDH6: ACTIF CIRCULANT HAO | HDP6: ACTIF CIRCULANT HAO | HDX6: ACTIF CIRCULANT HAO | HEF6: ACTIF CIRCULANT HAO | HEN6: ACTIF CIRCULANT HAO | HEV6: ACTIF CIRCULANT HAO | HFD6: ACTIF CIRCULANT HAO | HFL6: ACTIF CIRCULANT HAO | HFT6: ACTIF CIRCULANT HAO | HGB6: ACTIF CIRCULANT HAO | HGJ6: ACTIF CIRCULANT HAO | HGR6: ACTIF CIRCULANT HAO | HGZ6: ACTIF CIRCULANT HAO | HHH6: ACTIF CIRCULANT HAO | HHP6: ACTIF CIRCULANT HAO | HHX6: ACTIF CIRCULANT HAO | HIF6: ACTIF CIRCULANT HAO | HIN6: ACTIF CIRCULANT HAO | HIV6: ACTIF CIRCULANT HAO | HJD6: ACTIF CIRCULANT HAO | HJL6: ACTIF CIRCULANT HAO | HJT6: ACTIF CIRCULANT HAO | HKB6: ACTIF CIRCULANT HAO | HKJ6: ACTIF CIRCULANT HAO | HKR6: ACTIF CIRCULANT HAO | HKZ6: ACTIF CIRCULANT HAO | HLH6: ACTIF CIRCULANT HAO | HLP6: ACTIF CIRCULANT HAO | HLX6: ACTIF CIRCULANT HAO | HMF6: ACTIF CIRCULANT HAO | HMN6: ACTIF CIRCULANT HAO | HMV6: ACTIF CIRCULANT HAO | HND6: ACTIF CIRCULANT HAO | HNL6: ACTIF CIRCULANT HAO | HNT6: ACTIF CIRCULANT HAO | HOB6: ACTIF CIRCULANT HAO | HOJ6: ACTIF CIRCULANT HAO | HOR6: ACTIF CIRCULANT HAO | HOZ6: ACTIF CIRCULANT HAO | HPH6: ACTIF CIRCULANT HAO | HPP6: ACTIF CIRCULANT HAO | HPX6: ACTIF CIRCULANT HAO | HQF6: ACTIF CIRCULANT HAO | HQN6: ACTIF CIRCULANT HAO | HQV6: ACTIF CIRCULANT HAO | HRD6: ACTIF CIRCULANT HAO | HRL6: ACTIF CIRCULANT HAO | HRT6: ACTIF CIRCULANT HAO | HSB6: ACTIF CIRCULANT HAO | HSJ6: ACTIF CIRCULANT HAO | HSR6: ACTIF CIRCULANT HAO | HSZ6: ACTIF CIRCULANT HAO | HTH6: ACTIF CIRCULANT HAO | HTP6: ACTIF CIRCULANT HAO | HTX6: ACTIF CIRCULANT HAO | HUF6: ACTIF CIRCULANT HAO | HUN6: ACTIF CIRCULANT HAO | HUV6: ACTIF CIRCULANT HAO | HVD6: ACTIF CIRCULANT HAO | HVL6: ACTIF CIRCULANT HAO | HVT6: ACTIF CIRCULANT HAO | HWB6: ACTIF CIRCULANT HAO | HWJ6: ACTIF CIRCULANT HAO | HWR6: ACTIF CIRCULANT HAO | HWZ6: ACTIF CIRCULANT HAO | HXH6: ACTIF CIRCULANT HAO | HXP6: ACTIF CIRCULANT HAO | HXX6: ACTIF CIRCULANT HAO | HYF6: ACTIF CIRCULANT HAO | HYN6: ACTIF CIRCULANT HAO | HYV6: ACTIF CIRCULANT HAO | HZD6: ACTIF CIRCULANT HAO | HZL6: ACTIF CIRCULANT HAO | HZT6: ACTIF CIRCULANT HAO | IAB6: ACTIF CIRCULANT HAO | IAJ6: ACTIF CIRCULANT HAO | IAR6: ACTIF CIRCULANT HAO | IAZ6: ACTIF CIRCULANT HAO | IBH6: ACTIF CIRCULANT HAO | IBP6: ACTIF CIRCULANT HAO | IBX6: ACTIF CIRCULANT HAO | ICF6: ACTIF CIRCULANT HAO | ICN6: ACTIF CIRCULANT HAO | ICV6: ACTIF CIRCULANT HAO | IDD6: ACTIF CIRCULANT HAO | IDL6: ACTIF CIRCULANT HAO | IDT6: ACTIF CIRCULANT HAO | IEB6: ACTIF CIRCULANT HAO | IEJ6: ACTIF CIRCULANT HAO | IER6: ACTIF CIRCULANT HAO | IEZ6: ACTIF CIRCULANT HAO | IFH6: ACTIF CIRCULANT HAO | IFP6: ACTIF CIRCULANT HAO | IFX6: ACTIF CIRCULANT HAO | IGF6: ACTIF CIRCULANT HAO | IGN6: ACTIF CIRCULANT HAO | IGV6: ACTIF CIRCULANT HAO | IHD6: ACTIF CIRCULANT HAO | IHL6: ACTIF CIRCULANT HAO | IHT6: ACTIF CIRCULANT HAO | IIB6: ACTIF CIRCULANT HAO | IIJ6: ACTIF CIRCULANT HAO | IIR6: ACTIF CIRCULANT HAO | IIZ6: ACTIF CIRCULANT HAO | IJH6: ACTIF CIRCULANT HAO | IJP6: ACTIF CIRCULANT HAO | IJX6: ACTIF CIRCULANT HAO | IKF6: ACTIF CIRCULANT HAO | IKN6: ACTIF CIRCULANT HAO | IKV6: ACTIF CIRCULANT HAO | ILD6: ACTIF CIRCULANT HAO | ILL6: ACTIF CIRCULANT HAO | ILT6: ACTIF CIRCULANT HAO | IMB6: ACTIF CIRCULANT HAO | IMJ6: ACTIF CIRCULANT HAO | IMR6: ACTIF CIRCULANT HAO | IMZ6: ACTIF CIRCULANT HAO | INH6: ACTIF CIRCULANT HAO | INP6: ACTIF CIRCULANT HAO | INX6: ACTIF CIRCULANT HAO | IOF6: ACTIF CIRCULANT HAO | ION6: ACTIF CIRCULANT HAO | IOV6: ACTIF CIRCULANT HAO | IPD6: ACTIF CIRCULANT HAO | IPL6: ACTIF CIRCULANT HAO | IPT6: ACTIF CIRCULANT HAO | IQB6: ACTIF CIRCULANT HAO | IQJ6: ACTIF CIRCULANT HAO | IQR6: ACTIF CIRCULANT HAO | IQZ6: ACTIF CIRCULANT HAO | IRH6: ACTIF CIRCULANT HAO | IRP6: ACTIF CIRCULANT HAO | IRX6: ACTIF CIRCULANT HAO | ISF6: ACTIF CIRCULANT HAO | ISN6: ACTIF CIRCULANT HAO | ISV6: ACTIF CIRCULANT HAO | ITD6: ACTIF CIRCULANT HAO | ITL6: ACTIF CIRCULANT HAO | ITT6: ACTIF CIRCULANT HAO | IUB6: ACTIF CIRCULANT HAO | IUJ6: ACTIF CIRCULANT HAO | IUR6: ACTIF CIRCULANT HAO | IUZ6: ACTIF CIRCULANT HAO | IVH6: ACTIF CIRCULANT HAO | IVP6: ACTIF CIRCULANT HAO | IVX6: ACTIF CIRCULANT HAO | IWF6: ACTIF CIRCULANT HAO | IWN6: ACTIF CIRCULANT HAO | IWV6: ACTIF CIRCULANT HAO | IXD6: ACTIF CIRCULANT HAO | IXL6: ACTIF CIRCULANT HAO | IXT6: ACTIF CIRCULANT HAO | IYB6: ACTIF CIRCULANT HAO | IYJ6: ACTIF CIRCULANT HAO | IYR6: ACTIF CIRCULANT HAO | IYZ6: ACTIF CIRCULANT HAO | IZH6: ACTIF CIRCULANT HAO | IZP6: ACTIF CIRCULANT HAO | IZX6: ACTIF CIRCULANT HAO | JAF6: ACTIF CIRCULANT HAO | JAN6: ACTIF CIRCULANT HAO | JAV6: ACTIF CIRCULANT HAO | JBD6: ACTIF CIRCULANT HAO | JBL6: ACTIF CIRCULANT HAO | JBT6: ACTIF CIRCULANT HAO | JCB6: ACTIF CIRCULANT HAO | JCJ6: ACTIF CIRCULANT HAO | JCR6: ACTIF CIRCULANT HAO | JCZ6: ACTIF CIRCULANT HAO | JDH6: ACTIF CIRCULANT HAO | JDP6: ACTIF CIRCULANT HAO | JDX6: ACTIF CIRCULANT HAO | JEF6: ACTIF CIRCULANT HAO | JEN6: ACTIF CIRCULANT HAO | JEV6: ACTIF CIRCULANT HAO | JFD6: ACTIF CIRCULANT HAO | JFL6: ACTIF CIRCULANT HAO | JFT6: ACTIF CIRCULANT HAO | JGB6: ACTIF CIRCULANT HAO | JGJ6: ACTIF CIRCULANT HAO | JGR6: ACTIF CIRCULANT HAO | JGZ6: ACTIF CIRCULANT HAO | JHH6: ACTIF CIRCULANT HAO | JHP6: ACTIF CIRCULANT HAO | JHX6: ACTIF CIRCULANT HAO | JIF6: ACTIF CIRCULANT HAO | JIN6: ACTIF CIRCULANT HAO | JIV6: ACTIF CIRCULANT HAO | JJD6: ACTIF CIRCULANT HAO | JJL6: ACTIF CIRCULANT HAO | JJT6: ACTIF CIRCULANT HAO | JKB6: ACTIF CIRCULANT HAO | JKJ6: ACTIF CIRCULANT HAO | JKR6: ACTIF CIRCULANT HAO | JKZ6: ACTIF CIRCULANT HAO | JLH6: ACTIF CIRCULANT HAO | JLP6: ACTIF CIRCULANT HAO | JLX6: ACTIF CIRCULANT HAO | JMF6: ACTIF CIRCULANT HAO | JMN6: ACTIF CIRCULANT HAO | JMV6: ACTIF CIRCULANT HAO | JND6: ACTIF CIRCULANT HAO | JNL6: ACTIF CIRCULANT HAO | JNT6: ACTIF CIRCULANT HAO | JOB6: ACTIF CIRCULANT HAO | JOJ6: ACTIF CIRCULANT HAO | JOR6: ACTIF CIRCULANT HAO | JOZ6: ACTIF CIRCULANT HAO | JPH6: ACTIF CIRCULANT HAO | JPP6: ACTIF CIRCULANT HAO | JPX6: ACTIF CIRCULANT HAO | JQF6: ACTIF CIRCULANT HAO | JQN6: ACTIF CIRCULANT HAO | JQV6: ACTIF CIRCULANT HAO | JRD6: ACTIF CIRCULANT HAO | JRL6: ACTIF CIRCULANT HAO | JRT6: ACTIF CIRCULANT HAO | JSB6: ACTIF CIRCULANT HAO | JSJ6: ACTIF CIRCULANT HAO | JSR6: ACTIF CIRCULANT HAO | JSZ6: ACTIF CIRCULANT HAO | JTH6: ACTIF CIRCULANT HAO | JTP6: ACTIF CIRCULANT HAO | JTX6: ACTIF CIRCULANT HAO | JUF6: ACTIF CIRCULANT HAO | JUN6: ACTIF CIRCULANT HAO | JUV6: ACTIF CIRCULANT HAO | JVD6: ACTIF CIRCULANT HAO | JVL6: ACTIF CIRCULANT HAO | JVT6: ACTIF CIRCULANT HAO | JWB6: ACTIF CIRCULANT HAO | JWJ6: ACTIF CIRCULANT HAO | JWR6: ACTIF CIRCULANT HAO | JWZ6: ACTIF CIRCULANT HAO | JXH6: ACTIF CIRCULANT HAO | JXP6: ACTIF CIRCULANT HAO | JXX6: ACTIF CIRCULANT HAO | JYF6: ACTIF CIRCULANT HAO | JYN6: ACTIF CIRCULANT HAO | JYV6: ACTIF CIRCULANT HAO | JZD6: ACTIF CIRCULANT HAO | JZL6: ACTIF CIRCULANT HAO | JZT6: ACTIF CIRCULANT HAO | KAB6: ACTIF CIRCULANT HAO | KAJ6: ACTIF CIRCULANT HAO | KAR6: ACTIF CIRCULANT HAO | KAZ6: ACTIF CIRCULANT HAO | KBH6: ACTIF CIRCULANT HAO | KBP6: ACTIF CIRCULANT HAO | KBX6: ACTIF CIRCULANT HAO | KCF6: ACTIF CIRCULANT HAO | KCN6: ACTIF CIRCULANT HAO | KCV6: ACTIF CIRCULANT HAO | KDD6: ACTIF CIRCULANT HAO | KDL6: ACTIF CIRCULANT HAO | KDT6: ACTIF CIRCULANT HAO | KEB6: ACTIF CIRCULANT HAO | KEJ6: ACTIF CIRCULANT HAO | KER6: ACTIF CIRCULANT HAO | KEZ6: ACTIF CIRCULANT HAO | KFH6: ACTIF CIRCULANT HAO | KFP6: ACTIF CIRCULANT HAO | KFX6: ACTIF CIRCULANT HAO | KGF6: ACTIF CIRCULANT HAO | KGN6: ACTIF CIRCULANT HAO | KGV6: ACTIF CIRCULANT HAO | KHD6: ACTIF CIRCULANT HAO | KHL6: ACTIF CIRCULANT HAO | KHT6: ACTIF CIRCULANT HAO | KIB6: ACTIF CIRCULANT HAO | KIJ6: ACTIF CIRCULANT HAO | KIR6: ACTIF CIRCULANT HAO | KIZ6: ACTIF CIRCULANT HAO | KJH6: ACTIF CIRCULANT HAO | KJP6: ACTIF CIRCULANT HAO | KJX6: ACTIF CIRCULANT HAO | KKF6: ACTIF CIRCULANT HAO | KKN6: ACTIF CIRCULANT HAO | KKV6: ACTIF CIRCULANT HAO | KLD6: ACTIF CIRCULANT HAO | KLL6: ACTIF CIRCULANT HAO | KLT6: ACTIF CIRCULANT HAO | KMB6: ACTIF CIRCULANT HAO | KMJ6: ACTIF CIRCULANT HAO | KMR6: ACTIF CIRCULANT HAO | KMZ6: ACTIF CIRCULANT HAO | KNH6: ACTIF CIRCULANT HAO | KNP6: ACTIF CIRCULANT HAO | KNX6: ACTIF CIRCULANT HAO | KOF6: ACTIF CIRCULANT HAO | KON6: ACTIF CIRCULANT HAO | KOV6: ACTIF CIRCULANT HAO | KPD6: ACTIF CIRCULANT HAO | KPL6: ACTIF CIRCULANT HAO | KPT6: ACTIF CIRCULANT HAO | KQB6: ACTIF CIRCULANT HAO | KQJ6: ACTIF CIRCULANT HAO | KQR6: ACTIF CIRCULANT HAO | KQZ6: ACTIF CIRCULANT HAO | KRH6: ACTIF CIRCULANT HAO | KRP6: ACTIF CIRCULANT HAO | KRX6: ACTIF CIRCULANT HAO | KSF6: ACTIF CIRCULANT HAO | KSN6: ACTIF CIRCULANT HAO | KSV6: ACTIF CIRCULANT HAO | KTD6: ACTIF CIRCULANT HAO | KTL6: ACTIF CIRCULANT HAO | KTT6: ACTIF CIRCULANT HAO | KUB6: ACTIF CIRCULANT HAO | KUJ6: ACTIF CIRCULANT HAO | KUR6: ACTIF CIRCULANT HAO | KUZ6: ACTIF CIRCULANT HAO | KVH6: ACTIF CIRCULANT HAO | KVP6: ACTIF CIRCULANT HAO | KVX6: ACTIF CIRCULANT HAO | KWF6: ACTIF CIRCULANT HAO | KWN6: ACTIF CIRCULANT HAO | KWV6: ACTIF CIRCULANT HAO | KXD6: ACTIF CIRCULANT HAO | KXL6: ACTIF CIRCULANT HAO | KXT6: ACTIF CIRCULANT HAO | KYB6: ACTIF CIRCULANT HAO | KYJ6: ACTIF CIRCULANT HAO | KYR6: ACTIF CIRCULANT HAO | KYZ6: ACTIF CIRCULANT HAO | KZH6: ACTIF CIRCULANT HAO | KZP6: ACTIF CIRCULANT HAO | KZX6: ACTIF CIRCULANT HAO | LAF6: ACTIF CIRCULANT HAO | LAN6: ACTIF CIRCULANT HAO | LAV6: ACTIF CIRCULANT HAO | LBD6: ACTIF CIRCULANT HAO | LBL6: ACTIF CIRCULANT HAO | LBT6: ACTIF CIRCULANT HAO | LCB6: ACTIF CIRCULANT HAO | LCJ6: ACTIF CIRCULANT HAO | LCR6: ACTIF CIRCULANT HAO | LCZ6: ACTIF CIRCULANT HAO | LDH6: ACTIF CIRCULANT HAO | LDP6: ACTIF CIRCULANT HAO | LDX6: ACTIF CIRCULANT HAO | LEF6: ACTIF CIRCULANT HAO | LEN6: ACTIF CIRCULANT HAO | LEV6: ACTIF CIRCULANT HAO | LFD6: ACTIF CIRCULANT HAO | LFL6: ACTIF CIRCULANT HAO | LFT6: ACTIF CIRCULANT HAO | LGB6: ACTIF CIRCULANT HAO | LGJ6: ACTIF CIRCULANT HAO | LGR6: ACTIF CIRCULANT HAO | LGZ6: ACTIF CIRCULANT HAO | LHH6: ACTIF CIRCULANT HAO | LHP6: ACTIF CIRCULANT HAO | LHX6: ACTIF CIRCULANT HAO | LIF6: ACTIF CIRCULANT HAO | LIN6: ACTIF CIRCULANT HAO | LIV6: ACTIF CIRCULANT HAO | LJD6: ACTIF CIRCULANT HAO | LJL6: ACTIF CIRCULANT HAO | LJT6: ACTIF CIRCULANT HAO | LKB6: ACTIF CIRCULANT HAO | LKJ6: ACTIF CIRCULANT HAO | LKR6: ACTIF CIRCULANT HAO | LKZ6: ACTIF CIRCULANT HAO | LLH6: ACTIF CIRCULANT HAO | LLP6: ACTIF CIRCULANT HAO | LLX6: ACTIF CIRCULANT HAO | LMF6: ACTIF CIRCULANT HAO | LMN6: ACTIF CIRCULANT HAO | LMV6: ACTIF CIRCULANT HAO | LND6: ACTIF CIRCULANT HAO | LNL6: ACTIF CIRCULANT HAO | LNT6: ACTIF CIRCULANT HAO | LOB6: ACTIF CIRCULANT HAO | LOJ6: ACTIF CIRCULANT HAO | LOR6: ACTIF CIRCULANT HAO | LOZ6: ACTIF CIRCULANT HAO | LPH6: ACTIF CIRCULANT HAO | LPP6: ACTIF CIRCULANT HAO | LPX6: ACTIF CIRCULANT HAO | LQF6: ACTIF CIRCULANT HAO | LQN6: ACTIF CIRCULANT HAO | LQV6: ACTIF CIRCULANT HAO | LRD6: ACTIF CIRCULANT HAO | LRL6: ACTIF CIRCULANT HAO | LRT6: ACTIF CIRCULANT HAO | LSB6: ACTIF CIRCULANT HAO | LSJ6: ACTIF CIRCULANT HAO | LSR6: ACTIF CIRCULANT HAO | LSZ6: ACTIF CIRCULANT HAO | LTH6: ACTIF CIRCULANT HAO | LTP6: ACTIF CIRCULANT HAO | LTX6: ACTIF CIRCULANT HAO | LUF6: ACTIF CIRCULANT HAO | LUN6: ACTIF CIRCULANT HAO | LUV6: ACTIF CIRCULANT HAO | LVD6: ACTIF CIRCULANT HAO | LVL6: ACTIF CIRCULANT HAO | LVT6: ACTIF CIRCULANT HAO | LWB6: ACTIF CIRCULANT HAO | LWJ6: ACTIF CIRCULANT HAO | LWR6: ACTIF CIRCULANT HAO | LWZ6: ACTIF CIRCULANT HAO | LXH6: ACTIF CIRCULANT HAO | LXP6: ACTIF CIRCULANT HAO | LXX6: ACTIF CIRCULANT HAO | LYF6: ACTIF CIRCULANT HAO | LYN6: ACTIF CIRCULANT HAO | LYV6: ACTIF CIRCULANT HAO | LZD6: ACTIF CIRCULANT HAO | LZL6: ACTIF CIRCULANT HAO | LZT6: ACTIF CIRCULANT HAO | MAB6: ACTIF CIRCULANT HAO | MAJ6: ACTIF CIRCULANT HAO | MAR6: ACTIF CIRCULANT HAO | MAZ6: ACTIF CIRCULANT HAO | MBH6: ACTIF CIRCULANT HAO | MBP6: ACTIF CIRCULANT HAO | MBX6: ACTIF CIRCULANT HAO | MCF6: ACTIF CIRCULANT HAO | MCN6: ACTIF CIRCULANT HAO | MCV6: ACTIF CIRCULANT HAO | MDD6: ACTIF CIRCULANT HAO | MDL6: ACTIF CIRCULANT HAO | MDT6: ACTIF CIRCULANT HAO | MEB6: ACTIF CIRCULANT HAO | MEJ6: ACTIF CIRCULANT HAO | MER6: ACTIF CIRCULANT HAO | MEZ6: ACTIF CIRCULANT HAO | MFH6: ACTIF CIRCULANT HAO | MFP6: ACTIF CIRCULANT HAO | MFX6: ACTIF CIRCULANT HAO | MGF6: ACTIF CIRCULANT HAO | MGN6: ACTIF CIRCULANT HAO | MGV6: ACTIF CIRCULANT HAO | MHD6: ACTIF CIRCULANT HAO | MHL6: ACTIF CIRCULANT HAO | MHT6: ACTIF CIRCULANT HAO | MIB6: ACTIF CIRCULANT HAO | MIJ6: ACTIF CIRCULANT HAO | MIR6: ACTIF CIRCULANT HAO | MIZ6: ACTIF CIRCULANT HAO | MJH6: ACTIF CIRCULANT HAO | MJP6: ACTIF CIRCULANT HAO | MJX6: ACTIF CIRCULANT HAO | MKF6: ACTIF CIRCULANT HAO | MKN6: ACTIF CIRCULANT HAO | MKV6: ACTIF CIRCULANT HAO | MLD6: ACTIF CIRCULANT HAO | MLL6: ACTIF CIRCULANT HAO | MLT6: ACTIF CIRCULANT HAO | MMB6: ACTIF CIRCULANT HAO | MMJ6: ACTIF CIRCULANT HAO | MMR6: ACTIF CIRCULANT HAO | MMZ6: ACTIF CIRCULANT HAO | MNH6: ACTIF CIRCULANT HAO | MNP6: ACTIF CIRCULANT HAO | MNX6: ACTIF CIRCULANT HAO | MOF6: ACTIF CIRCULANT HAO | MON6: ACTIF CIRCULANT HAO | MOV6: ACTIF CIRCULANT HAO | MPD6: ACTIF CIRCULANT HAO | MPL6: ACTIF CIRCULANT HAO | MPT6: ACTIF CIRCULANT HAO | MQB6: ACTIF CIRCULANT HAO | MQJ6: ACTIF CIRCULANT HAO | MQR6: ACTIF CIRCULANT HAO | MQZ6: ACTIF CIRCULANT HAO | MRH6: ACTIF CIRCULANT HAO | MRP6: ACTIF CIRCULANT HAO | MRX6: ACTIF CIRCULANT HAO | MSF6: ACTIF CIRCULANT HAO | MSN6: ACTIF CIRCULANT HAO | MSV6: ACTIF CIRCULANT HAO | MTD6: ACTIF CIRCULANT HAO | MTL6: ACTIF CIRCULANT HAO | MTT6: ACTIF CIRCULANT HAO | MUB6: ACTIF CIRCULANT HAO | MUJ6: ACTIF CIRCULANT HAO | MUR6: ACTIF CIRCULANT HAO | MUZ6: ACTIF CIRCULANT HAO | MVH6: ACTIF CIRCULANT HAO | MVP6: ACTIF CIRCULANT HAO | MVX6: ACTIF CIRCULANT HAO | MWF6: ACTIF CIRCULANT HAO | MWN6: ACTIF CIRCULANT HAO | MWV6: ACTIF CIRCULANT HAO | MXD6: ACTIF CIRCULANT HAO | MXL6: ACTIF CIRCULANT HAO | MXT6: ACTIF CIRCULANT HAO | MYB6: ACTIF CIRCULANT HAO | MYJ6: ACTIF CIRCULANT HAO | MYR6: ACTIF CIRCULANT HAO | MYZ6: ACTIF CIRCULANT HAO | MZH6: ACTIF CIRCULANT HAO | MZP6: ACTIF CIRCULANT HAO | MZX6: ACTIF CIRCULANT HAO | NAF6: ACTIF CIRCULANT HAO | NAN6: ACTIF CIRCULANT HAO | NAV6: ACTIF CIRCULANT HAO | NBD6: ACTIF CIRCULANT HAO | NBL6: ACTIF CIRCULANT HAO | NBT6: ACTIF CIRCULANT HAO | NCB6: ACTIF CIRCULANT HAO | NCJ6: ACTIF CIRCULANT HAO | NCR6: ACTIF CIRCULANT HAO | NCZ6: ACTIF CIRCULANT HAO | NDH6: ACTIF CIRCULANT HAO | NDP6: ACTIF CIRCULANT HAO | NDX6: ACTIF CIRCULANT HAO | NEF6: ACTIF CIRCULANT HAO | NEN6: ACTIF CIRCULANT HAO | NEV6: ACTIF CIRCULANT HAO | NFD6: ACTIF CIRCULANT HAO | NFL6: ACTIF CIRCULANT HAO | NFT6: ACTIF CIRCULANT HAO | NGB6: ACTIF CIRCULANT HAO | NGJ6: ACTIF CIRCULANT HAO | NGR6: ACTIF CIRCULANT HAO | NGZ6: ACTIF CIRCULANT HAO | NHH6: ACTIF CIRCULANT HAO | NHP6: ACTIF CIRCULANT HAO | NHX6: ACTIF CIRCULANT HAO | NIF6: ACTIF CIRCULANT HAO | NIN6: ACTIF CIRCULANT HAO | NIV6: ACTIF CIRCULANT HAO | NJD6: ACTIF CIRCULANT HAO | NJL6: ACTIF CIRCULANT HAO | NJT6: ACTIF CIRCULANT HAO | NKB6: ACTIF CIRCULANT HAO | NKJ6: ACTIF CIRCULANT HAO | NKR6: ACTIF CIRCULANT HAO | NKZ6: ACTIF CIRCULANT HAO | NLH6: ACTIF CIRCULANT HAO | NLP6: ACTIF CIRCULANT HAO | NLX6: ACTIF CIRCULANT HAO | NMF6: ACTIF CIRCULANT HAO | NMN6: ACTIF CIRCULANT HAO | NMV6: ACTIF CIRCULANT HAO | NND6: ACTIF CIRCULANT HAO | NNL6: ACTIF CIRCULANT HAO | NNT6: ACTIF CIRCULANT HAO | NOB6: ACTIF CIRCULANT HAO | NOJ6: ACTIF CIRCULANT HAO | NOR6: ACTIF CIRCULANT HAO | NOZ6: ACTIF CIRCULANT HAO | NPH6: ACTIF CIRCULANT HAO | NPP6: ACTIF CIRCULANT HAO | NPX6: ACTIF CIRCULANT HAO | NQF6: ACTIF CIRCULANT HAO | NQN6: ACTIF CIRCULANT HAO | NQV6: ACTIF CIRCULANT HAO | NRD6: ACTIF CIRCULANT HAO | NRL6: ACTIF CIRCULANT HAO | NRT6: ACTIF CIRCULANT HAO | NSB6: ACTIF CIRCULANT HAO | NSJ6: ACTIF CIRCULANT HAO | NSR6: ACTIF CIRCULANT HAO | NSZ6: ACTIF CIRCULANT HAO | NTH6: ACTIF CIRCULANT HAO | NTP6: ACTIF CIRCULANT HAO | NTX6: ACTIF CIRCULANT HAO | NUF6: ACTIF CIRCULANT HAO | NUN6: ACTIF CIRCULANT HAO | NUV6: ACTIF CIRCULANT HAO | NVD6: ACTIF CIRCULANT HAO | NVL6: ACTIF CIRCULANT HAO | NVT6: ACTIF CIRCULANT HAO | NWB6: ACTIF CIRCULANT HAO | NWJ6: ACTIF CIRCULANT HAO | NWR6: ACTIF CIRCULANT HAO | NWZ6: ACTIF CIRCULANT HAO | NXH6: ACTIF CIRCULANT HAO | NXP6: ACTIF CIRCULANT HAO | NXX6: ACTIF CIRCULANT HAO | NYF6: ACTIF CIRCULANT HAO | NYN6: ACTIF CIRCULANT HAO | NYV6: ACTIF CIRCULANT HAO | NZD6: ACTIF CIRCULANT HAO | NZL6: ACTIF CIRCULANT HAO | NZT6: ACTIF CIRCULANT HAO | OAB6: ACTIF CIRCULANT HAO | OAJ6: ACTIF CIRCULANT HAO | OAR6: ACTIF CIRCULANT HAO | OAZ6: ACTIF CIRCULANT HAO | OBH6: ACTIF CIRCULANT HAO | OBP6: ACTIF CIRCULANT HAO | OBX6: ACTIF CIRCULANT HAO | OCF6: ACTIF CIRCULANT HAO | OCN6: ACTIF CIRCULANT HAO | OCV6: ACTIF CIRCULANT HAO | ODD6: ACTIF CIRCULANT HAO | ODL6: ACTIF CIRCULANT HAO | ODT6: ACTIF CIRCULANT HAO | OEB6: ACTIF CIRCULANT HAO | OEJ6: ACTIF CIRCULANT HAO | OER6: ACTIF CIRCULANT HAO | OEZ6: ACTIF CIRCULANT HAO | OFH6: ACTIF CIRCULANT HAO | OFP6: ACTIF CIRCULANT HAO | OFX6: ACTIF CIRCULANT HAO | OGF6: ACTIF CIRCULANT HAO | OGN6: ACTIF CIRCULANT HAO | OGV6: ACTIF CIRCULANT HAO | OHD6: ACTIF CIRCULANT HAO | OHL6: ACTIF CIRCULANT HAO | OHT6: ACTIF CIRCULANT HAO | OIB6: ACTIF CIRCULANT HAO | OIJ6: ACTIF CIRCULANT HAO | OIR6: ACTIF CIRCULANT HAO | OIZ6: ACTIF CIRCULANT HAO | OJH6: ACTIF CIRCULANT HAO | OJP6: ACTIF CIRCULANT HAO | OJX6: ACTIF CIRCULANT HAO | OKF6: ACTIF CIRCULANT HAO | OKN6: ACTIF CIRCULANT HAO | OKV6: ACTIF CIRCULANT HAO | OLD6: ACTIF CIRCULANT HAO | OLL6: ACTIF CIRCULANT HAO | OLT6: ACTIF CIRCULANT HAO | OMB6: ACTIF CIRCULANT HAO | OMJ6: ACTIF CIRCULANT HAO | OMR6: ACTIF CIRCULANT HAO | OMZ6: ACTIF CIRCULANT HAO | ONH6: ACTIF CIRCULANT HAO | ONP6: ACTIF CIRCULANT HAO | ONX6: ACTIF CIRCULANT HAO | OOF6: ACTIF CIRCULANT HAO | OON6: ACTIF CIRCULANT HAO | OOV6: ACTIF CIRCULANT HAO | OPD6: ACTIF CIRCULANT HAO | OPL6: ACTIF CIRCULANT HAO | OPT6: ACTIF CIRCULANT HAO | OQB6: ACTIF CIRCULANT HAO | OQJ6: ACTIF CIRCULANT HAO | OQR6: ACTIF CIRCULANT HAO | OQZ6: ACTIF CIRCULANT HAO | ORH6: ACTIF CIRCULANT HAO | ORP6: ACTIF CIRCULANT HAO | ORX6: ACTIF CIRCULANT HAO | OSF6: ACTIF CIRCULANT HAO | OSN6: ACTIF CIRCULANT HAO | OSV6: ACTIF CIRCULANT HAO | OTD6: ACTIF CIRCULANT HAO | OTL6: ACTIF CIRCULANT HAO | OTT6: ACTIF CIRCULANT HAO | OUB6: ACTIF CIRCULANT HAO | OUJ6: ACTIF CIRCULANT HAO | OUR6: ACTIF CIRCULANT HAO | OUZ6: ACTIF CIRCULANT HAO | OVH6: ACTIF CIRCULANT HAO | OVP6: ACTIF CIRCULANT HAO | OVX6: ACTIF CIRCULANT HAO | OWF6: ACTIF CIRCULANT HAO | OWN6: ACTIF CIRCULANT HAO | OWV6: ACTIF CIRCULANT HAO | OXD6: ACTIF CIRCULANT HAO | OXL6: ACTIF CIRCULANT HAO | OXT6: ACTIF CIRCULANT HAO | OYB6: ACTIF CIRCULANT HAO | OYJ6: ACTIF CIRCULANT HAO | OYR6: ACTIF CIRCULANT HAO | OYZ6: ACTIF CIRCULANT HAO | OZH6: ACTIF CIRCULANT HAO | OZP6: ACTIF CIRCULANT HAO | OZX6: ACTIF CIRCULANT HAO | PAF6: ACTIF CIRCULANT HAO | PAN6: ACTIF CIRCULANT HAO | PAV6: ACTIF CIRCULANT HAO | PBD6: ACTIF CIRCULANT HAO | PBL6: ACTIF CIRCULANT HAO | PBT6: ACTIF CIRCULANT HAO | PCB6: ACTIF CIRCULANT HAO | PCJ6: ACTIF CIRCULANT HAO | PCR6: ACTIF CIRCULANT HAO | PCZ6: ACTIF CIRCULANT HAO | PDH6: ACTIF CIRCULANT HAO | PDP6: ACTIF CIRCULANT HAO | PDX6: ACTIF CIRCULANT HAO | PEF6: ACTIF CIRCULANT HAO | PEN6: ACTIF CIRCULANT HAO | PEV6: ACTIF CIRCULANT HAO | PFD6: ACTIF CIRCULANT HAO | PFL6: ACTIF CIRCULANT HAO | PFT6: ACTIF CIRCULANT HAO | PGB6: ACTIF CIRCULANT HAO | PGJ6: ACTIF CIRCULANT HAO | PGR6: ACTIF CIRCULANT HAO | PGZ6: ACTIF CIRCULANT HAO | PHH6: ACTIF CIRCULANT HAO | PHP6: ACTIF CIRCULANT HAO | PHX6: ACTIF CIRCULANT HAO | PIF6: ACTIF CIRCULANT HAO | PIN6: ACTIF CIRCULANT HAO | PIV6: ACTIF CIRCULANT HAO | PJD6: ACTIF CIRCULANT HAO | PJL6: ACTIF CIRCULANT HAO | PJT6: ACTIF CIRCULANT HAO | PKB6: ACTIF CIRCULANT HAO | PKJ6: ACTIF CIRCULANT HAO | PKR6: ACTIF CIRCULANT HAO | PKZ6: ACTIF CIRCULANT HAO | PLH6: ACTIF CIRCULANT HAO | PLP6: ACTIF CIRCULANT HAO | PLX6: ACTIF CIRCULANT HAO | PMF6: ACTIF CIRCULANT HAO | PMN6: ACTIF CIRCULANT HAO | PMV6: ACTIF CIRCULANT HAO | PND6: ACTIF CIRCULANT HAO | PNL6: ACTIF CIRCULANT HAO | PNT6: ACTIF CIRCULANT HAO | POB6: ACTIF CIRCULANT HAO | POJ6: ACTIF CIRCULANT HAO | POR6: ACTIF CIRCULANT HAO | POZ6: ACTIF CIRCULANT HAO | PPH6: ACTIF CIRCULANT HAO | PPP6: ACTIF CIRCULANT HAO | PPX6: ACTIF CIRCULANT HAO | PQF6: ACTIF CIRCULANT HAO | PQN6: ACTIF CIRCULANT HAO | PQV6: ACTIF CIRCULANT HAO | PRD6: ACTIF CIRCULANT HAO | PRL6: ACTIF CIRCULANT HAO | PRT6: ACTIF CIRCULANT HAO | PSB6: ACTIF CIRCULANT HAO | PSJ6: ACTIF CIRCULANT HAO | PSR6: ACTIF CIRCULANT HAO | PSZ6: ACTIF CIRCULANT HAO | PTH6: ACTIF CIRCULANT HAO | PTP6: ACTIF CIRCULANT HAO | PTX6: ACTIF CIRCULANT HAO | PUF6: ACTIF CIRCULANT HAO | PUN6: ACTIF CIRCULANT HAO | PUV6: ACTIF CIRCULANT HAO | PVD6: ACTIF CIRCULANT HAO | PVL6: ACTIF CIRCULANT HAO | PVT6: ACTIF CIRCULANT HAO | PWB6: ACTIF CIRCULANT HAO | PWJ6: ACTIF CIRCULANT HAO | PWR6: ACTIF CIRCULANT HAO | PWZ6: ACTIF CIRCULANT HAO | PXH6: ACTIF CIRCULANT HAO | PXP6: ACTIF CIRCULANT HAO | PXX6: ACTIF CIRCULANT HAO | PYF6: ACTIF CIRCULANT HAO | PYN6: ACTIF CIRCULANT HAO | PYV6: ACTIF CIRCULANT HAO | PZD6: ACTIF CIRCULANT HAO | PZL6: ACTIF CIRCULANT HAO | PZT6: ACTIF CIRCULANT HAO | QAB6: ACTIF CIRCULANT HAO | QAJ6: ACTIF CIRCULANT HAO | QAR6: ACTIF CIRCULANT HAO | QAZ6: ACTIF CIRCULANT HAO | QBH6: ACTIF CIRCULANT HAO | QBP6: ACTIF CIRCULANT HAO | QBX6: ACTIF CIRCULANT HAO | QCF6: ACTIF CIRCULANT HAO | QCN6: ACTIF CIRCULANT HAO | QCV6: ACTIF CIRCULANT HAO | QDD6: ACTIF CIRCULANT HAO | QDL6: ACTIF CIRCULANT HAO | QDT6: ACTIF CIRCULANT HAO | QEB6: ACTIF CIRCULANT HAO | QEJ6: ACTIF CIRCULANT HAO | QER6: ACTIF CIRCULANT HAO | QEZ6: ACTIF CIRCULANT HAO | QFH6: ACTIF CIRCULANT HAO | QFP6: ACTIF CIRCULANT HAO | QFX6: ACTIF CIRCULANT HAO | QGF6: ACTIF CIRCULANT HAO | QGN6: ACTIF CIRCULANT HAO | QGV6: ACTIF CIRCULANT HAO | QHD6: ACTIF CIRCULANT HAO | QHL6: ACTIF CIRCULANT HAO | QHT6: ACTIF CIRCULANT HAO | QIB6: ACTIF CIRCULANT HAO | QIJ6: ACTIF CIRCULANT HAO | QIR6: ACTIF CIRCULANT HAO | QIZ6: ACTIF CIRCULANT HAO | QJH6: ACTIF CIRCULANT HAO | QJP6: ACTIF CIRCULANT HAO | QJX6: ACTIF CIRCULANT HAO | QKF6: ACTIF CIRCULANT HAO | QKN6: ACTIF CIRCULANT HAO | QKV6: ACTIF CIRCULANT HAO | QLD6: ACTIF CIRCULANT HAO | QLL6: ACTIF CIRCULANT HAO | QLT6: ACTIF CIRCULANT HAO | QMB6: ACTIF CIRCULANT HAO | QMJ6: ACTIF CIRCULANT HAO | QMR6: ACTIF CIRCULANT HAO | QMZ6: ACTIF CIRCULANT HAO | QNH6: ACTIF CIRCULANT HAO | QNP6: ACTIF CIRCULANT HAO | QNX6: ACTIF CIRCULANT HAO | QOF6: ACTIF CIRCULANT HAO | QON6: ACTIF CIRCULANT HAO | QOV6: ACTIF CIRCULANT HAO | QPD6: ACTIF CIRCULANT HAO | QPL6: ACTIF CIRCULANT HAO | QPT6: ACTIF CIRCULANT HAO | QQB6: ACTIF CIRCULANT HAO | QQJ6: ACTIF CIRCULANT HAO | QQR6: ACTIF CIRCULANT HAO | QQZ6: ACTIF CIRCULANT HAO | QRH6: ACTIF CIRCULANT HAO | QRP6: ACTIF CIRCULANT HAO | QRX6: ACTIF CIRCULANT HAO | QSF6: ACTIF CIRCULANT HAO | QSN6: ACTIF CIRCULANT HAO | QSV6: ACTIF CIRCULANT HAO | QTD6: ACTIF CIRCULANT HAO | QTL6: ACTIF CIRCULANT HAO | QTT6: ACTIF CIRCULANT HAO | QUB6: ACTIF CIRCULANT HAO | QUJ6: ACTIF CIRCULANT HAO | QUR6: ACTIF CIRCULANT HAO | QUZ6: ACTIF CIRCULANT HAO | QVH6: ACTIF CIRCULANT HAO | QVP6: ACTIF CIRCULANT HAO | QVX6: ACTIF CIRCULANT HAO | QWF6: ACTIF CIRCULANT HAO | QWN6: ACTIF CIRCULANT HAO | QWV6: ACTIF CIRCULANT HAO | QXD6: ACTIF CIRCULANT HAO | QXL6: ACTIF CIRCULANT HAO | QXT6: ACTIF CIRCULANT HAO | QYB6: ACTIF CIRCULANT HAO | QYJ6: ACTIF CIRCULANT HAO | QYR6: ACTIF CIRCULANT HAO | QYZ6: ACTIF CIRCULANT HAO | QZH6: ACTIF CIRCULANT HAO | QZP6: ACTIF CIRCULANT HAO | QZX6: ACTIF CIRCULANT HAO | RAF6: ACTIF CIRCULANT HAO | RAN6: ACTIF CIRCULANT HAO | RAV6: ACTIF CIRCULANT HAO | RBD6: ACTIF CIRCULANT HAO | RBL6: ACTIF CIRCULANT HAO | RBT6: ACTIF CIRCULANT HAO | RCB6: ACTIF CIRCULANT HAO | RCJ6: ACTIF CIRCULANT HAO | RCR6: ACTIF CIRCULANT HAO | RCZ6: ACTIF CIRCULANT HAO | RDH6: ACTIF CIRCULANT HAO | RDP6: ACTIF CIRCULANT HAO | RDX6: ACTIF CIRCULANT HAO | REF6: ACTIF CIRCULANT HAO | REN6: ACTIF CIRCULANT HAO | REV6: ACTIF CIRCULANT HAO | RFD6: ACTIF CIRCULANT HAO | RFL6: ACTIF CIRCULANT HAO | RFT6: ACTIF CIRCULANT HAO | RGB6: ACTIF CIRCULANT HAO | RGJ6: ACTIF CIRCULANT HAO | RGR6: ACTIF CIRCULANT HAO | RGZ6: ACTIF CIRCULANT HAO | RHH6: ACTIF CIRCULANT HAO | RHP6: ACTIF CIRCULANT HAO | RHX6: ACTIF CIRCULANT HAO | RIF6: ACTIF CIRCULANT HAO | RIN6: ACTIF CIRCULANT HAO | RIV6: ACTIF CIRCULANT HAO | RJD6: ACTIF CIRCULANT HAO | RJL6: ACTIF CIRCULANT HAO | RJT6: ACTIF CIRCULANT HAO | RKB6: ACTIF CIRCULANT HAO | RKJ6: ACTIF CIRCULANT HAO | RKR6: ACTIF CIRCULANT HAO | RKZ6: ACTIF CIRCULANT HAO | RLH6: ACTIF CIRCULANT HAO | RLP6: ACTIF CIRCULANT HAO | RLX6: ACTIF CIRCULANT HAO | RMF6: ACTIF CIRCULANT HAO | RMN6: ACTIF CIRCULANT HAO | RMV6: ACTIF CIRCULANT HAO | RND6: ACTIF CIRCULANT HAO | RNL6: ACTIF CIRCULANT HAO | RNT6: ACTIF CIRCULANT HAO | ROB6: ACTIF CIRCULANT HAO | ROJ6: ACTIF CIRCULANT HAO | ROR6: ACTIF CIRCULANT HAO | ROZ6: ACTIF CIRCULANT HAO | RPH6: ACTIF CIRCULANT HAO | RPP6: ACTIF CIRCULANT HAO | RPX6: ACTIF CIRCULANT HAO | RQF6: ACTIF CIRCULANT HAO | RQN6: ACTIF CIRCULANT HAO | RQV6: ACTIF CIRCULANT HAO | RRD6: ACTIF CIRCULANT HAO | RRL6: ACTIF CIRCULANT HAO | RRT6: ACTIF CIRCULANT HAO | RSB6: ACTIF CIRCULANT HAO | RSJ6: ACTIF CIRCULANT HAO | RSR6: ACTIF CIRCULANT HAO | RSZ6: ACTIF CIRCULANT HAO | RTH6: ACTIF CIRCULANT HAO | RTP6: ACTIF CIRCULANT HAO | RTX6: ACTIF CIRCULANT HAO | RUF6: ACTIF CIRCULANT HAO | RUN6: ACTIF CIRCULANT HAO | RUV6: ACTIF CIRCULANT HAO | RVD6: ACTIF CIRCULANT HAO | RVL6: ACTIF CIRCULANT HAO | RVT6: ACTIF CIRCULANT HAO | RWB6: ACTIF CIRCULANT HAO | RWJ6: ACTIF CIRCULANT HAO | RWR6: ACTIF CIRCULANT HAO | RWZ6: ACTIF CIRCULANT HAO | RXH6: ACTIF CIRCULANT HAO | RXP6: ACTIF CIRCULANT HAO | RXX6: ACTIF CIRCULANT HAO | RYF6: ACTIF CIRCULANT HAO | RYN6: ACTIF CIRCULANT HAO | RYV6: ACTIF CIRCULANT HAO | RZD6: ACTIF CIRCULANT HAO | RZL6: ACTIF CIRCULANT HAO | RZT6: ACTIF CIRCULANT HAO | SAB6: ACTIF CIRCULANT HAO | SAJ6: ACTIF CIRCULANT HAO | SAR6: ACTIF CIRCULANT HAO | SAZ6: ACTIF CIRCULANT HAO | SBH6: ACTIF CIRCULANT HAO | SBP6: ACTIF CIRCULANT HAO | SBX6: ACTIF CIRCULANT HAO | SCF6: ACTIF CIRCULANT HAO | SCN6: ACTIF CIRCULANT HAO | SCV6: ACTIF CIRCULANT HAO | SDD6: ACTIF CIRCULANT HAO | SDL6: ACTIF CIRCULANT HAO | SDT6: ACTIF CIRCULANT HAO | SEB6: ACTIF CIRCULANT HAO | SEJ6: ACTIF CIRCULANT HAO | SER6: ACTIF CIRCULANT HAO | SEZ6: ACTIF CIRCULANT HAO | SFH6: ACTIF CIRCULANT HAO | SFP6: ACTIF CIRCULANT HAO | SFX6: ACTIF CIRCULANT HAO | SGF6: ACTIF CIRCULANT HAO | SGN6: ACTIF CIRCULANT HAO | SGV6: ACTIF CIRCULANT HAO | SHD6: ACTIF CIRCULANT HAO | SHL6: ACTIF CIRCULANT HAO | SHT6: ACTIF CIRCULANT HAO | SIB6: ACTIF CIRCULANT HAO | SIJ6: ACTIF CIRCULANT HAO | SIR6: ACTIF CIRCULANT HAO | SIZ6: ACTIF CIRCULANT HAO | SJH6: ACTIF CIRCULANT HAO | SJP6: ACTIF CIRCULANT HAO | SJX6: ACTIF CIRCULANT HAO | SKF6: ACTIF CIRCULANT HAO | SKN6: ACTIF CIRCULANT HAO | SKV6: ACTIF CIRCULANT HAO | SLD6: ACTIF CIRCULANT HAO | SLL6: ACTIF CIRCULANT HAO | SLT6: ACTIF CIRCULANT HAO | SMB6: ACTIF CIRCULANT HAO | SMJ6: ACTIF CIRCULANT HAO | SMR6: ACTIF CIRCULANT HAO | SMZ6: ACTIF CIRCULANT HAO | SNH6: ACTIF CIRCULANT HAO | SNP6: ACTIF CIRCULANT HAO | SNX6: ACTIF CIRCULANT HAO | SOF6: ACTIF CIRCULANT HAO | SON6: ACTIF CIRCULANT HAO | SOV6: ACTIF CIRCULANT HAO | SPD6: ACTIF CIRCULANT HAO | SPL6: ACTIF CIRCULANT HAO | SPT6: ACTIF CIRCULANT HAO | SQB6: ACTIF CIRCULANT HAO | SQJ6: ACTIF CIRCULANT HAO | SQR6: ACTIF CIRCULANT HAO | SQZ6: ACTIF CIRCULANT HAO | SRH6: ACTIF CIRCULANT HAO | SRP6: ACTIF CIRCULANT HAO | SRX6: ACTIF CIRCULANT HAO | SSF6: ACTIF CIRCULANT HAO | SSN6: ACTIF CIRCULANT HAO | SSV6: ACTIF CIRCULANT HAO | STD6: ACTIF CIRCULANT HAO | STL6: ACTIF CIRCULANT HAO | STT6: ACTIF CIRCULANT HAO | SUB6: ACTIF CIRCULANT HAO | SUJ6: ACTIF CIRCULANT HAO | SUR6: ACTIF CIRCULANT HAO | SUZ6: ACTIF CIRCULANT HAO | SVH6: ACTIF CIRCULANT HAO | SVP6: ACTIF CIRCULANT HAO | SVX6: ACTIF CIRCULANT HAO | SWF6: ACTIF CIRCULANT HAO | SWN6: ACTIF CIRCULANT HAO | SWV6: ACTIF CIRCULANT HAO | SXD6: ACTIF CIRCULANT HAO | SXL6: ACTIF CIRCULANT HAO | SXT6: ACTIF CIRCULANT HAO | SYB6: ACTIF CIRCULANT HAO | SYJ6: ACTIF CIRCULANT HAO | SYR6: ACTIF CIRCULANT HAO | SYZ6: ACTIF CIRCULANT HAO | SZH6: ACTIF CIRCULANT HAO | SZP6: ACTIF CIRCULANT HAO | SZX6: ACTIF CIRCULANT HAO | TAF6: ACTIF CIRCULANT HAO | TAN6: ACTIF CIRCULANT HAO | TAV6: ACTIF CIRCULANT HAO | TBD6: ACTIF CIRCULANT HAO | TBL6: ACTIF CIRCULANT HAO | TBT6: ACTIF CIRCULANT HAO | TCB6: ACTIF CIRCULANT HAO | TCJ6: ACTIF CIRCULANT HAO | TCR6: ACTIF CIRCULANT HAO | TCZ6: ACTIF CIRCULANT HAO | TDH6: ACTIF CIRCULANT HAO | TDP6: ACTIF CIRCULANT HAO | TDX6: ACTIF CIRCULANT HAO | TEF6: ACTIF CIRCULANT HAO | TEN6: ACTIF CIRCULANT HAO | TEV6: ACTIF CIRCULANT HAO | TFD6: ACTIF CIRCULANT HAO | TFL6: ACTIF CIRCULANT HAO | TFT6: ACTIF CIRCULANT HAO | TGB6: ACTIF CIRCULANT HAO | TGJ6: ACTIF CIRCULANT HAO | TGR6: ACTIF CIRCULANT HAO | TGZ6: ACTIF CIRCULANT HAO | THH6: ACTIF CIRCULANT HAO | THP6: ACTIF CIRCULANT HAO | THX6: ACTIF CIRCULANT HAO | TIF6: ACTIF CIRCULANT HAO | TIN6: ACTIF CIRCULANT HAO | TIV6: ACTIF CIRCULANT HAO | TJD6: ACTIF CIRCULANT HAO | TJL6: ACTIF CIRCULANT HAO | TJT6: ACTIF CIRCULANT HAO | TKB6: ACTIF CIRCULANT HAO | TKJ6: ACTIF CIRCULANT HAO | TKR6: ACTIF CIRCULANT HAO | TKZ6: ACTIF CIRCULANT HAO | TLH6: ACTIF CIRCULANT HAO | TLP6: ACTIF CIRCULANT HAO | TLX6: ACTIF CIRCULANT HAO | TMF6: ACTIF CIRCULANT HAO | TMN6: ACTIF CIRCULANT HAO | TMV6: ACTIF CIRCULANT HAO | TND6: ACTIF CIRCULANT HAO | TNL6: ACTIF CIRCULANT HAO | TNT6: ACTIF CIRCULANT HAO | TOB6: ACTIF CIRCULANT HAO | TOJ6: ACTIF CIRCULANT HAO | TOR6: ACTIF CIRCULANT HAO | TOZ6: ACTIF CIRCULANT HAO | TPH6: ACTIF CIRCULANT HAO | TPP6: ACTIF CIRCULANT HAO | TPX6: ACTIF CIRCULANT HAO | TQF6: ACTIF CIRCULANT HAO | TQN6: ACTIF CIRCULANT HAO | TQV6: ACTIF CIRCULANT HAO | TRD6: ACTIF CIRCULANT HAO | TRL6: ACTIF CIRCULANT HAO | TRT6: ACTIF CIRCULANT HAO | TSB6: ACTIF CIRCULANT HAO | TSJ6: ACTIF CIRCULANT HAO | TSR6: ACTIF CIRCULANT HAO | TSZ6: ACTIF CIRCULANT HAO | TTH6: ACTIF CIRCULANT HAO | TTP6: ACTIF CIRCULANT HAO | TTX6: ACTIF CIRCULANT HAO | TUF6: ACTIF CIRCULANT HAO | TUN6: ACTIF CIRCULANT HAO | TUV6: ACTIF CIRCULANT HAO | TVD6: ACTIF CIRCULANT HAO | TVL6: ACTIF CIRCULANT HAO | TVT6: ACTIF CIRCULANT HAO | TWB6: ACTIF CIRCULANT HAO | TWJ6: ACTIF CIRCULANT HAO | TWR6: ACTIF CIRCULANT HAO | TWZ6: ACTIF CIRCULANT HAO | TXH6: ACTIF CIRCULANT HAO | TXP6: ACTIF CIRCULANT HAO | TXX6: ACTIF CIRCULANT HAO | TYF6: ACTIF CIRCULANT HAO | TYN6: ACTIF CIRCULANT HAO | TYV6: ACTIF CIRCULANT HAO | TZD6: ACTIF CIRCULANT HAO | TZL6: ACTIF CIRCULANT HAO | TZT6: ACTIF CIRCULANT HAO | UAB6: ACTIF CIRCULANT HAO | UAJ6: ACTIF CIRCULANT HAO | UAR6: ACTIF CIRCULANT HAO | UAZ6: ACTIF CIRCULANT HAO | UBH6: ACTIF CIRCULANT HAO | UBP6: ACTIF CIRCULANT HAO | UBX6: ACTIF CIRCULANT HAO | UCF6: ACTIF CIRCULANT HAO | UCN6: ACTIF CIRCULANT HAO | UCV6: ACTIF CIRCULANT HAO | UDD6: ACTIF CIRCULANT HAO | UDL6: ACTIF CIRCULANT HAO | UDT6: ACTIF CIRCULANT HAO | UEB6: ACTIF CIRCULANT HAO | UEJ6: ACTIF CIRCULANT HAO | UER6: ACTIF CIRCULANT HAO | UEZ6: ACTIF CIRCULANT HAO | UFH6: ACTIF CIRCULANT HAO | UFP6: ACTIF CIRCULANT HAO | UFX6: ACTIF CIRCULANT HAO | UGF6: ACTIF CIRCULANT HAO | UGN6: ACTIF CIRCULANT HAO | UGV6: ACTIF CIRCULANT HAO | UHD6: ACTIF CIRCULANT HAO | UHL6: ACTIF CIRCULANT HAO | UHT6: ACTIF CIRCULANT HAO | UIB6: ACTIF CIRCULANT HAO | UIJ6: ACTIF CIRCULANT HAO | UIR6: ACTIF CIRCULANT HAO | UIZ6: ACTIF CIRCULANT HAO | UJH6: ACTIF CIRCULANT HAO | UJP6: ACTIF CIRCULANT HAO | UJX6: ACTIF CIRCULANT HAO | UKF6: ACTIF CIRCULANT HAO | UKN6: ACTIF CIRCULANT HAO | UKV6: ACTIF CIRCULANT HAO | ULD6: ACTIF CIRCULANT HAO | ULL6: ACTIF CIRCULANT HAO | ULT6: ACTIF CIRCULANT HAO | UMB6: ACTIF CIRCULANT HAO | UMJ6: ACTIF CIRCULANT HAO | UMR6: ACTIF CIRCULANT HAO | UMZ6: ACTIF CIRCULANT HAO | UNH6: ACTIF CIRCULANT HAO | UNP6: ACTIF CIRCULANT HAO | UNX6: ACTIF CIRCULANT HAO | UOF6: ACTIF CIRCULANT HAO | UON6: ACTIF CIRCULANT HAO | UOV6: ACTIF CIRCULANT HAO | UPD6: ACTIF CIRCULANT HAO | UPL6: ACTIF CIRCULANT HAO | UPT6: ACTIF CIRCULANT HAO | UQB6: ACTIF CIRCULANT HAO | UQJ6: ACTIF CIRCULANT HAO | UQR6: ACTIF CIRCULANT HAO | UQZ6: ACTIF CIRCULANT HAO | URH6: ACTIF CIRCULANT HAO | URP6: ACTIF CIRCULANT HAO | URX6: ACTIF CIRCULANT HAO | USF6: ACTIF CIRCULANT HAO | USN6: ACTIF CIRCULANT HAO | USV6: ACTIF CIRCULANT HAO | UTD6: ACTIF CIRCULANT HAO | UTL6: ACTIF CIRCULANT HAO | UTT6: ACTIF CIRCULANT HAO | UUB6: ACTIF CIRCULANT HAO | UUJ6: ACTIF CIRCULANT HAO | UUR6: ACTIF CIRCULANT HAO | UUZ6: ACTIF CIRCULANT HAO | UVH6: ACTIF CIRCULANT HAO | UVP6: ACTIF CIRCULANT HAO | UVX6: ACTIF CIRCULANT HAO | UWF6: ACTIF CIRCULANT HAO | UWN6: ACTIF CIRCULANT HAO | UWV6: ACTIF CIRCULANT HAO | UXD6: ACTIF CIRCULANT HAO | UXL6: ACTIF CIRCULANT HAO | UXT6: ACTIF CIRCULANT HAO | UYB6: ACTIF CIRCULANT HAO | UYJ6: ACTIF CIRCULANT HAO | UYR6: ACTIF CIRCULANT HAO | UYZ6: ACTIF CIRCULANT HAO | UZH6: ACTIF CIRCULANT HAO | UZP6: ACTIF CIRCULANT HAO | UZX6: ACTIF CIRCULANT HAO | VAF6: ACTIF CIRCULANT HAO | VAN6: ACTIF CIRCULANT HAO | VAV6: ACTIF CIRCULANT HAO | VBD6: ACTIF CIRCULANT HAO | VBL6: ACTIF CIRCULANT HAO | VBT6: ACTIF CIRCULANT HAO | VCB6: ACTIF CIRCULANT HAO | VCJ6: ACTIF CIRCULANT HAO | VCR6: ACTIF CIRCULANT HAO | VCZ6: ACTIF CIRCULANT HAO | VDH6: ACTIF CIRCULANT HAO | VDP6: ACTIF CIRCULANT HAO | VDX6: ACTIF CIRCULANT HAO | VEF6: ACTIF CIRCULANT HAO | VEN6: ACTIF CIRCULANT HAO | VEV6: ACTIF CIRCULANT HAO | VFD6: ACTIF CIRCULANT HAO | VFL6: ACTIF CIRCULANT HAO | VFT6: ACTIF CIRCULANT HAO | VGB6: ACTIF CIRCULANT HAO | VGJ6: ACTIF CIRCULANT HAO | VGR6: ACTIF CIRCULANT HAO | VGZ6: ACTIF CIRCULANT HAO | VHH6: ACTIF CIRCULANT HAO | VHP6: ACTIF CIRCULANT HAO | VHX6: ACTIF CIRCULANT HAO | VIF6: ACTIF CIRCULANT HAO | VIN6: ACTIF CIRCULANT HAO | VIV6: ACTIF CIRCULANT HAO | VJD6: ACTIF CIRCULANT HAO | VJL6: ACTIF CIRCULANT HAO | VJT6: ACTIF CIRCULANT HAO | VKB6: ACTIF CIRCULANT HAO | VKJ6: ACTIF CIRCULANT HAO | VKR6: ACTIF CIRCULANT HAO | VKZ6: ACTIF CIRCULANT HAO | VLH6: ACTIF CIRCULANT HAO | VLP6: ACTIF CIRCULANT HAO | VLX6: ACTIF CIRCULANT HAO | VMF6: ACTIF CIRCULANT HAO | VMN6: ACTIF CIRCULANT HAO | VMV6: ACTIF CIRCULANT HAO | VND6: ACTIF CIRCULANT HAO | VNL6: ACTIF CIRCULANT HAO | VNT6: ACTIF CIRCULANT HAO | VOB6: ACTIF CIRCULANT HAO | VOJ6: ACTIF CIRCULANT HAO | VOR6: ACTIF CIRCULANT HAO | VOZ6: ACTIF CIRCULANT HAO | VPH6: ACTIF CIRCULANT HAO | VPP6: ACTIF CIRCULANT HAO | VPX6: ACTIF CIRCULANT HAO | VQF6: ACTIF CIRCULANT HAO | VQN6: ACTIF CIRCULANT HAO | VQV6: ACTIF CIRCULANT HAO | VRD6: ACTIF CIRCULANT HAO | VRL6: ACTIF CIRCULANT HAO | VRT6: ACTIF CIRCULANT HAO | VSB6: ACTIF CIRCULANT HAO | VSJ6: ACTIF CIRCULANT HAO | VSR6: ACTIF CIRCULANT HAO | VSZ6: ACTIF CIRCULANT HAO | VTH6: ACTIF CIRCULANT HAO | VTP6: ACTIF CIRCULANT HAO | VTX6: ACTIF CIRCULANT HAO | VUF6: ACTIF CIRCULANT HAO | VUN6: ACTIF CIRCULANT HAO | VUV6: ACTIF CIRCULANT HAO | VVD6: ACTIF CIRCULANT HAO | VVL6: ACTIF CIRCULANT HAO | VVT6: ACTIF CIRCULANT HAO | VWB6: ACTIF CIRCULANT HAO | VWJ6: ACTIF CIRCULANT HAO | VWR6: ACTIF CIRCULANT HAO | VWZ6: ACTIF CIRCULANT HAO | VXH6: ACTIF CIRCULANT HAO | VXP6: ACTIF CIRCULANT HAO | VXX6: ACTIF CIRCULANT HAO | VYF6: ACTIF CIRCULANT HAO | VYN6: ACTIF CIRCULANT HAO | VYV6: ACTIF CIRCULANT HAO | VZD6: ACTIF CIRCULANT HAO | VZL6: ACTIF CIRCULANT HAO | VZT6: ACTIF CIRCULANT HAO | WAB6: ACTIF CIRCULANT HAO | WAJ6: ACTIF CIRCULANT HAO | WAR6: ACTIF CIRCULANT HAO | WAZ6: ACTIF CIRCULANT HAO | WBH6: ACTIF CIRCULANT HAO | WBP6: ACTIF CIRCULANT HAO | WBX6: ACTIF CIRCULANT HAO | WCF6: ACTIF CIRCULANT HAO | WCN6: ACTIF CIRCULANT HAO | WCV6: ACTIF CIRCULANT HAO | WDD6: ACTIF CIRCULANT HAO | WDL6: ACTIF CIRCULANT HAO | WDT6: ACTIF CIRCULANT HAO | WEB6: ACTIF CIRCULANT HAO | WEJ6: ACTIF CIRCULANT HAO | WER6: ACTIF CIRCULANT HAO | WEZ6: ACTIF CIRCULANT HAO | WFH6: ACTIF CIRCULANT HAO | WFP6: ACTIF CIRCULANT HAO | WFX6: ACTIF CIRCULANT HAO | WGF6: ACTIF CIRCULANT HAO | WGN6: ACTIF CIRCULANT HAO | WGV6: ACTIF CIRCULANT HAO | WHD6: ACTIF CIRCULANT HAO | WHL6: ACTIF CIRCULANT HAO | WHT6: ACTIF CIRCULANT HAO | WIB6: ACTIF CIRCULANT HAO | WIJ6: ACTIF CIRCULANT HAO | WIR6: ACTIF CIRCULANT HAO | WIZ6: ACTIF CIRCULANT HAO | WJH6: ACTIF CIRCULANT HAO | WJP6: ACTIF CIRCULANT HAO | WJX6: ACTIF CIRCULANT HAO | WKF6: ACTIF CIRCULANT HAO | WKN6: ACTIF CIRCULANT HAO | WKV6: ACTIF CIRCULANT HAO | WLD6: ACTIF CIRCULANT HAO | WLL6: ACTIF CIRCULANT HAO | WLT6: ACTIF CIRCULANT HAO | WMB6: ACTIF CIRCULANT HAO | WMJ6: ACTIF CIRCULANT HAO | WMR6: ACTIF CIRCULANT HAO | WMZ6: ACTIF CIRCULANT HAO | WNH6: ACTIF CIRCULANT HAO | WNP6: ACTIF CIRCULANT HAO | WNX6: ACTIF CIRCULANT HAO | WOF6: ACTIF CIRCULANT HAO | WON6: ACTIF CIRCULANT HAO | WOV6: ACTIF CIRCULANT HAO | WPD6: ACTIF CIRCULANT HAO | WPL6: ACTIF CIRCULANT HAO | WPT6: ACTIF CIRCULANT HAO | WQB6: ACTIF CIRCULANT HAO | WQJ6: ACTIF CIRCULANT HAO | WQR6: ACTIF CIRCULANT HAO | WQZ6: ACTIF CIRCULANT HAO | WRH6: ACTIF CIRCULANT HAO | WRP6: ACTIF CIRCULANT HAO | WRX6: ACTIF CIRCULANT HAO | WSF6: ACTIF CIRCULANT HAO | WSN6: ACTIF CIRCULANT HAO | WSV6: ACTIF CIRCULANT HAO | WTD6: ACTIF CIRCULANT HAO | WTL6: ACTIF CIRCULANT HAO | WTT6: ACTIF CIRCULANT HAO | WUB6: ACTIF CIRCULANT HAO | WUJ6: ACTIF CIRCULANT HAO | WUR6: ACTIF CIRCULANT HAO | WUZ6: ACTIF CIRCULANT HAO | WVH6: ACTIF CIRCULANT HAO | WVP6: ACTIF CIRCULANT HAO | WVX6: ACTIF CIRCULANT HAO | WWF6: ACTIF CIRCULANT HAO | WWN6: ACTIF CIRCULANT HAO | WWV6: ACTIF CIRCULANT HAO | WXD6: ACTIF CIRCULANT HAO | WXL6: ACTIF CIRCULANT HAO | WXT6: ACTIF CIRCULANT HAO | WYB6: ACTIF CIRCULANT HAO | WYJ6: ACTIF CIRCULANT HAO | WYR6: ACTIF CIRCULANT HAO | WYZ6: ACTIF CIRCULANT HAO | WZH6: ACTIF CIRCULANT HAO | WZP6: ACTIF CIRCULANT HAO | WZX6: ACTIF CIRCULANT HAO | XAF6: ACTIF CIRCULANT HAO | XAN6: ACTIF CIRCULANT HAO | XAV6: ACTIF CIRCULANT HAO | XBD6: ACTIF CIRCULANT HAO | XBL6: ACTIF CIRCULANT HAO | XBT6: ACTIF CIRCULANT HAO | XCB6: ACTIF CIRCULANT HAO | XCJ6: ACTIF CIRCULANT HAO | XCR6: ACTIF CIRCULANT HAO | XCZ6: ACTIF CIRCULANT HAO | XDH6: ACTIF CIRCULANT HAO | XDP6: ACTIF CIRCULANT HAO | XDX6: ACTIF CIRCULANT HAO | XEF6: ACTIF CIRCULANT HAO | XEN6: ACTIF CIRCULANT HAO | XEV6: ACTIF CIRCULANT HAO
A8: LIBELLES | B8: =IFERROR(YEAR('Fiche de renseignement R1'!V10),"Annee N") -> 1900 | D8: =IFERROR(YEAR('Fiche de renseignement R1'!Q20),"Annee N-1") -> 2020 | F8: Variation en %
A10: Créances sur cessions d'immobilisations | B10: =+SUMIF('BAL N'!J:J,"=485",'BAL N'!G:G) -> 0 | D10: =+SUMIF('BAL N'!J:J,"=485",'BAL N'!C:C) -> 0 | F10: =IFERROR((B10-D10)/B10,0) -> 0
A11: Autres créances hors activités ordinaires | B11: =+SUMIF('BAL N'!J:J,"=488",'BAL N'!G:G) -> 0 | D11: =+SUMIF('BAL N'!J:J,"=488",'BAL N'!C:C) -> 0 | F11: =IFERROR((B11-D11)/B11,0) -> 0
A12: TOTAL BRUT | B12: =SUM(B10:C11) -> 0 | D12: =SUM(D10:E11) -> 0 | F12: =SUM(F10:G11) -> 0
A13: Dépréciations des créances HAO
A14: TOTAL NET DE DEPRECIATION
A15: Commentaire :
A16: · Commenter touter variation significative
A17: · Dépréciation : indiquer les évènements et les circonstances qui ont motivé
A18: la dépréciation ou la reprise
A20: DETTES CIRCULANTES HAO
A22: LIBELLES | B22: =IFERROR(YEAR('Fiche de renseignement R1'!V10),"Annee N") -> 1900 | D22: =IFERROR(YEAR('Fiche de renseignement R1'!Q20),"Annee N-1") -> 2020 | F22: VARIATION EN %
A24: Fournisseurs d'investissements
A25: Fournisseurs d'investissements effets à payer
A26: Versements restant à effectuer sur titres de participation et titres immobilisés non libérés
A27: Autres dettes hors activités ordinaires
A28: TOTAL
A29: Commentaire :
A30: · Indiquer la date de cession et la nature de l'immobilisation achétée et/ou cédée
A31: · Expliquer toute variation significative

Sheet Note 6
A1: NOTE 6 : STOCKS ET ENCOURS(1)
A3: Désignation entité : | B3: ='Fiche de renseignement R1'!$J$4 -> 0 | C3: Excercice clos le : | D3: =+'Note 1'!E3 -> 0
A4: Numéro d'identification : | B4: =+'Note 1'!B4 -> 0 | C4: Durée en mois : | D4: =+'Note 1'!E4 -> 12
A6: LIBELLES | B6: =IFERROR(YEAR('Fiche de renseignement R1'!V10),"Annee N") -> 1900 | C6: =IFERROR(YEAR('Fiche de renseignement R1'!Q20),"Annee N-1") -> 2020 | D6: VARIATION EN %
A8: Marchandises | B8: =+SUMIF('BAL N'!I:I,"=31",'BAL N'!G:G) -> 0 | C8: =+SUMIF('BAL N'!I:I,"=31",'BAL N'!C:C) -> 0 | D8: =IFERROR((B8-C8)/B8,0) -> 0
A9: Matières premières et fournitures liées | B9: =+SUMIF('BAL N'!I:I,"=32",'BAL N'!G:G) -> 0 | C9: =+SUMIF('BAL N'!I:I,"=32",'BAL N'!C:C) -> 0 | D9: =IFERROR((B9-C9)/B9,0) -> 0
A10: Autres approvisionnements | B10: =+SUMIF('BAL N'!I:I,"=33",'BAL N'!G:G) -> 0 | C10: =+SUMIF('BAL N'!I:I,"=33",'BAL N'!C:C) -> 0 | D10: =IFERROR((B10-C10)/B10,0) -> 0
A11: Produits en cours | B11: =+SUMIF('BAL N'!I:I,"=34",'BAL N'!G:G) -> 0 | C11: =+SUMIF('BAL N'!I:I,"=34",'BAL N'!C:C) -> 0 | D11: =IFERROR((B11-C11)/B11,0) -> 0
A12: Services en cours | B12: =+SUMIF('BAL N'!I:I,"=35",'BAL N'!G:G) -> 0 | C12: =+SUMIF('BAL N'!I:I,"=35",'BAL N'!C:C) -> 0 | D12: =IFERROR((B12-C12)/B12,0) -> 0
A13: Produits finis | B13: =+SUMIF('BAL N'!I:I,"=36",'BAL N'!G:G) -> 0 | C13: =+SUMIF('BAL N'!I:I,"=36",'BAL N'!C:C) -> 0 | D13: =IFERROR((B13-C13)/B13,0) -> 0
A14: Produits intermédiaires | B14: =+SUMIF('BAL N'!I:I,"=37",'BAL N'!G:G) -> 0 | C14: =+SUMIF('BAL N'!I:I,"=37",'BAL N'!C:C) -> 0 | D14: =IFERROR((B14-C14)/B14,0) -> 0
A15: Stocks en cours de route, en consignation ou en dépôt | B15: =+SUMIF('BAL N'!I:I,"=38",'BAL N'!G:G) -> 0 | C15: =+SUMIF('BAL N'!I:I,"=38",'BAL N'!C:C) -> 0 | D15: =IFERROR((B15-C15)/B15,0) -> 0
A16: TOTAL BRUT STOCKS ET EN COURS | B16: =SUM(B8:B15) -> 0 | C16: =SUM(C8:C15) -> 0 | D16: =IFERROR((B16-C16)/B16,0) -> 0
A17: Dépréciations des stocks | B17: =+SUMIF('BAL N'!I:I,"=39",'BAL N'!H:H) -> 0 | C17: =+SUMIF('BAL N'!I:I,"=39",'BAL N'!D:D) -> 0 | D17: =IFERROR((B17-C17)/B17,0) -> 0
D18: =IFERROR((B18-C18)/B18,0) -> 0
A19: Total net de dépréciation | B19: =SUM(B17) -> 0 | C19: =SUM(C17) -> 0 | D19: =IFERROR((B19-C19)/B19,0) -> 0
A20: (1) : Les stocks HAO seront inscrits dans l'actif circulant HAO que lorsque leur montant total est significatif
A21: (supérieur à 5% du total de l'actif circulant)
A22: Commentaire :
A23: · Indiquer la date de prise d'inventaire et décrire brièvement la procédure, les méthodes comptables adoptées
A24: pour évaluer le stock
A25: · Commenter toute variation significative des stocks
A26: · Indiquer le détail des stocks dépréciés et les évènements et circonstances qui ont conduit à la dépréciation
A27: et à la reprise

Sheet Note 7
A1: NOTE 7 : CLIENTS
A3: Désignation entité : | B3: ='Fiche de renseignement R1'!$J$4 -> 0 | E3: Excercice clos le : | F3: =+'Note 1'!E3 -> 0
A4: Numéro d'identification : | B4: =+'Note 1'!B4 -> 0 | E4: Durée en mois : | F4: =+'Note 1'!E4 -> 12
A7: LIBELLES | B7: =IFERROR(YEAR('Fiche de renseignement R1'!V10),"Annee N") -> 1900 | C7: =IFERROR(YEAR('Fiche de renseignement R1'!Q20),"Annee N-1") -> 2020 | D7: Variation en % | E7: Créances à un an au plus | F7: Créances à plus d'un an et à deux ans au plus | G7: Créances à plus de deux ans
A9: Clients (hors réserves de propriété Groupe) | B9: =+SUMIF('BAL N'!J:J,"=411",'BAL N'!G:G)-SUMIF('BAL N'!K:K,"=4116",'BAL N'!G:G) -> 0 | C9: =+SUMIF('BAL N'!J:J,"=411",'BAL N'!C:C)-SUMIF('BAL N'!K:K,"=4116",'BAL N'!C:C) -> 0 | D9: =IFERROR((B9-C9)/B9,0) -> 0
A10: Clients effets à recevoir (hors réserves de propriété Groupe) | B10: =+SUMIF('BAL N'!J:J,"=412",'BAL N'!G:G)-SUMIF('BAL N'!K:K,"=4126",'BAL N'!G:G) -> 0 | C10: =+SUMIF('BAL N'!J:J,"=412",'BAL N'!C:C)-SUMIF('BAL N'!K:K,"=4122",'BAL N'!C:C) -> 0 | D10: =IFERROR((B10-C10)/B10,0) -> 0
A11: Clients effets à recevoir avec réserves de propriété | B11: =+SUMIF('BAL N'!K:K,"=4116",'BAL N'!G:G)+SUMIF('BAL N'!K:K,"=4126",'BAL N'!G:G) -> 0 | C11: =+SUMIF('BAL N'!J:J,"=412",'BAL N'!C:C) -> 0 | D11: =IFERROR((B11-C11)/B11,0) -> 0
A12: Clients et effets à recevoir Groupe | B12: =+SUMIF('BAL N'!K:K,"=4122",'BAL N'!G:G) -> 0 | C12: =+SUMIF('BAL N'!K:K,"=4122",'BAL N'!C:C) -> 0 | D12: =IFERROR((B12-C12)/B12,0) -> 0
A13: Créances sur cession d'immobilisations | B13: =+SUMIF('BAL N'!J:J,"=414",'BAL N'!G:G) -> 0 | C13: =+SUMIF('BAL N'!J:J,"=485",'BAL N'!C:C) -> 0 | D13: =IFERROR((B13-C13)/B13,0) -> 0
A14: Clients effets escomptés et non échus | B14: =+SUMIF('BAL N'!J:J,"=415",'BAL N'!G:G) -> 0 | C14: =+SUMIF('BAL N'!J:J,"=415",'BAL N'!C:C) -> 0 | D14: =IFERROR((B14-C14)/B14,0) -> 0
A15: Créances litigieuses ou douteuses | B15: =+SUMIF('BAL N'!J:J,"=416",'BAL N'!G:G) -> 0 | C15: =+SUMIF('BAL N'!J:J,"=416",'BAL N'!C:C) -> 0 | D15: =IFERROR((B15-C15)/B15,0) -> 0
A16: Clients produits à recevoir | B16: =+SUMIF('BAL N'!J:J,"=482",'BAL N'!G:G) -> 0 | C16: =+SUMIF('BAL N'!J:J,"=482",'BAL N'!C:C) -> 0 | D16: =IFERROR((B16-C16)/B16,0) -> 0
A17: TOTAL BRUT CLIENTS | B17: =SUM(B9:B16) -> 0 | C17: =SUM(C9:C16) -> 0 | D17: =IFERROR((B17-C17)/B17,0) -> 0
A18: Dépréciations des comptes clients | B18: =+SUMIF('BAL N'!J:J,"=491",'BAL N'!H:H) -> 0 | D18: =IFERROR((B18-C18)/B18,0) -> 0
A19: TOTAL NET DE DEPRECIATION | B19: =SUM(B18) -> 0 | C19: =SUM(C18) -> 0 | D19: =IFERROR((B19-C19)/B19,0) -> 0
A20: Clients, avances reçues hors groupe | B20: =+SUMIF('BAL N'!K:K,"=4191",'BAL N'!H:H)+SUMIF('BAL N'!J:J,"=419",'BAL N'!H:H) -> 0 | C20: =+SUMIF('BAL N'!K:K,"=4191",'BAL N'!D:D) -> 0 | D20: =IFERROR((B20-C20)/B20,0) -> 0
A21: Clients, avances reçues groupe | B21: =+SUMIF('BAL N'!K:K,"=4192",'BAL N'!H:H) -> 0 | C21: =+SUMIF('BAL N'!K:K,"=4192",'BAL N'!D:D) -> 0 | D21: =IFERROR((B21-C21)/B21,0) -> 0
A22: Autres clients créditeurs | B22: =+SUMIF('BAL N'!K:K,"=4193",'BAL N'!H:H)+SUMIF('BAL N'!K:K,"=4194",'BAL N'!H:H)+SUMIF('BAL N'!K:K,"=4195",'BAL N'!H:H)+SUMIF('BAL N'!K:K,"=4196",'BAL N'!H:H) -> 0 | C22: =+SUMIF('BAL N'!K:K,"=4192",'BAL N'!D:D)+SUMIF('BAL N'!K:K,"=4193",'BAL N'!D:D)+SUMIF('BAL N'!K:K,"=4194",'BAL N'!D:D)+SUMIF('BAL N'!K:K,"=4195",'BAL N'!D:D) -> 0 | D22: =IFERROR((B22-C22)/B22,0) -> 0
A23: TOTAL CLIENTS CREDITEURS | B23: =SUM(B20:B22) -> 0 | C23: =SUM(C20:C22) -> 0 | D23: =IFERROR((B23-C23)/B23,0) -> 0
A24: Commentaire :
A25: · Commenter toutes variations significatives
A26: · Indiquer pour les créances du groupe, le nom de la société du groupe et le % de titres détenues
A27: · Commenter toutes les créances anciennes
A28: · Indiquer les évènements et les circonstances qui ont conduit à la dépréciation et à la reprise

Sheet Note 8
A1: NOTE 8 : AUTRES CREANCES
A3: Désignation entité : | B3: ='Fiche de renseignement R1'!$J$4 -> 0 | E3: Excercice clos le : | F3: =+'Note 1'!E3 -> 0
A4: Numéro d'identification : | B4: =+'Note 1'!B4 -> 0 | E4: Durée en mois : | F4: =+'Note 1'!E4 -> 12
A7: LIBELLES | B7: =IFERROR(YEAR('Fiche de renseignement R1'!V10),"Annee N") -> 1900 | C7: =IFERROR(YEAR('Fiche de renseignement R1'!Q20),"Annee N-1") -> 2020 | D7: Variation en % | E7: Créances à un an au plus | F7: Créances à plus d'un an et à deux ans au plus | G7: Créances à plus de deux ans
A9: Personnel | B9: =SUMIF('BAL N'!J:J,"=421",'BAL N'!G:G) -> 0 | C9: =+SUMIF('BAL N'!J:J,"=421",'BAL N'!C:C) -> 0 | D9: =IFERROR((B9-C9)/B9,0) -> 0
A10: Organismes sociaux | B10: =+SUMIF('BAL N'!I:I,"=43",'BAL N'!G:G) -> 0 | C10: =+SUMIF('BAL N'!I:I,"=43",'BAL N'!C:C) -> 0 | D10: =IFERROR((B10-C10)/B10,0) -> 0
A11: Etat et collectivités publiques | B11: =+SUMIF('BAL N'!I:I,"=44",'BAL N'!G:G) -> 0 | C11: =+SUMIF('BAL N'!I:I,"=44",'BAL N'!C:C) -> 0 | D11: =IFERROR((B11-C11)/B11,0) -> 0
A12: Organismes internationaux | B12: =+SUMIF('BAL N'!I:I,"=45",'BAL N'!G:G) -> 0 | C12: =+SUMIF('BAL N'!I:I,"=45",'BAL N'!C:C) -> 0 | D12: =IFERROR((B12-C12)/B12,0) -> 0
A13: Apporteurs, associés et Groupe | B13: =+SUMIF('BAL N'!I:I,"=46",'BAL N'!G:G) -> 0 | C13: =+SUMIF('BAL N'!I:I,"=46",'BAL N'!C:C) -> 0 | D13: =IFERROR((B13-C13)/B13,0) -> 0
A14: Compte transitoire ajustement spécial lié à la révision du SYSCOHADA | B14: =+SUMIF('BAL N'!J:J,"=475",'BAL N'!G:G) -> 0 | C14: =+SUMIF('BAL N'!J:J,"=475",'BAL N'!C:C) -> 0 | D14: =IFERROR((B14-C14)/B14,0) -> 0
A15: Autres débiteurs divers | B15: =+SUMIF('BAL N'!I:I,"=47",'BAL N'!G:G)-SUMIF('BAL N'!J:J,"=475",'BAL N'!G:G) -> 0 | C15: =+SUMIF('BAL N'!I:I,"=47",'BAL N'!C:C)-SUMIF('BAL N'!J:J,"=475",'BAL N'!C:C) -> 0 | D15: =IFERROR((B15-C15)/B15,0) -> 0
A16: Comptes permanents non bloqués des établissements et des succursales | D16: =IFERROR((B16-C16)/B16,0) -> 0
A17: Comptes de liaison charges et produits | D17: =IFERROR((B17-C17)/B17,0) -> 0
A18: Comptes de liaison des sociétés en participation | D18: =IFERROR((B18-C18)/B18,0) -> 0
A19: TOTAL BRUT AUTRES CREANCES | B19: =SUM(B9:B18) -> 0 | C19: =SUM(C9:C18) -> 0 | D19: =IFERROR((B19-C19)/B19,0) -> 0
A20: Dépréciations des autres créances | B20: =+SUMIF('BAL N'!J:J,"=497",'BAL N'!H:H) -> 0 | C20: =+SUMIF('BAL N'!J:J,"=497",'BAL N'!D:D) -> 0 | D20: =IFERROR((B20-C20)/B20,0) -> 0
A21: TOTAL NET DE DEPRECIATION | B21: =+B19-B20 -> 0 | C21: =+C19-C20 -> 0 | D21: =IFERROR((B21-C21)/B21,0) -> 0
A22: Commentaire :
A23: · Justifier toute variation significative
A24: · Détailler les créances dont le montant est significatif
A25: · Justifier les créances anciennes
A26: · Indiquer les évènements et les circonstances qui ont conduit à la dépréciation et à la reprise
A27: · Compte transitoire ajustement spécial, indiquer le détail du compte et la durée restant pour l'apurement

Sheet Note 8A
A1: NOTE 8 A: TABLEAU D'ETALEMENT DES CHARGES IMMOBILISEES
A3: Désignation entité : | B3: ='Fiche de renseignement R1'!$J$4 -> 0 | E3: Excercice clos le : | F3: =+'Note 1'!E3 -> 0
A4: Numéro d'identification : | B4: =+'Note 1'!B4 -> 0 | E4: Durée en mois : | F4: =+'Note 1'!E4 -> 12
A6: LIBELLES | B6: Frais d'établissement | D6: Charges à répartir sur plusiers exercices | F6: Primes de remboursement des obligations
A8: Montant global à étaler au 1er janvier 2018
A9: Durée d'étalement retenue
B10: Comptes | C10: Montants | D10: Comptes | E10: Montants | F10: Comptes | G10: Montants
A11: Exercice 2018 | B11: 60… | D11: 60… | F11: 6714
B12: 61… | D12: 61…
B13: 62… | D13: 62…
B14: 63… | D14: 63…
B15: … | D15: …
A16: Total exercice 2018
A17: Total exercice 2019
A18: Total exercice 2020
A19: Total exercice 2021
A20: Total exercice 2022
A21: TOTAL GENERAL

Sheet Note 9
A1: NOTE 9 : TITRES DE PLACEMENT
A3: Désignation entité : | B3: ='Fiche de renseignement R1'!$J$4 -> 0 | C3: Excercice clos le : | D3: =+'Note 1'!E3 -> 0
A4: Numéro d'identification : | B4: =+'Note 1'!B4 -> 0 | C4: Durée en mois : | D4: =+'Note 1'!E4 -> 12
A6: LIBELLES | B6: =IFERROR(YEAR('Fiche de renseignement R1'!V10),"Annee N") -> 1900 | C6: =IFERROR(YEAR('Fiche de renseignement R1'!Q20),"Annee N-1") -> 2020 | D6: VARIATION EN %
A8: Titres de trésor et bons de caisse à court terme | B8: =+SUMIF('BAL N'!K:K,"5011",'BAL N'!G:G)+SUMIF('BAL N'!K:K,"5013",'BAL N'!G:G) -> 0 | C8: =+SUMIF('BAL N'!K:K,"5011",'BAL N'!C:C)+SUMIF('BAL N'!K:K,"5013",'BAL N'!C:C) -> 0 | D8: =IFERROR((B8-C8)/B8,0) -> 0
A9: Actions | B9: =+SUMIF('BAL N'!K:K,"502",'BAL N'!G:G) -> 0 | C9: =+SUMIF('BAL N'!J:J,"502",'BAL N'!C:C) -> 0 | D9: =IFERROR((B9-C9)/B9,0) -> 0
A10: Obligations | B10: =+SUMIF('BAL N'!K:K,"503",'BAL N'!G:G) -> 0 | C10: =+SUMIF('BAL N'!J:J,"503",'BAL N'!C:C) -> 0 | D10: =IFERROR((B10-C10)/B10,0) -> 0
A11: Bons de souscription | B11: =+SUMIF('BAL N'!K:K,"504",'BAL N'!G:G) -> 0 | C11: =+SUMIF('BAL N'!J:J,"504",'BAL N'!C:C) -> 0 | D11: =IFERROR((B11-C11)/B11,0) -> 0
A12: Titres négociables hors régions | B12: =+SUMIF('BAL N'!K:K,"505",'BAL N'!G:G) -> 0 | C12: =+SUMIF('BAL N'!J:J,"505",'BAL N'!C:C) -> 0 | D12: =IFERROR((B12-C12)/B12,0) -> 0
A13: Intérêts courus | B13: =+SUMIF('BAL N'!K:K,"506",'BAL N'!G:G) -> 0 | C13: =+SUMIF('BAL N'!J:J,"506",'BAL N'!C:C) -> 0 | D13: =IFERROR((B13-C13)/B13,0) -> 0
A14: Autres valeurs assimilées | B14: =+SUMIF('BAL N'!K:K,"508",'BAL N'!G:G) -> 0 | C14: =+SUMIF('BAL N'!J:J,"508",'BAL N'!C:C) -> 0 | D14: =IFERROR((B14-C14)/B14,0) -> 0
A15: TOTAL BRUT TITRES | B15: =SUM(B8:B14) -> 0 | C15: =SUM(C8:C14) -> 0 | D15: =IFERROR((B15-C15)/B15,0) -> 0
A16: Dépréciations des titres | B16: =+SUMIF('BAL N'!K:K,"590",'BAL N'!H:H) -> 0 | C16: =+SUMIF('BAL N'!J:J,"590",'BAL N'!C:C) -> 0 | D16: =IFERROR((B16-C16)/B16,0) -> 0
A18: TOTAL NET DE DEPRECIATION | B18: =SUM(B16) -> 0 | C18: =SUM(C16) -> 0 | D18: =IFERROR((B18-C18)/B18,0) -> 0
A19: Commentaire :
A20: · Justifier toutes variations significatives
A21: · Pour les titres côtés à une bourse de valeur : indiquer le nombre, le prix unitaire d'acquisition et le cours de
A22: la bourse au 31 décembre
A23: · Faire ressortir les actions ou parts propres et indiquer la date d'acquisition et le nombre de titres détenus
A24: · Indiquer les évènements et les circonstances qui ont conduit à la dépréciation et à la reprise

Sheet Note 10
A1: NOTE 10 : VALEURS A ENCAISSER
A3: Désignation entité : | B3: ='Fiche de renseignement R1'!$J$4 -> 0 | C3: Excercice clos le : | D3: =+'Note 1'!E3 -> 0
A4: Numéro d'identification : | B4: =+'Note 1'!B4 -> 0 | C4: Durée en mois : | D4: =+'Note 1'!E4 -> 12
A6: LIBELLES | B6: =IFERROR(YEAR('Fiche de renseignement R1'!V10),"Annee N") -> 1900 | C6: =IFERROR(YEAR('Fiche de renseignement R1'!Q20),"Annee N-1") -> 2020 | D6: VARIATION EN %
A8: Effets à encaisser | B8: =+SUMIF('BAL N'!J:J,"=511",'BAL N'!G:G) -> 0 | C8: =+SUMIF('BAL N'!J:J,"=511",'BAL N'!C:C) -> 0 | D8: =IFERROR((B8-C8)/B8,0) -> 0
A9: Effets à l'encaissement | B9: =+SUMIF('BAL N'!J:J,"=512",'BAL N'!G:G) -> 0 | C9: =+SUMIF('BAL N'!J:J,"=512",'BAL N'!C:C) -> 0 | D9: =IFERROR((B9-C9)/B9,0) -> 0
A10: Chèques à encaisser | B10: =+SUMIF('BAL N'!J:J,"=513",'BAL N'!G:G) -> 0 | C10: =+SUMIF('BAL N'!J:J,"=513",'BAL N'!C:C) -> 0 | D10: =IFERROR((B10-C10)/B10,0) -> 0
A11: Chèques à l'encaissement | B11: =+SUMIF('BAL N'!J:J,"=514",'BAL N'!G:G) -> 0 | C11: =+SUMIF('BAL N'!J:J,"=514",'BAL N'!C:C) -> 0 | D11: =IFERROR((B11-C11)/B11,0) -> 0
A12: Cartes de crédit à encaisser | B12: =+SUMIF('BAL N'!J:J,"=515",'BAL N'!G:G) -> 0 | C12: =+SUMIF('BAL N'!J:J,"=515",'BAL N'!C:C) -> 0 | D12: =IFERROR((B12-C12)/B12,0) -> 0
A13: Autres valeurs à encaisser | B13: =+SUMIF('BAL N'!J:J,"=518",'BAL N'!G:G) -> 0 | C13: =+SUMIF('BAL N'!J:J,"=518",'BAL N'!C:C) -> 0 | D13: =IFERROR((B13-C13)/B13,0) -> 0
A14: TOTAL BRUT VALEURS A ENCAISSER | B14: =SUM(B8:B13) -> 0 | C14: =SUM(C8:C13) -> 0 | D14: =IFERROR((B14-C14)/B14,0) -> 0
A15: Dépréciations des valeurs à encaisser | B15: =+SUMIF('BAL N'!J:J,"=591",'BAL N'!H:H) -> 0 | C15: =+SUMIF('BAL N'!J:J,"=591",'BAL N'!D:D) -> 0 | D15: =IFERROR((B15-C15)/B15,0) -> 0
A17: TOTAL NET DE DEPRECIATION | B17: =SUM(B15) -> 0 | C17: =SUM(C15) -> 0 | D17: =IFERROR((B17-C17)/B17,0) -> 0
A18: Commentaire :
A19: · Commenter toute variation significative
A20: · Indiquer les évènements et les circonstances qui ont conduit à la dépréciation et à la reprise

Sheet Note 11
A1: NOTE 11 : DISPONIBILITES
A3: Désignation entité : | B3: ='Fiche de renseignement R1'!$J$4 -> 0 | C3: Excercice clos le : | D3: =+'Note 1'!E3 -> 0
A4: Numéro d'identification : | B4: =+'Note 1'!B4 -> 0 | C4: Durée en mois : | D4: =+'Note 1'!E4 -> 12
A6: LIBELLES | B6: =IFERROR(YEAR('Fiche de renseignement R1'!V10),"Annee N") -> 1900 | C6: =IFERROR(YEAR('Fiche de renseignement R1'!Q20),"Annee N-1") -> 2020 | D6: VARIATION EN %
A8: Banques locales | B8: =+SUMIF('BAL N'!J:J,"=521",'BAL N'!G:G) -> 0 | C8: =+SUMIF('BAL N'!J:J,"=521",'BAL N'!C:C) -> 0 | D8: =IFERROR((B8-C8)/B8,0) -> 0
A9: Banques autres états région | B9: =+SUMIF('BAL N'!J:J,"=522",'BAL N'!G:G) -> 0 | C9: =+SUMIF('BAL N'!J:J,"=522",'BAL N'!C:C) -> 0 | D9: =IFERROR((B9-C9)/B9,0) -> 0
A10: Banques, dépôt à terme | B10: =+SUMIF('BAL N'!J:J,"=525",'BAL N'!G:G) -> 0 | C10: =+SUMIF('BAL N'!J:J,"=525",'BAL N'!C:C) -> 0 | D10: =IFERROR((B10-C10)/B10,0) -> 0
A11: Autres banques | B11: =+SUMIF('BAL N'!J:J,"=523",'BAL N'!G:G)+SUMIF('BAL N'!J:J,"=524",'BAL N'!G:G) -> 0 | C11: =+SUMIF('BAL N'!J:J,"=523",'BAL N'!C:C)+SUMIF('BAL N'!J:J,"=524",'BAL N'!C:C) -> 0 | D11: =IFERROR((B11-C11)/B11,0) -> 0
A12: Banques, intérêts courus | B12: =+SUMIF('BAL N'!J:J,"=526",'BAL N'!G:G) -> 0 | C12: =+SUMIF('BAL N'!J:J,"=526",'BAL N'!C:C) -> 0 | D12: =IFERROR((B12-C12)/B12,0) -> 0
A13: Chèques postaux | B13: =+SUMIF('BAL N'!J:J,"=531",'BAL N'!G:G) -> 0 | C13: =+SUMIF('BAL N'!J:J,"=531",'BAL N'!C:C) -> 0 | D13: =IFERROR((B13-C13)/B13,0) -> 0
A14: Autres établissements financiers | B14: =+SUMIF('BAL N'!J:J,"=532",'BAL N'!G:G)+SUMIF('BAL N'!J:J,"=533",'BAL N'!G:G)+SUMIF('BAL N'!J:J,"=538",'BAL N'!G:G) -> 0 | C14: =+SUMIF('BAL N'!J:J,"=532",'BAL N'!C:C)+SUMIF('BAL N'!J:J,"=533",'BAL N'!C:C)+SUMIF('BAL N'!J:J,"=538",'BAL N'!C:C) -> 0 | D14: =IFERROR((B14-C14)/B14,0) -> 0
A15: Etablissements financiers intérêts courus | B15: =+SUMIF('BAL N'!J:J,"=536",'BAL N'!G:G) -> 0 | C15: =+SUMIF('BAL N'!J:J,"=536",'BAL N'!C:C) -> 0 | D15: =IFERROR((B15-C15)/B15,0) -> 0
A16: Instruments de trésorerie | B16: =+SUMIF('BAL N'!I:I,"=54",'BAL N'!G:G) -> 0 | C16: =+SUMIF('BAL N'!I:I,"=54",'BAL N'!C:C) -> 0 | D16: =IFERROR((B16-C16)/B16,0) -> 0
A17: Caisse | B17: =+SUMIF('BAL N'!J:J,"=571",'BAL N'!G:G) -> 0 | C17: =+SUMIF('BAL N'!J:J,"=571",'BAL N'!C:C) -> 0 | D17: =IFERROR((B17-C17)/B17,0) -> 0
A18: Casse électronique mobile | B18: =+SUMIF('BAL N'!I:I,"=55",'BAL N'!G:G) -> 0 | C18: =+SUMIF('BAL N'!I:I,"=55",'BAL N'!C:C) -> 0 | D18: =IFERROR((B18-C18)/B18,0) -> 0
A19: Régies d'avances et virements accréditifs | B19: =+SUMIF('BAL N'!I:I,"=58",'BAL N'!G:G) -> 0 | C19: =+SUMIF('BAL N'!I:I,"=58",'BAL N'!C:C) -> 0 | D19: =IFERROR((B19-C19)/B19,0) -> 0
A20: TOTAL BRUT DISPONIBILITES | B20: =SUM(B8:B19) -> 0 | C20: =SUM(C8:C19) -> 0 | D20: =IFERROR((B20-C20)/B20,0) -> 0
A21: Dépréciations | B21: =+SUMIF('BAL N'!I:I,"=59",'BAL N'!H:H) -> 0 | C21: =+SUMIF('BAL N'!I:I,"=59",'BAL N'!D:D) -> 0 | D21: =IFERROR((B21-C21)/B21,0) -> 0
A23: TOTAL NET DE DEPRECIATIONS | B23: =SUM(B21) -> 0 | C23: =SUM(C21) -> 0 | D23: =IFERROR((B23-C23)/B23,0) -> 0
A24: Commentaire :
A25: · Indiquer la date de rapprochement des comptes bancaires
A26: · Indiquer la date d'inventaire de la caisse et des instruments de monnaie électronique
A27: · Justifier toute variation significative
A28: · Détailler les instruments de monnaie électronique si le montant est significatif
A29: · Indiquer les évènements et les circonstances qui ont conduit à la dépréciation et à la reprise
A31: NB : Banques et intérêts courus et Etablissement financiers intérêts courus figurent dans cette rubrique
A32: en négatif si le compte principal est débiteur

Sheet Note 12
A1: NOTE 12 : ECARTS DE CONVERSION
A3: Désignation entité : | B3: ='Fiche de renseignement R1'!$J$4 -> 0 | E3: Excercice clos le : | F3: =+'Note 1'!E3 -> 0
A4: Numéro d'identification : | B4: =+'Note 1'!B4 -> 0 | E4: Durée en mois : | F4: =+'Note 1'!E4 -> 12
A6: LIBELLES | B6: Devises | C6: Montant en devises | E6: Cours UML année acquisition | F6: Cours UML 31/12 | G6: Variation en valeur absolue
A8: Ecarts de conversion actif : Détailler les créances et dettes concernées
A11: Ecarts de conversion passif : Détailler les créances et dettes concernées
A16: Commentaire :
A17: · Faire un commentaire
A21: TRANSFERTS DE CHARGES
A23: LIBELLES | B23: ANNEE N | D23: ANNEE N-1 | F23: VARIATION EN %
A25: Transferts de charges d'exploitation : Détailler la nature des charges transférées
A28: Transferts de charges financières : Détailler la nature des charges transférées
A33: Commentaire :
A34: · Faire un commentaire

Sheet Note 13
A1: NOTE 13 : CAPITAL
A3: Désignation entité : | B3: ='Fiche de renseignement R1'!$J$4 -> 0 | E3: Excercice clos le : | F3: =+'Note 1'!E3 -> 0
A4: Numéro d'identification : | B4: =+'Note 1'!B4 -> 0 | E4: Durée en mois : | F4: =+'Note 1'!E4 -> 12
E7: Valeur nominale des actions ou parts : | G7: 10000
A8: NOMS ET PRENOMS | B8: Nationalité | C8: Nature des actions ou parts (ordinaires ou préférences) | E8: Montant total | F8: Nombre | G8: Cessions ou remboursements en cours d'exercice
F10: =IFERROR(E10/G7,0) -> 0
F11: =IFERROR(E11/G7,0) -> 0
F12: =IFERROR(E12/G7,0) -> 0
F13: =IFERROR(E13/G7,0) -> 0
F14: =IFERROR(E14/G7,0) -> 0
F15: =IFERROR(E15/G7,0) -> 0
F16: =IFERROR(E16/G7,0) -> 0
F17: =IFERROR(E17/G7,0) -> 0
A18: Apporteurs, capital non appelé
C19: TOTAL | E19: =SUM(E10:E17) -> 0 | F19: =SUM(F10:F17) -> 0
A20: Commentaire :
A21: · Indiquer si possible le montant du capital à la constitution
A22: · Indiquer si possible les dates des AGE et le montant du capital augmenté en cas d'augmentation de capital
A23: · Indiquer si possible les dates des AGE et le montant du capital diminué en cas de réduction de capital
A24: · Indiquer les avantages accordés aux actions de préférence
A25: · Apporteurs, capital non appelé : indiquer le délai restant pour appeler le capital

Sheet Note 14
A1: NOTE 14 : PRIMES ET RESERVES
A3: Désignation entité : | B3: ='Fiche de renseignement R1'!$J$4 -> 0 | E3: Excercice clos le : | F3: =+'Note 1'!E3 -> 0
A4: Numéro d'identification : | B4: =+'Note 1'!B4 -> 0 | E4: Durée en mois : | F4: =+'Note 1'!E4 -> 12
A7: LIBELLES | B7: =IFERROR(YEAR('Fiche de renseignement R1'!V10),"Annee N") -> 1900 | D7: =IFERROR(YEAR('Fiche de renseignement R1'!Q20),"Annee N-1") -> 2020 | F7: VARIATION EN VALEUR ABSOLUE
A9: Prime d'apport | B9: =+SUMIF('BAL N'!K:K,"=1051",'BAL N'!H:H) -> 0 | D9: =+SUMIF('BAL N'!K:K,"=1051",'BAL N'!D:D) -> 0 | F9: =+B9-D9 -> 0
A10: Primes d'émission | B10: =+SUMIF('BAL N'!J:J,"=1052",'BAL N'!H:H) -> 0 | D10: =+SUMIF('BAL N'!K:K,"=1052",'BAL N'!D:D) -> 0 | F10: =+B10-D10 -> 0
A11: Prime de fusion | B11: =+SUMIF('BAL N'!K:K,"=1053",'BAL N'!H:H) -> 0 | D11: =+SUMIF('BAL N'!K:K,"=1053",'BAL N'!D:D) -> 0 | F11: =+B11-D11 -> 0
A12: Primes de conversion | B12: =+SUMIF('BAL N'!K:K,"=1054",'BAL N'!H:H) -> 0 | D12: =+SUMIF('BAL N'!K:K,"=1054",'BAL N'!D:D) -> 0 | F12: =+B12-D12 -> 0
A13: Autres primes | B13: =+SUMIF('BAL N'!K:K,"=1058",'BAL N'!H:H) -> 0 | D13: =+SUMIF('BAL N'!K:K,"=1058",'BAL N'!D:D) -> 0 | F13: =+B13-D13 -> 0
A14: TOTAL PRIMES | B14: =SUM(B9:C13) -> 0 | D14: =SUM(D9:E13) -> 0 | F14: =+B14-D14 -> 0
A16: Réserves légales | B16: =+SUMIF('BAL N'!J:J,"=111",'BAL N'!H:H) -> 0 | D16: =+SUMIF('BAL N'!J:J,"=111",'BAL N'!D:D) -> 0 | F16: =+B16-D16 -> 0
A17: Réserves statutaires | B17: =+SUMIF('BAL N'!J:J,"=112",'BAL N'!H:H) -> 0 | D17: =+SUMIF('BAL N'!J:J,"=112",'BAL N'!D:D) -> 0 | F17: =+B17-D17 -> 0
A18: Réserves de plus-values nettes à long terme | B18: =+SUMIF('BAL N'!K:K,"=1131",'BAL N'!H:H) -> 0 | D18: =+SUMIF('BAL N'!K:K,"=1131",'BAL N'!D:D) -> 0 | F18: =+B18-D18 -> 0
A19: Réserves d'attribution gratuite d'actions au personnel salarié et aux dirigeants | B19: =+SUMIF('BAL N'!K:K,"=1132",'BAL N'!H:H) -> 0 | D19: =+SUMIF('BAL N'!K:K,"=1132",'BAL N'!D:D) -> 0 | F19: =+B19-D19 -> 0
A20: Autres réserves réglementées | B20: =+SUMIF('BAL N'!J:J,"=118",'BAL N'!H:H) -> 0 | D20: =+SUMIF('BAL N'!J:J,"=118",'BAL N'!D:D) -> 0 | F20: =+B20-D20 -> 0
A21: TOTAL RESERVES INDISPONIBLES | B21: =SUM(B15:C20) -> 0 | D21: =SUM(D15:E20) -> 0 | F21: =+B21-D21 -> 0
A22: Réserves libres | B22: =+SUMIF('BAL N'!J:J,"=118",'BAL N'!H:H) -> 0 | D22: =+SUMIF('BAL N'!J:J,"=118",'BAL N'!D:D) -> 0 | F22: =+B22-D22 -> 0
A23: Report à nouveau | B23: =+SUMIF('BAL N'!I:I,"=12",'BAL N'!H:H)-SUMIF('BAL N'!I:I,"=12",'BAL N'!G:G) -> 0 | D23: =+SUMIF('BAL N'!I:I,"=12",'BAL N'!D:D)-SUMIF('BAL N'!I:I,"=12",'BAL N'!C:C) -> 0 | F23: =+B23-D23 -> 0
A25: Commentaire :
A26: · Indiquer les dates de l'AGE qui a décidé des primes d'apport, d'émission de fusion
A27: · Indiquer le détail des réserves libres
A28: · Indiquer le montant restant à doter et le taux de dotation de la réserve légale
A29: · Indiquer la date de l'AGO qui justifie la variation des réserves et du report à nouveau

Sheet Note 15A
A1: NOTE 15A : SUBVENTIONS ET PROVISIONS REGLEMENTEES
A3: Désignation entité : | B3: ='Fiche de renseignement R1'!$J$4 -> 0 | E3: Excercice clos le : | G3: =+'Note 1'!E3 -> 0
A4: Numéro d'identification : | B4: =+'Note 1'!B4 -> 0 | E4: Durée en mois : | G4: =+'Note 1'!E4 -> 12
A7: LIBELLES | B7: NOTE | C7: =IFERROR(YEAR('Fiche de renseignement R1'!V10),"Annee N") -> 1900 | D7: =IFERROR(YEAR('Fiche de renseignement R1'!Q20),"Annee N-1") -> 2020 | E7: Variation en valeur absolue | F7: Variation en % | G7: Régime fiscal | H7: Échéances
A9: Etat | C9: =+SUMIF('BAL N'!K:K,"=1411",'BAL N'!H:H) -> 0 | D9: =+SUMIF('BAL N'!K:K,"=1411",'BAL N'!D:D) -> 0 | F9: =IFERROR((C9-D9)/C9,0) -> 0
A10: Régions | C10: =+SUMIF('BAL N'!K:K,"=1412",'BAL N'!H:H) -> 0 | D10: =+SUMIF('BAL N'!K:K,"=1412",'BAL N'!D:D) -> 0 | F10: =IFERROR((C10-D10)/C10,0) -> 0
A11: Départements | C11: =+SUMIF('BAL N'!K:K,"=1413",'BAL N'!H:H) -> 0 | D11: =+SUMIF('BAL N'!K:K,"=1413",'BAL N'!D:D) -> 0 | F11: =IFERROR((C11-D11)/C11,0) -> 0
A12: Communes et collectivités publiques décentralisées | C12: =+SUMIF('BAL N'!K:K,"=1414",'BAL N'!H:H) -> 0 | D12: =+SUMIF('BAL N'!K:K,"=1414",'BAL N'!D:D) -> 0 | F12: =IFERROR((C12-D12)/C12,0) -> 0
A13: Entités publiques ou mixtes | C13: =+SUMIF('BAL N'!K:K,"=1415",'BAL N'!H:H) -> 0 | D13: =+SUMIF('BAL N'!K:K,"=1415",'BAL N'!D:D) -> 0 | F13: =IFERROR((C13-D13)/C13,0) -> 0
A14: Entités et organismes privés | C14: =+SUMIF('BAL N'!K:K,"=1416",'BAL N'!H:H) -> 0 | D14: =+SUMIF('BAL N'!K:K,"=1416",'BAL N'!D:D) -> 0 | F14: =IFERROR((C14-D14)/C14,0) -> 0
A15: Organismes internationaux | C15: =+SUMIF('BAL N'!K:K,"=1417",'BAL N'!H:H) -> 0 | D15: =+SUMIF('BAL N'!K:K,"=1417",'BAL N'!D:D) -> 0 | F15: =IFERROR((C15-D15)/C15,0) -> 0
A16: Autres | C16: =+SUMIF('BAL N'!K:K,"=1418",'BAL N'!H:H) -> 0 | D16: =+SUMIF('BAL N'!K:K,"=1418",'BAL N'!D:D) -> 0 | F16: =IFERROR((C16-D16)/C16,0) -> 0
A17: TOTAL SUBVENTIONS | C17: =SUM(C9:C16) -> 0 | D17: =SUM(D9:D16) -> 0 | F17: =IFERROR((C17-D17)/C17,0) -> 0
F18: =IFERROR((C18-D18)/C18,0) -> 0
A19: Amortissements dérogatoires | C19: =+SUMIF('BAL N'!J:J,"=151",'BAL N'!H:H) -> 0 | D19: =+SUMIF('BAL N'!J:J,"=151",'BAL N'!D:D) -> 0 | F19: =IFERROR((C19-D19)/C19,0) -> 0
A20: Plus-values de cession à réinvestir | C20: =+SUMIF('BAL N'!J:J,"=152",'BAL N'!H:H) -> 0 | D20: =+SUMIF('BAL N'!J:J,"=152",'BAL N'!D:D) -> 0 | F20: =IFERROR((C20-D20)/C20,0) -> 0
A21: Provision spéciale de réévaluation | C21: =+SUMIF('BAL N'!J:J,"=154",'BAL N'!H:H) -> 0 | D21: =+SUMIF('BAL N'!J:J,"=154",'BAL N'!D:D) -> 0 | F21: =IFERROR((C21-D21)/C21,0) -> 0
A22: Provisions réglementées relatives aux immobilisations | C22: =+SUMIF('BAL N'!J:J,"=155",'BAL N'!H:H) -> 0 | D22: =+SUMIF('BAL N'!J:J,"=155",'BAL N'!D:D) -> 0 | F22: =IFERROR((C22-D22)/C22,0) -> 0
A23: Provisions réglementées relatives aux stocks | C23: =+SUMIF('BAL N'!J:J,"=156",'BAL N'!H:H) -> 0 | D23: =+SUMIF('BAL N'!J:J,"=156",'BAL N'!D:D) -> 0 | F23: =IFERROR((C23-D23)/C23,0) -> 0
A24: Provisions pour investissement | C24: =+SUMIF('BAL N'!J:J,"=157",'BAL N'!H:H) -> 0 | D24: =+SUMIF('BAL N'!J:J,"=157",'BAL N'!D:D) -> 0 | F24: =IFERROR((C24-D24)/C24,0) -> 0
A25: Autres provisions et fonds réglementés | C25: =+SUMIF('BAL N'!J:J,"=158",'BAL N'!H:H) -> 0 | D25: =+SUMIF('BAL N'!J:J,"=158",'BAL N'!D:D) -> 0 | F25: =IFERROR((C25-D25)/C25,0) -> 0
A26: TOTAL PROVISIONS REGLEMENTEES | C26: =SUM(C18:C25) -> 0 | D26: =SUM(D18:D25) -> 0 | F26: =IFERROR((C26-D26)/C26,0) -> 0
A28: TOTAL SUBVENTIONS ET PROVISIONS REGLEMENTEES | C28: =C17+C26 -> 0 | D28: =D17+D26 -> 0 | F28: =IFERROR((C28-D28)/C28,0) -> 0
A30: Commentaire :
A31: Indiquer pour la subvention la date d'octroi, la nature, les obligations éventuelles.
A32: Pour les provisions réglementées, indiquer le texte de référence, les obligations.
A33: Commenter toute variation significative.

Sheet Note 15B
A1: NOTE 15B : AUTRES FONDS PROPRES(1)
A3: Désignation entité : | B3: ='Fiche de renseignement R1'!$J$4 -> 0 | E3: Excercice clos le : | F3: =+'Note 1'!E3 -> 0
A4: Numéro d'identification : | B4: =+'Note 1'!B4 -> 0 | E4: Durée en mois : | F4: =+'Note 1'!E4 -> 12
A7: LIBELLES | B7: NOTE | C7: =IFERROR(YEAR('Fiche de renseignement R1'!V10),"Annee N") -> 1900 | D7: =IFERROR(YEAR('Fiche de renseignement R1'!Q20),"Annee N-1") -> 2020 | E7: Variation en valeur absolue | F7: Variation en % | G7: Échéances
A9: Titres participatifs | C9: =+SUMIF('BAL N'!K:K,"=2742",'BAL N'!G:G) -> 0 | D9: =+SUMIF('BAL N'!K:K,"=2742",'BAL N'!C:C) -> 0 | F9: =IFERROR((C9-D9)/C9,0) -> 0
A10: Avances conditionnées | C10: =+SUMIF('BAL N'!K:K,"=2743",'BAL N'!G:G) -> 0 | D10: =+SUMIF('BAL N'!K:K,"=2743",'BAL N'!C:C) -> 0 | F10: =IFERROR((C10-D10)/C10,0) -> 0
A11: Titres subordonnés à durée indéterminée (TSDI) | C11: =+SUMIF('BAL N'!K:K,"=2744",'BAL N'!G:G) -> 0 | D11: =+SUMIF('BAL N'!K:K,"=2744",'BAL N'!C:C) -> 0 | F11: =IFERROR((C11-D11)/C11,0) -> 0
A12: Obligations remboursables en actions (ORA) | C12: =+SUMIF('BAL N'!K:K,"=2745",'BAL N'!G:G) -> 0 | D12: =+SUMIF('BAL N'!K:K,"=2745",'BAL N'!C:C) -> 0 | F12: =IFERROR((C12-D12)/C12,0) -> 0
A13: Autres | C13: =+SUMIF('BAL N'!K:K,"=2748",'BAL N'!G:G) -> 0 | D13: =+SUMIF('BAL N'!K:K,"=2748",'BAL N'!C:C) -> 0 | F13: =IFERROR((C13-D13)/C13,0) -> 0
A14: TOTAL AUTRES FONDS PROPRES | C14: =SUM(C9:C13) -> 0 | D14: =SUM(D9:D13) -> 0 | F14: =IFERROR((C14-D14)/C14,0) -> 0
A16: (1) : Le cas échéant, une rubrique "Autres fonds propres" (montant des émissions de titres participatifs,
A17: avances conditionnées,…) sur une ligne séparée est intercalée entre les rubriques
A18: "TOTAL CAPTAUX PROPRES ET RESSOURCES ASSIMILEES" et "EMPRUNTS ET DETTES FINANCIERES" si le
A19: montant des autres fonds propres est significatif.
A21: Commentaire :
A22: · Justifier l'inscription de ces dettes dans une rubrique spécifique du passif du bilan "autres fonds
A23: propres" (faible probabilité de remboursement, absence d'échéancier…)
A24: · Justifier le caractère significatif du montant total de cette rubrique
A25: · Commenter toute variation significative

Sheet Note 16A
A1: NOTE 16A : DETTES FINANCIERES ET RESSOURCES ASSIMILEES
A3: Désignation entité : | B3: ='Fiche de renseignement R1'!$J$4 -> 0 | E3: Excercice clos le : | G3: =+'Note 1'!E3 -> 0
A4: Numéro d'identification : | B4: =+'Note 1'!B4 -> 0 | E4: Durée en mois : | G4: =+'Note 1'!E4 -> 12
A6: LIBELLES | B6: =IFERROR(YEAR('Fiche de renseignement R1'!V10),"Annee N") -> 1900 | C6: =IFERROR(YEAR('Fiche de renseignement R1'!Q20),"Annee N-1") -> 2020 | D6: Variation en valeur absolue | E6: Variation en % | F6: Dettes à un an au plus | G6: Dettes à plus d'un an et à deux ans au plus | H6: Dettes à plus de deux ans
A8: Emprunts obligataires | B8: =+SUMIF('BAL N'!J:J,"=161",'BAL N'!H:H) -> 0 | C8: =+SUMIF('BAL N'!J:J,"=161",'BAL N'!D:D) -> 0 | E8: =IFERROR((B8-C8)/B8,0) -> 0
A9: Emprunts et dettes auprès des établissements de crédit | B9: =+SUMIF('BAL N'!J:J,"=162",'BAL N'!H:H) -> 0 | C9: =+SUMIF('BAL N'!J:J,"=162",'BAL N'!D:D) -> 0 | E9: =IFERROR((B9-C9)/B9,0) -> 0
A10: Avances reçues de l'Etat | B10: =+SUMIF('BAL N'!J:J,"=163",'BAL N'!H:H) -> 0 | C10: =+SUMIF('BAL N'!J:J,"=163",'BAL N'!D:D) -> 0 | E10: =IFERROR((B10-C10)/B10,0) -> 0
A11: Avances reçues et comptes courants bloqués | B11: =+SUMIF('BAL N'!J:J,"=164",'BAL N'!H:H) -> 0 | C11: =+SUMIF('BAL N'!J:J,"=164",'BAL N'!D:D) -> 0 | E11: =IFERROR((B11-C11)/B11,0) -> 0
A12: Dépôts et cautionnements reçus | B12: =+SUMIF('BAL N'!J:J,"=165",'BAL N'!H:H) -> 0 | C12: =+SUMIF('BAL N'!J:J,"=165",'BAL N'!D:D) -> 0 | E12: =IFERROR((B12-C12)/B12,0) -> 0
A13: Intérêts courus | B13: =+SUMIF('BAL N'!J:J,"=166",'BAL N'!H:H) -> 0 | C13: =+SUMIF('BAL N'!J:J,"=166",'BAL N'!D:D) -> 0 | E13: =IFERROR((B13-C13)/B13,0) -> 0
A14: Avances assorties de conditions particulières | B14: =+SUMIF('BAL N'!J:J,"=167",'BAL N'!H:H) -> 0 | C14: =+SUMIF('BAL N'!J:J,"=167",'BAL N'!D:D) -> 0 | E14: =IFERROR((B14-C14)/B14,0) -> 0
A15: Autres emprunts et dettes | B15: =+SUMIF('BAL N'!J:J,"=168",'BAL N'!H:H) -> 0 | C15: =+SUMIF('BAL N'!J:J,"=1683",'BAL N'!D:D) -> 0 | E15: =IFERROR((B15-C15)/B15,0) -> 0
A16: Dettes liées à des participations | B16: =+SUMIF('BAL N'!I:I,"=18",'BAL N'!H:H) -> 0 | C16: =+SUMIF('BAL N'!K:K,"=18",'BAL N'!I:I) -> 0 | E16: =IFERROR((B16-C16)/B16,0) -> 0
A17: Comptes permanents bloqués des établissements et succursales | E17: =IFERROR((B17-C17)/B17,0) -> 0
A18: TOTAL EMPRUNTS ET DETTES FINANCIERES | B18: =SUM(B8:B17) -> 0 | C18: =SUM(C8:C17) -> 0 | E18: =IFERROR((B18-C18)/B18,0) -> 0
A20: Crédit bail immobilier | B20: =+SUMIF('BAL N'!J:J,"=172",'BAL N'!H:H) -> 0 | C20: =+SUMIF('BAL N'!J:J,"=172",'BAL N'!D:D) -> 0 | E20: =IFERROR((B20-C20)/B20,0) -> 0
A21: Crédit bail mobilier | B21: =+SUMIF('BAL N'!J:J,"=173",'BAL N'!H:H) -> 0 | C21: =+SUMIF('BAL N'!J:J,"=173",'BAL N'!D:D) -> 0 | E21: =IFERROR((B21-C21)/B21,0) -> 0
A22: Location vente | B22: =+SUMIF('BAL N'!J:J,"=174",'BAL N'!H:H) -> 0 | C22: =+SUMIF('BAL N'!J:J,"=174",'BAL N'!D:D) -> 0 | E22: =IFERROR((B22-C22)/B22,0) -> 0
A23: Intérêts courus | B23: =+SUMIF('BAL N'!J:J,"=176",'BAL N'!H:H) -> 0 | C23: =+SUMIF('BAL N'!J:J,"=176",'BAL N'!D:D) -> 0 | E23: =IFERROR((B23-C23)/B23,0) -> 0
A24: Autres dettes de location acquisition | B24: =+SUMIF('BAL N'!J:J,"=178",'BAL N'!H:H) -> 0 | C24: =+SUMIF('BAL N'!J:J,"=178",'BAL N'!D:D) -> 0 | E24: =IFERROR((B24-C24)/B24,0) -> 0
A25: TOTAL DETTES DE LOCATION ACQUISITION | B25: =SUM(B20:B24) -> 0 | C25: =SUM(C20:C24) -> 0 | E25: =IFERROR((B25-C25)/B25,0) -> 0
A27: Provisions pour litiges | B27: =+SUMIF('BAL N'!J:J,"=191",'BAL N'!H:H) -> 0 | C27: =+SUMIF('BAL N'!J:J,"=191",'BAL N'!D:D) -> 0 | E27: =IFERROR((B27-C27)/B27,0) -> 0
A28: Provisions pour garantie donnés aux clients | B28: =+SUMIF('BAL N'!J:J,"=192",'BAL N'!H:H) -> 0 | C28: =+SUMIF('BAL N'!J:J,"=192",'BAL N'!D:D) -> 0 | E28: =IFERROR((B28-C28)/B28,0) -> 0
A29: Provisions pour pertes sur marchés à achèvement futur | B29: =+SUMIF('BAL N'!J:J,"=193",'BAL N'!H:H) -> 0 | C29: =+SUMIF('BAL N'!J:J,"=193",'BAL N'!D:D) -> 0 | E29: =IFERROR((B29-C29)/B29,0) -> 0
A30: Provisions pour pertes de change | B30: =+SUMIF('BAL N'!J:J,"=194",'BAL N'!H:H) -> 0 | C30: =+SUMIF('BAL N'!J:J,"=194",'BAL N'!D:D) -> 0 | E30: =IFERROR((B30-C30)/B30,0) -> 0
A31: Provisions pour impôts | B31: =+SUMIF('BAL N'!J:J,"=195",'BAL N'!H:H) -> 0 | C31: =+SUMIF('BAL N'!J:J,"=195",'BAL N'!D:D) -> 0 | E31: =IFERROR((B31-C31)/B31,0) -> 0
A32: Provisions pour pensions et obligations assimilées | B32: =+SUMIF('BAL N'!K:K,"=1961",'BAL N'!H:H) -> 0 | C32: =+SUMIF('BAL N'!K:K,"=1961",'BAL N'!D:D) -> 0 | E32: =IFERROR((B32-C32)/B32,0) -> 0
A33: Actif du régime de retraite | B33: =+SUMIF('BAL N'!K:K,"=1962",'BAL N'!H:H) -> 0 | C33: =+SUMIF('BAL N'!K:K,"=1962",'BAL N'!D:D) -> 0 | E33: =IFERROR((B33-C33)/B33,0) -> 0
A34: Provisions pour restructuration | B34: =+SUMIF('BAL N'!J:J,"=197",'BAL N'!H:H) -> 0 | C34: =+SUMIF('BAL N'!J:J,"=197",'BAL N'!D:D) -> 0 | E34: =IFERROR((B34-C34)/B34,0) -> 0
A35: Provisions pour amendes et pénalités | B35: =+SUMIF('BAL N'!K:K,"=1981",'BAL N'!H:H) -> 0 | C35: =+SUMIF('BAL N'!K:K,"=1981",'BAL N'!D:D) -> 0 | E35: =IFERROR((B35-C35)/B35,0) -> 0
A36: Provisions de propre assureur | B36: =+SUMIF('BAL N'!K:K,"=1983",'BAL N'!H:H) -> 0 | C36: =+SUMIF('BAL N'!K:K,"=1983",'BAL N'!D:D) -> 0 | E36: =IFERROR((B36-C36)/B36,0) -> 0
A37: Provisions pour démantèlement et remise en état | B37: =+SUMIF('BAL N'!K:K,"=1984",'BAL N'!H:H) -> 0 | C37: =+SUMIF('BAL N'!K:K,"=1984",'BAL N'!D:D) -> 0 | E37: =IFERROR((B37-C37)/B37,0) -> 0
A38: Provisions de droits à déduction | B38: =+SUMIF('BAL N'!K:K,"=1985",'BAL N'!H:H) -> 0 | C38: =+SUMIF('BAL N'!K:K,"=1985",'BAL N'!D:D) -> 0 | E38: =IFERROR((B38-C38)/B38,0) -> 0
A39: Autres provisions | B39: =+SUMIF('BAL N'!K:K,"=1988",'BAL N'!H:H) -> 0 | C39: =+SUMIF('BAL N'!K:K,"=1988",'BAL N'!D:D) -> 0 | E39: =IFERROR((B39-C39)/B39,0) -> 0
A40: TOTAL PROVISIONS POUR RISQUES ET CHARGES | B40: =SUM(B27:B39) -> 0 | C40: =SUM(C27:C39) -> 0 | E40: =IFERROR((B40-C40)/B40,0) -> 0
A42: Commentaire :
A43: Pour chaque emprunt et dette de location acquisition : mentionner la date d'octroi, le nom de l'organisme
A44: financier, le montant initial de l'emprunt ou de la dette, la durée du crédit, les garanties donnéee par la société.
A45: Indiquer les évènements et circonstances qui ont conduit à la provision et à la reprise.
A46: Pour les pensions et obligations de retraite indiquer :
A47: · la méthode d'évaluation retenue ;
A48: · pour les actifs du régime, indiquer le nom de la compagnie d'assurance ou du fonds de pension, le descriptif
A49: de la convention signée avec l'orgganisme, la périodicité des versements, le montant et la durée de la convention ;
A50: · indication de la valeur retenue pour les principales hypothèses actuarielles à la date de clôture et leur base de
A51: détermination.

Sheet Note 16B
A1: NOTE 16B : ENGAGEMENTS DE RETRAITE ET AVANTAGES ASSIMILES (METHODE ACTUARIELLE)
A3: Désignation entité : | B3: ='Fiche de renseignement R1'!$J$4 -> 0 | D3: Excercice clos le : | E3: =+'Note 1'!E3 -> 0
A4: Numéro d'identification : | B4: =+'Note 1'!B4 -> 0 | D4: Durée en mois : | E4: =+'Note 1'!E4 -> 12
A7: HYPOTHESES ACTUARIELLES
A8: LIBELLES | B8: =IFERROR(YEAR('Fiche de renseignement R1'!V10),"Annee N") -> 1900 | D8: =IFERROR(YEAR('Fiche de renseignement R1'!Q20),"Annee N-1") -> 2020
A9: Taux d'augmentation des salaires
A10: Taux d'actualisation
A11: Taux d'inflation
A12: Probabilité d'être présent dans l'entité à la date de départ à la retraite (expérience passée)
A13: Probabilité d'être en vie à l'âge de départ à la retraite (table de mortalité)
A14: Taux de rendement effectif des actifs du régime
A16: Commentaire :
A17: · Commenter les variations d'hypothèses actuarielles utilisées pour le calcul des
A18: engagements de retraite et avantages assimilés.
A21: VARIATION DE LA VALEUR DE L'ENGAGEMENT DE RETRAITE AU COURS DE L'EXERCICE
A22: LIBELLES | B22: =IFERROR(YEAR('Fiche de renseignement R1'!V10),"Annee N") -> 1900 | D22: =IFERROR(YEAR('Fiche de renseignement R1'!Q20),"Annee N-1") -> 2020
A23: OBLIGATION AU TITRE DES ENGAGEMENTS DE RETRAITE A L'OUVERTURE
A24: Coût des services rendus au cours de l'exercice
A25: Coût financier
A26: Pertes actuarielles / (gain)
A27: Prestations payées au cours de l'exercice
A28: Coût des services passés
A29: OBLIGATION AU TITRE DES ENGAGEMENTS DE RETRAITE A LA CLÔTURE
A31: Commentaire :
A32: · indiquer le montant de la charge par nature comptabilisée au cours de l'exercice.
A35: ANALYSES DE SENSIBILITE DES HYPOTHESES ACTUARIELLES
A36: LIBELLES | C36: =IFERROR(YEAR('Fiche de renseignement R1'!V10),"Annee N") -> 1900 | E36: =IFERROR(YEAR('Fiche de renseignement R1'!Q20),"Annee N-1") -> 2020
C37: Augmentation | D37: Diminution | E37: Augmentation | F37: Diminution
A38: Taux d'actualisation (variation de …%)
A39: Taux de progression des salaires (variation de …%)
A40: Taux de départ du personnel (variation de …%)
A42: Commentaire :
A43: · Indiquer l'impact des variations obtenues sur le montant des engagements de retraite.

Sheet Note 16B bis
A1: NOTE 16B bis : ENGAGEMENTS DE RETRAITE ET AVANTAGES ASSIMILES
A3: Désignation entité : | B3: ='Fiche de renseignement R1'!$J$4 -> 0 | D3: Excercice clos le : | E3: =+'Note 1'!E3 -> 0
A4: Numéro d'identification : | B4: =+'Note 1'!B4 -> 0 | D4: Durée en mois : | E4: =+'Note 1'!E4 -> 12
A6: ACTIF/PASSIF NET COMPTABILISE AU TITRE DES REGIMES FINANCES
A7: LIBELLES | B7: =IFERROR(YEAR('Fiche de renseignement R1'!V10),"Annee N") -> 1900 | D7: =IFERROR(YEAR('Fiche de renseignement R1'!Q20),"Annee N-1") -> 2020
A8: Valeur actuelle de l'obligation résultant de régimes financés
A9: Valeur actuelle des actifs affectés aux plans de retraite
A10: Excédent / Déficit de régime
A12: Commentaire :
A13: · indiquer le montant comptabilisé au passif (ou actif) à la clôture de l'exercice.
A16: VALEUR ACTUELLE DES ACTIFS DU REGIME
A17: LIBELLES | B17: =IFERROR(YEAR('Fiche de renseignement R1'!V10),"Annee N") -> 1900 | D17: =IFERROR(YEAR('Fiche de renseignement R1'!Q20),"Annee N-1") -> 2020
B18: Rendement attendu | C18: Juste valeur des actifs | D18: Rendement attendu | E18: Juste valeur des actifs
A19: Actions
A20: Obligations
A21: Autres
A22: TOTAL
A24: Commentaire :
A25: · Expliquer comment les taux de rendement par catégorie d'actifs et global ont été déterminés.
A26: · Indiquer le montant des rendements réels des actifs affectés aux plans en N et N-1.

Sheet Note 16C
A1: NOTE 16C : ACTIFS ET PASSIFS EVENTUELS
A3: Désignation entité : | B3: ='Fiche de renseignement R1'!$J$4 -> 0 | C3: Excercice clos le : | D3: =+'Note 1'!E3 -> 0
A4: Numéro d'identification : | B4: =+'Note 1'!B4 -> 0 | C4: Durée en mois : | D4: =+'Note 1'!E4 -> 12
A7: LIBELLES | C7: =IFERROR(YEAR('Fiche de renseignement R1'!V10),"Annee N") -> 1900 | D7: =IFERROR(YEAR('Fiche de renseignement R1'!Q20),"Annee N-1") -> 2020
A8: Actif éventuel
A9: Litiges
A10: …………………………..
A11: …………………………..
A12: Passif éventuel
A13: Litiges
A14: …………………………..
A15: …………………………..
A17: Commentaire :
A18: · Décrire les principales caractéristiques des actifs / passifs éventuels, l'horizon de temps auquel
A19: les encaissements / décaissements sont attendus et les éventuels remboursements à percevoir.

Sheet Note 17
A1: NOTE 17 : FOURNISSEURS D'EXPLOITATION
A3: Désignation entité : | B3: ='Fiche de renseignement R1'!$J$4 -> 0 | D3: Excercice clos le : | F3: =+'Note 1'!E3 -> 0
A4: Numéro d'identification : | B4: =+'Note 1'!B4 -> 0 | D4: Durée en mois : | F4: =+'Note 1'!E4 -> 12
A6: LIBELLES | B6: =IFERROR(YEAR('Fiche de renseignement R1'!V10),"Annee N") -> 1900 | C6: =IFERROR(YEAR('Fiche de renseignement R1'!Q20),"Annee N-1") -> 2020 | D6: Variation en % | E6: Dettes à un an au plus | F6: Dettes à plus d'un an et à deux ans au plus | G6: Dettes à plus de deux ans
A8: Fournisseurs dettes en compte (hors groupe) | B8: =+SUMIF('BAL N'!J:J,"=401",'BAL N'!H:H)-SUMIF('BAL N'!K:K,"=4012",'BAL N'!H:H) -> 0 | C8: =+SUMIF('BAL N'!J:J,"=401",'BAL N'!D:D)-SUMIF('BAL N'!K:K,"=4012",'BAL N'!D:D)-SUMIF('BAL N'!J:J,"=401",'BAL N'!C:C) -> 0 | D8: =IFERROR((B8-C8)/B8,0) -> 0
A9: Fournisseurs effets à payer (hors groupe) | B9: =+SUMIF('BAL N'!J:J,"=402",'BAL N'!H:H)-SUMIF('BAL N'!K:K,"=4022",'BAL N'!H:H) -> 0 | C9: =+SUMIF('BAL N'!J:J,"=402",'BAL N'!D:D)-SUMIF('BAL N'!K:K,"=4022",'BAL N'!D:D) -> 0 | D9: =IFERROR((B9-C9)/B9,0) -> 0
A10: Fournisseurs, dettes et effets à payer (groupe) | B10: =SUMIF('BAL N'!K:K,"=4022",'BAL N'!H:H)+SUMIF('BAL N'!K:K,"=4012",'BAL N'!H:H) -> 0 | C10: =SUMIF('BAL N'!K:K,"=4022",'BAL N'!D:D)+SUMIF('BAL N'!K:K,"=4012",'BAL N'!D:D) -> 0 | D10: =IFERROR((B10-C10)/B10,0) -> 0
A11: Fournisseurs, factures non parvenues (hors groupe) | B11: =SUMIF('BAL N'!K:K,"=4081",'BAL N'!H:H) -> 0 | C11: =SUMIF('BAL N'!K:K,"=4081",'BAL N'!D:D) -> 0 | D11: =IFERROR((B11-C11)/B11,0) -> 0
A12: Fournisseurs, factures non parvenues (groupe) | B12: =SUMIF('BAL N'!K:K,"=4082",'BAL N'!H:H) -> 0 | C12: =SUMIF('BAL N'!K:K,"=4082",'BAL N'!D:D) -> 0 | D12: =IFERROR((B12-C12)/B12,0) -> 0
A13: TOTAL FOURNISSEURS | B13: =SUM(B8:B12) -> 0 | C13: =SUM(C8:C12) -> 0 | D13: =IFERROR((B13-C13)/B13,0) -> 0
D14: =IFERROR((B14-C14)/B14,0) -> 0
A15: Fournisseurs, avances et acomptes (hors groupe) | B15: =+SUMIF('BAL N'!J:J,"=409",'BAL N'!H:H)-SUMIF('BAL N'!K:K,"=4092",'BAL N'!H:H) -> 0 | C15: =+SUMIF('BAL N'!J:J,"=409",'BAL N'!D:D)-SUMIF('BAL N'!K:K,"=4092",'BAL N'!D:D) -> 0 | D15: =IFERROR((B15-C15)/B15,0) -> 0
A16: Fournisseurs, avances et acomptes (groupe) | B16: =+SUMIF('BAL N'!K:K,"=4092",'BAL N'!H:H) -> 0 | C16: =+SUMIF('BAL N'!K:K,"=4092",'BAL N'!D:D) -> 0 | D16: =IFERROR((B16-C16)/B16,0) -> 0
A17: Autres fournisseurs débiteurs | B17: =+SUMIF('BAL N'!K:K,"=4093",'BAL N'!H:H)+SUMIF('BAL N'!K:K,"=4094",'BAL N'!H:H)+SUMIF('BAL N'!K:K,"=4095",'BAL N'!H:H)+SUMIF('BAL N'!K:K,"=4096",'BAL N'!H:H)+SUMIF('BAL N'!K:K,"=4098",'BAL N'!H:H) -> 0 | C17: =+SUMIF('BAL N'!K:K,"=4093",'BAL N'!C:C)+SUMIF('BAL N'!K:K,"=4094",'BAL N'!C:C)+SUMIF('BAL N'!K:K,"=4095",'BAL N'!C:C)+SUMIF('BAL N'!K:K,"=4096",'BAL N'!C:C)+SUMIF('BAL N'!K:K,"=4098",'BAL N'!C:C) -> 0 | D17: =IFERROR((B17-C17)/B17,0) -> 0
A18: TOTAL FOURNISSEURS DEBITEURS | B18: =SUM(B15:B17) -> 0 | C18: =SUM(C15:C17) -> 0 | D18: =IFERROR((B18-C18)/B18,0) -> 0
A20: Commentaire :
A21: · Commenter toutes variations significatives
A22: · Indiquer pour les dettes du groupe, le nom de la société du groupe et le % de titres détenues
A23: · Commenter toutes les dettes anciennes

Sheet Note 18
A1: NOTE 18 : DETTES FISCALES ET SOCIALES
A3: Désignation entité : | B3: ='Fiche de renseignement R1'!$J$4 -> 0 | F3: Excercice clos le : | G3: =+'Note 1'!E3 -> 0
A4: Numéro d'identification : | B4: =+'Note 1'!B4 -> 0 | F4: Durée en mois : | G4: =+'Note 1'!E4 -> 12
A6: LIBELLES | B6: =IFERROR(YEAR('Fiche de renseignement R1'!V10),"Annee N") -> 1900 | C6: =IFERROR(YEAR('Fiche de renseignement R1'!Q20),"Annee N-1") -> 2020 | D6: Variation en valeur absolue | E6: Variation en % | F6: Dettes à un an au plus | G6: Dettes à plus d'un an et à deux ans au plus | H6: Dettes à plus de deux ans
A8: Personnel congés à payer | B8: =+SUMIF('BAL N'!J:J,"=421",'BAL N'!H:H) -> 0 | C8: =+SUMIF('BAL N'!J:J,"=421",'BAL N'!D:D) -> 0 | E8: =IFERROR((B8-C8)/B8,0) -> 0
A9: Personnel rémunérations dues | B9: =+SUMIF('BAL N'!J:J,"=422",'BAL N'!H:H) -> 0 | C9: =+SUMIF('BAL N'!J:J,"=422",'BAL N'!D:D) -> 0 | E9: =IFERROR((B9-C9)/B9,0) -> 0
A10: Autres personnel | B10: =+SUMIF('BAL N'!J:J,"=428",'BAL N'!H:H)+SUMIF('BAL N'!J:J,"=423",'BAL N'!H:H)+SUMIF('BAL N'!J:J,"=424",'BAL N'!H:H)+SUMIF('BAL N'!J:J,"=425",'BAL N'!H:H)+SUMIF('BAL N'!J:J,"=426",'BAL N'!H:H)+SUMIF('BAL N'!J:J,"=427",'BAL N'!H:H) -> 0 | C10: =+SUMIF('BAL N'!J:J,"=428",'BAL N'!D:D)+SUMIF('BAL N'!J:J,"=423",'BAL N'!D:D)+SUMIF('BAL N'!J:J,"=424",'BAL N'!D:D)+SUMIF('BAL N'!J:J,"=425",'BAL N'!D:D)+SUMIF('BAL N'!J:J,"=426",'BAL N'!D:D)+SUMIF('BAL N'!J:J,"=4273",'BAL N'!D:D) -> 0 | E10: =IFERROR((B10-C10)/B10,0) -> 0
A11: Caisse de sécurité sociale | B11: =+SUMIF('BAL N'!K:K,"=4311",'BAL N'!H:H)+SUMIF('BAL N'!K:K,"=4312",'BAL N'!H:H) -> 0 | C11: =+SUMIF('BAL N'!K:K,"=4311",'BAL N'!D:D)+SUMIF('BAL N'!K:K,"=4312",'BAL N'!D:D) -> 0 | E11: =IFERROR((B11-C11)/B11,0) -> 0
A12: Caisse de retraite | B12: =+SUMIF('BAL N'!K:K,"=4313",'BAL N'!H:H)+SUMIF('BAL N'!K:K,"=4314",'BAL N'!H:H) -> 0 | C12: =+SUMIF('BAL N'!K:K,"=4313",'BAL N'!D:D)+SUMIF('BAL N'!K:K,"=4314",'BAL N'!D:D) -> 0 | E12: =IFERROR((B12-C12)/B12,0) -> 0
A13: Autres organismes sociaux | B13: =+SUMIF('BAL N'!K:K,"=4318",'BAL N'!H:H)+SUMIF('BAL N'!J:J,"=433",'BAL N'!H:H) -> 0 | C13: =+SUMIF('BAL N'!K:K,"=4318",'BAL N'!D:D)+SUMIF('BAL N'!J:J,"=433",'BAL N'!D:D) -> 0 | E13: =IFERROR((B13-C13)/B13,0) -> 0
A14: TOTAL DETTES SOCIALES | B14: =SUM(B8:B13) -> 0 | C14: =SUM(C8:C13) -> 0 | E14: =IFERROR((B14-C14)/B14,0) -> 0
E15: =IFERROR((B15-C15)/B15,0) -> 0
A16: Etat, impôts sur les bénéfices | B16: =+SUMIF('BAL N'!J:J,"=441",'BAL N'!H:H) -> 0 | C16: =+SUMIF('BAL N'!J:J,"=441",'BAL N'!D:D) -> 0 | E16: =IFERROR((B16-C16)/B16,0) -> 0
A17: Etat, impôts et taxes | B17: =+SUMIF('BAL N'!J:J,"=442",'BAL N'!H:H) -> 0 | C17: =+SUMIF('BAL N'!J:J,"=442",'BAL N'!D:D) -> 0 | E17: =IFERROR((B17-C17)/B17,0) -> 0
A18: Etat, TVA | B18: =+SUMIF('BAL N'!J:J,"=443",'BAL N'!H:H)+SUMIF('BAL N'!J:J,"=444",'BAL N'!H:H)++SUMIF('BAL N'!J:J,"=445",'BAL N'!H:H) -> 0 | C18: =+SUMIF('BAL N'!J:J,"=443",'BAL N'!D:D)+SUMIF('BAL N'!J:J,"=444",'BAL N'!D:D)+SUMIF('BAL N'!J:J,"=445",'BAL N'!D:D) -> 0 | E18: =IFERROR((B18-C18)/B18,0) -> 0
A19: Etat, impôts retenus à la source | B19: =+SUMIF('BAL N'!J:J,"=447",'BAL N'!H:H) -> 0 | C19: =+SUMIF('BAL N'!J:J,"=447",'BAL N'!D:D) -> 0 | E19: =IFERROR((B19-C19)/B19,0) -> 0
A20: Autres dettes Etat | B20: =+SUMIF('BAL N'!J:J,"=446",'BAL N'!H:H)+SUMIF('BAL N'!J:J,"=448",'BAL N'!H:H)+SUMIF('BAL N'!J:J,"=449",'BAL N'!H:H) -> 0 | C20: =+SUMIF('BAL N'!J:J,"=446",'BAL N'!D:D)+SUMIF('BAL N'!J:J,"=448",'BAL N'!D:D)+SUMIF('BAL N'!J:J,"=449",'BAL N'!D:D) -> 0 | E20: =IFERROR((B20-C20)/B20,0) -> 0
A21: TOTAL DETTES FISCALES | B21: =SUM(B16:B20) -> 0 | C21: =SUM(C16:C20) -> 0 | E21: =IFERROR((B21-C21)/B21,0) -> 0
A23: TOTAL DETTES SOCIALES ET FISCALES | B23: =+B21+B14 -> 0 | C23: =+C21+C14 -> 0 | E23: =IFERROR((B23-C23)/B23,0) -> 0
A25: Commentaire :
A26: · Commenter toutes variations significatives
A27: · Commenter toutes les dettes anciennes

Sheet Note 19
A1: NOTE 19 : AUTRES DETTES ET PROVISIONS POUR RISQUES A COURT TERME
A3: Désignation entité : | B3: ='Fiche de renseignement R1'!$J$4 -> 0 | E3: Excercice clos le : | G3: =+'Note 1'!E3 -> 0
A4: Numéro d'identification : | B4: =+'Note 1'!B4 -> 0 | E4: Durée en mois : | G4: =+'Note 1'!E4 -> 12
A6: LIBELLES | B6: =IFERROR(YEAR('Fiche de renseignement R1'!V10),"Annee N") -> 1900 | C6: =IFERROR(YEAR('Fiche de renseignement R1'!Q20),"Annee N-1") -> 2020 | D6: Variation en valeur absolue | E6: Variation en % | F6: Dettes à un an au plus | G6: Dettes à plus d'un an et à deux ans au plus | H6: Dettes à plus de deux ans
A8: Organismes internationaux | B8: =+SUMIF('BAL N'!I:I,"=45",'BAL N'!H:H) -> 0 | C8: =+SUMIF('BAL N'!I:I,"=45",'BAL N'!D:D) -> 0 | E8: =IFERROR((B8-C8)/B8,0) -> 0
A9: Apporteurs, opérations sur le capital | B9: =+SUMIF('BAL N'!J:J,"=461",'BAL N'!H:H) -> 0 | C9: =+SUMIF('BAL N'!J:J,"=461",'BAL N'!D:D) -> 0 | E9: =IFERROR((B9-C9)/B9,0) -> 0
A10: Associés, compte courant | B10: =+SUMIF('BAL N'!J:J,"=462",'BAL N'!H:H) -> 0 | C10: =+SUMIF('BAL N'!J:J,"=462",'BAL N'!D:D) -> 0 | E10: =IFERROR((B10-C10)/B10,0) -> 0
A11: Associés, dividendes à payer | B11: =+SUMIF('BAL N'!J:J,"=465",'BAL N'!H:H) -> 0 | C11: =+SUMIF('BAL N'!J:J,"=465",'BAL N'!D:D) -> 0 | E11: =IFERROR((B11-C11)/B11,0) -> 0
A12: Groupe, comptes courants | B12: =+SUMIF('BAL N'!J:J,"=466",'BAL N'!H:H) -> 0 | C12: =+SUMIF('BAL N'!J:J,"=466",'BAL N'!D:D) -> 0 | E12: =IFERROR((B12-C12)/B12,0) -> 0
A13: Autres dettes associés | B13: =+SUMIF('BAL N'!J:J,"=467",'BAL N'!H:H)+SUMIF('BAL N'!J:J,"=463",'BAL N'!H:H) -> 0 | C13: =+SUMIF('BAL N'!J:J,"=463",'BAL N'!D:D)+SUMIF('BAL N'!J:J,"=467",'BAL N'!D:D) -> 0 | E13: =IFERROR((B13-C13)/B13,0) -> 0
A14: TOTAL DETTES ASSOCIES | B14: =SUM(B8:B13) -> 0 | C14: =SUM(C8:C13) -> 0 | E14: =IFERROR((B14-C14)/B14,0) -> 0
A16: Créditeurs divers | B16: =+SUMIF('BAL N'!K:K,"=4712",'BAL N'!H:H) -> 0 | C16: =+SUMIF('BAL N'!K:K,"=4712",'BAL N'!D:D) -> 0 | E16: =IFERROR((B16-C16)/B16,0) -> 0
A17: Obligataires | B17: =+SUMIF('BAL N'!K:K,"=4713",'BAL N'!H:H) -> 0 | C17: =+SUMIF('BAL N'!K:K,"=4713",'BAL N'!D:D) -> 0 | E17: =IFERROR((B17-C17)/B17,0) -> 0
A18: Rémunérations d'administrateurs | B18: =+SUMIF('BAL N'!K:K,"=4715",'BAL N'!H:H) -> 0 | C18: =+SUMIF('BAL N'!K:K,"=4715",'BAL N'!D:D) -> 0 | E18: =IFERROR((B18-C18)/B18,0) -> 0
A19: Compte du factor | B19: =+SUMIF('BAL N'!K:K,"=4716",'BAL N'!H:H) -> 0 | C19: =+SUMIF('BAL N'!K:K,"=4716",'BAL N'!D:D) -> 0 | E19: =IFERROR((B19-C19)/B19,0) -> 0
A20: Versements restant à effectuer sur titres de placements non libérés | B20: =+SUMIF('BAL N'!J:J,"=472",'BAL N'!H:H) -> 0 | C20: =+SUMIF('BAL N'!J:J,"=472",'BAL N'!D:D) -> 0 | E20: =IFERROR((B20-C20)/B20,0) -> 0
A21: Compte transitoire ajustement spécial lié à la révision du SYSCOHADA | B21: =+SUMIF('BAL N'!J:J,"=475",'BAL N'!H:H) -> 0 | C21: =+SUMIF('BAL N'!J:J,"=475",'BAL N'!D:D) -> 0 | E21: =IFERROR((B21-C21)/B21,0) -> 0
A22: Autres créditeurs divers | B22: =+SUMIF('BAL N'!J:J,"=477",'BAL N'!H:H)+SUMIF('BAL N'!J:J,"=479",'BAL N'!H:H) -> 0 | C22: =+SUMIF('BAL N'!J:J,"=477",'BAL N'!D:D)+SUMIF('BAL N'!J:J,"=479",'BAL N'!D:D) -> 0 | E22: =IFERROR((B22-C22)/B22,0) -> 0
A23: TOTAL CREDITEURS DIVERS | B23: =SUM(B16:B22) -> 0 | C23: =SUM(C16:C22) -> 0 | E23: =IFERROR((B23-C23)/B23,0) -> 0
A25: Comptes permanents non bloqués des établissements et des succursales | E25: =IFERROR((B25-C25)/B25,0) -> 0
