Workbook

Sheet Page de garde
A1: Page de garde
B5: REPUBLIQUE | I5: DU SENEGAL
B7: MINISTERE | I7: DES FINANCES ET DU BUDGET
B9: DIRECTION | I9: DIRECTION GENERALE DES IMPÔTS ET DES DOMAINES
B17: CENTRE DE DEPOT : | V17: xxxx
A23: ETATS FINANCIERS NORMALISES
A24: SYSTÈME COMPTABLE (SYSCOHADA)
B27: EXERCICE CLOS LE :
A30: DESIGNATION DE L'ENTREPRISE
C35: DENOMINATION SOCIALE :
C36: (ou nom et prénoms de l'exploitant)
C41: SIGLE USUEL :
C46: ADRESSE COMPLETE :
C51: N° D'IDENTIFICATION FISCALE :
C55: SYSTEME NORMAL
C59: Documents déposés | V59: Réservé à la Direction Générale des Impôts
C62: Fiche d'identification et renseignements divers | S62: X | V62: Date de dépôt
C64: Bilan | S64: X
C66: Compte de résultat | S66: X | V66: Nom de l'agent de DGI ayant réceptionné le dépôt
C68: Tableau des flux de trésorerie | S68: X
C70: Notes annexes | S70: X | V70: Signature de l'agent et cachet du service
C72: Nombre de pages déposées par exemplaire
C73: Nombre d'exemplaires déposés

Sheet Fiche de renseignement R1
A1: Fiche R1
I4: Dénomination sociale de l’entreprise | J4: =+'Page de garde'!L35 -> 0
I7: Adresse de l'entreprise | J7: ='Page de garde'!J46 -> 0 | AC7: Sigle usuel | AD7: =+'Page de garde'!H41 -> 0
I10: N° d'identification fiscale | J10: ='Page de garde'!N51 -> 0 | U10: Exercice clos le | V10: =+'Page de garde'!M27 -> 0 | AG10: Durée (en mois) | AH10: 12
B13: ZA | E13: EXERCICE COMPTABLE | W13: DU | Y13: 43466 | AF13: AU | AH13: 43830
B16: ZB | E16: DATE D'ARRETE EFFECTIF DES COMPTES | U16: =+V10 -> 0
B20: ZC | E20: EXERCICE PRECEDENT CLOS LE | Q20: 44196 | AK20: DUREE EXERCICE PRECEDENT EN MOIS : | AL20: 12
B24: ZD | F24: SN | I24: SN-DKR-2007-X XXXXX | W24: XX
F25: Greffe | I25: N° registre du Commerce | W25: N° répertoire des entreprises
B28: ZE | G28: XXX
G29: N° de caisse sociale | S29: N° Code importateur | AE29: Code activité principale
B32: ZF | D32: =+J4 -> 0 | AE32: =+AD7 -> 0
D33: Désignation de l'entreprise | AE33: Sigle
B36: ZG | G36: XXXXXXX | Q36: XXX | Y36: 3 | AA36: 4 | AE36: Dakar
G37: N° de téléphone | Q37: email | Y37: Code | AA37: Boîte postale | AE37: Ville
B40: ZH | D40: XXX
D41: Adresse géographique complète (Immeuble, rue, quartier, ville, pays)
B44: ZI | D44: XX
D45: Désignation précise de l'activité principale exercée par l'entreprise
D48: xxxxxx
D49: Nom, adresse et qualité de personne à contacter en cas de demande d'informations complémentaires
D52: XXXXXXXXXXXX
D53: Nom du professionnel salarié de l'entreprise ou Nom, adresse et téléphone du cabinet comptable ou du professionnel INSCRIT A L'ORDRE NATIONAL DES EXPERTS COMPTABLES ET DES COMPTABLES AGREES ayant établi les états financiers.
D56: XXXXXXXXXXX
D57: Noms et adresses du ou des commissaires au comptes
E64: Non assujettie | K64: Non (refus) | O64: Oui avec réserves | S64: X | T64: Oui sans réserves | Z64: Non assujettie | AG64: Non | AK64: X | AL64: Oui
C66: Etats financiers certifiés (cocher la case) | X66: Etats financiers approuvés par l'Assemblée Générale (cocher la case)
T69: Domiciliations bancaires
D70: Nom du signataire des états financiers | T70: Banque | AD70: Numéro de compte
T71: UBA | AD71: 93ODD
D73: Qualité du signataire des états financiers
D76: Date de signature
D83: Signature

Sheet BAL N
A1: N° Comptes | B1: Libellés | C1: S 1 Débit | D1: S 1 Crédit | E1: Mouv Débit | F1: Mouv Crédit | G1: S 2 Débit | H1: S 2 Crédit | I1: Ext 2 | J1: Ext 3 | K1: Ext 4 | L1: Ext 5 | M1: Ext 1
A2: 101000 | B2: Capital | D2: 145000000 | H2: 145000000 | I2: =LEFT(A2,2) -> 10 | J2: =LEFT(A2,3) -> 101 | K2: =LEFT(A2,4) -> 1010 | L2: =LEFT(A2,5) -> 10100 | M2: =LEFT(A2,1) -> 1
A3: 111000 | B3: RESERVES LEGALES | D3: 200000 | H3: 200000 | I3: =LEFT(A3,2) -> 11 | J3: =LEFT(A3,3) -> 111 | K3: =LEFT(A3,4) -> 1110 | L3: =LEFT(A3,5) -> 11100 | M3: =LEFT(A3,1) -> 1
A4: 118800 | B4: RESERVES LIBRES | D4: 118365583 | H4: 118365583 | I4: =LEFT(A4,2) -> 11 | J4: =LEFT(A4,3) -> 118 | K4: =LEFT(A4,4) -> 1188 | L4: =LEFT(A4,5) -> 11880 | M4: =LEFT(A4,1) -> 1
A5: 130100 | B5: RESULTAT EN | D5: 290958290 | H5: 290958290 | I5: =LEFT(A5,2) -> 13 | J5: =LEFT(A5,3) -> 130 | K5: =LEFT(A5,4) -> 1301 | L5: =LEFT(A5,5) -> 13010 | M5: =LEFT(A5,1) -> 1
A6: 130110 | B6: RESULTAT A AFFECTER | D6: 167236460 | H6: 167236460 | I6: =LEFT(A6,2) -> 13 | J6: =LEFT(A6,3) -> 130 | K6: =LEFT(A6,4) -> 1301 | L6: =LEFT(A6,5) -> 13011 | M6: =LEFT(A6,1) -> 1
A7: 130120 | B7: RESULTAT A AFFECTER 2021 | D7: 325128014 | H7: 325128014 | I7: =LEFT(A7,2) -> 13 | J7: =LEFT(A7,3) -> 130 | K7: =LEFT(A7,4) -> 1301 | L7: =LEFT(A7,5) -> 13012 | M7: =LEFT(A7,1) -> 1
A8: 130130 | B8: RESULTAT A AFFECTER 2022 | D8: 109430079 | H8: 109430079 | I8: =LEFT(A8,2) -> 13 | J8: =LEFT(A8,3) -> 130 | K8: =LEFT(A8,4) -> 1301 | L8: =LEFT(A8,5) -> 13013 | M8: =LEFT(A8,1) -> 1
A9: 222000 | B9: TERRAINS | C9: 55070000 | E9: 91000000 | G9: 146070000 | I9: =LEFT(A9,2) -> 22 | J9: =LEFT(A9,3) -> 222 | K9: =LEFT(A9,4) -> 2220 | L9: =LEFT(A9,5) -> 22200 | M9: =LEFT(A9,1) -> 2
A10: 229800 | B10: ETUDE TUBO GRAPHIQUE | C10: 1599000 | G10: 1599000 | I10: =LEFT(A10,2) -> 22 | J10: =LEFT(A10,3) -> 229 | K10: =LEFT(A10,4) -> 2298 | L10: =LEFT(A10,5) -> 22980 | M10: =LEFT(A10,1) -> 2
A11: 231100 | B11: BATIMENTS INDUSTRIELS | C11: 474597458 | G11: 474597458 | I11: =LEFT(A11,2) -> 23 | J11: =LEFT(A11,3) -> 231 | K11: =LEFT(A11,4) -> 2311 | L11: =LEFT(A11,5) -> 23110 | M11: =LEFT(A11,1) -> 2
A12: 231110 | B12: BATIMENT 2017 | C12: 108355497 | G12: 108355497 | I12: =LEFT(A12,2) -> 23 | J12: =LEFT(A12,3) -> 231 | K12: =LEFT(A12,4) -> 2311 | L12: =LEFT(A12,5) -> 23111 | M12: =LEFT(A12,1) -> 2
A13: 231120 | B13: BATIMENTS 2022 | E13: 518717871 | G13: 518717871 | I13: =LEFT(A13,2) -> 23 | J13: =LEFT(A13,3) -> 231 | K13: =LEFT(A13,4) -> 2311 | L13: =LEFT(A13,5) -> 23112 | M13: =LEFT(A13,1) -> 2
A14: 234100 | B14: INSTALLATION COMPLEXE SPEC SUR | C14: 268942370 | G14: 268942370 | I14: =LEFT(A14,2) -> 23 | J14: =LEFT(A14,3) -> 234 | K14: =LEFT(A14,4) -> 2341 | L14: =LEFT(A14,5) -> 23410 | M14: =LEFT(A14,1) -> 2
A15: 235000 | B15: AMENAGEMENT DE BUREAUX | C15: 152970201 | E15: 8270033 | G15: 161240234 | I15: =LEFT(A15,2) -> 23 | J15: =LEFT(A15,3) -> 235 | K15: =LEFT(A15,4) -> 2350 | L15: =LEFT(A15,5) -> 23500 | M15: =LEFT(A15,1) -> 2
A16: 238000 | B16: AUTRES INTALATION ET AGENCE | C16: 16992250 | G16: 16992250 | I16: =LEFT(A16,2) -> 23 | J16: =LEFT(A16,3) -> 238 | K16: =LEFT(A16,4) -> 2380 | L16: =LEFT(A16,5) -> 23800 | M16: =LEFT(A16,1) -> 2
A17: 239000 | B17: BATIMENT ET INSTALLATION EN COURS | C17: 518717871 | E17: 53596539 | F17: 518717871 | G17: 53596539 | I17: =LEFT(A17,2) -> 23 | J17: =LEFT(A17,3) -> 239 | K17: =LEFT(A17,4) -> 2390 | L17: =LEFT(A17,5) -> 23900 | M17: =LEFT(A17,1) -> 2
A18: 241100 | B18: MATERIEL INDUSTRIEL | C18: 393621547 | E18: 33956828 | G18: 427578375 | I18: =LEFT(A18,2) -> 24 | J18: =LEFT(A18,3) -> 241 | K18: =LEFT(A18,4) -> 2411 | L18: =LEFT(A18,5) -> 24110 | M18: =LEFT(A18,1) -> 2
A19: 241500 | B19: MATERIEL DE COMMUNICATION | C19: 496000 | G19: 496000 | I19: =LEFT(A19,2) -> 24 | J19: =LEFT(A19,3) -> 241 | K19: =LEFT(A19,4) -> 2415 | L19: =LEFT(A19,5) -> 24150 | M19: =LEFT(A19,1) -> 2
A20: 244200 | B20: MATERIEL INFORMATIQUE | C20: 20964652 | E20: 320000 | G20: 21284652 | I20: =LEFT(A20,2) -> 24 | J20: =LEFT(A20,3) -> 244 | K20: =LEFT(A20,4) -> 2442 | L20: =LEFT(A20,5) -> 24420 | M20: =LEFT(A20,1) -> 2
A21: 244400 | B21: MOBILIER DE BUREAU | C21: 4462000 | G21: 4462000 | I21: =LEFT(A21,2) -> 24 | J21: =LEFT(A21,3) -> 244 | K21: =LEFT(A21,4) -> 2444 | L21: =LEFT(A21,5) -> 24440 | M21: =LEFT(A21,1) -> 2
A22: 245100 | B22: MATERIEL DE TRANSPORT | C22: 65268881 | G22: 65268881 | I22: =LEFT(A22,2) -> 24 | J22: =LEFT(A22,3) -> 245 | K22: =LEFT(A22,4) -> 2451 | L22: =LEFT(A22,5) -> 24510 | M22: =LEFT(A22,1) -> 2
A23: 275100 | B23: DEPOT LOYER D'AVANCE | C23: 5463000 | G23: 5463000 | I23: =LEFT(A23,2) -> 27 | J23: =LEFT(A23,3) -> 275 | K23: =LEFT(A23,4) -> 2751 | L23: =LEFT(A23,5) -> 27510 | M23: =LEFT(A23,1) -> 2
A24: 275200 | B24: DEPOT POUR ELECTRICITE | C24: 6717480 | G24: 6717480 | I24: =LEFT(A24,2) -> 27 | J24: =LEFT(A24,3) -> 275 | K24: =LEFT(A24,4) -> 2752 | L24: =LEFT(A24,5) -> 27520 | M24: =LEFT(A24,1) -> 2
A25: 282980 | B25: AMORTS ETUDES TOPOGRAPHIQUE | F25: 79950 | H25: 79950 | I25: =LEFT(A25,2) -> 28 | J25: =LEFT(A25,3) -> 282 | K25: =LEFT(A25,4) -> 2829 | L25: =LEFT(A25,5) -> 28298 | M25: =LEFT(A25,1) -> 2
A26: 283110 | B26: AMORTS BATIMENT INDUSTRIELS | D26: 207100843 | F26: 55083541 | H26: 262184384 | I26: =LEFT(A26,2) -> 28 | J26: =LEFT(A26,3) -> 283 | K26: =LEFT(A26,4) -> 2831 | L26: =LEFT(A26,5) -> 28311 | M26: =LEFT(A26,1) -> 2
A27: 283410 | B27: AMOTS INST COMPL SPEC SUR SOL | D27: 102013896 | F27: 13447119 | H27: 115461015 | I27: =LEFT(A27,2) -> 28 | J27: =LEFT(A27,3) -> 283 | K27: =LEFT(A27,4) -> 2834 | L27: =LEFT(A27,5) -> 28341 | M27: =LEFT(A27,1) -> 2
A28: 283500 | B28: AMORT AMGMT DE BUREAUX | D28: 49911215 | F28: 15882284 | H28: 65793499 | I28: =LEFT(A28,2) -> 28 | J28: =LEFT(A28,3) -> 283 | K28: =LEFT(A28,4) -> 2835 | L28: =LEFT(A28,5) -> 28350 | M28: =LEFT(A28,1) -> 2
A29: 283800 | B29: AMORTS AUTRE SINSTAL &AGENCMT | D29: 11162168 | F29: 1699225 | H29: 12861393 | I29: =LEFT(A29,2) -> 28 | J29: =LEFT(A29,3) -> 283 | K29: =LEFT(A29,4) -> 2838 | L29: =LEFT(A29,5) -> 28380 | M29: =LEFT(A29,1) -> 2
A30: 284110 | B30: AMORTS MAT &OUTIL IND | D30: 231215269 | F30: 66298765 | H30: 297514034 | I30: =LEFT(A30,2) -> 28 | J30: =LEFT(A30,3) -> 284 | K30: =LEFT(A30,4) -> 2841 | L30: =LEFT(A30,5) -> 28411 | M30: =LEFT(A30,1) -> 2
A31: 284150 | B31: AMORTS MAT DE COMMUNICATION | D31: 360513 | F31: 99200 | H31: 459713 | I31: =LEFT(A31,2) -> 28 | J31: =LEFT(A31,3) -> 284 | K31: =LEFT(A31,4) -> 2841 | L31: =LEFT(A31,5) -> 28415 | M31: =LEFT(A31,1) -> 2
A32: 284420 | B32: AMOTS MAT INFORMATIQUE | D32: 13353898 | F32: 2644115 | H32: 15998013 | I32: =LEFT(A32,2) -> 28 | J32: =LEFT(A32,3) -> 284 | K32: =LEFT(A32,4) -> 2844 | L32: =LEFT(A32,5) -> 28442 | M32: =LEFT(A32,1) -> 2
A33: 284440 | B33: AMORTS MOBILIER DE BUREAU | D33: 4462000 | H33: 4462000 | I33: =LEFT(A33,2) -> 28 | J33: =LEFT(A33,3) -> 284 | K33: =LEFT(A33,4) -> 2844 | L33: =LEFT(A33,5) -> 28444 | M33: =LEFT(A33,1) -> 2
A34: 284500 | B34: AMORTS MAT DE TRANSPORT | D34: 46129364 | F34: 12293776 | H34: 58423140 | I34: =LEFT(A34,2) -> 28 | J34: =LEFT(A34,3) -> 284 | K34: =LEFT(A34,4) -> 2845 | L34: =LEFT(A34,5) -> 28450 | M34: =LEFT(A34,1) -> 2
A35: 321000 | B35: STOCK POISSONS | C35: 433749204 | E35: 365270359 | F35: 433749204 | G35: 365270359 | I35: =LEFT(A35,2) -> 32 | J35: =LEFT(A35,3) -> 321 | K35: =LEFT(A35,4) -> 3210 | L35: =LEFT(A35,5) -> 32100 | M35: =LEFT(A35,1) -> 3
A36: 401100 | B36: FOURNISSEURS | C36: 6915443168 | D36: 6915443168 | E36: 5142562463 | F36: 5142562463 | I36: =LEFT(A36,2) -> 40 | J36: =LEFT(A36,3) -> 401 | K36: =LEFT(A36,4) -> 4011 | L36: =LEFT(A36,5) -> 40110 | M36: =LEFT(A36,1) -> 4
A37: 408100 | B37: CAP | D37: 12004500 | E37: 12004500 | F37: 3938800 | H37: 3938800 | I37: =LEFT(A37,2) -> 40 | J37: =LEFT(A37,3) -> 408 | K37: =LEFT(A37,4) -> 4081 | L37: =LEFT(A37,5) -> 40810 | M37: =LEFT(A37,1) -> 4
A38: 409100 | B38: FACTURES PAYER D'AVANCE | C38: 87473353 | E38: 130837030 | F38: 87473353 | G38: 130837030 | I38: =LEFT(A38,2) -> 40 | J38: =LEFT(A38,3) -> 409 | K38: =LEFT(A38,4) -> 4091 | L38: =LEFT(A38,5) -> 40910 | M38: =LEFT(A38,1) -> 4
A39: 409200 | B39: FOURNIISSEURS D'INV.PAYES A L'AVANC | C39: 7349490 | F39: 7349490 | I39: =LEFT(A39,2) -> 40 | J39: =LEFT(A39,3) -> 409 | K39: =LEFT(A39,4) -> 4092 | L39: =LEFT(A39,5) -> 40920 | M39: =LEFT(A39,1) -> 4
A40: 411000 | B40: Clients | C40: 28202258525 | E40: 5294648115 | G40: 33496906640 | I40: =LEFT(A40,2) -> 41 | J40: =LEFT(A40,3) -> 411 | K40: =LEFT(A40,4) -> 4110 | L40: =LEFT(A40,5) -> 41100 | M40: =LEFT(A40,1) -> 4
A41: 411100 | B41: AUTRES CLIENTS | C41: 8260000 | D41: 8200000 | F41: 60000 | I41: =LEFT(A41,2) -> 41 | J41: =LEFT(A41,3) -> 411 | K41: =LEFT(A41,4) -> 4111 | L41: =LEFT(A41,5) -> 41110 | M41: =LEFT(A41,1) -> 4
A42: 419100 | B42: Clients - avances et acomptes | D42: 29055421827 | F42: 5332269946 | H42: 34387691773 | I42: =LEFT(A42,2) -> 41 | J42: =LEFT(A42,3) -> 419 | K42: =LEFT(A42,4) -> 4191 | L42: =LEFT(A42,5) -> 41910 | M42: =LEFT(A42,1) -> 4
A43: 421000 | B43: Personnel AVCES ET ACOMPTE | C43: 29887116 | D43: 6805000 | E43: 7290000 | F43: 11964931 | G43: 18407185 | I43: =LEFT(A43,2) -> 42 | J43: =LEFT(A43,3) -> 421 | K43: =LEFT(A43,4) -> 4210 | L43: =LEFT(A43,5) -> 42100 | M43: =LEFT(A43,1) -> 4
A44: 422000 | B44: PERSONNEL REMUNERATION DUE | D44: 3327014 | E44: 106165794 | F44: 102838780 | I44: =LEFT(A44,2) -> 42 | J44: =LEFT(A44,3) -> 422 | K44: =LEFT(A44,4) -> 4220 | L44: =LEFT(A44,5) -> 42200 | M44: =LEFT(A44,1) -> 4
A45: 431000 | B45: Sécurité sociale | D45: 126000 | E45: 5655823 | F45: 6182481 | H45: 652658 | I45: =LEFT(A45,2) -> 43 | J45: =LEFT(A45,3) -> 431 | K45: =LEFT(A45,4) -> 4310 | L45: =LEFT(A45,5) -> 43100 | M45: =LEFT(A45,1) -> 4
A46: 431300 | B46: IPRES | D46: 496275 | E46: 5343531 | F46: 6545928 | H46: 1698672 | I46: =LEFT(A46,2) -> 43 | J46: =LEFT(A46,3) -> 431 | K46: =LEFT(A46,4) -> 4313 | L46: =LEFT(A46,5) -> 43130 | M46: =LEFT(A46,1) -> 4
A47: 441000 | B47: ETAT IMPOTS SUR LES BENEFICES | D47: 19930950 | E47: 19930950 | F47: 15445350 | H47: 15445350 | I47: =LEFT(A47,2) -> 44 | J47: =LEFT(A47,3) -> 441 | K47: =LEFT(A47,4) -> 4410 | L47: =LEFT(A47,5) -> 44100 | M47: =LEFT(A47,1) -> 4
A48: 442200 | B48: IMPOT SUR TAXES COLLECTIVES | D48: 66000 | H48: 66000 | I48: =LEFT(A48,2) -> 44 | J48: =LEFT(A48,3) -> 442 | K48: =LEFT(A48,4) -> 4422 | L48: =LEFT(A48,5) -> 44220 | M48: =LEFT(A48,1) -> 4
A49: 445200 | B49: TVA/ACHATS | E49: 199564 | G49: 199564 | I49: =LEFT(A49,2) -> 44 | J49: =LEFT(A49,3) -> 445 | K49: =LEFT(A49,4) -> 4452 | L49: =LEFT(A49,5) -> 44520 | M49: =LEFT(A49,1) -> 4
A50: 447200 | B50: VRS | D50: 137500 | E50: 2893783 | F50: 3046654 | H50: 290371 | I50: =LEFT(A50,2) -> 44 | J50: =LEFT(A50,3) -> 447 | K50: =LEFT(A50,4) -> 4472 | L50: =LEFT(A50,5) -> 44720 | M50: =LEFT(A50,1) -> 4
A51: 447210 | B51: BRS | E51: 3707183 | F51: 3707183 | I51: =LEFT(A51,2) -> 44 | J51: =LEFT(A51,3) -> 447 | K51: =LEFT(A51,4) -> 4472 | L51: =LEFT(A51,5) -> 44721 | M51: =LEFT(A51,1) -> 4
A52: 448600 | B52: Etat - Autres charges à payer | D52: 2951700 | H52: 2951700 | I52: =LEFT(A52,2) -> 44 | J52: =LEFT(A52,3) -> 448 | K52: =LEFT(A52,4) -> 4486 | L52: =LEFT(A52,5) -> 44860 | M52: =LEFT(A52,1) -> 4
A53: 449010 | B53: VRS DE TROP | C53: 630308 | G53: 630308 | I53: =LEFT(A53,2) -> 44 | J53: =LEFT(A53,3) -> 449 | K53: =LEFT(A53,4) -> 4490 | L53: =LEFT(A53,5) -> 44901 | M53: =LEFT(A53,1) -> 4
A54: 449020 | B54: BRS DE TROP | C54: 366814 | G54: 366814 | I54: =LEFT(A54,2) -> 44 | J54: =LEFT(A54,3) -> 449 | K54: =LEFT(A54,4) -> 4490 | L54: =LEFT(A54,5) -> 44902 | M54: =LEFT(A54,1) -> 4
A55: 449030 | B55: IS DE TROP | C55: 5237217 | G55: 5237217 | I55: =LEFT(A55,2) -> 44 | J55: =LEFT(A55,3) -> 449 | K55: =LEFT(A55,4) -> 4490 | L55: =LEFT(A55,5) -> 44903 | M55: =LEFT(A55,1) -> 4
A56: 462000 | B56: COMPTES COURANT | D56: 7374167 | H56: 7374167 | I56: =LEFT(A56,2) -> 46 | J56: =LEFT(A56,3) -> 462 | K56: =LEFT(A56,4) -> 4620 | L56: =LEFT(A56,5) -> 46200 | M56: =LEFT(A56,1) -> 4
A57: 462010 | B57: DIVIDENTES A PAYER | D57: 23000000 | H57: 23000000 | I57: =LEFT(A57,2) -> 46 | J57: =LEFT(A57,3) -> 462 | K57: =LEFT(A57,4) -> 4620 | L57: =LEFT(A57,5) -> 46201 | M57: =LEFT(A57,1) -> 4
A58: 521501 | B58: BANK OF AFRICA | C58: 77023740 | E58: 5332828110 | F58: 5230419074 | G58: 179432776 | I58: =LEFT(A58,2) -> 52 | J58: =LEFT(A58,3) -> 521 | K58: =LEFT(A58,4) -> 5215 | L58: =LEFT(A58,5) -> 52150 | M58: =LEFT(A58,1) -> 5
A59: 521505 | B59: FBNBANK | C59: 12214769 | F59: 10666849 | G59: 1547920 | I59: =LEFT(A59,2) -> 52 | J59: =LEFT(A59,3) -> 521 | K59: =LEFT(A59,4) -> 5215 | L59: =LEFT(A59,5) -> 52150 | M59: =LEFT(A59,1) -> 5
A60: 571000 | B60: CAISSE | C60: 3179782 | E60: 798716000 | F60: 761923588 | G60: 39972194 | I60: =LEFT(A60,2) -> 57 | J60: =LEFT(A60,3) -> 571 | K60: =LEFT(A60,4) -> 5710 | L60: =LEFT(A60,5) -> 57100 | M60: =LEFT(A60,1) -> 5
A61: 585000 | B61: VIREMENT DE FONDS | E61: 793006000 | F61: 793006000 | I61: =LEFT(A61,2) -> 58 | J61: =LEFT(A61,3) -> 585 | K61: =LEFT(A61,4) -> 5850 | L61: =LEFT(A61,5) -> 58500 | M61: =LEFT(A61,1) -> 5
A62: 602100 | B62: ACHATS LOCAUX DE MATIERES 1ERES | E62: 4195126324 | G62: 4195126324 | I62: =LEFT(A62,2) -> 60 | J62: =LEFT(A62,3) -> 602 | K62: =LEFT(A62,4) -> 6021 | L62: =LEFT(A62,5) -> 60210 | M62: =LEFT(A62,1) -> 6
A63: 602510 | B63: FRET | E63: 566973 | G63: 566973 | I63: =LEFT(A63,2) -> 60 | J63: =LEFT(A63,3) -> 602 | K63: =LEFT(A63,4) -> 6025 | L63: =LEFT(A63,5) -> 60251 | M63: =LEFT(A63,1) -> 6
A64: 603200 | B64: Variation stocks autres approv. | E64: 433749204 | F64: 365270359 | G64: 68478845 | I64: =LEFT(A64,2) -> 60 | J64: =LEFT(A64,3) -> 603 | K64: =LEFT(A64,4) -> 6032 | L64: =LEFT(A64,5) -> 60320 | M64: =LEFT(A64,1) -> 6
A65: 604300 | B65: PRODUIT D'ENTRETIEN | E65: 2631800 | G65: 2631800 | I65: =LEFT(A65,2) -> 60 | J65: =LEFT(A65,3) -> 604 | K65: =LEFT(A65,4) -> 6043 | L65: =LEFT(A65,5) -> 60430 | M65: =LEFT(A65,1) -> 6
A66: 604600 | B66: FOURNITURE DE MAGASIN | E66: 7665142 | G66: 7665142 | I66: =LEFT(A66,2) -> 60 | J66: =LEFT(A66,3) -> 604 | K66: =LEFT(A66,4) -> 6046 | L66: =LEFT(A66,5) -> 60460 | M66: =LEFT(A66,1) -> 6
A67: 605000 | B67: AUTRE ACHAT | E67: 8656214 | G67: 8656214 | I67: =LEFT(A67,2) -> 60 | J67: =LEFT(A67,3) -> 605 | K67: =LEFT(A67,4) -> 6050 | L67: =LEFT(A67,5) -> 60500 | M67: =LEFT(A67,1) -> 6
A68: 605200 | B68: ELECTRICITE | E68: 47319400 | F68: 10904500 | G68: 36414900 | I68: =LEFT(A68,2) -> 60 | J68: =LEFT(A68,3) -> 605 | K68: =LEFT(A68,4) -> 6052 | L68: =LEFT(A68,5) -> 60520 | M68: =LEFT(A68,1) -> 6
A69: 605300 | B69: ESSENCE | E69: 2078714 | G69: 2078714 | I69: =LEFT(A69,2) -> 60 | J69: =LEFT(A69,3) -> 605 | K69: =LEFT(A69,4) -> 6053 | L69: =LEFT(A69,5) -> 60530 | M69: =LEFT(A69,1) -> 6
A70: 605310 | B70: CARBURANT | E70: 3419980 | G70: 3419980 | I70: =LEFT(A70,2) -> 60 | J70: =LEFT(A70,3) -> 605 | K70: =LEFT(A70,4) -> 6053 | L70: =LEFT(A70,5) -> 60531 | M70: =LEFT(A70,1) -> 6
A71: 605500 | B71: FOURNITURE DE BUREAU NON STOCKAB | E71: 3169599 | G71: 3169599 | I71: =LEFT(A71,2) -> 60 | J71: =LEFT(A71,3) -> 605 | K71: =LEFT(A71,4) -> 6055 | L71: =LEFT(A71,5) -> 60550 | M71: =LEFT(A71,1) -> 6
A72: 605600 | B72: ACH DE PETIT MAT OUTILLAGE | E72: 2893567 | G72: 2893567 | I72: =LEFT(A72,2) -> 60 | J72: =LEFT(A72,3) -> 605 | K72: =LEFT(A72,4) -> 6056 | L72: =LEFT(A72,5) -> 60560 | M72: =LEFT(A72,1) -> 6
A73: 605700 | B73: ACHA DETUDE DE PRESTATION DE SERV | E73: 57320000 | G73: 57320000 | I73: =LEFT(A73,2) -> 60 | J73: =LEFT(A73,3) -> 605 | K73: =LEFT(A73,4) -> 6057 | L73: =LEFT(A73,5) -> 60570 | M73: =LEFT(A73,1) -> 6
A74: 605810 | B74: TENUES DE TRAVAIL | E74: 14193000 | G74: 14193000 | I74: =LEFT(A74,2) -> 60 | J74: =LEFT(A74,3) -> 605 | K74: =LEFT(A74,4) -> 6058 | L74: =LEFT(A74,5) -> 60581 | M74: =LEFT(A74,1) -> 6
A75: 606120 | B75: Gaz | E75: 8580 | G75: 8580 | I75: =LEFT(A75,2) -> 60 | J75: =LEFT(A75,3) -> 606 | K75: =LEFT(A75,4) -> 6061 | L75: =LEFT(A75,5) -> 60612 | M75: =LEFT(A75,1) -> 6
A76: 608100 | B76: EMBALLAGES PERDUS | E76: 100975325 | G76: 100975325 | I76: =LEFT(A76,2) -> 60 | J76: =LEFT(A76,3) -> 608 | K76: =LEFT(A76,4) -> 6081 | L76: =LEFT(A76,5) -> 60810 | M76: =LEFT(A76,1) -> 6
A77: 612100 | B77: FRET/EXPORT | E77: 88268051 | G77: 88268051 | I77: =LEFT(A77,2) -> 61 | J77: =LEFT(A77,3) -> 612 | K77: =LEFT(A77,4) -> 6121 | L77: =LEFT(A77,5) -> 61210 | M77: =LEFT(A77,1) -> 6
A78: 612110 | B78: TRANSPORT SUR VENTE EXPORTATION | E78: 2823400 | G78: 2823400 | I78: =LEFT(A78,2) -> 61 | J78: =LEFT(A78,3) -> 612 | K78: =LEFT(A78,4) -> 6121 | L78: =LEFT(A78,5) -> 61211 | M78: =LEFT(A78,1) -> 6
A79: 616000 | B79: POSTE | E79: 1489547 | G79: 1489547 | I79: =LEFT(A79,2) -> 61 | J79: =LEFT(A79,3) -> 616 | K79: =LEFT(A79,4) -> 6160 | L79: =LEFT(A79,5) -> 61600 | M79: =LEFT(A79,1) -> 6
A80: 618000 | B80: AUTRES FRAIS DE TRANSPORT | E80: 6097992 | G80: 6097992 | I80: =LEFT(A80,2) -> 61 | J80: =LEFT(A80,3) -> 618 | K80: =LEFT(A80,4) -> 6180 | L80: =LEFT(A80,5) -> 61800 | M80: =LEFT(A80,1) -> 6
... A88: 628100 | B88: FRAIS DE TELEPHONE | E88: 1579122 | G88: 1579122 | I88: =LEFT(A88,2) -> 62 | J88: =LEFT(A88,3) -> 628 | K88: =LEFT(A88,4) -> 6281 | L88: =LEFT(A88,5) -> 62810 | M88: =LEFT(A88,1) -> 6
A89: 631000 | B89: FRAIS BANCAIRE | E89: 11403262 | F89: 102375 | G89: 11300887 | I89: =LEFT(A89,2) -> 63 | J89: =LEFT(A89,3) -> 631 | K89: =LEFT(A89,4) -> 6310 | L89: =LEFT(A89,5) -> 63100 | M89: =LEFT(A89,1) -> 6
A90: 632400 | B90: HONORAIRE | E90: 9777600 | F90: 1100000 | G90: 8677600 | I90: =LEFT(A90,2) -> 63 | J90: =LEFT(A90,3) -> 632 | K90: =LEFT(A90,4) -> 6324 | L90: =LEFT(A90,5) -> 63240 | M90: =LEFT(A90,1) -> 6
A91: 632410 | B91: HONORAIRES | E91: 8625000 | G91: 8625000 | I91: =LEFT(A91,2) -> 63 | J91: =LEFT(A91,3) -> 632 | K91: =LEFT(A91,4) -> 6324 | L91: =LEFT(A91,5) -> 63241 | M91: =LEFT(A91,1) -> 6
A92: 632700 | B92: CMACGM/EXPORT | E92: 42708533 | G92: 42708533 | I92: =LEFT(A92,2) -> 63 | J92: =LEFT(A92,3) -> 632 | K92: =LEFT(A92,4) -> 6327 | L92: =LEFT(A92,5) -> 63270 | M92: =LEFT(A92,1) -> 6
A93: 632710 | B93: BIRA TRANSIT/EXPORT | E93: 48166076 | G93: 48166076 | I93: =LEFT(A93,2) -> 63 | J93: =LEFT(A93,3) -> 632 | K93: =LEFT(A93,4) -> 6327 | L93: =LEFT(A93,5) -> 63271 | M93: =LEFT(A93,1) -> 6
A94: 632720 | B94: DP WORLD | E94: 41300 | G94: 41300 | I94: =LEFT(A94,2) -> 63 | J94: =LEFT(A94,3) -> 632 | K94: =LEFT(A94,4) -> 6327 | L94: =LEFT(A94,5) -> 63272 | M94: =LEFT(A94,1) -> 6
A95: 632730 | B95: WEST AFRICA LOGISTICS LTD | E95: 934423 | G95: 934423 | I95: =LEFT(A95,2) -> 63 | J95: =LEFT(A95,3) -> 632 | K95: =LEFT(A95,4) -> 6327 | L95: =LEFT(A95,5) -> 63273 | M95: =LEFT(A95,1) -> 6
A96: 632740 | B96: DIAMOND SHIPPING | E96: 24151956 | G96: 24151956 | I96: =LEFT(A96,2) -> 63 | J96: =LEFT(A96,3) -> 632 | K96: =LEFT(A96,4) -> 6327 | L96: =LEFT(A96,5) -> 63274 | M96: =LEFT(A96,1) -> 6
A97: 632750 | B97: S.I.W.A | E97: 452624 | G97: 452624 | I97: =LEFT(A97,2) -> 63 | J97: =LEFT(A97,3) -> 632 | K97: =LEFT(A97,4) -> 6327 | L97: =LEFT(A97,5) -> 63275 | M97: =LEFT(A97,1) -> 6
A98: 637000 | B98: REMUNERATION DU PERSONNEL EX | E98: 23106116 | G98: 23106116 | I98: =LEFT(A98,2) -> 63 | J98: =LEFT(A98,3) -> 637 | K98: =LEFT(A98,4) -> 6370 | L98: =LEFT(A98,5) -> 63700 | M98: =LEFT(A98,1) -> 6
A99: 637010 | B99: PRESTATION | E99: 74143628 | G99: 74143628 | I99: =LEFT(A99,2) -> 63 | J99: =LEFT(A99,3) -> 637 | K99: =LEFT(A99,4) -> 6370 | L99: =LEFT(A99,5) -> 63701 | M99: =LEFT(A99,1) -> 6
A100: 641800 | B100: AUTRES IMPOTS ET TAXES DIRECTES | E100: 5166230 | G100: 5166230 | I100: =LEFT(A100,2) -> 64 | J100: =LEFT(A100,3) -> 641 | K100: =LEFT(A100,4) -> 6418 | L100: =LEFT(A100,5) -> 64180 | M100: =LEFT(A100,1) -> 6
A101: 658200 | B101: DONS | E101: 2100000 | G101: 2100000 | I101: =LEFT(A101,2) -> 65 | J101: =LEFT(A101,3) -> 658 | K101: =LEFT(A101,4) -> 6582 | L101: =LEFT(A101,5) -> 65820 | M101: =LEFT(A101,1) -> 6
A102: 661100 | B102: SALAIRE VERSE AU PERSONNEL | E102: 45123838 | G102: 45123838 | I102: =LEFT(A102,2) -> 66 | J102: =LEFT(A102,3) -> 661 | K102: =LEFT(A102,4) -> 6611 | L102: =LEFT(A102,5) -> 66110 | M102: =LEFT(A102,1) -> 6
... A110: 681300 | B110: DOTATIONS AUX AMORT.CORPORELS | E110: 167527975 | G110: 167527975 | I110: =LEFT(A110,2) -> 68 | J110: =LEFT(A110,3) -> 681 | K110: =LEFT(A110,4) -> 6813 | L110: =LEFT(A110,5) -> 68130 | M110: =LEFT(A110,1) -> 6
A111: 702200 | B111: VENTE DE PRODUIT FINIS HORS UEM | F111: 5294648115 | H111: 5294648115 | I111: =LEFT(A111,2) -> 70 | J111: =LEFT(A111,3) -> 702 | K111: =LEFT(A111,4) -> 7022 | L111: =LEFT(A111,5) -> 70220 | M111: =LEFT(A111,1) -> 7
A112: 891000 | B112: IMPOT/LES SOCIETES | E112: 15445350 | G112: 15445350 | I112: =LEFT(A112,2) -> 89 | J112: =LEFT(A112,3) -> 891 | K112: =LEFT(A112,4) -> 8910 | L112: =LEFT(A112,5) -> 89100 | M112: =LEFT(A112,1) -> 8
I113: =LEFT(A113,2) | J113: =LEFT(A113,3) | K113: =LEFT(A113,4) | L113: =LEFT(A113,5) | M113: =LEFT(A113,1)
I114: =LEFT(A114,2) | J114: =LEFT(A114,3) | K114: =LEFT(A114,4) | L114: =LEFT(A114,5) | M114: =LEFT(A114,1)
...

Sheet BAL N-1
A1: N° Comptes | B1: Libellés | C1: S 1 Débit | D1: S 1 Crédit | E1: Mouv Débit | F1: Mouv Crédit | G1: S 2 Débit | H1: S 2 Crédit | I1: Ext 2 | J1: Ext 3 | K1: Ext 4 | L1: Ext 5 | M1: Ext 1
A2: 101000 | B2: CAPITAL | D2: 145000000 | H2: 145000000 | I2: =LEFT(A2,2) -> 10 | J2: =LEFT(A2,3) -> 101 | K2: =LEFT(A2,4) -> 1010 | L2: =LEFT(A2,5) -> 10100 | M2: =LEFT(A2,1) -> 1
A3: 111000 | B3: RESERVE LEGALE | D3: 200000 | F3: 28800000 | H3: 29000000 | I3: =LEFT(A3,2) -> 11 | J3: =LEFT(A3,3) -> 111 | K3: =LEFT(A3,4) -> 1110 | L3: =LEFT(A3,5) -> 11100 | M3: =LEFT(A3,1) -> 1
A4: 118800 | B4: RESERVES LIBRES | D4: 118365583 | F4: 951477399 | H4: 1069842982 | I4: =LEFT(A4,2) -> 11 | J4: =LEFT(A4,3) -> 118 | K4: =LEFT(A4,4) -> 1188 | L4: =LEFT(A4,5) -> 11880 | M4: =LEFT(A4,1) -> 1
A5: 130100 | B5: RESULTAT EN INTANCE D AFFECTION | D5: 290958290 | E5: 290958290 | I5: =LEFT(A5,2) -> 13 | J5: =LEFT(A5,3) -> 130 | K5: =LEFT(A5,4) -> 1301 | L5: =LEFT(A5,5) -> 13010 | M5: =LEFT(A5,1) -> 1
A6: 130110 | B6: RESULTAT A AFFECTER | D6: 167236460 | E6: 167236460 | I6: =LEFT(A6,2) -> 13 | J6: =LEFT(A6,3) -> 130 | K6: =LEFT(A6,4) -> 1301 | L6: =LEFT(A6,5) -> 13011 | M6: =LEFT(A6,1) -> 1
A7: 130120 | B7: RESULTAT A AFFECTER 2021 | D7: 325128014 | E7: 325128014 | I7: =LEFT(A7,2) -> 13 | J7: =LEFT(A7,3) -> 130 | K7: =LEFT(A7,4) -> 1301 | L7: =LEFT(A7,5) -> 13012 | M7: =LEFT(A7,1) -> 1
A8: 130130 | B8: RESULTAT A AFFECTER 2022 | D8: 109430079 | E8: 109430079 | I8: =LEFT(A8,2) -> 13 | J8: =LEFT(A8,3) -> 130 | K8: =LEFT(A8,4) -> 1301 | L8: =LEFT(A8,5) -> 13013 | M8: =LEFT(A8,1) -> 1
A9: 131000 | B9: RESULTAT NET : BENEFICE | D9: 87524556 | E9: 87524556 | I9: =LEFT(A9,2) -> 13 | J9: =LEFT(A9,3) -> 131 | K9: =LEFT(A9,4) -> 1310 | L9: =LEFT(A9,5) -> 13100 | M9: =LEFT(A9,1) -> 1
A10: 222000 | B10: TERRAINS | C10: 146070000 | E10: 107500000 | G10: 253570000 | I10: =LEFT(A10,2) -> 22 | J10: =LEFT(A10,3) -> 222 | K10: =LEFT(A10,4) -> 2220 | L10: =LEFT(A10,5) -> 22200 | M10: =LEFT(A10,1) -> 2
A11: 229800 | B11: ETUDE TUBO GRAFIQUE | C11: 1599000 | E11: 1400000 | G11: 2999000 | I11: =LEFT(A11,2) -> 22 | J11: =LEFT(A11,3) -> 229 | K11: =LEFT(A11,4) -> 2298 | L11: =LEFT(A11,5) -> 22980 | M11: =LEFT(A11,1) -> 2
A12: 231100 | B12: BATIMENTS INDUSTRIELS | C12: 474597458 | G12: 474597458 | I12: =LEFT(A12,2) -> 23 | J12: =LEFT(A12,3) -> 231 | K12: =LEFT(A12,4) -> 2311 | L12: =LEFT(A12,5) -> 23110 | M12: =LEFT(A12,1) -> 2
A13: 231110 | B13: BATIMENTS AUTRES | C13: 108355497 | G13: 108355497 | I13: =LEFT(A13,2) -> 23 | J13: =LEFT(A13,3) -> 231 | K13: =LEFT(A13,4) -> 2311 | L13: =LEFT(A13,5) -> 23111 | M13: =LEFT(A13,1) -> 2
A14: 231120 | B14: AUTRES BATIMENTS | C14: 518717871 | G14: 518717871 | I14: =LEFT(A14,2) -> 23 | J14: =LEFT(A14,3) -> 231 | K14: =LEFT(A14,4) -> 2311 | L14: =LEFT(A14,5) -> 23112 | M14: =LEFT(A14,1) -> 2
A15: 234100 | B15: INSTALLATION COMPLEXE SPEC | C15: 268942370 | G15: 268942370 | I15: =LEFT(A15,2) -> 23 | J15: =LEFT(A15,3) -> 234 | K15: =LEFT(A15,4) -> 2341 | L15: =LEFT(A15,5) -> 23410 | M15: =LEFT(A15,1) -> 2
A16: 235100 | B16: AMENAG BUREAU ET INSTALLATION | C16: 161240234 | G16: 161240234 | I16: =LEFT(A16,2) -> 23 | J16: =LEFT(A16,3) -> 235 | K16: =LEFT(A16,4) -> 2351 | L16: =LEFT(A16,5) -> 23510 | M16: =LEFT(A16,1) -> 2
A17: 238000 | B17: AUTRES INTALLA ET AGENCEM | C17: 16992250 | E17: 1838250 | G17: 18830500 | I17: =LEFT(A17,2) -> 23 | J17: =LEFT(A17,3) -> 238 | K17: =LEFT(A17,4) -> 2380 | L17: =LEFT(A17,5) -> 23800 | M17: =LEFT(A17,1) -> 2
A18: 239000 | B18: BATIMENT ET INSTAL EN COURS | C18: 53596539 | E18: 49513650 | G18: 103110189 | I18: =LEFT(A18,2) -> 23 | J18: =LEFT(A18,3) -> 239 | K18: =LEFT(A18,4) -> 2390 | L18: =LEFT(A18,5) -> 23900 | M18: =LEFT(A18,1) -> 2
A19: 241100 | B19: MATERIEL INDUSTRIEL | C19: 427578375 | E19: 20108194 | G19: 447686569 | I19: =LEFT(A19,2) -> 24 | J19: =LEFT(A19,3) -> 241 | K19: =LEFT(A19,4) -> 2411 | L19: =LEFT(A19,5) -> 24110 | M19: =LEFT(A19,1) -> 2
A20: 241500 | B20: MATERIEL DE COMMUNICATION | C20: 496000 | G20: 496000 | I20: =LEFT(A20,2) -> 24 | J20: =LEFT(A20,3) -> 241 | K20: =LEFT(A20,4) -> 2415 | L20: =LEFT(A20,5) -> 24150 | M20: =LEFT(A20,1) -> 2
A21: 244100 | B21: MATERIEL DE BUREAU | E21: 100000 | G21: 100000 | I21: =LEFT(A21,2) -> 24 | J21: =LEFT(A21,3) -> 244 | K21: =LEFT(A21,4) -> 2441 | L21: =LEFT(A21,5) -> 24410 | M21: =LEFT(A21,1) -> 2
A22: 244200 | B22: Matériel et mobilier informatique | C22: 21284652 | E22: 474000 | G22: 21758652 | I22: =LEFT(A22,2) -> 24 | J22: =LEFT(A22,3) -> 244 | K22: =LEFT(A22,4) -> 2442 | L22: =LEFT(A22,5) -> 24420 | M22: =LEFT(A22,1) -> 2
A23: 244400 | B23: MOBILIER DE BUREAU | C23: 4462000 | G23: 4462000 | I23: =LEFT(A23,2) -> 24 | J23: =LEFT(A23,3) -> 244 | K23: =LEFT(A23,4) -> 2444 | L23: =LEFT(A23,5) -> 24440 | M23: =LEFT(A23,1) -> 2
A24: 245100 | B24: Matériel automobile | C24: 65268881 | E24: 90000 | G24: 65358881 | I24: =LEFT(A24,2) -> 24 | J24: =LEFT(A24,3) -> 245 | K24: =LEFT(A24,4) -> 2451 | L24: =LEFT(A24,5) -> 24510 | M24: =LEFT(A24,1) -> 2
A25: 272000 | B25: PRET AU PERSONNEL | E25: 10138000 | F25: 6558000 | G25: 3580000 | I25: =LEFT(A25,2) -> 27 | J25: =LEFT(A25,3) -> 272 | K25: =LEFT(A25,4) -> 2720 | L25: =LEFT(A25,5) -> 27200 | M25: =LEFT(A25,1) -> 2
A26: 272100 | B26: PRET AUX MAREYEUR | E26: 2318147 | G26: 2318147 | I26: =LEFT(A26,2) -> 27 | J26: =LEFT(A26,3) -> 272 | K26: =LEFT(A26,4) -> 2721 | L26: =LEFT(A26,5) -> 27210 | M26: =LEFT(A26,1) -> 2
A27: 275100 | B27: DEPOTS ET CAUT POUR LOYERS D'AVANCE | C27: 5463000 | G27: 5463000 | I27: =LEFT(A27,2) -> 27 | J27: =LEFT(A27,3) -> 275 | K27: =LEFT(A27,4) -> 2751 | L27: =LEFT(A27,5) -> 27510 | M27: =LEFT(A27,1) -> 2
A28: 275200 | B28: DEPOT POUR ELECTRICITE | C28: 6717480 | G28: 6717480 | I28: =LEFT(A28,2) -> 27 | J28: =LEFT(A28,3) -> 275 | K28: =LEFT(A28,4) -> 2752 | L28: =LEFT(A28,5) -> 27520 | M28: =LEFT(A28,1) -> 2
A29: 282980 | B29: AMORTS ETUDES TOPOGRAPHIQUE | D29: 79950 | F29: 83450 | H29: 163400 | I29: =LEFT(A29,2) -> 28 | J29: =LEFT(A29,3) -> 282 | K29: =LEFT(A29,4) -> 2829 | L29: =LEFT(A29,5) -> 28298 | M29: =LEFT(A29,1) -> 2
A30: 283110 | B30: AMORTS BATIMENT INDUSTRIELS | D30: 377645399 | F30: 57763368 | H30: 435408767 | I30: =LEFT(A30,2) -> 28 | J30: =LEFT(A30,3) -> 283 | K30: =LEFT(A30,4) -> 2831 | L30: =LEFT(A30,5) -> 28311 | M30: =LEFT(A30,1) -> 2
A31: 283410 | B31: AMORT AMENAG & INST TECH SOL PROPRE | F31: 13447119 | H31: 13447119 | I31: =LEFT(A31,2) -> 28 | J31: =LEFT(A31,3) -> 283 | K31: =LEFT(A31,4) -> 2834 | L31: =LEFT(A31,5) -> 28341 | M31: =LEFT(A31,1) -> 2
A32: 283510 | B32: AMORT DES AMENAG DE BUREAUX | D32: 65793499 | F32: 16124023 | H32: 81917522 | I32: =LEFT(A32,2) -> 28 | J32: =LEFT(A32,3) -> 283 | K32: =LEFT(A32,4) -> 2835 | L32: =LEFT(A32,5) -> 28351 | M32: =LEFT(A32,1) -> 2
A33: 283800 | B33: AMORTS AUTRES INSTAL & AGENCMENT | D33: 12861393 | F33: 1867731 | H33: 14729124 | I33: =LEFT(A33,2) -> 28 | J33: =LEFT(A33,3) -> 283 | K33: =LEFT(A33,4) -> 2838 | L33: =LEFT(A33,5) -> 28380 | M33: =LEFT(A33,1) -> 2
A34: 284110 | B34: AMORTS MAT ET OUTILS IND | D34: 297514034 | F34: 26814122 | H34: 324328156 | I34: =LEFT(A34,2) -> 28 | J34: =LEFT(A34,3) -> 284 | K34: =LEFT(A34,4) -> 2841 | L34: =LEFT(A34,5) -> 28411 | M34: =LEFT(A34,1) -> 2
A35: 284150 | B35: AMORT MAT DE COMMUNICATION | D35: 459713 | F35: 24620 | H35: 484333 | I35: =LEFT(A35,2) -> 28 | J35: =LEFT(A35,3) -> 284 | K35: =LEFT(A35,4) -> 2841 | L35: =LEFT(A35,5) -> 28415 | M35: =LEFT(A35,1) -> 2
A36: 284420 | B36: AMORT MATERIEL INFORMAIQUE | D36: 15998013 | F36: 2583580 | H36: 18581593 | I36: =LEFT(A36,2) -> 28 | J36: =LEFT(A36,3) -> 284 | K36: =LEFT(A36,4) -> 2844 | L36: =LEFT(A36,5) -> 28442 | M36: =LEFT(A36,1) -> 2
A37: 284440 | B37: AMORT MOBILIER DE BUREAU | D37: 4462000 | F37: 16667 | H37: 4478667 | I37: =LEFT(A37,2) -> 28 | J37: =LEFT(A37,3) -> 284 | K37: =LEFT(A37,4) -> 2844 | L37: =LEFT(A37,5) -> 28444 | M37: =LEFT(A37,1) -> 2
A38: 284500 | B38: AMORTS MATERIEL TRANSP | D38: 58423140 | F38: 4149241 | H38: 62572381 | I38: =LEFT(A38,2) -> 28 | J38: =LEFT(A38,3) -> 284 | K38: =LEFT(A38,4) -> 2845 | L38: =LEFT(A38,5) -> 28450 | M38: =LEFT(A38,1) -> 2
A39: 321000 | B39: STOCK POISSONS | C39: 365270359 | E39: 431895875 | F39: 365270359 | G39: 431895875 | I39: =LEFT(A39,2) -> 32 | J39: =LEFT(A39,3) -> 321 | K39: =LEFT(A39,4) -> 3210 | L39: =LEFT(A39,5) -> 32100 | M39: =LEFT(A39,1) -> 3
A40: 401000 | B40: Fr. FOURNISSEUR : MAREYEUR | E40: 4721812043 | F40: 4726300688 | H40: 4488645 | I40: =LEFT(A40,2) -> 40 | J40: =LEFT(A40,3) -> 401 | K40: =LEFT(A40,4) -> 4010 | L40: =LEFT(A40,5) -> 40100 | M40: =LEFT(A40,1) -> 4
A41: 401100 | B41: Fournisseurs | E41: 1114709403 | F41: 1099333737 | G41: 15375666 | I41: =LEFT(A41,2) -> 40 | J41: =LEFT(A41,3) -> 401 | K41: =LEFT(A41,4) -> 4011 | L41: =LEFT(A41,5) -> 40110 | M41: =LEFT(A41,1) -> 4
A42: 408100 | B42: FNRS FACT NON PARVENUES | D42: 3938800 | E42: 3938800 | I42: =LEFT(A42,2) -> 40 | J42: =LEFT(A42,3) -> 408 | K42: =LEFT(A42,4) -> 4081 | L42: =LEFT(A42,5) -> 40810 | M42: =LEFT(A42,1) -> 4
A43: 409100 | B43: Fournisseurs avances et acomptes ve | C43: 130837030 | G43: 130837030 | I43: =LEFT(A43,2) -> 40 | J43: =LEFT(A43,3) -> 409 | K43: =LEFT(A43,4) -> 4091 | L43: =LEFT(A43,5) -> 40910 | M43: =LEFT(A43,1) -> 4
A44: 411000 | B44: CLIENTS | C44: 33496906640 | E44: 6110078435 | F44: 39529551148 | G44: 77433927 | I44: =LEFT(A44,2) -> 41 | J44: =LEFT(A44,3) -> 411 | K44: =LEFT(A44,4) -> 4110 | L44: =LEFT(A44,5) -> 41100 | M44: =LEFT(A44,1) -> 4
A45: 419000 | B45: CLIENTS CREDITEUR | E45: 6032644998 | F45: 6113893063 | H45: 81248065 | I45: =LEFT(A45,2) -> 41 | J45: =LEFT(A45,3) -> 419 | K45: =LEFT(A45,4) -> 4190 | L45: =LEFT(A45,5) -> 41900 | M45: =LEFT(A45,1) -> 4
A46: 419100 | B46: CLIENTS AVANCE ET ACOMPTE | D46: 34387691773 | E46: 34387691773 | F46: 968219060 | H46: 968219060 | I46: =LEFT(A46,2) -> 41 | J46: =LEFT(A46,3) -> 419 | K46: =LEFT(A46,4) -> 4191 | L46: =LEFT(A46,5) -> 41910 | M46: =LEFT(A46,1) -> 4
A47: 421000 | B47: PERSONNEL AVCES ET ACOMPTE | C47: 18407185 | E47: 2525000 | F47: 20932185 | I47: =LEFT(A47,2) -> 42 | J47: =LEFT(A47,3) -> 421 | K47: =LEFT(A47,4) -> 4210 | L47: =LEFT(A47,5) -> 42100 | M47: =LEFT(A47,1) -> 4
A48: 422000 | B48: PERSONNEL REMUNERATIONS DUE | E48: 50903972 | F48: 54726607 | H48: 3822635 | I48: =LEFT(A48,2) -> 42 | J48: =LEFT(A48,3) -> 422 | K48: =LEFT(A48,4) -> 4220 | L48: =LEFT(A48,5) -> 42200 | M48: =LEFT(A48,1) -> 4
A49: 431000 | B49: SECURITE SOCIALE | D49: 652658 | E49: 6567141 | F49: 7511396 | H49: 1596913 | I49: =LEFT(A49,2) -> 43 | J49: =LEFT(A49,3) -> 431 | K49: =LEFT(A49,4) -> 4310 | L49: =LEFT(A49,5) -> 43100 | M49: =LEFT(A49,1) -> 4
A50: 431200 | B50: ACCIDENTS DE TRAVAIL | E50: 126485 | G50: 126485 | I50: =LEFT(A50,2) -> 43 | J50: =LEFT(A50,3) -> 431 | K50: =LEFT(A50,4) -> 4312 | L50: =LEFT(A50,5) -> 43120 | M50: =LEFT(A50,1) -> 4
A51: 431300 | B51: CAISSE RETRAITE OBLIGATOIRE IPRES | D51: 1698672 | E51: 7443089 | F51: 7531940 | H51: 1787523 | I51: =LEFT(A51,2) -> 43 | J51: =LEFT(A51,3) -> 431 | K51: =LEFT(A51,4) -> 4313 | L51: =LEFT(A51,5) -> 43130 | M51: =LEFT(A51,1) -> 4
A52: 441000 | B52: ETAT IMPOT SUR LES BENEFICES | D52: 15445350 | E52: 15445350 | F52: 17126791 | H52: 17126791 | I52: =LEFT(A52,2) -> 44 | J52: =LEFT(A52,3) -> 441 | K52: =LEFT(A52,4) -> 4410 | L52: =LEFT(A52,5) -> 44100 | M52: =LEFT(A52,1) -> 4
A53: 442200 | B53: IMPOTS ET TAXES SUR LES COLLECT PUB | D53: 66000 | H53: 66000 | I53: =LEFT(A53,2) -> 44 | J53: =LEFT(A53,3) -> 442 | K53: =LEFT(A53,4) -> 4422 | L53: =LEFT(A53,5) -> 44220 | M53: =LEFT(A53,1) -> 4
A54: 445000 | B54: ETAT, TVA RECUPERABLE | E54: 78407 | G54: 78407 | I54: =LEFT(A54,2) -> 44 | J54: =LEFT(A54,3) -> 445 | K54: =LEFT(A54,4) -> 4450 | L54: =LEFT(A54,5) -> 44500 | M54: =LEFT(A54,1) -> 4
A55: 445200 | B55: T.V.A. récupérable sur achats | C55: 199564 | E55: 480164 | G55: 679728 | I55: =LEFT(A55,2) -> 44 | J55: =LEFT(A55,3) -> 445 | K55: =LEFT(A55,4) -> 4452 | L55: =LEFT(A55,5) -> 44520 | M55: =LEFT(A55,1) -> 4
A56: 447200 | B56: IMPOT SUR SALAIRES : VRS | D56: 290371 | E56: 5006336 | F56: 4915609 | H56: 199644 | I56: =LEFT(A56,2) -> 44 | J56: =LEFT(A56,3) -> 447 | K56: =LEFT(A56,4) -> 4472 | L56: =LEFT(A56,5) -> 44720 | M56: =LEFT(A56,1) -> 4
A57: 447210 | B57: BRS | E57: 4723189 | F57: 4723189 | I57: =LEFT(A57,2) -> 44 | J57: =LEFT(A57,3) -> 447 | K57: =LEFT(A57,4) -> 4472 | L57: =LEFT(A57,5) -> 44721 | M57: =LEFT(A57,1) -> 4
A58: 448600 | B58: ETAT,CHARGES A PAYER | D58: 2951700 | H58: 2951700 | I58: =LEFT(A58,2) -> 44 | J58: =LEFT(A58,3) -> 448 | K58: =LEFT(A58,4) -> 4486 | L58: =LEFT(A58,5) -> 44860 | M58: =LEFT(A58,1) -> 4
A59: 449000 | B59: IS | E59: 30000000 | G59: 30000000 | I59: =LEFT(A59,2) -> 44 | J59: =LEFT(A59,3) -> 449 | K59: =LEFT(A59,4) -> 4490 | L59: =LEFT(A59,5) -> 44900 | M59: =LEFT(A59,1) -> 4
A60: 449010 | B60: VRS DE TROP | C60: 630308 | G60: 630308 | I60: =LEFT(A60,2) -> 44 | J60: =LEFT(A60,3) -> 449 | K60: =LEFT(A60,4) -> 4490 | L60: =LEFT(A60,5) -> 44901 | M60: =LEFT(A60,1) -> 4
A61: 449020 | B61: BRS DE TROP | C61: 366814 | G61: 366814 | I61: =LEFT(A61,2) -> 44 | J61: =LEFT(A61,3) -> 449 | K61: =LEFT(A61,4) -> 4490 | L61: =LEFT(A61,5) -> 44902 | M61: =LEFT(A61,1) -> 4
A62: 449030 | B62: IS DE TROP | C62: 5237217 | G62: 5237217 | I62: =LEFT(A62,2) -> 44 | J62: =LEFT(A62,3) -> 449 | K62: =LEFT(A62,4) -> 4490 | L62: =LEFT(A62,5) -> 44903 | M62: =LEFT(A62,1) -> 4
A63: 462000 | B63: ASSOCIES, COMPTES COURANTS | D63: 7374167 | H63: 7374167 | I63: =LEFT(A63,2) -> 46 | J63: =LEFT(A63,3) -> 462 | K63: =LEFT(A63,4) -> 4620 | L63: =LEFT(A63,5) -> 46200 | M63: =LEFT(A63,1) -> 4
A64: 465000 | B64: ASSOCIES DIVIDENDES A PAYER | D64: 23000000 | H64: 23000000 | I64: =LEFT(A64,2) -> 46 | J64: =LEFT(A64,3) -> 465 | K64: =LEFT(A64,4) -> 4650 | L64: =LEFT(A64,5) -> 46500 | M64: =LEFT(A64,1) -> 4
A65: 521501 | B65: BANK OF AFRICA | C65: 179432776 | E65: 6114809563 | F65: 6049606195 | G65: 244636144 | I65: =LEFT(A65,2) -> 52 | J65: =LEFT(A65,3) -> 521 | K65: =LEFT(A65,4) -> 5215 | L65: =LEFT(A65,5) -> 52150 | M65: =LEFT(A65,1) -> 5
A66: 521505 | B66: FBNBANK | C66: 1547920 | F66: 1500000 | G66: 47920 | I66: =LEFT(A66,2) -> 52 | J66: =LEFT(A66,3) -> 521 | K66: =LEFT(A66,4) -> 5215 | L66: =LEFT(A66,5) -> 52150 | M66: =LEFT(A66,1) -> 5
A67: 571000 | B67: CAISSE | C67: 39972194 | E67: 1376070891 | F67: 1412805451 | G67: 3237634 | I67: =LEFT(A67,2) -> 57 | J67: =LEFT(A67,3) -> 571 | K67: =LEFT(A67,4) -> 5710 | L67: =LEFT(A67,5) -> 57100 | M67: =LEFT(A67,1) -> 5
A68: 585000 | B68: VIREMENTS DE FONDS | E68: 1369484885 | F68: 1369484885 | I68: =LEFT(A68,2) -> 58 | J68: =LEFT(A68,3) -> 585 | K68: =LEFT(A68,4) -> 5850 | L68: =LEFT(A68,5) -> 58500 | M68: =LEFT(A68,1) -> 5
A69: 602100 | B69: ACHAT LOCAUX DE MATIERES 1ER | E69: 4805921959 | G69: 4805921959 | I69: =LEFT(A69,2) -> 60 | J69: =LEFT(A69,3) -> 602 | K69: =LEFT(A69,4) -> 6021 | L69: =LEFT(A69,5) -> 60210 | M69: =LEFT(A69,1) -> 6
A70: 603200 | B70: VARIATION STOCK MAT 1ER AU APPROV | E70: 365270359 | F70: 431895875 | H70: 66625516 | I70: =LEFT(A70,2) -> 60 | J70: =LEFT(A70,3) -> 603 | K70: =LEFT(A70,4) -> 6032 | L70: =LEFT(A70,5) -> 60320 | M70: =LEFT(A70,1) -> 6
A71: 604000 | B71: ACHAT STOCKE MATIER ET FOURNI CONSO | E71: 129250 | G71: 129250 | I71: =LEFT(A71,2) -> 60 | J71: =LEFT(A71,3) -> 604 | K71: =LEFT(A71,4) -> 6040 | L71: =LEFT(A71,5) -> 60400 | M71: =LEFT(A71,1) -> 6
A72: 604300 | B72: PRODUIT D'ENTRETIEN | E72: 2650000 | G72: 2650000 | I72: =LEFT(A72,2) -> 60 | J72: =LEFT(A72,3) -> 604 | K72: =LEFT(A72,4) -> 6043 | L72: =LEFT(A72,5) -> 60430 | M72: =LEFT(A72,1) -> 6
A73: 604600 | B73: FOURNITURE DE MAGASIN | E73: 64255977 | G73: 64255977 | I73: =LEFT(A73,2) -> 60 | J73: =LEFT(A73,3) -> 604 | K73: =LEFT(A73,4) -> 6046 | L73: =LEFT(A73,5) -> 60460 | M73: =LEFT(A73,1) -> 6
A74: 605000 | B74: AUTRES ACHATS | E74: 7144626 | F74: 18260 | G74: 7126366 | I74: =LEFT(A74,2) -> 60 | J74: =LEFT(A74,3) -> 605 | K74: =LEFT(A74,4) -> 6050 | L74: =LEFT(A74,5) -> 60500 | M74: =LEFT(A74,1) -> 6
A75: 605100 | B75: FOURNITURE NON STOKABLE EAU | E75: 6250 | G75: 6250 | I75: =LEFT(A75,2) -> 60 | J75: =LEFT(A75,3) -> 605 | K75: =LEFT(A75,4) -> 6051 | L75: =LEFT(A75,5) -> 60510 | M75: =LEFT(A75,1) -> 6
A76: 605200 | B76: Fournitures non stockab - Electrici | E76: 105380200 | G76: 105380200 | I76: =LEFT(A76,2) -> 60 | J76: =LEFT(A76,3) -> 605 | K76: =LEFT(A76,4) -> 6052 | L76: =LEFT(A76,5) -> 60520 | M76: =LEFT(A76,1) -> 6
A77: 605300 | B77: Fourn non soctk. ESSENCE | E77: 4558097 | G77: 4558097 | I77: =LEFT(A77,2) -> 60 | J77: =LEFT(A77,3) -> 605 | K77: =LEFT(A77,4) -> 6053 | L77: =LEFT(A77,5) -> 60530 | M77: =LEFT(A77,1) -> 6
A78: 605310 | B78: CARBURANT | E78: 2204267 | G78: 2204267 | I78: =LEFT(A78,2) -> 60 | J78: =LEFT(A78,3) -> 605 | K78: =LEFT(A78,4) -> 6053 | L78: =LEFT(A78,5) -> 60531 | M78: =LEFT(A78,1) -> 6
A79: 605400 | B79: Fournitures d'entretien non stockab | E79: 927000 | G79: 927000 | I79: =LEFT(A79,2) -> 60 | J79: =LEFT(A79,3) -> 605 | K79: =LEFT(A79,4) -> 6054 | L79: =LEFT(A79,5) -> 60540 | M79: =LEFT(A79,1) -> 6
A80: 605500 | B80: Fournitures de bureau non stockable | E80: 3318750 | G80: 3318750 | I80: =LEFT(A80,2) -> 60 | J80: =LEFT(A80,3) -> 605 | K80: =LEFT(A80,4) -> 6055 | L80: =LEFT(A80,5) -> 60550 | M80: =LEFT(A80,1) -> 6
A81: 605600 | B81: Achats de petit matériel et outilla | E81: 42893270 | G81: 42893270 | I81: =LEFT(A81,2) -> 60 | J81: =LEFT(A81,3) -> 605 | K81: =LEFT(A81,4) -> 6056 | L81: =LEFT(A81,5) -> 60560 | M81: =LEFT(A81,1) -> 6
A82: 605700 | B82: Achats d'études et presta de servic | E82: 98835743 | G82: 98835743 | I82: =LEFT(A82,2) -> 60 | J82: =LEFT(A82,3) -> 605 | K82: =LEFT(A82,4) -> 6057 | L82: =LEFT(A82,5) -> 60570 | M82: =LEFT(A82,1) -> 6
A83: 605800 | B83: Achats de travaux, matériels et équ | E83: 14167145 | G83: 14167145 | I83: =LEFT(A83,2) -> 60 | J83: =LEFT(A83,3) -> 605 | K83: =LEFT(A83,4) -> 6058 | L83: =LEFT(A83,5) -> 60580 | M83: =LEFT(A83,1) -> 6
A84: 605810 | B84: TENUES DE TRAVAIL | E84: 23569013 | G84: 23569013 | I84: =LEFT(A84,2) -> 60 | J84: =LEFT(A84,3) -> 605 | K84: =LEFT(A84,4) -> 6058 | L84: =LEFT(A84,5) -> 60581 | M84: =LEFT(A84,1) -> 6
A85: 606120 | B85: GAZ | E85: 231250 | G85: 231250 | I85: =LEFT(A85,2) -> 60 | J85: =LEFT(A85,3) -> 606 | K85: =LEFT(A85,4) -> 6061 | L85: =LEFT(A85,5) -> 60612 | M85: =LEFT(A85,1) -> 6
A86: 608100 | B86: EMBALLAGES PERDUS | E86: 88988546 | G86: 88988546 | I86: =LEFT(A86,2) -> 60 | J86: =LEFT(A86,3) -> 608 | K86: =LEFT(A86,4) -> 6081 | L86: =LEFT(A86,5) -> 60810 | M86: =LEFT(A86,1) -> 6
... A99: 631000 | B99: FRAIS BANCAIRE | E99: 3618855 | G99: 3618855 | I99: =LEFT(A99,2) -> 63 | J99: =LEFT(A99,3) -> 631 | K99: =LEFT(A99,4) -> 6310 | L99: =LEFT(A99,5) -> 63100 | M99: =LEFT(A99,1) -> 6
A100: 631800 | B100: Autres frais bancaires | E100: 7937445 | F100: 17500 | G100: 7919945 | I100: =LEFT(A100,2) -> 63 | J100: =LEFT(A100,3) -> 631 | K100: =LEFT(A100,4) -> 6318 | L100: =LEFT(A100,5) -> 63180 | M100: =LEFT(A100,1) -> 6
A101: 632400 | B101: HONORAIRES DES PROFESSIONS REGLEMEN | E101: 31802000 | G101: 31802000 | I101: =LEFT(A101,2) -> 63 | J101: =LEFT(A101,3) -> 632 | K101: =LEFT(A101,4) -> 6324 | L101: =LEFT(A101,5) -> 63240 | M101: =LEFT(A101,1) -> 6
A102: 632410 | B102: HONORAIRES | E102: 11855000 | G102: 11855000 | I102: =LEFT(A102,2) -> 63 | J102: =LEFT(A102,3) -> 632 | K102: =LEFT(A102,4) -> 6324 | L102: =LEFT(A102,5) -> 63241 | M102: =LEFT(A102,1) -> 6
A103: 632500 | B103: FRAIS D ACTES ET DE CONTENTIEUX | E103: 6131709 | G103: 6131709 | I103: =LEFT(A103,2) -> 63 | J103: =LEFT(A103,3) -> 632 | K103: =LEFT(A103,4) -> 6325 | L103: =LEFT(A103,5) -> 63250 | M103: =LEFT(A103,1) -> 6
A104: 632700 | B104: Rémunération des autres prestataire | E104: 592324 | G104: 592324 | I104: =LEFT(A104,2) -> 63 | J104: =LEFT(A104,3) -> 632 | K104: =LEFT(A104,4) -> 6327 | L104: =LEFT(A104,5) -> 63270 | M104: =LEFT(A104,1) -> 6
A105: 632701 | B105: CMACGM/EXPORT | E105: 13573904 | G105: 13573904 | I105: =LEFT(A105,2) -> 63 | J105: =LEFT(A105,3) -> 632 | K105: =LEFT(A105,4) -> 6327 | L105: =LEFT(A105,5) -> 63270 | M105: =LEFT(A105,1) -> 6
A106: 632710 | B106: BIRA TRANSIT/EXPORT | E106: 63617713 | G106: 63617713 | I106: =LEFT(A106,2) -> 63 | J106: =LEFT(A106,3) -> 632 | K106: =LEFT(A106,4) -> 6327 | L106: =LEFT(A106,5) -> 63271 | M106: =LEFT(A106,1) -> 6
A107: 632720 | B107: DP WORLD | E107: 757456 | G107: 757456 | I107: =LEFT(A107,2) -> 63 | J107: =LEFT(A107,3) -> 632 | K107: =LEFT(A107,4) -> 6327 | L107: =LEFT(A107,5) -> 63272 | M107: =LEFT(A107,1) -> 6
A108: 632760 | B108: MSC MEDITERRANEAN SHIPPING COMPANY | E108: 34002988 | G108: 34002988 | I108: =LEFT(A108,2) -> 63 | J108: =LEFT(A108,3) -> 632 | K108: =LEFT(A108,4) -> 6327 | L108: =LEFT(A108,5) -> 63276 | M108: =LEFT(A108,1) -> 6
A109: 632770 | B109: WELCOME ITALIE B FALL | E109: 1275000 | G109: 1275000 | I109: =LEFT(A109,2) -> 63 | J109: =LEFT(A109,3) -> 632 | K109: =LEFT(A109,4) -> 6327 | L109: =LEFT(A109,5) -> 63277 | M109: =LEFT(A109,1) -> 6
A110: 633000 | B110: FRAIS DE FORMATION DU PERSONNEL | E110: 425000 | G110: 425000 | I110: =LEFT(A110,2) -> 63 | J110: =LEFT(A110,3) -> 633 | K110: =LEFT(A110,4) -> 6330 | L110: =LEFT(A110,5) -> 63300 | M110: =LEFT(A110,1) -> 6
A111: 637000 | B111: RENUMERATION DU PERSONNEL EXTERIEUR | E111: 193651042 | G111: 193651042 | I111: =LEFT(A111,2) -> 63 | J111: =LEFT(A111,3) -> 637 | K111: =LEFT(A111,4) -> 6370 | L111: =LEFT(A111,5) -> 63700 | M111: =LEFT(A111,1) -> 6
A112: 637010 | B112: PRESTATION | E112: 2117350 | G112: 2117350 | I112: =LEFT(A112,2) -> 63 | J112: =LEFT(A112,3) -> 637 | K112: =LEFT(A112,4) -> 6370 | L112: =LEFT(A112,5) -> 63701 | M112: =LEFT(A112,1) -> 6
...

Sheet Activités de l'entreprise R2
A1: Fiche R2
B4: Désignation de l'entreprise : | C4: ='Fiche de renseignement R1'!$J$4 -> 0
B5: Adresse de l'entreprise :
B6: ='Fiche de renseignement R1'!J7 -> 0 | L6: Sigle usuel : | M6: ='Fiche de renseignement R1'!AD7 -> 0
B7: N° d'identification : | L7: Exercice clos le :
B8: =+'Fiche de renseignement R1'!J10 -> 0 | K8: ='Fiche de renseignement R1'!V10 -> 0 | M8: Durée (en mois) | N8: ='Fiche de renseignement R1'!AH10 -> 12
A10: FICHE D'IDENTIFICATION ET RENSEIGNEMENTS DIVERS 2
L12: Contrôle de l'entreprise (cocher la case)
A14: ZK | B14: Forme juridique (1) | F14: 0 | G14: 2 | K14: ZQ | L14: Entreprise sous contrôle public
A16: ZL | B16: Régime fiscal (1) | F16: 2 | K16: ZR | L16: Entreprise sous contrôle privé national | Q16: X
A18: ZM | B18: Pays du siège social (1) | F18: 0 | G18: 7 | K18: ZS | L18: Entreprise sous contrôle privé étranger
A20: ZN | B20: Nbre d'établissements dans le pays | F20: 0 | G20: 1
A22: ZO | B22: Nbre d'établissements hors du pays | F22: 0 | G22: 0
B23: pour lesquels une comptabilité distincte est tenue
A25: ZP | B25: 1ère année exercice dans le pays | E25: 2 | F25: 0 | G25: 0 | H25: 1
A28: ACTIVITE DE L'ENTREPRISE
B30: DESIGNATION DE L'ACTIVITE (2) | C30: Code nomenclature d'activité (1) | K30: Valeur Ajoutée (VA) HT/ Chiffre d'affaire | M30: % activité dans le CA HT ou la VA
B33: TRAITEMENT ET EXPORTATION DE PRODUITS HALIEUTIQUES | D33: 3 | E33: 0 | F33: 0 | G33: 0 | H33: 2 | I33: 0 | L33: =IFERROR(VLOOKUP("702200",'BAL N'!A:H,8,FALSE),IFERROR(VLOOKUP(702200,'BAL N'!A:H,8,FALSE),0)) -> 5294648115 | M33: =IFERROR(+L33/$L$59,0) -> 1
M36: =IFERROR(+L36/$L$59,0) -> 0
M39: =IFERROR(+L39/$L$59,0) -> 0
M42: =IFERROR(+L42/$L$59,0) -> 0
M45: =IFERROR(+L45/$L$59,0) -> 0
M48: =IFERROR(+L48/$L$59,0) -> 0
M51: =IFERROR(+L51/$L$59,0) -> 0
M54: =IFERROR(+L54/$L$59,0) -> 0
B57: Divers
I59: TOTAL | L59: =SUM(L32:L56) -> 5294648115 | M59: =SUM(M32:M57) -> 1
B62: (1) Se réréfer aux tables des codes
B63: (2) Lister de manière précise les activités dans l'ordre décroissant du CAHT, ou de la valeur ajoutée (V.A.)
B64: (3) Rayer la mention inutile (utiliser de préférence la V.A.)

Sheet Dirigeants R3
A1: Fiche R3
A3: Désignation de l'entreprise | B3: ='Fiche de renseignement R1'!$J$4 -> 0
A4: Adresse de l'entreprise | B4: ='Activités de l''entreprise R2'!B6 -> 0 | D4: Sigle usuel | E4: ='Activités de l''entreprise R2'!M6 -> 0
A5: N° d'identification fiscale | B5: ='Activités de l''entreprise R2'!B8 -> 0 | C5: Exercice clos le | D5: ='Activités de l''entreprise R2'!K8 -> 0 | E5: Durée (en mois) | F5: ='Activités de l''entreprise R2'!N8 -> 12
A7: FICHE D'IDENTIFICATION ET RENSEIGNEMENTS DIVERS 3
A9: DIRIGEANTS (1)
A11: Nom | B11: Prénoms | C11: Qualité | D11: N° d'identification fiscale | E11: Adressse (BP, ville, pays)
A12: HDH | B12: HDDH | C12: HH | D12: DHD | E12: DHHH
A27: (1) Dirigeants = Président Directeur Général, Directeur Général, Adminsitrateur Général, Gérant, Autres.
A29: MEMBRES DU CONSEIL D'ADMINISTRATION
A31: Nom | B31: Prénoms | C31: Qualité | E31: Adressse (BP, ville, pays)

Sheet Tableau des Notes R4
A1: FICHE R4
A2: Désignation entité : | B2: ='Fiche de renseignement R1'!$J$4 -> 0 | D2: Excercice clos le : | E2: =+'Fiche de renseignement R1'!$V$10 -> 0
A3: Numéro d'identification : | B3: =+'Fiche de renseignement R1'!$J$10 -> 0 | D3: Durée en mois : | E3: =+'Fiche de renseignement R1'!$AH$10 -> 12
A6: FICHE RECAPITULATIVE DES NOTES ANNEXES PRESENTEES
A8: NOTES | B8: INTITULES | C8: A | E8: N/A
A9: NOTE 1 | B9: DETTES GARANTIES PAR DES SURETES REELLES
A10: NOTE 2 | B10: INFORMATIONS OBLIGATOIRES
A11: NOTE 3A | B11: IMMOBILISATION BRUTE
A12: NOTE 3B | B12: BIENS PRIS EN LOCATION ACQUISITION
A13: NOTE 3C | B13: IMMOBILISATIONS : AMORTISSEMENTS
A14: NOTE 3D | B14: IMMOBILISATIONS : PLUS-VALUES ET MOINS VALUES DE CESSION
A15: NOTE 3E | B15: INFORMATIONS SUR LES REEVALUATIONS EFFECTUEES PAR L'ENTITE
A16: NOTE 4 | B16: IMMOBILISATIONS FINANCIERES
A17: NOTE 5 | B17: ACTIF CIRCULANT HAO
A18: NOTE 6 | B18: STOCKS ET ENCOURS
A19: NOTE 7 | B19: CLIENTS PRODUITS A RECEVOIR
A20: NOTE 8 | B20: AUTRES CREANCES
... A54: NOTE 36 | B54: TABLES DES CODES

Sheet BILAN PAYSAGE
A1: BILAN PAYSAGE
A3: Désignation entité : | D3: ='Fiche de renseignement R1'!$J$4 -> 0 | I3: Excercice clos le : | J3: =+'Fiche de renseignement R1'!$V$10 -> 0
A4: Numéro d'identification : | D4: =+'Fiche de renseignement R1'!$J$10 -> 0 | I4: Durée en mois : | J4: =+'Fiche de renseignement R1'!$AH$10 -> 12
A6: REF | B6: ACTIF | C6: Note | D6: =IFERROR("Exercice au 31/12/"&YEAR('Fiche de renseignement R1'!V10),"Exercice au 31/12/N") -> Exercice au 31/12/1900 | G6: =IFERROR("Exercice au 31/12/"&YEAR('Fiche de renseignement R1'!Q20),"Exercice au 31/12/N-1") -> Exercice au 31/12/2020 | H6: REF | I6: PASSIF | J6: Note | K6: =IFERROR("Exercice au 31/12/"&YEAR('Fiche de renseignement R1'!V10),"Exercice au 31/12/N") -> Exercice au 31/12/1900 | L6: =IFERROR("Exercice au 31/12/"&YEAR('Fiche de renseignement R1'!Q20),"Exercice au 31/12/N-1") -> Exercice au 31/12/2020
D7: Brut | E7: Amorts et Dépréc. | F7: Net | G7: Net | K7: Net | L7: Net
A8: AD | B8: IMMOBILISATIONS INCORPORELLES | C8: 3 | D8: =+D9+D10+D11+D12 -> 0 | E8: =+E9+E10+E11+E12 -> 0 | F8: =+F9+F10+F11+F12 -> 0 | G8: =+G9+G10+G11+G12 -> 0 | H8: CA | I8: CAPITAL | J8: 13 | K8: =+SUMIF('BAL N'!J:J,"=101",'BAL N'!H:H)+SUMIF('BAL N'!J:J,"=102",'BAL N'!H:H)+SUMIF('BAL N'!J:J,"=103",'BAL N'!H:H)+SUMIF('BAL N'!J:J,"=104",'BAL N'!H:H) -> 145000000 | L8: =+SUMIF('BAL N'!J:J,"=101",'BAL N'!D:D)+SUMIF('BAL N'!J:J,"=102",'BAL N'!D:D)+SUMIF('BAL N'!J:J,"=103",'BAL N'!D:D)+SUMIF('BAL N'!J:J,"=104",'BAL N'!D:D) -> 145000000
A9: AE | B9: Frais de développement et de prospection | D9: =+SUMIF('BAL N'!J:J,"=211",'BAL N'!G:G)+SUMIF('BAL N'!K:K,"=2181",'BAL N'!G:G)+SUMIF('BAL N'!K:K,"=2191",'BAL N'!G:G) -> 0 | E9: =+SUMIF('BAL N'!K:K,"=2811",'BAL N'!H:H)+SUMIF('BAL N'!L:L,"=28181",'BAL N'!H:H)+SUMIF('BAL N'!L:L,"=28191",'BAL N'!H:H)+SUMIF('BAL N'!K:K,"=2911",'BAL N'!H:H)+SUMIF('BAL N'!K:K,"=2918",'BAL N'!H:H)+SUMIF('BAL N'!K:K,"=2919",'BAL N'!H:H) -> 0 | F9: =+D9-E9 -> 0 | G9: =+SUMIF('BAL N'!J:J,"=211",'BAL N'!C:C)+SUMIF('BAL N'!K:K,"=2181",'BAL N'!C:C)+SUMIF('BAL N'!K:K,"=2191",'BAL N'!C:C)-(SUMIF('BAL N'!K:K,"=2811",'BAL N'!D:D)+SUMIF('BAL N'!L:L,"=28181",'BAL N'!D:D)+SUMIF('BAL N'!L:L,"=28191",'BAL N'!D:D)+SUMIF('BAL N'!K:K,"=2911",'BAL N'!D:D)+SUMIF('BAL N'!K:K,"=2918",'BAL N'!D:D)+SUMIF('BAL N'!K:K,"=2919",'BAL N'!D:D)) -> 0 | H9: CB | I9: Apporteurs capital non appelé | J9: 13 | K9: =+SUMIF('BAL N'!J:J,"=109",'BAL N'!H:H) -> 0 | L9: =+SUMIF('BAL N'!J:J,"=109",'BAL N'!D:D) -> 0
A10: AF | B10: Brevets, licences, logiciels et droits similaires | D10: =+SUMIF('BAL N'!J:J,"=212",'BAL N'!G:G)+SUMIF('BAL N'!J:J,"=213",'BAL N'!G:G)+SUMIF('BAL N'!J:J,"=214",'BAL N'!G:G)+SUMIF('BAL N'!K:K,"=2193",'BAL N'!G:G) -> 0 | E10: =+SUMIF('BAL N'!K:K,"=2812",'BAL N'!H:H)+SUMIF('BAL N'!K:K,"=2813",'BAL N'!H:H)+SUMIF('BAL N'!K:K,"=2814",'BAL N'!H:H)+SUMIF('BAL N'!K:K,"=2912",'BAL N'!H:H)+SUMIF('BAL N'!K:K,"=2913",'BAL N'!H:H)+SUMIF('BAL N'!K:K,"=2914",'BAL N'!H:H)+SUMIF('BAL N'!K:K,"=2919",'BAL N'!H:H) -> 0 | F10: =+D10-E10 -> 0 | G10: =+SUMIF('BAL N'!J:J,"=212",'BAL N'!C:C)+SUMIF('BAL N'!J:J,"=213",'BAL N'!C:C)+SUMIF('BAL N'!J:J,"=214",'BAL N'!C:C)+SUMIF('BAL N'!K:K,"=2193",'BAL N'!C:C)-(SUMIF('BAL N'!K:K,"=2811",'BAL N'!D:D)+SUMIF('BAL N'!K:K,"=2812",'BAL N'!D:D)+SUMIF('BAL N'!K:K,"=2813",'BAL N'!D:D)+SUMIF('BAL N'!K:K,"=2814",'BAL N'!D:D)+SUMIF('BAL N'!L:L,"=28181",'BAL N'!D:D)+SUMIF('BAL N'!L:L,"=28191",'BAL N'!D:D)+SUMIF('BAL N'!K:K,"=2911",'BAL N'!D:D)+SUMIF('BAL N'!K:K,"=2912",'BAL N'!D:D)+SUMIF('BAL N'!K:K,"=2913",'BAL N'!D:D)+SUMIF('BAL N'!K:K,"=2914",'BAL N'!D:D)+SUMIF('BAL N'!K:K,"=2918",'BAL N'!D:D)+SUMIF('BAL N'!K:K,"=2919",'BAL N'!D:D)) -> 0 | H10: CD | I10: Primes liées au capital social | J10: 14 | K10: =+SUMIF('BAL N'!J:J,"=105",'BAL N'!H:H) -> 0 | L10: =+SUMIF('BAL N'!J:J,"=105",'BAL N'!D:D) -> 0
A11: AG | B11: Fonds commercial et droit au bail | D11: =+SUMIF('BAL N'!J:J,"=215",'BAL N'!G:G)+SUMIF('BAL N'!J:J,"=216",'BAL N'!G:G) -> 0 | E11: =+SUMIF('BAL N'!K:K,"=2815",'BAL N'!H:H)+SUMIF('BAL N'!K:K,"=2816",'BAL N'!H:H)+SUMIF('BAL N'!K:K,"=2915",'BAL N'!H:H)+SUMIF('BAL N'!K:K,"=2916",'BAL N'!H:H) -> 0 | F11: =+D11-E11 -> 0 | G11: =+SUMIF('BAL N'!J:J,"=215",'BAL N'!C:C)+SUMIF('BAL N'!J:J,"=216",'BAL N'!C:C)-(SUMIF('BAL N'!K:K,"=2815",'BAL N'!D:D)+SUMIF('BAL N'!K:K,"=2816",'BAL N'!D:D)+SUMIF('BAL N'!K:K,"=2915",'BAL N'!D:D)+SUMIF('BAL N'!K:K,"=2916",'BAL N'!D:D)) -> 0 | H11: CE | I11: Ecarts de réévaluation | J11: 3e | K11: =+SUMIF('BAL N'!J:J,"=106",'BAL N'!H:H) -> 0 | L11: =+SUMIF('BAL N'!J:J,"=106",'BAL N'!D:D) -> 0
A12: AH | B12: Autres immobilisations incorporelles | D12: =+SUMIF('BAL N'!J:J,"=217",'BAL N'!G:G)+SUMIF('BAL N'!J:J,"=218",'BAL N'!G:G)-SUMIF('BAL N'!K:K,"=2181",'BAL N'!G:G)+SUMIF('BAL N'!K:K,"=2198",'BAL N'!G:G) -> 0 | E12: =+SUMIF('BAL N'!K:K,"=2817",'BAL N'!H:H)+SUMIF('BAL N'!K:K,"=2818",'BAL N'!H:H)+SUMIF('BAL N'!K:K,"=2917",'BAL N'!H:H)+SUMIF('BAL N'!K:K,"=2918",'BAL N'!H:H)+SUMIF('BAL N'!K:K,"=2919",'BAL N'!H:H) -> 0 | F12: =+D12-E12 -> 0 | G12: =+SUMIF('BAL N'!J:J,"=217",'BAL N'!C:C)+SUMIF('BAL N'!J:J,"=218",'BAL N'!C:C)-SUMIF('BAL N'!K:K,"=2181",'BAL N'!C:C)+SUMIF('BAL N'!K:K,"=2198",'BAL N'!C:C)-(SUMIF('BAL N'!K:K,"=2817",'BAL N'!D:D)+SUMIF('BAL N'!K:K,"=2818",'BAL N'!D:D)+SUMIF('BAL N'!K:K,"=2917",'BAL N'!D:D)+SUMIF('BAL N'!K:K,"=2918",'BAL N'!D:D)+SUMIF('BAL N'!K:K,"=2919",'BAL N'!D:D)) -> 0 | H12: CF | I12: Réserves indisponibles | J12: 14 | K12: =+SUMIF('BAL N'!J:J,"=111",'BAL N'!H:H)+SUMIF('BAL N'!J:J,"=112",'BAL N'!H:H)+SUMIF('BAL N'!J:J,"=113",'BAL N'!H:H) -> 200000 | L12: =+SUMIF('BAL N'!J:J,"=111",'BAL N'!D:D)+SUMIF('BAL N'!J:J,"=112",'BAL N'!D:D)+SUMIF('BAL N'!J:J,"=113",'BAL N'!D:D) -> 200000
A13: AI | B13: IMMOBILISATIONS CORPORELLES | C13: 3 | D13: =SUM(D14:D19) -> 2269201127 | E13: =SUM(E14:E19) -> 833237141 | F13: =SUM(F14:F19) -> 1435963986 | G13: =SUM(G14:G19) -> 1416348561 | H13: CG | I13: Réserves libres | J13: 14 | K13: =+SUMIF('BAL N'!J:J,"=118",'BAL N'!H:H) -> 118365583 | L13: =+SUMIF('BAL N'!J:J,"=118",'BAL N'!D:D) -> 118365583
A14: AJ | B14: Terrains (1) (1) dont placement en net ………../………… | D14: =+SUMIF('BAL N'!I:I,"=22",'BAL N'!G:G) -> 147669000 | E14: =+SUMIF('BAL N'!J:J,"=282",'BAL N'!H:H)+SUMIF('BAL N'!J:J,"=292",'BAL N'!H:H) -> 79950 | F14: =+D14-E14 -> 147589050 | G14: =+SUMIF('BAL N'!I:I,"=22",'BAL N'!C:C)-(SUMIF('BAL N'!J:J,"=282",'BAL N'!D:D)+SUMIF('BAL N'!J:J,"=292",'BAL N'!D:D)) -> 56669000 | H14: CH | I14: Report à nouveau (+ ou -) | J14: 14 | K14: =+SUMIF('BAL N'!I:I,"=12",'BAL N'!H:H)-SUMIF('BAL N'!I:I,"=12",'BAL N'!G:G) -> 0 | L14: =+SUMIF('BAL N'!I:I,"=13",'BAL N'!D:D)-SUMIF('BAL N'!I:I,"=13",'BAL N'!C:C) -> 892752843
A15: AK | B15: Bâtiments (1) dont placement en net ………../………… | D15: =+SUMIF('BAL N'!J:J,"=231",'BAL N'!G:G)+SUMIF('BAL N'!J:J,"=232",'BAL N'!G:G)+SUMIF('BAL N'!J:J,"=233",'BAL N'!G:G)+SUMIF('BAL N'!J:J,"=237",'BAL N'!G:G)+SUMIF('BAL N'!K:K,"=2391",'BAL N'!G:G) -> 1101670826 | E15: =+SUMIF('BAL N'!K:K,"=2831",'BAL N'!H:H)+SUMIF('BAL N'!K:K,"=2832",'BAL N'!H:H)+SUMIF('BAL N'!K:K,"=2833",'BAL N'!H:H)+SUMIF('BAL N'!K:K,"=2837",'BAL N'!H:H)+SUMIF('BAL N'!K:K,"=2931",'BAL N'!H:H)+SUMIF('BAL N'!K:K,"=2932",'BAL N'!H:H)+SUMIF('BAL N'!K:K,"=2933",'BAL N'!H:H)+SUMIF('BAL N'!K:K,"=2937",'BAL N'!H:H)+SUMIF('BAL N'!K:K,"=2939",'BAL N'!H:H) -> 262184384 | F15: =+D15-E15 -> 839486442 | G15: =+SUMIF('BAL N'!J:J,"=231",'BAL N'!C:C)+SUMIF('BAL N'!J:J,"=232",'BAL N'!C:C)+SUMIF('BAL N'!J:J,"=233",'BAL N'!C:C)+SUMIF('BAL N'!J:J,"=237",'BAL N'!C:C)++SUMIF('BAL N'!J:J,"=239",'BAL N'!C:C)-SUMIF('BAL N'!J:J,"=238",'BAL N'!D:D)-(SUMIF('BAL N'!K:K,"=2831",'BAL N'!D:D)+SUMIF('BAL N'!K:K,"=2832",'BAL N'!D:D)+SUMIF('BAL N'!K:K,"=2833",'BAL N'!D:D)+SUMIF('BAL N'!K:K,"=2837",'BAL N'!D:D)+SUMIF('BAL N'!K:K,"=2931",'BAL N'!D:D)+SUMIF('BAL N'!K:K,"=2932",'BAL N'!D:D)+SUMIF('BAL N'!K:K,"=2933",'BAL N'!D:D)+SUMIF('BAL N'!K:K,"=2937",'BAL N'!D:D)+SUMIF('BAL N'!K:K,"=2939",'BAL N'!D:D)) -> 894569983 | H15: CJ | I15: Résutat net de l'exercice (bénéfice + ou perte -) | K15: =+SUMIF('BAL N'!M:M,"=7",'BAL N'!H:H)+SUMIF('BAL N'!M:M,"=8",'BAL N'!H:H)-SUMIF('BAL N'!M:M,"=6",'BAL N'!G:G)-SUMIF('BAL N'!M:M,"=8",'BAL N'!G:G)+SUMIF('BAL N'!J:J,"=603",'BAL N'!H:H) -> 87524556 | L15: =-SUMIF('BAL N'!J:J,"=131",'BAL N'!C:C)+SUMIF('BAL N'!J:J,"=131",'BAL N'!D:D) -> 0
A16: AL | B16: Aménagements, agencements et installations | D16: =+SUMIF('BAL N'!J:J,"=234",'BAL N'!G:G)+SUMIF('BAL N'!J:J,"=235",'BAL N'!G:G)+SUMIF('BAL N'!J:J,"=238",'BAL N'!G:G)+SUMIF('BAL N'!J:J,"=239",'BAL N'!G:G) -> 500771393 | E16: =+SUMIF('BAL N'!K:K,"=2834",'BAL N'!H:H)+SUMIF('BAL N'!K:K,"=2835",'BAL N'!H:H)+SUMIF('BAL N'!K:K,"=2838",'BAL N'!H:H)+SUMIF('BAL N'!K:K,"=2934",'BAL N'!H:H)+SUMIF('BAL N'!K:K,"=2935",'BAL N'!H:H)+SUMIF('BAL N'!K:K,"=2938",'BAL N'!H:H)+SUMIF('BAL N'!K:K,"=2939",'BAL N'!H:H) -> 194115907 | F16: =+D16-E16 -> 306655486 | G16: =+SUMIF('BAL N'!J:J,"=234",'BAL N'!C:C)+SUMIF('BAL N'!J:J,"=235",'BAL N'!C:C)+SUMIF('BAL N'!J:J,"=238",'BAL N'!C:C)+SUMIF('BAL N'!K:K,"=2392",'BAL N'!C:C)+SUMIF('BAL N'!K:K,"=2393",'BAL N'!C:C)-(+SUMIF('BAL N'!K:K,"=2834",'BAL N'!D:D)+SUMIF('BAL N'!K:K,"=2835",'BAL N'!D:D)+SUMIF('BAL N'!K:K,"=2838",'BAL N'!D:D)+SUMIF('BAL N'!K:K,"=2934",'BAL N'!D:D)+SUMIF('BAL N'!K:K,"=2935",'BAL N'!D:D)+SUMIF('BAL N'!K:K,"=2938",'BAL N'!D:D)+SUMIF('BAL N'!K:K,"=2939",'BAL N'!D:D)) -> 275817542 | H16: CL | I16: Subventions d'investissement | J16: 15 | K16: =+SUMIF('BAL N'!I:I,"=14",'BAL N'!H:H) -> 0 | L16: =+SUMIF('BAL N'!I:I,"=14",'BAL N'!D:D) -> 0
A17: AM | B17: Matériel, mobilier et actifs biologiques | D17: =+SUMIF('BAL N'!I:I,"=24",'BAL N'!G:G)-SUMIF('BAL N'!J:J,"=245",'BAL N'!G:G)-SUMIF('BAL N'!K:K,"=2495",'BAL N'!G:G) -> 453821027 | E17: =+SUMIF('BAL N'!J:J,"=284",'BAL N'!H:H)-SUMIF('BAL N'!K:K,"=2845",'BAL N'!H:H)+SUMIF('BAL N'!J:J,"=294",'BAL N'!H:H)-SUMIF('BAL N'!K:K,"=2945",'BAL N'!H:H)-SUMIF('BAL N'!K:K,"=2949",'BAL N'!H:H) -> 318433760 | F17: =+D17-E17 -> 135387267 | G17: =+SUMIF('BAL N'!I:I,"=24",'BAL N'!C:C)-SUMIF('BAL N'!J:J,"=245",'BAL N'!C:C)-SUMIF('BAL N'!J:J,"=2495",'BAL N'!C:C)-(SUMIF('BAL N'!J:J,"=284",'BAL N'!D:D)-SUMIF('BAL N'!K:K,"=2845",'BAL N'!D:D)+SUMIF('BAL N'!J:J,"=294",'BAL N'!D:D)-SUMIF('BAL N'!K:K,"=2945",'BAL N'!D:D)-SUMIF('BAL N'!K:K,"=2949",'BAL N'!D:D)) -> 170152519 | H17: CM | I17: Provisions réglementées et fonds assimilés | J17: 15 | K17: =+SUMIF('BAL N'!I:I,"=15",'BAL N'!H:H) -> 0 | L17: =+SUMIF('BAL N'!I:I,"=15",'BAL N'!D:D) -> 0
A18: AN | B18: Matériel de transport | D18: =+SUMIF('BAL N'!J:J,"=245",'BAL N'!G:G)+SUMIF('BAL N'!K:K,"=2495",'BAL N'!G:G) -> 65268881 | E18: =+SUMIF('BAL N'!K:K,"=2845",'BAL N'!H:H)+SUMIF('BAL N'!K:K,"=2849",'BAL N'!H:H)+SUMIF('BAL N'!K:K,"=2945",'BAL N'!H:H) -> 58423140 | F18: =+D18-E18 -> 6845741 | G18: =+SUMIF('BAL N'!J:J,"=245",'BAL N'!C:C)+SUMIF('BAL N'!K:K,"=2495",'BAL N'!C:C)-(+SUMIF('BAL N'!K:K,"=2845",'BAL N'!D:D)+SUMIF('BAL N'!K:K,"=2849",'BAL N'!D:D)+SUMIF('BAL N'!K:K,"=2945",'BAL N'!D:D)) -> 19139517 | H18: CP | I18: TOTAL CAPITAUX PROPRES ET RESSOURCES ASSIMILEES | K18: =SUM(K8:K17) -> 351090139 | L18: =SUM(L8:L17) -> 1156318426
A19: AP | B19: Avances & acomptes versés sur immobilisations | C19: 3 | D19: =+SUMIF('BAL N'!I:I,"=25",'BAL N'!G:G) -> 0 | E19: =+SUMIF('BAL N'!J:J,"=295",'BAL N'!H:H) -> 0 | F19: =+D19-E19 -> 0 | G19: =+SUMIF('BAL N'!I:I,"=25",'BAL N'!C:C)-SUMIF('BAL N'!J:J,"=295",'BAL N'!D:D) -> 0 | H19: DA | I19: Emprunts et dettes financières diverses | J19: 16 | K19: =+SUMIF('BAL N'!I:I,"=16",'BAL N'!H:H)+SUMIF('BAL N'!J:J,"=181",'BAL N'!H:H)+SUMIF('BAL N'!J:J,"=182",'BAL N'!H:H)+SUMIF('BAL N'!J:J,"=184",'BAL N'!H:H) -> 0 | L19: =+SUMIF('BAL N'!I:I,"=16",'BAL N'!D:D)+SUMIF('BAL N'!J:J,"=181",'BAL N'!D:D)+SUMIF('BAL N'!J:J,"=182",'BAL N'!D:D)+SUMIF('BAL N'!J:J,"=183",'BAL N'!D:D)+SUMIF('BAL N'!J:J,"=184",'BAL N'!D:D) -> 0
A20: AQ | B20: IMMOBILISATIONS FINANCIERES | C20: 4 | D20: =SUM(D21:D22) -> 12180480 | E20: =SUM(E21:E22) -> 0 | F20: =SUM(F21:F22) -> 12180480 | G20: =SUM(G21:G22) -> 12180480 | H20: DB | I20: Dettes de location acquisition | J20: 16 | K20: =+SUMIF('BAL N'!I:I,"=17",'BAL N'!H:H) -> 0 | L20: =+SUMIF('BAL N'!I:I,"=17",'BAL N'!D:D) -> 0
A21: AR | B21: Titres de participation | D21: =+SUMIF('BAL N'!I:I,"=26",'BAL N'!G:G) -> 0 | E21: =+SUMIF('BAL N'!J:J,"=296",'BAL N'!H:H) -> 0 | F21: =+D21-E21 -> 0 | G21: =+SUMIF('BAL N'!I:I,"=26",'BAL N'!C:C)-SUMIF('BAL N'!J:J,"=296",'BAL N'!D:D) -> 0 | H21: DC | I21: Provisions pour risques et charges | J21: 16 | K21: =+SUMIF('BAL N'!I:I,"=19",'BAL N'!H:H) -> 0 | L21: =+SUMIF('BAL N'!I:I,"=19",'BAL N'!D:D) -> 0
A22: AS | B22: Autres immobilisations financières | D22: =+SUMIF('BAL N'!I:I,"=27",'BAL N'!G:G) -> 12180480 | E22: =+SUMIF('BAL N'!J:J,"=297",'BAL N'!H:H) -> 0 | F22: =+D22-E22 -> 12180480 | G22: =+SUMIF('BAL N'!I:I,"=27",'BAL N'!C:C)-SUMIF('BAL N'!J:J,"=297",'BAL N'!D:D) -> 12180480 | H22: DD | I22: TOTAL DETTES FINANCIERES ET RESSOURCES ASSIMILEES | K22: =SUM(K19:K21) -> 0 | L22: =SUM(L19:L21) -> 0
A23: AZ | B23: TOTAL ACTIF IMMOBILISE | D23: =+D20+D13+D8 -> 2281381607 | E23: =+E20+E13+E8 -> 833237141 | F23: =+F20+F13+F8 -> 1448144466 | G23: =+G20+G13+G8 -> 1428529041 | H23: DF | I23: TOTAL RESSOURCES STABLES
A24: BA | B24: ACTIF CIRCULANT H.A.O. | C24: 5 | D24: =+SUMIF('BAL N'!J:J,"=485",'BAL N'!G:G)+SUMIF('BAL N'!J:J,"=488",'BAL N'!G:G) -> 0 | E24: =+SUMIF('BAL N'!J:J,"=498",'BAL N'!H:H) -> 0 | F24: =+D24-E24 -> 0 | G24: =+SUMIF('BAL N'!J:J,"=485",'BAL N'!C:C)+SUMIF('BAL N'!J:J,"=488",'BAL N'!C:C)-SUMIF('BAL N'!J:J,"=498",'BAL N'!D:D) -> 0 | H24: DH | I24: Dettes circulantes HAO | J24: 5 | K24: =+SUMIF('BAL N'!J:J,"=481",'BAL N'!H:H)+SUMIF('BAL N'!J:J,"=482",'BAL N'!H:H)+SUMIF('BAL N'!J:J,"=484",'BAL N'!H:H)+SUMIF('BAL N'!K:K,"=4998",'BAL N'!H:H) -> 0 | L24: =+SUMIF('BAL N'!J:J,"=481",'BAL N'!D:D)+SUMIF('BAL N'!J:J,"=482",'BAL N'!D:D)+SUMIF('BAL N'!J:J,"=484",'BAL N'!D:D)+SUMIF('BAL N'!K:K,"=4998",'BAL N'!D:D) -> 0
A25: BB | B25: STOCKS ET ENCOURS | C25: 6 | D25: =+SUMIF('BAL N'!I:I,"=31",'BAL N'!G:G)+SUMIF('BAL N'!I:I,"=32",'BAL N'!G:G)+SUMIF('BAL N'!I:I,"=33",'BAL N'!G:G)+SUMIF('BAL N'!I:I,"=34",'BAL N'!G:G)+SUMIF('BAL N'!I:I,"=35",'BAL N'!G:G)+SUMIF('BAL N'!I:I,"=36",'BAL N'!G:G)+SUMIF('BAL N'!I:I,"=37",'BAL N'!G:G)+SUMIF('BAL N'!I:I,"=38",'BAL N'!G:G) -> 365270359 | E25: =+SUMIF('BAL N'!I:I,"=39",'BAL N'!H:H) -> 0 | F25: =+D25-E25 -> 365270359 | G25: =+SUMIF('BAL N'!I:I,"=31",'BAL N'!C:C)+SUMIF('BAL N'!I:I,"=32",'BAL N'!C:C)+SUMIF('BAL N'!I:I,"=33",'BAL N'!C:C)+SUMIF('BAL N'!I:I,"=34",'BAL N'!C:C)+SUMIF('BAL N'!I:I,"=35",'BAL N'!C:C)+SUMIF('BAL N'!I:I,"=36",'BAL N'!C:C)+SUMIF('BAL N'!I:I,"=37",'BAL N'!C:C)+SUMIF('BAL N'!I:I,"=38",'BAL N'!C:C)-SUMIF('BAL N'!I:I,"=39",'BAL N'!D:D) -> 433749204 | H25: DI | I25: Clients, avances reçues | J25: 7 | K25: =+SUMIF('BAL N'!J:J,"=419",'BAL N'!H:H) -> 34387691773 | L25: =+SUMIF('BAL N'!J:J,"=419",'BAL N'!D:D) -> 29055421827
A26: BG | B26: CREANCES ET EMPLOIS ASSIMILES | F26: =+D26-E26 -> 0 | H26: DJ | I26: Fournisseurs d'exploitation | J26: 17 | K26: =+SUMIF('BAL N'!I:I,"=40",'BAL N'!H:H)-SUMIF('BAL N'!J:J,"=409",'BAL N'!H:H) -> 3938800 | L26: =+SUMIF('BAL N'!J:J,"=401",'BAL N'!D:D)+SUMIF('BAL N'!J:J,"=402",'BAL N'!D:D)+SUMIF('BAL N'!J:J,"=408",'BAL N'!D:D)-SUMIF('BAL N'!J:J,"=401",'BAL N'!C:C) -> 12004500
A27: BH | B27: Fournisseurs, avances versées | C27: 17 | D27: =+SUMIF('BAL N'!I:I,"=40",'BAL N'!G:G)-SUMIF('BAL N'!J:J,"=490",'BAL N'!D:D) -> 130837030 | E27: =+SUMIF('BAL N'!J:J,"=490",'BAL N'!H:H) -> 0 | F27: =+D27-E27 -> 130837030 | G27: =+SUMIF('BAL N'!I:I,"=40",'BAL N'!C:C)-SUMIF('BAL N'!J:J,"=490",'BAL N'!D:D)-SUMIF('BAL N'!J:J,"409",'BAL N'!D:D) -> 7010266011 | H27: DK | I27: Dettes fiscales et sociales | J27: 18 | K27: =+SUMIF('BAL N'!I:I,"=42",'BAL N'!H:H)+SUMIF('BAL N'!I:I,"=43",'BAL N'!H:H)+SUMIF('BAL N'!I:I,"=44",'BAL N'!H:H) -> 21104751 | L27: =+SUMIF('BAL N'!I:I,"=42",'BAL N'!D:D)-SUMIF('BAL N'!J:J,"=421",'BAL N'!D:D)+SUMIF('BAL N'!K:K,"=4287",'BAL N'!D:D)+SUMIF('BAL N'!I:I,"=43",'BAL N'!D:D)-SUMIF('BAL N'!K:K,"=4387",'BAL N'!D:D)+SUMIF('BAL N'!J:J,"=441",'BAL N'!D:D)+SUMIF('BAL N'!J:J,"=442",'BAL N'!D:D)+SUMIF('BAL N'!J:J,"=443",'BAL N'!D:D)+SUMIF('BAL N'!K:K,"=4441",'BAL N'!D:D)+SUMIF('BAL N'!J:J,"=446",'BAL N'!D:D)+SUMIF('BAL N'!J:J,"=447",'BAL N'!D:D)+SUMIF('BAL N'!K:K,"=4486",'BAL N'!D:D)+SUMIF('BAL N'!K:K,"=4494",'BAL N'!D:D) -> 27035439
A28: BI | B28: Clients | C28: 7 | D28: =+SUMIF('BAL N'!I:I,"=41",'BAL N'!G:G)-SUMIF('BAL N'!J:J,"=419",'BAL N'!G:G) -> 33496906640 | E28: =+SUMIF('BAL N'!J:J,"=491",'BAL N'!H:H) -> 0 | F28: =+D28-E28 -> 33496906640 | G28: =+SUMIF('BAL N'!I:I,"=41",'BAL N'!C:C)-SUMIF('BAL N'!J:J,"=491",'BAL N'!D:D)-SUMIF('BAL N'!J:J,"=411",'BAL N'!D:D) -> 28202318525 | H28: DM | I28: Autres dettes | J28: 19 | K28: =+SUMIF('BAL N'!J:J,"=185",'BAL N'!H:H)+SUMIF('BAL N'!I:I,"=45",'BAL N'!H:H)+SUMIF('BAL N'!I:I,"=47",'BAL N'!H:H)+SUMIF('BAL N'!I:I,"=46",'BAL N'!H:H)-SUMIF('BAL N'!J:J,"=479",'BAL N'!H:H) -> 30374167 | L28: =+SUMIF('BAL N'!J:J,"=185",'BAL N'!D:D)+SUMIF('BAL N'!K:K,"=4712",'BAL N'!D:D)+SUMIF('BAL N'!J:J,"=472",'BAL N'!D:D)+SUMIF('BAL N'!J:J,"=477",'BAL N'!D:D)+SUMIF('BAL N'!I:I,"=46",'BAL N'!D:D)-SUMIF('BAL N'!J:J,"=4712",'BAL N'!C:C) -> 30374167
A29: BJ | B29: Autres créances | C29: 8 | D29: =SUMIF('BAL N'!J:J,"=185",'BAL N'!G:G)+SUMIF('BAL N'!I:I,"=42",'BAL N'!G:G)+SUMIF('BAL N'!I:I,"=43",'BAL N'!G:G)+SUMIF('BAL N'!I:I,"=44",'BAL N'!G:G)+SUMIF('BAL N'!I:I,"=45",'BAL N'!G:G)+SUMIF('BAL N'!I:I,"=46",'BAL N'!G:G)+SUMIF('BAL N'!I:I,"=47",'BAL N'!G:G)-SUMIF('BAL N'!J:J,"=478",'BAL N'!G:G) -> 24841088 | E29: =+SUMIF('BAL N'!J:J,"=492",'BAL N'!H:H)+SUMIF('BAL N'!J:J,"=493",'BAL N'!H:H)+SUMIF('BAL N'!J:J,"=494",'BAL N'!H:H)+SUMIF('BAL N'!J:J,"=495",'BAL N'!H:H)+SUMIF('BAL N'!J:J,"=496",'BAL N'!H:H)+SUMIF('BAL N'!J:J,"=497",'BAL N'!H:H) -> 0 | F29: =+D29-E29 -> 24841088 | G29: =+SUMIF('BAL N'!K:K,"=4287",'BAL N'!C:C)+SUMIF('BAL N'!K:K,"=4387",'BAL N'!C:C)+SUMIF('BAL N'!K:K,"=4449",'BAL N'!C:C)+SUMIF('BAL N'!J:J,"=421",'BAL N'!C:C)+SUMIF('BAL N'!J:J,"=445",'BAL N'!C:C)+SUMIF('BAL N'!K:K,"=4487",'BAL N'!C:C)+SUMIF('BAL N'!J:J,"=449",'BAL N'!C:C)+SUMIF('BAL N'!I:I,"=45",'BAL N'!C:C)+SUMIF('BAL N'!I:I,"=46",'BAL N'!C:C)+SUMIF('BAL N'!K:K,"=4711",'BAL N'!C:C)+SUMIF('BAL N'!J:J,"=475",'BAL N'!C:C)+SUMIF('BAL N'!J:J,"=476",'BAL N'!C:C)-(SUMIF('BAL N'!J:J,"=492",'BAL N'!D:D)+SUMIF('BAL N'!J:J,"=493",'BAL N'!D:D)+SUMIF('BAL N'!J:J,"=495",'BAL N'!D:D)+SUMIF('BAL N'!J:J,"=496",'BAL N'!D:D)+SUMIF('BAL N'!J:J,"=497",'BAL N'!D:D))-SUMIF('BAL N'!K:K,"=4711",'BAL N'!D:D) -> 36121455 | H29: DN | I29: Provisions pour risques à court terme | J29: 19 | K29: =+SUMIF('BAL N'!J:J,"=499",'BAL N'!H:H)+SUMIF('BAL N'!J:J,"=599",'BAL N'!H:H)-SUMIF('BAL N'!K:K,"=4998",'BAL N'!H:H) -> 0 | L29: =+SUMIF('BAL N'!J:J,"=499",'BAL N'!D:D)+SUMIF('BAL N'!J:J,"=599",'BAL N'!D:D)-SUMIF('BAL N'!K:K,"=4998",'BAL N'!D:D) -> 0
A30: BK | B30: TOTAL ACTIF CIRCULANT | D30: =SUM(D24:D29) -> 34017855117 | E30: =SUM(E24:E29) -> 0 | F30: =SUM(F24:F29) -> 34017855117 | G30: =SUM(G24:G29) -> 35682455195 | H30: DP | I30: TOTAL PASSIF CIRCULANT | K30: =SUM(K24:K29) -> 34443109491 | L30: =SUM(L24:L29) -> 29124835933
A31: BQ | B31: Titres de placement | C31: 9 | D31: =+SUMIF('BAL N'!I:I,"=50",'BAL N'!G:G) -> 0 | E31: =+SUMIF('BAL N'!J:J,"=590",'BAL N'!H:H) -> 0 | F31: =+D31-E31 -> 0 | G31: =+SUMIF('BAL N'!I:I,"=59",'BAL N'!C:C)-SUMIF('BAL N'!J:J,"=590",'BAL N'!D:D) -> 0
A32: BR | B32: Valeurs à encaisser | C32: 10 | D32: =+SUMIF('BAL N'!I:I,"=51",'BAL N'!G:G) -> 0 | E32: =+SUMIF('BAL N'!J:J,"=591",'BAL N'!H:H) -> 0 | F32: =+D32-E32 -> 0 | G32: =+SUMIF('BAL N'!I:I,"=51",'BAL N'!C:C)-SUMIF('BAL N'!J:J,"=591",'BAL N'!D:D) -> 0 | H32: DQ | I32: Banques, crédits d'escompte | J32: 20 | K32: =+SUMIF('BAL N'!J:J,"=564",'BAL N'!H:H)+SUMIF('BAL N'!J:J,"=565",'BAL N'!H:H) -> 0 | L32: =+SUMIF('BAL N'!J:J,"=564",'BAL N'!D:D)+SUMIF('BAL N'!J:J,"=565",'BAL N'!D:D) -> 0
A33: BS | B33: Banques, chèques postaux, caisse et assimilés | C33: 11 | D33: =SUMIF('BAL N'!I:I,"=52",'BAL N'!G:G)+SUMIF('BAL N'!I:I,"=53",'BAL N'!G:G)+SUMIF('BAL N'!I:I,"=54",'BAL N'!G:G)+SUMIF('BAL N'!I:I,"=55",'BAL N'!G:G)+SUMIF('BAL N'!I:I,"=57",'BAL N'!G:G)+SUMIF('BAL N'!J:J,"=581",'BAL N'!G:G)+SUMIF('BAL N'!J:J,"=582",'BAL N'!G:G) -> 220952890 | E33: =+SUMIF('BAL N'!J:J,"=592",'BAL N'!H:H)+SUMIF('BAL N'!J:J,"=593",'BAL N'!H:H)+SUMIF('BAL N'!J:J,"=594",'BAL N'!H:H) -> 0 | F33: =+D33-E33 -> 220952890 | G33: =SUMIF('BAL N'!I:I,"=52",'BAL N'!C:C)+SUMIF('BAL N'!I:I,"=57",'BAL N'!C:C)+SUMIF('BAL N'!I:I,"=58",'BAL N'!C:C)+SUMIF('BAL N'!I:I,"=55",'BAL N'!C:C)+SUMIF('BAL N'!I:I,"=54",'BAL N'!C:C)+SUMIF('BAL N'!I:I,"=53",'BAL N'!C:C)-SUMIF('BAL N'!J:J,"=592",'BAL N'!D:D) -> 92418291 | H33: DR | I33: Banques, établissements financiers et crédits de trésorerie | J33: 20 | K33: =+SUMIF('BAL N'!I:I,"=52",'BAL N'!H:H)+SUMIF('BAL N'!I:I,"=53",'BAL N'!H:H)+SUMIF('BAL N'!J:J,"=561",'BAL N'!H:H)+SUMIF('BAL N'!J:J,"=566",'BAL N'!H:H) -> 0 | L33: =+SUMIF('BAL N'!I:I,"=52",'BAL N'!D:D)+SUMIF('BAL N'!J:J,"=561",'BAL N'!D:D)+SUMIF('BAL N'!J:J,"=566",'BAL N'!D:D) -> 0
A34: BT | B34: TOTAL TRESORERIE - ACTIF | D34: =SUM(D31:D33) -> 220952890 | E34: =SUM(E31:E33) -> 0 | F34: =SUM(F31:F33) -> 220952890 | G34: =SUM(G31:G33) -> 92418291 | H34: DT | I34: TOTAL TRESORERIE - PASSIF | K34: =+K32+K33 -> 0 | L34: =+L32+L33 -> 0
A35: BU | B35: Ecarts de conversion - Actif | C35: 12 | D35: =+SUMIF('BAL N'!J:J,"=478",'BAL N'!G:G) -> 0 | G35: =+SUMIF('BAL N'!J:J,"=478",'BAL N'!C:C) -> 0 | H35: DV | I35: Ecarts de conversion - Passif | J35: 12 | K35: =+SUMIF('BAL N'!J:J,"=479",'BAL N'!H:H) -> 0 | L35: =+SUMIF('BAL N'!J:J,"=479",'BAL N'!D:D) -> 0
A36: BZ | B36: TOTAL GENERAL | D36: =+D34+D30+D23 -> 36520189614 | E36: =+E34+E30+E23 -> 833237141 | F36: =+F34+F30+F23 -> 35686952473 | G36: =+G34+G30+G23 -> 37203402527 | H36: DZ | I36: TOTAL GENERAL | K36: =+K34+K30+K22+K18 -> 34794199630 | L36: =+L34+L30+L22+L18 -> 30281154359

Sheet COMPTE DE RESULTAT
A1: COMPTE DE RESULTAT
A3: Désignation entité : | B3: ='Fiche de renseignement R1'!$J$4 -> 0 | D3: Excercice clos le : | E3: =+'Fiche de renseignement R1'!$V$10 -> 0
A4: Numéro d'identification : | B4: =+'Fiche de renseignement R1'!$J$10 -> 0 | D4: Durée en mois : | E4: =+'Fiche de renseignement R1'!$AH$10 -> 12
A6: REF | B6: LIBELLES | D6: NOTE | E6: =IFERROR("31/12/"&YEAR('Fiche de renseignement R1'!V10),"Exercice au 31/12/N") -> 31/12/1900 | F6: =IFERROR("31/12/"&YEAR('Fiche de renseignement R1'!Q20),"Exercice au 31/12/N-1") -> 31/12/2020
A7: TA | B7: Ventes de marchandises A | C7: + | D7: 21 | E7: =+SUMIF('BAL N'!J:J,"=701",'BAL N'!H:H) -> 0 | F7: =+SUMIF('BAL N-1'!J:J,"=701",'BAL N-1'!H:H) -> 0
A8: RA | B8: Achats de marchandises | C8: - | D8: 22 | E8: =+SUMIF('BAL N'!J:J,"=601",'BAL N'!G:G) -> 0 | F8: =+SUMIF('BAL N-1'!J:J,"=601",'BAL N-1'!G:G) -> 0
A9: RB | B9: Variation de stocks de marchandises | C9: -/+ | D9: 6 | E9: =-(+SUMIF('BAL N'!K:K,"=6031",'BAL N'!H:H)-SUMIF('BAL N'!K:K,"=6031",'BAL N'!G:G)) -> 0 | F9: =-(+SUMIF('BAL N-1'!K:K,"=6031",'BAL N-1'!H:H)-SUMIF('BAL N-1'!K:K,"=6031",'BAL N-1'!G:G)) -> 0
A10: XA | B10: MARGE BRUTE SUR MARCHANDISES (somme TA à RB) | E10: =+E14-E8-E9 -> 5294648115 | F10: =+F14-F8-F9 -> 6032644508
A11: TB | B11: Ventes de produits fabriqués B | C11: + | D11: 21 | E11: =+SUMIF('BAL N'!J:J,"=702",'BAL N'!H:H)+SUMIF('BAL N'!J:J,"=703",'BAL N'!H:H)+SUMIF('BAL N'!J:J,"=704",'BAL N'!H:H) -> 5294648115 | F11: =+SUMIF('BAL N-1'!J:J,"=702",'BAL N-1'!H:H)+SUMIF('BAL N-1'!J:J,"=703",'BAL N-1'!H:H)+SUMIF('BAL N-1'!J:J,"=704",'BAL N-1'!H:H) -> 6032644508
A12: TC | B12: Travaux, services vendus C | C12: + | D12: 21 | E12: =+SUMIF('BAL N'!J:J,"=705",'BAL N'!H:H)+SUMIF('BAL N'!J:J,"=706",'BAL N'!H:H) -> 0 | F12: =+SUMIF('BAL N-1'!J:J,"=705",'BAL N-1'!H:H)+SUMIF('BAL N-1'!J:J,"=706",'BAL N-1'!H:H) -> 0
A13: TD | B13: Produits accessoires D | C13: + | D13: 21 | E13: =+SUMIF('BAL N'!J:J,"=707",'BAL N'!H:H) -> 0 | F13: =+SUMIF('BAL N-1'!J:J,"=707",'BAL N-1'!H:H) -> 0
A14: XB | B14: CHIFFRE D'AFFAIRES (A + B + C + D) | E14: =+E7+E13+E12+E11 -> 5294648115 | F14: =+F7+F13+F12+F11 -> 6032644508
A15: TE | B15: Production stockée (ou destockage) | C15: -/+ | D15: 6 | E15: =+SUMIF('BAL N'!I:I,"=73",'BAL N'!H:H) -> 0 | F15: =+SUMIF('BAL N-1'!I:I,"=73",'BAL N-1'!H:H) -> 0
A16: TF | B16: Production immobilisée | D16: 21 | E16: =+SUMIF('BAL N'!I:I,"=72",'BAL N'!H:H) -> 0 | F16: =+SUMIF('BAL N-1'!I:I,"=72",'BAL N-1'!H:H) -> 0
A17: TG | B17: Subventions d'exploitation | D17: 21 | E17: =+SUMIF('BAL N'!I:I,"=71",'BAL N'!H:H) -> 0 | F17: =+SUMIF('BAL N-1'!I:I,"=71",'BAL N-1'!H:H) -> 0
A18: TH | B18: Autres produits | C18: + | D18: 21 | E18: =+SUMIF('BAL N'!I:I,"=75",'BAL N'!H:H) -> 0 | F18: =+SUMIF('BAL N-1'!I:I,"=75",'BAL N-1'!H:H) -> 0
A19: TI | B19: Transferts de charges d'exploitation | C19: + | D19: 12 | E19: =+SUMIF('BAL N'!J:J,"=781",'BAL N'!H:H) -> 0 | F19: =+SUMIF('BAL N-1'!J:J,"=781",'BAL N-1'!H:H) -> 0
A20: RC | B20: Achats de matières premières et fournitures liées | C20: - | D20: 22 | E20: =+SUMIF('BAL N'!J:J,"=602",'BAL N'!G:G) -> 4195693297 | F20: =+SUMIF('BAL N-1'!J:J,"=602",'BAL N-1'!G:G) -> 4805921959
A21: RD | B21: Variation de stocks de stocks de matières premières et fournitures liées | C21: -/+ | D21: 6 | E21: =-SUMIF('BAL N'!K:K,"=6032",'BAL N'!H:H)+SUMIF('BAL N'!K:K,"=6032",'BAL N'!G:G)-SUMIF('BAL N'!K:K,"=6034",'BAL N'!H:H)+SUMIF('BAL N'!K:K,"=6034",'BAL N'!G:G) -> 68478845 | F21: =-SUMIF('BAL N-1'!K:K,"=6032",'BAL N-1'!H:H)+SUMIF('BAL N-1'!K:K,"=6032",'BAL N-1'!G:G)-SUMIF('BAL N-1'!K:K,"=6034",'BAL N-1'!H:H)+SUMIF('BAL N-1'!K:K,"=6034",'BAL N-1'!G:G) -> -66625516
A22: RE | B22: Autres achats | C22: - | D22: 22 | E22: =+SUMIF('BAL N'!J:J,"=604",'BAL N'!G:G)+SUMIF('BAL N'!J:J,"=605",'BAL N'!G:G)+SUMIF('BAL N'!J:J,"=608",'BAL N'!G:G)+SUMIF('BAL N'!J:J,"=606",'BAL N'!G:G) -> 239426821 | F22: =+SUMIF('BAL N-1'!J:J,"=604",'BAL N-1'!G:G)+SUMIF('BAL N-1'!J:J,"=605",'BAL N-1'!G:G)+SUMIF('BAL N-1'!J:J,"=608",'BAL N-1'!G:G)+SUMIF('BAL N-1'!J:J,"=606",'BAL N-1'!G:G) -> 459241124
A23: RF | B23: Variation de stocks d'autres approvisionnements | C23: -/+ | D23: 6 | E23: =+SUMIF('BAL N'!K:K,"=6033",'BAL N'!H:H)-SUMIF('BAL N'!K:K,"=6033",'BAL N'!G:G) -> 0 | F23: =+SUMIF('BAL N-1'!K:K,"=6033",'BAL N-1'!H:H)-SUMIF('BAL N-1'!K:K,"=6033",'BAL N-1'!G:G) -> 0
A24: RG | B24: Transports | C24: - | D24: 23 | E24: =+SUMIF('BAL N'!I:I,"=61",'BAL N'!G:G) -> 108008609 | F24: =+SUMIF('BAL N-1'!I:I,"=61",'BAL N-1'!G:G) -> 130715952
A25: RH | B25: Services extérieurs | C25: - | D25: 24 | E25: =+SUMIF('BAL N'!I:I,"=62",'BAL N'!G:G)+SUMIF('BAL N'!I:I,"=63",'BAL N'!G:G) -> 281499882 | F25: =+SUMIF('BAL N-1'!I:I,"=62",'BAL N-1'!G:G)+SUMIF('BAL N-1'!I:I,"=63",'BAL N-1'!G:G) -> 383033096
A26: RI | B26: Impôts et taxes | C26: - | D26: 25 | E26: =+SUMIF('BAL N'!I:I,"=64",'BAL N'!G:G) -> 5166230 | F26: =+SUMIF('BAL N-1'!I:I,"=64",'BAL N-1'!G:G) -> 431794
A27: RJ | B27: Autres charges | C27: - | D27: 26 | E27: =+SUMIF('BAL N'!I:I,"=65",'BAL N'!G:G) -> 2100000 | F27: =+SUMIF('BAL N-1'!I:I,"=65",'BAL N-1'!G:G) -> 6638784
A28: XC | B28: VALEUR AJOUTEE (XB + RA + RB) + (somme TE à RJ) | E28: =+E10+E15+E16+E17+E18+E19-E20-E21-E22-E23-E24-E25-E26-E27 -> 394274431 | F28: =+F10+F15+F16+F17+F18+F19-F20-F21-F22-F23-F24-F25-F26-F27 -> 313287315
A29: RK | B29: Charges de personnel | C29: - | D29: 27 | E29: =+SUMIF('BAL N'!I:I,"=66",'BAL N'!G:G) -> 123776550 | F29: =+SUMIF('BAL N-1'!I:I,"=66",'BAL N-1'!G:G) -> 76234787
A30: XD | B30: EXCEDENT BRUT D'EXPLOITATION (XC + RK) | E30: =+E28-E29 -> 270497881 | F30: =+F28-F29 -> 237052528
A31: TJ | B31: Reprises d'amortissements, provisions et dépréciations | C31: + | D31: 28 | E31: =+SUMIF('BAL N'!J:J,"=791",'BAL N'!H:H)+SUMIF('BAL N'!J:J,"=798",'BAL N'!H:H)+SUMIF('BAL N'!J:J,"=799",'BAL N'!H:H) -> 0 | F31: =+SUMIF('BAL N-1'!J:J,"=791",'BAL N-1'!H:H)+SUMIF('BAL N-1'!J:J,"=798",'BAL N-1'!H:H)+SUMIF('BAL N-1'!J:J,"=799",'BAL N-1'!H:H) -> 0
A32: RL | B32: Dotations aux amortissements, aux provisions et dépréciations | C32: - | D32: 3C & 28 | E32: =+SUMIF('BAL N'!J:J,"=681",'BAL N'!G:G)+SUMIF('BAL N'!J:J,"=691",'BAL N'!G:G) -> 167527975 | F32: =+SUMIF('BAL N-1'!J:J,"=681",'BAL N-1'!G:G)+SUMIF('BAL N-1'!J:J,"=691",'BAL N-1'!G:G) -> 122873921
A33: XE | B33: RESULTAT D'EXPLOITATION (XD + TJ + RL) | E33: =+E30+E31-E32 -> 102969906 | F33: =+F30+F31-F32 -> 114178607
A34: TK | B34: Revenus financiers et assimilés | C34: + | D34: 29 | E34: =+SUMIF('BAL N'!I:I,"=77",'BAL N'!H:H) -> 0 | F34: =+SUMIF('BAL N-1'!I:I,"=77",'BAL N-1'!H:H) -> 0
A35: TL | B35: Reprises de provisions et dépréciations financières | C35: + | D35: 28 | E35: =+SUMIF('BAL N'!J:J,"=797",'BAL N'!H:H) -> 0 | F35: =+SUMIF('BAL N-1'!J:J,"=797",'BAL N-1'!H:H) -> 0
A36: TM | B36: Tranferts de charges financières | C36: + | D36: 12 | E36: =+SUMIF('BAL N'!J:J,"=787",'BAL N'!H:H) -> 0 | F36: =+SUMIF('BAL N-1'!J:J,"=787",'BAL N-1'!H:H) -> 0
A37: RM | B37: Frais financiers et charges assimilées | C37: - | D37: 29 | E37: =+SUMIF('BAL N'!I:I,"=67",'BAL N'!G:G) -> 0 | F37: =+SUMIF('BAL N-1'!I:I,"=67",'BAL N-1'!G:G) -> 0
A38: RN | B38: Dotations aux provisions et aux dépréciations financières | C38: - | D38: 3C & 28 | E38: =SUMIF('BAL N'!J:J,"=697",'BAL N'!G:G) -> 0 | F38: =+SUMIF('BAL N-1'!J:J,"=697",'BAL N-1'!G:G) -> 0
A39: XF | B39: RESULTAT FINANCIER (somme TK à RN) | E39: =+E34+E35+E36-E37-E38 -> 0 | F39: =+F34+F35+F36-F37-F38 -> 0
A40: XG | B40: RESULTAT DES ACTIVITES ORDINAIRES (XE + XF) | E40: =+E33+E39 -> 102969906 | F40: =+F33+F39 -> 114178607
A41: TN | B41: Produits des cessions d'immobilisations | C41: + | D41: 3D | E41: =+SUMIF('BAL N'!I:I,"=82",'BAL N'!H:H) -> 0 | F41: =+SUMIF('BAL N-1'!I:I,"=82",'BAL N-1'!H:H) -> 0
A42: TO | B42: Autres produits H.A.O. | C42: + | D42: 30 | E42: =+SUMIF('BAL N'!I:I,"=84",'BAL N'!H:H)+SUMIF('BAL N'!I:I,"=86",'BAL N'!H:H)+SUMIF('BAL N'!I:I,"=88",'BAL N'!H:H) -> 0 | F42: =+SUMIF('BAL N-1'!I:I,"=84",'BAL N-1'!H:H)+SUMIF('BAL N-1'!I:I,"=86",'BAL N-1'!H:H) -> 0
A43: RO | B43: Valeurs comptables des cessions d'immobilisations | C43: - | D43: 3D | E43: =+SUMIF('BAL N'!I:I,"=81",'BAL N'!G:G) -> 0 | F43: =+SUMIF('BAL N-1'!I:I,"=81",'BAL N-1'!G:G) -> 0
A44: RP | B44: Autres charges H.A.O. | C44: - | D44: 30 | E44: =+SUMIF('BAL N'!I:I,"=83",'BAL N'!G:G)+SUMIF('BAL N'!I:I,"=85",'BAL N'!G:G) -> 0 | F44: =+SUMIF('BAL N-1'!I:I,"=83",'BAL N-1'!G:G)+SUMIF('BAL N-1'!I:I,"=85",'BAL N-1'!G:G) -> 0
A45: XH | B45: RESULTAT HORS ACTIVITES ORDINAIRES (somme TN à RP) | E45: =+E41+E42-E43-E44 -> 0 | F45: =+F41+F42-F43-F44 -> 0
A46: RQ | B46: Participation des travailleurs | C46: - | D46: 30 | E46: =+SUMIF('BAL N'!I:I,"=87",'BAL N'!G:G) -> 0 | F46: =+SUMIF('BAL N-1'!I:I,"=87",'BAL N-1'!G:G) -> 0
A47: RS | B47: Impôts sur le résultat | C47: - | E47: =+SUMIF('BAL N'!I:I,"=89",'BAL N'!G:G) -> 15445350 | F47: =+SUMIF('BAL N-1'!I:I,"=89",'BAL N-1'!G:G) -> 17126791
A48: XI | B48: RESULTAT NET (XG + XH + RQ + RS) | E48: =+E40+E45-E46-E47 -> 87524556 | F48: =+F40+F45-F46-F47 -> 97051816

Sheet FLUX DE TRESORERIE
A1: FLUX DE TRESORERIE
A3: Désignation entité : | B3: ='Fiche de renseignement R1'!$J$4 -> 0 | D3: Excercice clos le : | E3: =+'Fiche de renseignement R1'!$V$10 -> 0
A4: Numéro d'identification : | B4: =+'Fiche de renseignement R1'!$J$10 -> 0 | D4: Durée en mois : | E4: =+'Fiche de renseignement R1'!$AH$10 -> 12
A6: REF | B6: LIBELLES | D6: NOTE | E6: =IFERROR("31/12/"&YEAR('Fiche de renseignement R1'!V10),"Exercice au 31/12/N") -> 31/12/1900 | F6: =IFERROR("31/12/"&YEAR('Fiche de renseignement R1'!Q20),"Exercice au 31/12/N-1") -> 31/12/2020
A7: ZA | B7: Trésorerie nette au 1er janvier (Trésorerie actif N-1 - Trésorerie passif N-1) | C7: A | E7: ='BILAN PAYSAGE'!F34-'BILAN PAYSAGE'!K34 -> 220952890 | F7: -
B8: Flux de trésorerie provenant des activités opérationnelles
A9: FA | B9: Capacité d'Autofinancement Globale (CAFG) | E9: ='COMPTE DE RESULTAT'!E48+'COMPTE DE RESULTAT'!E32-'COMPTE DE RESULTAT'!E31-'COMPTE DE RESULTAT'!E45 -> 255052531 | F9: -
A10: FB | B10: - Variation d'actif circulant HAO (1)
A11: FC | B11: - Variation des stocks | E11: =+'BILAN PAYSAGE'!F25-'BILAN PAYSAGE'!G25 -> -68478845 | F11: -
A12: FD | B12: - Variation des créances | E12: =+('BILAN PAYSAGE'!F27-'BILAN PAYSAGE'!G27)+('BILAN PAYSAGE'!F28-'BILAN PAYSAGE'!G28)+('BILAN PAYSAGE'!F29-'BILAN PAYSAGE'!G29) -> -1596121233 | F12: -
A13: FE | B13: + Variation du passif circulant (1) | E13: =+'BILAN PAYSAGE'!K30-'BILAN PAYSAGE'!L30 -> 5318273558 | F13: -
B14: Variation du BF lié aux activités opérationnelles (FB + FC + FD + FE) : ……………………………………………..
A15: ZB | B15: Flux de trésorerie provenant des activités opérationnelles (somme FA à FE) | C15: B | E15: =+E9-E10-E11-E12+E13 -> 7237926167 | F15: =IFERROR(+F9-F10-F11-F12+F13,0) -> 0
B16: Flux de trésorerie provenant des activités d'investissement
A17: FF | B17: - Décaissements liés aux acquisitions d'immobilisations incorporelles | E17: =+SUMIF('BAL N'!J:J,"=211",'BAL N'!E:E)+SUMIF('BAL N'!J:J,"=212",'BAL N'!E:E)+SUMIF('BAL N'!J:J,"=213",'BAL N'!E:E)+SUMIF('BAL N'!J:J,"=214",'BAL N'!E:E)+SUMIF('BAL N'!J:J,"=215",'BAL N'!E:E)+SUMIF('BAL N'!J:J,"=216",'BAL N'!E:E)+SUMIF('BAL N'!J:J,"=217",'BAL N'!E:E)+SUMIF('BAL N'!J:J,"=218",'BAL N'!E:E) -> 0 | F17: -
A18: FG | B18: - Décaissements liés aux acquisitions d'immobilisations corporelles | E18: =+SUMIF('BAL N'!I:I,"=22",'BAL N'!E:E)+SUMIF('BAL N'!I:I,"=23",'BAL N'!E:E)+SUMIF('BAL N'!I:I,"=24",'BAL N'!E:E) -> 705861271 | F18: -
A19: FH | B19: - Décaissements liés aux acquisitions d'immobilisations financières | E19: =(+SUMIF('BAL N'!I:I,"=25",'BAL N'!E:E)+SUMIF('BAL N'!I:I,"=26",'BAL N'!E:E)+SUMIF('BAL N'!I:I,"=27",'BAL N'!E:E)) -> 0 | F19: -
A20: FI | B20: + Encaissements liés aux cessions d'immobilisations incorporelles et corporelles | E20: =+SUMIF('BAL N'!I:I,"=82",'BAL N'!H:H) -> 0 | F20: -
A21: FJ | B21: + Encaissements liés aux cessions d'immobilisations financières
A22: ZC | B22: Flux de trésorerie provenant des activités d'investissement (somme FF à FJ) | C22: C | E22: =-E17-E18-E19+E20+E21 -> -705861271 | F22: =IFERROR(-F17-F18-F19+F20+F21,0) -> 0
B23: Flux de trésorerie provenant du financement par les capitaux propres
A24: FK | B24: + Augmentations de capital par apports nouveaux
A25: FL | B25: + Subventions d'investissements reçues | E25: =+SUMIF('BAL N'!I:I,"=14",'BAL N'!F:F) -> 0 | F25: -
A26: FM | B26: - Prélèvements sur le capital
A27: FN | B27: - Dividendes versés
A28: ZD | B28: Flux de trésorerie provenant des capitaux propres (somme FK à FN) | C28: D | E28: =+E24+E25-E26-E27 -> 0 | F28: =IFERROR(+F24+F25-F26-F27,0) -> 0
B29: Flux de trésorerie provenant du financement par les capitaux étrangers
A30: FO | B30: + Emprunts | E30: =+SUMIF('BAL N'!J:J,"=161",'BAL N'!F:F)+SUMIF('BAL N'!J:J,"=162",'BAL N'!F:F)+SUMIF('BAL N'!K:K,"=1661",'BAL N'!F:F)+SUMIF('BAL N'!K:K,"=1662",'BAL N'!F:F) -> 0 | F30: -
A31: FP | B31: + Autres dettes financières | E31: =+SUMIF('BAL N'!I:I,"=17",'BAL N'!H:H) -> 0 | F31: -
A32: FQ | B32: - Remboursements des emprunts et autres dettes financières | E32: =+SUMIF('BAL N'!I:I,"=16",'BAL N'!E:E)+SUMIF('BAL N'!I:I,"=17",'BAL N'!E:E)+SUMIF('BAL N'!I:I,"=18",'BAL N'!E:E) -> 0 | F32: -
A33: ZE | B33: Flux de trésorerie provenant des capitaux étrangers (somme FO à FQ) | C33: E | E33: =+E30+E31-E32 -> 0 | F33: =IFERROR(+F30+F31-F32,0) -> 0
A34: ZF | B34: Flux de trésorerie provenant des activités de financement (D + E) | C34: F | E34: =+E28+E33 -> 0 | F34: =+F28+F33 -> 0
A35: ZG | B35: VARIATION DE LA TRESORERIE NETTE DE LA PERIODE (B + C + F) | C35: G | E35: =+E34+E22+E15 -> 6532064896 | F35: =IFERROR(+F34+F22+F15,0) -> 0
A36: ZH | B36: Trésorerie nette au 31 décembre (G + A) Contrôle : Trésorerie actif N - Trésorerie passif N | C36: H | E36: =+E35+E7 -> 6753017786 | F36: =IFERROR(+F35+F7,0) -> 0
B37: Contrôle

Sheet Note 1
A1: NOTE 1 : DETTES GARANTIES PAR DES SURETES REELLES
A3: Désignation entité : | B3: ='Fiche de renseignement R1'!$J$4 -> 0 | D3: Excercice clos le : | E3: =+'Fiche de renseignement R1'!$V$10 -> 0
A4: Numéro d'identification : | B4: =+'Fiche de renseignement R1'!$J$10 -> 0 | D4: Durée en mois : | E4: =+'Fiche de renseignement R1'!$AH$10 -> 12
A7: LIBELLES | B7: Note | C7: Montant brut | D7: SURETES REELLES
D8: Hypothèques | E8: Nantissements | F8: Gages
F9: Autres
A10: Dettes financières et ressources assimilées :
A11: Emprunts obligataires convertibles | C11: =+SUMIF('BAL N'!K:K,"=1612",'BAL N'!H:H) -> 0
A12: Autres emprunts obligataires | C12: =+SUMIF('BAL N'!K:K,"=1618",'BAL N'!H:H) -> 0
A13: Emprunts et dettes des établissements de crédit | C13: =+SUMIF('BAL N'!J:J,"=162",'BAL N'!H:H) -> 0
A14: Autres dettes financières | C14: =+SUMIF('BAL N'!J:J,"=163",'BAL N'!H:H)+SUMIF('BAL N'!J:J,"=164",'BAL N'!H:H)+SUMIF('BAL N'!J:J,"=165",'BAL N'!H:H)+SUMIF('BAL N'!J:J,"=167",'BAL N'!H:H)+SUMIF('BAL N'!J:J,"=168",'BAL N'!H:H) -> 0
A15: SOUS TOTAL (1) | C15: =SUM(C11:C14) -> 0 | D15: =SUM(D11:D14) -> 0 | E15: =SUM(E11:E14) -> 0 | F15: =SUM(F11:F14) -> 0
A17: Dettes de location-acquisition :
A18: Dettes de crédit-bail immobilier | C18: =+SUMIF('BAL N'!J:J,"=172",'BAL N'!H:H) -> 0
A19: Dettes de crédit-bail mobilier | C19: =+SUMIF('BAL N'!J:J,"=173",'BAL N'!H:H) -> 0
A20: Dettes sur contrats de location-vente | C20: =+SUMIF('BAL N'!J:J,"=174",'BAL N'!H:H) -> 0
A21: Dettes sur contrats de location-acquisition | C21: =+SUMIF('BAL N'!J:J,"=176",'BAL N'!H:H) -> 0
A22: SOUS TOTAL (2) | C22: =SUM(C18:C21) -> 0 | D22: =SUM(D18:D21) -> 0 | E22: =SUM(E18:E21) -> 0 | F22: =SUM(F18:F21) -> 0
A24: Dettes du passif circulant :
A25: Fournisseurs et comptes rattachés | C25: =+SUMIF('BAL N'!I:I,"=40",'BAL N'!H:H)-SUMIF('BAL N'!J:J,"=409",'BAL N'!H:H) -> 3938800
A26: Clients | C26: =SUMIF('BAL N'!J:J,"=419",'BAL N'!H:H) -> 34387691773
A27: Personnel | C27: =+SUMIF('BAL N'!I:I,"=42",'BAL N'!H:H) -> 0
A28: Sécurité sociale et organismes sociaux | C28: =+SUMIF('BAL N'!I:I,"=43",'BAL N'!H:H) -> 2351330
A29: Etat | C29: =+SUMIF('BAL N'!I:I,"=44",'BAL N'!H:H) -> 18753421
A30: Organismes internationaux | C30: =+SUMIF('BAL N'!I:I,"=45",'BAL N'!H:H) -> 0
A31: Associés et groupe | C31: =+SUMIF('BAL N'!I:I,"=46",'BAL N'!H:H) -> 30374167
A32: Créditeurs divers | C32: =+SUMIF('BAL N'!I:I,"=47",'BAL N'!H:H) -> 0
A33: SOUS TOTAL (3) | C33: =SUM(C25:C32) -> 34443109491 | D33: =SUM(D25:D32) -> 0 | E33: =SUM(E25:E32) -> 0 | F33: =SUM(F25:F32) -> 0
A34: TOTAL (1) + (2) + (3) | C34: =+C15+C22+C33 -> 34443109491 | D34: =+D15+D22+D33 -> 0 | E34: =+E15+E22+E33 -> 0 | F34: =+F15+F22+F33 -> 0
A35: ENGAGEMENTS FINANCIERS | E35: Engagements donnés | F35: Engagements reçus
A36: Engagements consentis à des entités liées
A37: Primes de remboursement non échus
A38: Avals, cautions, garanties
A39: Hypothèques, nantissements, gages, autres
A40: Effets escomptés non échus
A41: Créances commerciales et professionnelles cédées
A42: Abandons de créances conditionnels
A43: TOTAL | E43: =SUM(E36:E42) -> 0 | F43: =SUM(F36:F42) -> 0
A44: Commentaire :
A45: · Indiquer la raison d’être des suretés

Sheet Note 2
A1: NOTE 2 : INFORMATIONS OBLIGATOIRES
A3: Désignation entité : | B3: ='Fiche de renseignement R1'!$J$4 -> 0 | C3: Excercice clos le : | D3: =+'Note 1'!E3 -> 0
A4: Numéro d'identification : | B4: =+'Note 1'!B4 -> 0 | C4: Durée en mois : | D4: =+'Note 1'!E5 -> 0
A6: A - DECLARATION DE CONFORMITE AU SYSCOHADA
A7: Les états financiers sont établis en conformité avec le systéme comptable OHADA et l'acte uniforme relatif au droit comptable et à l'information financiére
A8: B - REGLES ET METHODES COMPTABLES
A9: Les états financiers ont été confectionnés dans le respect des postulats, des conventions et des régles d'évaluation édictés par le SYSCOHADA et l'Acte Uniforme
A10: C - DEROGATION AUX POSTULATS ET CONVENTIONS COMPTABLES
A11: Respect de tous les postulats et conventions comptables sans aucune dérogation
A12: D - INFORMATIONS COMPLEMENTAIRES RELATIVES AU BILAN, AU COMPTE DE RESULTAT ET AU TABLEAU DES FLUX DE TRESORERIE
A13: Pas d'informations complémentaires relatives aux autres états financiers

Sheet Note 3A
A1: NOTE 3A : IMMOBILISATION BRUTE
A3: Désignation entité : | B3: ='Fiche de renseignement R1'!$J$4 -> 0 | E3: Excercice clos le : | G3: =+'Note 1'!G3 -> 0
A4: Numéro d'identification : | B4: =+'Note 1'!B4 -> 0 | E4: Durée en mois : | G4: =+'Note 1'!E4 -> 12
A7: SITUATIONS ET MOUVEMENTS | B7: Montant brut à l'ouverture de l'exercice | C7: Acquisitions Apports Créations | D7: Virements de poste à poste | E7: Suite à une réévaluation pratiquée au cours de l'exercice | F7: Cessions Scissions Hors service | G7: Virements de poste à poste | H7: Montant brut à la clôture de l'exercice
A10: IMMOBILISATIONS INCORPORELLES
A11: Frais de développement et de prospection | B11: =+SUMIF('BAL N'!J:J,"=211",'BAL N'!G:G) -> 0 | H11: =+B11+C11+D11+E11-F11-G11 -> 0
A12: Brevets, licences, logiciels et droits similaires | B12: =+SUMIF('BAL N'!J:J,"=212",'BAL N'!G:G)+SUMIF('BAL N'!J:J,"=213",'BAL N'!G:G) -> 0 | H12: =+B12+C12+D12+E12-F12-G12 -> 0
A13: Fonds commercial et droit au bail | B13: =+SUMIF('BAL N'!J:J,"=215",'BAL N'!G:G) -> 0 | H13: =+B13+C13+D13+E13-F13-G13 -> 0
A14: Autres immobilisations incorporelles | B14: =+SUMIF('BAL N'!J:J,"=214",'BAL N'!G:G)+SUMIF('BAL N'!J:J,"=216",'BAL N'!G:G)+SUMIF('BAL N'!J:J,"=217",'BAL N'!G:G)+SUMIF('BAL N'!J:J,"=218",'BAL N'!G:G)+SUMIF('BAL N'!J:J,"=219",'BAL N'!G:G) -> 0 | H14: =+B14+C14+D14+E14-F14-G14 -> 0
A15: IMMOBILISATIONS CORPORELLES
A16: Terrains hors immeuble de placement | B16: =+SUMIF('BAL N'!I:I,"=22",'BAL N'!G:G)-SUMIF('BAL N'!J:J,"=228",'BAL N'!G:G) -> 147669000 | H16: =+B16+C16+D16+E16-F16-G16 -> 147669000
A17: Terrains immeuble de placement | B17: =+SUMIF('BAL N'!J:J,"=228",'BAL N'!G:G) -> 0 | H17: =+B17+C17+D17+E17-F17-G17 -> 0
A18: Bâtiments hors immeuble de placement | B18: =+SUMIF('BAL N'!I:I,"=23",'BAL N'!G:G)-SUMIF('BAL N'!K:K,"=2315",'BAL N'!G:G)-SUMIF('BAL N'!K:K,"=2325",'BAL N'!G:G) -> 1602442219 | H18: =+B18+C18+D18+E18-F18-G18 -> 1602442219
A19: Bâtiments immeuble de placement | B19: =+SUMIF('BAL N'!K:K,"=2315",'BAL N'!G:G)+SUMIF('BAL N'!K:K,"=2325",'BAL N'!G:G) -> 0 | H19: =+B19+C19+D19+E19-F19-G19 -> 0
A20: Aménagements, agencements et installations | B20: =+SUMIF('BAL N'!J:J,"=234",'BAL N'!G:G)+SUMIF('BAL N'!J:J,"=235",'BAL N'!G:G) -> 430182604 | H20: =+B20+C20+D20+E20-F20-G20 -> 430182604
A21: Matériel, mobilier et actifs biologiques | B21: =+SUMIF('BAL N'!I:I,"=24",'BAL N'!G:G)-SUMIF('BAL N'!J:J,"=245",'BAL N'!G:G) -> 453821027 | H21: =+B21+C21+D21+E21-F21-G21 -> 453821027
A22: Matériel de transport | B22: =+SUMIF('BAL N'!J:J,"=245",'BAL N'!G:G) -> 65268881 | H22: =+B22+C22+D22+E22-F22-G22 -> 65268881
A23: AVANCES ET ACOMPTES VERSES SUR IMMOBILISATIONS
A24: IMMOBILISATIONS FINANCIERES
A25: Titres de participation | B25: =+SUMIF('BAL N'!I:I,"=26",'BAL N'!G:G) -> 0 | H25: =+B25+C25+D25+E25-F25-G25 -> 0
A26: Autres immobilisations financières | B26: =+SUMIF('BAL N'!I:I,"=27",'BAL N'!G:G) -> 12180480 | H26: =+B26+C26+D26+E26-F26-G26 -> 12180480
A27: TOTAL GENERAL | B27: =SUM(B11:B26) -> 2711564211 | C27: =SUM(C11:C26) -> 0 | D27: =SUM(D11:D26) -> 0 | E27: =SUM(E11:E26) -> 0 | F27: =SUM(F11:F26) -> 0 | G27: =SUM(G11:G26) -> 0 | H27: =SUM(H11:H26) -> 2711564211
A28: Commentaire :
A29: · Toute variation significative doit être commentée
A30: · Détailler les éléments constitutifs du fonds commercial et indiquer la date d'acquisition
A31: · Pour l'immobilisation incorporelle relative à la concession faire un descriptif de l'accord
A32: · Indiquer :
A33: - la nature de la créance ;
A34: - la durée de la concession ;
A35: - l'échéance ;
A36: · Indiquer les créances du groupe avec nature et date d'échéance
A37: · Pour les banques, DAT indiquer le nom de labanque, le montant et la date d'échéance

Sheet Note 3B
A1: NOTE 3B : BIENS PRIS EN LOCATION ACQUISITION
A3: Désignation entité : | B3: ='Fiche de renseignement R1'!$J$4 -> 0 | G3: Excercice clos le : | H3: =+'Note 1'!E3 -> 0
A4: Numéro d'identification : | B4: =+'Note 1'!B4 -> 0 | G4: Durée en mois : | H4: =+'Note 1'!E4 -> 12
A6: SITUATIONS ET MOUVEMENTS | B6: NATURE DU CONTRAT (I; M; A) | C6: A | D6: AUGMENTATIONS B | G6: DIMINUTIONS C | I6: D = A +B - C
C7: Montant brut à l'ouverture de l'exercice | D7: Acquisitions Apports Créations | E7: Virements de poste à poste | F7: Suite à une réévaluation pratiquée au cours de l'exercice | G7: Cessions Scissions Hors service | H7: Virements de poste à poste | I7: Montant brut à l'ouverture de l'exercice
B8: [1]
A9: Brevets, licences, logiciels et droits similaires | I9: =SUM(B9:F9)-SUM(G9:H9) -> 0
A10: Fonds commercial et droit au bail | I10: =SUM(B10:F10)-SUM(G10:H10) -> 0
A11: Autres immobilisations incorporelles | I11: =SUM(B11:F11)-SUM(G11:H11) -> 0
A12: SOUS TOTAL : IMMOBILISATIONS INCORPORELLES | D12: =SUM(D9:D11) -> 0 | E12: =SUM(E9:E11) -> 0 | F12: =SUM(F9:F11) -> 0 | G12: =SUM(G9:G11) -> 0
A13: Terrains | I13: =SUM(B13:F13)-SUM(G13:H13) -> 0
A14: Bâtiments | I14: =SUM(B14:F14)-SUM(G14:H14) -> 0
A15: Aménagements, agencements et installations | I15: =SUM(B15:F15)-SUM(G15:H15) -> 0
A16: Matériel, mobilier et actifs biologiques | I16: =SUM(B16:F16)-SUM(G16:H16) -> 0
A17: Matériel de transport | I17: =SUM(B17:F17)-SUM(G17:H17) -> 0
A18: SOUS TOTAL : IMMOBILISATIONS CORPORELLES | C18: =SUM(C13:C17) -> 0 | I18: =SUM(I13:I17) -> 0
A20: TOTAL GENERAL | C20: =SUM(C9:C11)+SUM(C13:C17) -> 0 | D20: =SUM(D9:D11)+SUM(D13:D17) -> 0 | F20: =SUM(F9:F11)+SUM(F13:F17) -> 0 | G20: =SUM(G9:G11)+SUM(G13:G17) -> 0 | H20: =SUM(H9:H11)+SUM(H13:H17) -> 0 | I20: =SUM(I9:I11)+SUM(I13:I17) -> 0
A21: [1] I : crédit-bail immobilier; M : crédit-bail mobilier; A : autres contrats (dédoubler le poste si montants significatifs)
A22: Commentaire :
A23: · Indiquer la nature du bien, le nom du bailleur et la durée du bail

Sheet Note 3C
A1: NOTE 3C : IMMOBILISATIONS (AMORTISSEMENTS)
A3: Désignation entité : | B3: ='Fiche de renseignement R1'!$J$4 -> 0 | D3: Excercice clos le : | E3: =+'Note 1'!E3 -> 0
A4: Numéro d'identification : | B4: =+'Note 1'!B4 -> 0 | D4: Durée en mois : | E4: =+'Note 1'!E4 -> 12
A7: SITUATIONS ET MOUVEMENTS | B7: A | C7: B | D7: C | E7: D = A +B - C
B8: Amortissements cumulés à l'ouverture de l'exercice | C8: Augmentations : Dotations de l'exercice | D8: Diminutions : Amortissements relatifs aux éléments sortis de l'actif | E8: Cumul des amortissements à la clôture de l'exercice
A10: Frais de développement et de prospection | E10: =+B10+C10-D10 -> 0
A11: Brevets, licences, logiciels et droits similaires | B11: =+SUMIF('BAL N'!K:K,"=2811",'BAL N'!D:D) -> 0 | C11: =+SUMIF('BAL N'!K:K,"=2811",'BAL N'!F:F) -> 0 | D11: =+SUMIF('BAL N'!K:K,"=2811",'BAL N'!E:E) -> 0 | E11: =+B11+C11-D11 -> 0
A12: Fonds commercial et droit au bail | B12: =+SUMIF('BAL N'!K:K,"=2813",'BAL N'!D:D) -> 0 | C12: =+SUMIF('BAL N'!K:K,"=2813",'BAL N'!F:F) -> 0 | D12: =+SUMIF('BAL N'!K:K,"=2813",'BAL N'!E:E) -> 0 | E12: =+B12+C12-D12 -> 0
A13: Autres immobilisations incorporelles | B13: =+SUMIF('BAL N'!K:K,"=2815",'BAL N'!D:D) -> 0 | C13: =+SUMIF('BAL N'!K:K,"=2815",'BAL N'!F:F) -> 0 | D13: =+SUMIF('BAL N'!K:K,"=2815",'BAL N'!E:E) -> 0 | E13: =+B13+C13-D13 -> 0
A14: SOUS TOTAL : IMMOBILISATIONS INCORPORELLES | B14: =+SUMIF('BAL N'!K:K,"=2814",'BAL N'!D:D)+SUMIF('BAL N'!K:K,"=2816",'BAL N'!D:D)+SUMIF('BAL N'!K:K,"=2818",'BAL N'!D:D)+SUMIF('BAL N'!K:K,"=2817",'BAL N'!D:D) -> 0 | C14: =+SUMIF('BAL N'!K:K,"=2817",'BAL N'!F:F)+SUMIF('BAL N'!K:K,"=2814",'BAL N'!F:F)+SUMIF('BAL N'!K:K,"=2816",'BAL N'!F:F)+SUMIF('BAL N'!K:K,"=2817",'BAL N'!F:F)+SUMIF('BAL N'!K:K,"=2818",'BAL N'!F:F) -> 0 | D14: =+SUMIF('BAL N'!K:K,"=2814",'BAL N'!E:E)+SUMIF('BAL N'!K:K,"=2816",'BAL N'!E:E)++SUMIF('BAL N'!K:K,"=2817",'BAL N'!E:E)+SUMIF('BAL N'!K:K,"=2818",'BAL N'!E:E) -> 0 | E14: =+B14+C14-D14 -> 0
A15: Terrains hors immeuble de placement | B15: =+SUMIF('BAL N'!I:I,"=22",'BAL N'!G:G)-SUMIF('BAL N'!J:J,"=228",'BAL N'!G:G) -> 147669000 | C15: =+SUMIF('BAL N'!J:J,"=282",'BAL N'!F:F)-SUMIF('BAL N'!K:K,"=2828",'BAL N'!F:F) -> 79950 | D15: =+SUMIF('BAL N'!J:J,"=282",'BAL N'!E:E)-SUMIF('BAL N'!K:K,"=2828",'BAL N'!E:E) -> 0 | E15: =+B15+C15-D15 -> 147748950
A16: Terrains immeuble de placement | B16: =+SUMIF('BAL N'!J:J,"=228",'BAL N'!G:G) -> 0 | C16: =+SUMIF('BAL N'!K:K,"=2828",'BAL N'!F:F) -> 0 | D16: =+SUMIF('BAL N'!K:K,"=2828",'BAL N'!E:E) -> 0 | E16: =+B16+C16-D16 -> 0
A17: Bâtiments hors immeuble de placement | B17: =+SUMIF('BAL N'!J:J,"=283",'BAL N'!D:D)-SUMIF('BAL N'!L:L,"=28315",'BAL N'!D:D)-SUMIF('BAL N'!L:L,"=28325",'BAL N'!D:D) -> 370188122 | C17: =+SUMIF('BAL N'!J:J,"=283",'BAL N'!F:F)-SUMIF('BAL N'!L:L,"=28315",'BAL N'!F:F)-SUMIF('BAL N'!L:L,"=28325",'BAL N'!F:F) -> 86112169 | D17: =+SUMIF('BAL N'!J:J,"=283",'BAL N'!E:E)-SUMIF('BAL N'!L:L,"=28315",'BAL N'!E:E)-SUMIF('BAL N'!L:L,"=28325",'BAL N'!E:E) -> 0 | E17: =+B17+C17-D17 -> 456300291
A18: Bâtiments immeuble de placement | B18: =+SUMIF('BAL N'!L:L,"=28315",'BAL N'!D:D)+SUMIF('BAL N'!L:L,"=28325",'BAL N'!D:D) -> 0 | C18: =+SUMIF('BAL N'!L:L,"=28315",'BAL N'!F:F)+SUMIF('BAL N'!L:L,"=28325",'BAL N'!F:F) -> 0 | D18: =+SUMIF('BAL N'!L:L,"=28315",'BAL N'!E:E)+SUMIF('BAL N'!L:L,"=28325",'BAL N'!E:E) -> 0 | E18: =+B18+C18-D18 -> 0
A19: Aménagements, agencements et installations | B19: =+SUMIF('BAL N'!K:K,"=2834",'BAL N'!D:D)+SUMIF('BAL N'!K:K,"=2835",'BAL N'!D:D) -> 151925111 | C19: =+SUMIF('BAL N'!K:K,"=2834",'BAL N'!F:F)+SUMIF('BAL N'!K:K,"=2835",'BAL N'!F:F) -> 29329403 | D19: =+SUMIF('BAL N'!K:K,"=2834",'BAL N'!E:E)+SUMIF('BAL N'!K:K,"=2835",'BAL N'!E:E) -> 0 | E19: =+B19+C19-D19 -> 181254514
A20: Matériel, mobilier et actifs biologiques | B20: =+SUMIF('BAL N'!J:J,"=284",'BAL N'!D:D)-SUMIF('BAL N'!K:K,"=2845",'BAL N'!D:D) -> 249391680 | C20: =+SUMIF('BAL N'!J:J,"=284",'BAL N'!F:F)-SUMIF('BAL N'!K:K,"=2845",'BAL N'!F:F) -> 69042080 | D20: =+SUMIF('BAL N'!J:J,"=284",'BAL N'!E:E)-SUMIF('BAL N'!K:K,"=2845",'BAL N'!E:E) -> 0 | E20: =+B20+C20-D20 -> 318433760
A21: Matériel de transport | B21: =+SUMIF('BAL N'!K:K,"=2845",'BAL N'!D:D) -> 46129364 | C21: =+SUMIF('BAL N'!K:K,"=2845",'BAL N'!F:F) -> 12293776 | D21: =+SUMIF('BAL N'!K:K,"=2845",'BAL N'!E:E) -> 0 | E21: =+B21+C21-D21 -> 58423140
A22: SOUS TOTAL : IMMOBILISATIONS CORPORELLES | B22: =SUM(B15:B21) -> 965303277 | C22: =SUM(C15:C21) -> 196857378 | D22: =SUM(D15:D21) -> 0 | E22: =+B22+C22-D22 -> 1162160655
A24: TOTAL GENERAL | B24: =SUM(B14,B22) -> 965303277 | C24: =SUM(C14,C22) -> 196857378 | D24: =SUM(D14,D22) -> 0 | E24: =SUM(B24:D24) -> 1162160655
A25: Commentaire :
A26: · Indiquer :
A27: - les modes d'amortissements utilisés : amortissement linéaire
A28: - la durée de vie ou les taux d'amortissements utilisés ;

Sheet Note 3D
A1: NOTE 3D : IMMOBILISATIONS (PLUS-VALUES ET MOINS VALUES DE CESSION)
A3: Désignation entité : | B3: ='Fiche de renseignement R1'!$J$4 -> 0 | D3: Excercice clos le : | E3: =+'Note 1'!E3 -> 0
A4: Numéro d'identification : | B4: =+'Note 1'!B4 -> 0 | D4: Durée en mois : | E4: =+'Note 1'!E4 -> 12
B7: MONTANT BRUT | C7: AMORTISSEMENTS | D7: VALEUR COMPTABLE NETTE | E7: PRIX DE CESSION | F7: PLUS VALUE OU MOINS VALUE
C8: PRATIQUES
B9: A | C9: B | D9: C = A - B | E9: D | F9: E = D - C
A10: Frais de développement et de prospection
A11: Brevets, licences, logiciels et droits similaires | D11: =+B11-C11 -> 0 | F11: =+E11-D11 -> 0
A12: Fonds commercial et droit au bail | D12: =+B12-C12 -> 0 | F12: =+E12-D12 -> 0
A13: Autres immobilisations incorporelles | D13: =+B13-C13 -> 0 | F13: =+E13-D13 -> 0
A14: SOUS TOTAL : IMMOBILISATIONS INCORPORELLES | B14: =SUM(B11:B13) -> 0 | C14: =SUM(C11:C13) -> 0 | D14: =+B14-C14 -> 0 | E14: =SUM(E11:E13) -> 0 | F14: =+E14-D14 -> 0
A15: Terrains
A16: Bâtiments
A17: Aménagements, agencements et installations
A18: Matériel, mobilier et actifs biologiques
A19: Matériel de transport
A20: SOUS TOTAL : IMMOBILISATIONS CORPORELLES | B20: =SUM(B15:B19) -> 0 | C20: =SUM(C21:C22) -> 0 | D20: =+B20-C20 -> 0 | E20: =SUM(E21:E22) -> 0 | F20: =+E20-D20 -> 0
A21: Titres de participation | D21: =+B21-C21 -> 0 | F21: =+E21-D21 -> 0
A22: Autres immobilisations financières | D22: =+B22-C22 -> 0 | F22: =+E22-D22 -> 0
A23: SOUS TOTAL : IMMOBILISATIONS FINANCIERES | B23: =SUM(B21:B22) -> 0 | C23: =SUM(C21:C22) -> 0 | D23: =+B23-C23 -> 0 | F23: =+E23-D23 -> 0
A25: TOTAL GENERAL | B25: =+B14+B20+B23 -> 0 | C25: =+C14+C20+C23 -> 0 | D25: =+B25-C25 -> 0 | F25: =+E25-D25 -> 0
A26: Commentaire :
A27: · Mentionner la justification de la cession ainsi que la date d'acquisition et la date de sortie

Sheet Note 3E
A1: NOTE 3E : INFORMATIONS SUR LES REEVALUATIONS EFFECTUEES PAR L'ENTITE
A3: Désignation entité : | B3: ='Fiche de renseignement R1'!$J$4 -> 0 | C3: Excercice clos le : | D3: =+'Note 1'!E3 -> 0
A4: Numéro d'identification : | B4: =+'Note 1'!B4 -> 0 | C4: Durée en mois : | D4: =+'Note 1'!E4 -> 12
A7: Nature et date des réévaluations :
A13: Eléments réévalués par postes du bilan | B13: Montants coûts historiques | C13: Amortissements supplémentaires
A22: Méthode de réévaluation utilisée :
A24: Traitement fiscal de l'écart de réévaluation
A25: et des amortissements supplémentaires :
A27: Montant de l'écart incorporé au capital :

Sheet Note 4
A1: NOTE 4 : IMMOBILISATIONS FINANCIERES
A3: Désignation entité : | B3: ='Fiche de renseignement R1'!$J$4 -> 0 | E3: Excercice clos le : | F3: =+'Note 1'!E3 -> 0
A4: Numéro d'identification : | B4: =+'Note 1'!B4 -> 0 | E4: Durée en mois : | F4: =+'Note 1'!E4 -> 12
A7: SITUATIONS ET MOUVEMENTS | B7: =IFERROR(YEAR('Fiche de renseignement R1'!V10),"Annee N") -> 1900 | C7: =IFERROR(YEAR('Fiche de renseignement R1'!Q20),"Annee N-1") -> 2020 | D7: Variation en % | E7: Créances à un an au plus | F7: Créances à plus d'un an et à deux ans au plus | G7: Créances à plus de deux ans
A9: Titres de participation | B9: =+SUMIF('BAL N'!I:I,"=26",'BAL N'!G:G) -> 0 | C9: =+SUMIF('BAL N'!I:I,"=26",'BAL N'!C:C) -> 0 | D9: =IFERROR((B9-C9)/B9,0) -> 0
A10: Prêts et créances | B10: =+SUMIF('BAL N'!J:J,"=271",'BAL N'!G:G) -> 0 | C10: =+SUMIF('BAL N'!I:I,"=271",'BAL N'!C:C) -> 0 | D10: =IFERROR((B10-C10)/B10,0) -> 0
A11: Prêt au personnel | B11: =+SUMIF('BAL N'!J:J,"=272",'BAL N'!G:G) -> 0 | C11: =+SUMIF('BAL N'!I:I,"=272",'BAL N'!C:C) -> 0 | D11: =IFERROR((B11-C11)/B11,0) -> 0
A12: Créances sur l'Etat | B12: =+SUMIF('BAL N'!J:J,"=273",'BAL N'!G:G) -> 0 | C12: =+SUMIF('BAL N'!I:I,"=273",'BAL N'!C:C) -> 0 | D12: =IFERROR((B12-C12)/B12,0) -> 0
A13: Titres immobilisés | B13: =+SUMIF('BAL N'!J:J,"=274",'BAL N'!G:G) -> 0 | C13: =+SUMIF('BAL N'!I:I,"=274",'BAL N'!C:C) -> 0 | D13: =IFERROR((B13-C13)/B13,0) -> 0
A14: Dépôts et cautionnements | B14: =+SUMIF('BAL N'!J:J,"=275",'BAL N'!G:G) -> 12180480 | C14: =+SUMIF('BAL N'!J:J,"=275",'BAL N'!C:C) -> 12180480 | D14: =IFERROR((B14-C14)/B14,0) -> 0
A15: Intérêts courus | B15: =+SUMIF('BAL N'!J:J,"=276",'BAL N'!G:G) -> 0 | C15: =+SUMIF('BAL N'!J:J,"=276",'BAL N'!C:C) -> 0 | D15: =IFERROR((B15-C15)/B15,0) -> 0
A16: TOTAL BRUT | B16: =SUM(B9:B15) -> 12180480 | C16: =SUM(C9:C15) -> 12180480 | D16: =IFERROR((B16-C16)/B16,0) -> 0
A17: Dépréciations titres de participation | B17: =+SUMIF('BAL N'!J:J,"=296",'BAL N'!H:H) -> 0 | C17: =+SUMIF('BAL N'!J:J,"=296",'BAL N'!D:D) -> 0 | D17: =IFERROR((B17-C17)/B17,0) -> 0
A18: Dépréciations autres immobilisations | B18: =+SUMIF('BAL N'!J:J,"=297",'BAL N'!H:H) -> 0 | C18: =+SUMIF('BAL N'!J:J,"=297",'BAL N'!D:D) -> 0 | D18: =IFERROR((B18-C18)/B18,0) -> 0
A19: TOTAL NET DE DEPRECIATION | B19: =SUM(B17:B18) -> 0 | C19: =SUM(C17:C18) -> 0 | D19: =IFERROR((B19-C19)/B19,0) -> 0
A21: Liste des filiales et participations :
A23: Dénomination sociale | B23: Localisation (ville/pays) | C23: Valeur d'acquisition | E23: % détenu | F23: Montant des capitaux propres filiale | G23: Résultat dernier exercice filiale
A32: Commentaire :
A33: · Justifier toute variation significative
A34: · Commenter toutes les créances anciennes
A35: · Pour les créances relatives à la concession, faire un descriptif de l'accord
A36: · Indiquer :
A37: - la nature de la créance ;
A38: - la durée de la concession ;
A39: - l'échéance ;
A40: · Indiquer le nombre et la date d'acquisition des actions ou parts propres
A41: · Dépréciation : indiquer les évènements et les circonstances qui ont motivé
A42: la dépréciation ou la reprise

Sheet Note 5
A1: NOTE 5 : ACTIF CIRCULANT HAO
A3: Désignation entité : | B3: ='Fiche de renseignement R1'!$J$4 -> 0 | E3: Excercice clos le : | F3: =+'Note 1'!E3 -> 0
A4: Numéro d'identification : | B4: =+'Note 1'!B4 -> 0 | E4: Durée en mois : | F4: =+'Note 1'!E4 -> 12
A6: ACTIF CIRCULANT HAO | P6: ACTIF CIRCULANT HAO | X6: ACTIF CIRCULANT HAO | AF6: ACTIF CIRCULANT HAO | AN6: ACTIF CIRCULANT HAO | AV6: ACTIF CIRCULANT HAO | BD6: ACTIF CIRCULANT HAO | BL6: ACTIF CIRCULANT HAO | BT6: ACTIF CIRCULANT HAO | CB6: ACTIF CIRCULANT HAO | CJ6: ACTIF CIRCULANT HAO | CR6: ACTIF CIRCULANT HAO | CZ6: ACTIF CIRCULANT HAO | DH6: ACTIF CIRCULANT HAO | DP6: ACTIF CIRCULANT HAO | DX6: ACTIF CIRCULANT HAO | EF6: ACTIF CIRCULANT HAO | EN6: ACTIF CIRCULANT HAO | EV6: ACTIF CIRCULANT HAO | FD6: ACTIF CIRCULANT HAO | FL6: ACTIF CIRCULANT HAO | FT6: ACTIF CIRCULANT HAO | GB6: ACTIF CIRCULANT HAO | GJ6: ACTIF CIRCULANT HAO | GR6: ACTIF CIRCULANT HAO | GZ6: ACTIF CIRCULANT HAO | HH6: ACTIF CIRCULANT HAO | HP6: ACTIF CIRCULANT HAO | HX6: ACTIF CIRCULANT HAO | IF6: ACTIF CIRCULANT HAO | IN6: ACTIF CIRCULANT HAO | IV6: ACTIF CIRCULANT HAO | JD6: ACTIF CIRCULANT HAO | JL6: ACTIF CIRCULANT HAO | JT6: ACTIF CIRCULANT HAO | KB6: ACTIF CIRCULANT HAO | KJ6: ACTIF CIRCULANT HAO | KR6: ACTIF CIRCULANT HAO | KZ6: ACTIF CIRCULANT HAO | LH6: ACTIF CIRCULANT HAO | LP6: ACTIF CIRCULANT HAO | LX6: ACTIF CIRCULANT HAO | MF6: ACTIF CIRCULANT HAO | MN6: ACTIF CIRCULANT HAO | MV6: ACTIF CIRCULANT HAO | ND6: ACTIF CIRCULANT HAO | NL6: ACTIF CIRCULANT HAO | NT6: ACTIF CIRCULANT HAO | OB6: ACTIF CIRCULANT HAO | OJ6: ACTIF CIRCULANT HAO | OR6: ACTIF CIRCULANT HAO | OZ6: ACTIF CIRCULANT HAO | PH6: ACTIF CIRCULANT HAO | PP6: ACTIF CIRCULANT HAO | PX6: ACTIF CIRCULANT HAO | QF6: ACTIF CIRCULANT HAO | QN6: ACTIF CIRCULANT HAO | QV6: ACTIF CIRCULANT HAO | RD6: ACTIF CIRCULANT HAO | RL6: ACTIF CIRCULANT HAO | RT6: ACTIF CIRCULANT HAO | SB6: ACTIF CIRCULANT HAO | SJ6: ACTIF CIRCULANT HAO | SR6: ACTIF CIRCULANT HAO | SZ6: ACTIF CIRCULANT HAO | TH6: ACTIF CIRCULANT HAO | TP6: ACTIF CIRCULANT HAO | TX6: ACTIF CIRCULANT HAO | UF6: ACTIF CIRCULANT HAO | UN6: ACTIF CIRCULANT HAO | UV6: ACTIF CIRCULANT HAO | VD6: ACTIF CIRCULANT HAO | VL6: ACTIF CIRCULANT HAO | VT6: ACTIF CIRCULANT HAO | WB6: ACTIF CIRCULANT HAO | WJ6: ACTIF CIRCULANT HAO | WR6: ACTIF CIRCULANT HAO | WZ6: ACTIF CIRCULANT HAO | XH6: ACTIF CIRCULANT HAO | XP6: ACTIF CIRCULANT HAO | XX6: ACTIF CIRCULANT HAO | YF6: ACTIF CIRCULANT HAO | YN6: ACTIF CIRCULANT HAO | YV6: ACTIF CIRCULANT HAO | ZD6: ACTIF CIRCULANT HAO | ZL6: ACTIF CIRCULANT HAO | ZT6: ACTIF CIRCULANT HAO | AAB6: ACTIF CIRCULANT HAO | AAJ6: ACTIF CIRCULANT HAO | AAR6: ACTIF CIRCULANT HAO | AAZ6: ACTIF CIRCULANT HAO | ABH6: ACTIF CIRCULANT HAO | ABP6: ACTIF CIRCULANT HAO | ABX6: ACTIF CIRCULANT HAO | ACF6: ACTIF CIRCULANT HAO | ACN6: ACTIF CIRCULANT HAO | ACV6: ACTIF CIRCULANT HAO | ADD6: ACTIF CIRCULANT HAO | ADL6: ACTIF CIRCULANT HAO | ADT6: ACTIF CIRCULANT HAO | AEB6: ACTIF CIRCULANT HAO | AEJ6: ACTIF CIRCULANT HAO | AER6: ACTIF CIRCULANT HAO | AEZ6: ACTIF CIRCULANT HAO | AFH6: ACTIF CIRCULANT HAO | AFP6: ACTIF CIRCULANT HAO | AFX6: ACTIF CIRCULANT HAO | AGF6: ACTIF CIRCULANT HAO | AGN6: ACTIF CIRCULANT HAO | AGV6: ACTIF CIRCULANT HAO | AHD6: ACTIF CIRCULANT HAO | AHL6: ACTIF CIRCULANT HAO | AHT6: ACTIF CIRCULANT HAO | AIB6: ACTIF CIRCULANT HAO | AIJ6: ACTIF CIRCULANT HAO | AIR6: ACTIF CIRCULANT HAO | AIZ6: ACTIF CIRCULANT HAO | AJH6: ACTIF CIRCULANT HAO | AJP6: ACTIF CIRCULANT HAO | AJX6: ACTIF CIRCULANT HAO | AKF6: ACTIF CIRCULANT HAO | AKN6: ACTIF CIRCULANT HAO | AKV6: ACTIF CIRCULANT HAO | ALD6: ACTIF CIRCULANT HAO | ALL6: ACTIF CIRCULANT HAO | ALT6: ACTIF CIRCULANT HAO | AMB6: ACTIF CIRCULANT HAO | AMJ6: ACTIF CIRCULANT HAO | AMR6: ACTIF CIRCULANT HAO | AMZ6: ACTIF CIRCULANT HAO | ANH6: ACTIF CIRCULANT HAO | ANP6: ACTIF CIRCULANT HAO | ANX6: ACTIF CIRCULANT HAO | AOF6: ACTIF CIRCULANT HAO | AON6: ACTIF CIRCULANT HAO | AOV6: ACTIF CIRCULANT HAO | APD6: ACTIF CIRCULANT HAO | APL6: ACTIF CIRCULANT HAO | APT6: ACTIF CIRCULANT HAO | AQB6: ACTIF CIRCULANT HAO | AQJ6: ACTIF CIRCULANT HAO | AQR6: ACTIF CIRCULANT HAO | AQZ6: ACTIF CIRCULANT HAO | ARH6: ACTIF CIRCULANT HAO | ARP6: ACTIF CIRCULANT HAO | ARX6: ACTIF CIRCULANT HAO | ASF6: ACTIF CIRCULANT HAO | ASN6: ACTIF CIRCULANT HAO | ASV6: ACTIF CIRCULANT HAO | ATD6: ACTIF CIRCULANT HAO | ATL6: ACTIF CIRCULANT HAO | ATT6: ACTIF CIRCULANT HAO | AUB6: ACTIF CIRCULANT HAO | AUJ6: ACTIF CIRCULANT HAO | AUR6: ACTIF CIRCULANT HAO | AUZ6: ACTIF CIRCULANT HAO | AVH6: ACTIF CIRCULANT HAO | AVP6: ACTIF CIRCULANT HAO | AVX6: ACTIF CIRCULANT HAO | AWF6: ACTIF CIRCULANT HAO | AWN6: ACTIF CIRCULANT HAO | AWV6: ACTIF CIRCULANT HAO | AXD6: ACTIF CIRCULANT HAO | AXL6: ACTIF CIRCULANT HAO | AXT6: ACTIF CIRCULANT HAO | AYB6: ACTIF CIRCULANT HAO | AYJ6: ACTIF CIRCULANT HAO | AYR6: ACTIF CIRCULANT HAO | AYZ6: ACTIF CIRCULANT HAO | AZH6: ACTIF CIRCULANT HAO | AZP6: ACTIF CIRCULANT HAO | AZX6: ACTIF CIRCULANT HAO | BAF6: ACTIF CIRCULANT HAO | BAN6: ACTIF CIRCULANT HAO | BAV6: ACTIF CIRCULANT HAO | BBD6: ACTIF CIRCULANT HAO | BBL6: ACTIF CIRCULANT HAO | BBT6: ACTIF CIRCULANT HAO | BCB6: ACTIF CIRCULANT HAO | BCJ6: ACTIF CIRCULANT HAO | BCR6: ACTIF CIRCULANT HAO | BCZ6: ACTIF CIRCULANT HAO | BDH6: ACTIF CIRCULANT HAO | BDP6: ACTIF CIRCULANT HAO | BDX6: ACTIF CIRCULANT HAO | BEF6: ACTIF CIRCULANT HAO | BEN6: ACTIF CIRCULANT HAO | BEV6: ACTIF CIRCULANT HAO | BFD6: ACTIF CIRCULANT HAO | BFL6: ACTIF CIRCULANT HAO | BFT6: ACTIF CIRCULANT HAO | BGB6: ACTIF CIRCULANT HAO | BGJ6: ACTIF CIRCULANT HAO | BGR6: ACTIF CIRCULANT HAO | BGZ6: ACTIF CIRCULANT HAO | BHH6: ACTIF CIRCULANT HAO | BHP6: ACTIF CIRCULANT HAO | BHX6: ACTIF CIRCULANT HAO | BIF6: ACTIF CIRCULANT HAO | BIN6: ACTIF CIRCULANT HAO | BIV6: ACTIF CIRCULANT HAO | BJD6: ACTIF CIRCULANT HAO | BJL6: ACTIF CIRCULANT HAO | BJT6: ACTIF CIRCULANT HAO | BKB6: ACTIF CIRCULANT HAO | BKJ6: ACTIF CIRCULANT HAO | BKR6: ACTIF CIRCULANT HAO | BKZ6: ACTIF CIRCULANT HAO | BLH6: ACTIF CIRCULANT HAO | BLP6: ACTIF CIRCULANT HAO | BLX6: ACTIF CIRCULANT HAO | BMF6: ACTIF CIRCULANT HAO | BMN6: ACTIF CIRCULANT HAO | BMV6: ACTIF CIRCULANT HAO | BND6: ACTIF CIRCULANT HAO | BNL6: ACTIF CIRCULANT HAO | BNT6: ACTIF CIRCULANT HAO | BOB6: ACTIF CIRCULANT HAO | BOJ6: ACTIF CIRCULANT HAO | BOR6: ACTIF CIRCULANT HAO | BOZ6: ACTIF CIRCULANT HAO | BPH6: ACTIF CIRCULANT HAO | BPP6: ACTIF CIRCULANT HAO | BPX6: ACTIF CIRCULANT HAO | BQF6: ACTIF CIRCULANT HAO | BQN6: ACTIF CIRCULANT HAO | BQV6: ACTIF CIRCULANT HAO | BRD6: ACTIF CIRCULANT HAO | BRL6: ACTIF CIRCULANT HAO | BRT6: ACTIF CIRCULANT HAO | BSB6: ACTIF CIRCULANT HAO | BSJ6: ACTIF CIRCULANT HAO | BSR6: ACTIF CIRCULANT HAO | BSZ6: ACTIF CIRCULANT HAO | BTH6: ACTIF CIRCULANT HAO | BTP6: ACTIF CIRCULANT HAO | BTX6: ACTIF CIRCULANT HAO | BUF6: ACTIF CIRCULANT HAO | BUN6: ACTIF CIRCULANT HAO | BUV6: ACTIF CIRCULANT HAO | BVD6: ACTIF CIRCULANT HAO | BVL6: ACTIF CIRCULANT HAO | BVT6: ACTIF CIRCULANT HAO | BWB6: ACTIF CIRCULANT HAO | BWJ6: ACTIF CIRCULANT HAO | BWR6: ACTIF CIRCULANT HAO | BWZ6: ACTIF CIRCULANT HAO | BXH6: ACTIF CIRCULANT HAO | BXP6: ACTIF CIRCULANT HAO | BXX6: ACTIF CIRCULANT HAO | BYF6: ACTIF CIRCULANT HAO | BYN6: ACTIF CIRCULANT HAO | BYV6: ACTIF CIRCULANT HAO | BZD6: ACTIF CIRCULANT HAO | BZL6: ACTIF CIRCULANT HAO | BZT6: ACTIF CIRCULANT HAO | CAB6: ACTIF CIRCULANT HAO | CAJ6: ACTIF CIRCULANT HAO | CAR6: ACTIF CIRCULANT HAO | CAZ6: ACTIF CIRCULANT HAO | CBH6: ACTIF CIRCULANT HAO | CBP6: ACTIF CIRCULANT HAO | CBX6: ACTIF CIRCULANT HAO | CCF6: ACTIF CIRCULANT HAO | CCN6: ACTIF CIRCULANT HAO | CCV6: ACTIF CIRCULANT HAO | CDD6: ACTIF CIRCULANT HAO | CDL6: ACTIF CIRCULANT HAO | CDT6: ACTIF CIRCULANT HAO | CEB6: ACTIF CIRCULANT HAO | CEJ6: ACTIF CIRCULANT HAO | CER6: ACTIF CIRCULANT HAO | CEZ6: ACTIF CIRCULANT HAO | CFH6: ACTIF CIRCULANT HAO | CFP6: ACTIF CIRCULANT HAO | CFX6: ACTIF CIRCULANT HAO | CGF6: ACTIF CIRCULANT HAO | CGN6: ACTIF CIRCULANT HAO | CGV6: ACTIF CIRCULANT HAO | CHD6: ACTIF CIRCULANT HAO | CHL6: ACTIF CIRCULANT HAO | CHT6: ACTIF CIRCULANT HAO | CIB6: ACTIF CIRCULANT HAO | CIJ6: ACTIF CIRCULANT HAO | CIR6: ACTIF CIRCULANT HAO | CIZ6: ACTIF CIRCULANT HAO | CJH6: ACTIF CIRCULANT HAO | CJP6: ACTIF CIRCULANT HAO | CJX6: ACTIF CIRCULANT HAO | CKF6: ACTIF CIRCULANT HAO | CKN6: ACTIF CIRCULANT HAO | CKV6: ACTIF CIRCULANT HAO | CLD6: ACTIF CIRCULANT HAO | CLL6: ACTIF CIRCULANT HAO | CLT6: ACTIF CIRCULANT HAO | CMB6: ACTIF CIRCULANT HAO | CMJ6: ACTIF CIRCULANT HAO | CMR6: ACTIF CIRCULANT HAO | CMZ6: ACTIF CIRCULANT HAO | CNH6: ACTIF CIRCULANT HAO | CNP6: ACTIF CIRCULANT HAO | CNX6: ACTIF CIRCULANT HAO | COF6: ACTIF CIRCULANT HAO | CON6: ACTIF CIRCULANT HAO | COV6: ACTIF CIRCULANT HAO | CPD6: ACTIF CIRCULANT HAO | CPL6: ACTIF CIRCULANT HAO | CPT6: ACTIF CIRCULANT HAO | CQB6: ACTIF CIRCULANT HAO | CQJ6: ACTIF CIRCULANT HAO | CQR6: ACTIF CIRCULANT HAO | CQZ6: ACTIF CIRCULANT HAO | CRH6: ACTIF CIRCULANT HAO | CRP6: ACTIF CIRCULANT HAO | CRX6: ACTIF CIRCULANT HAO | CSF6: ACTIF CIRCULANT HAO | CSN6: ACTIF CIRCULANT HAO | CSV6: ACTIF CIRCULANT HAO | CTD6: ACTIF CIRCULANT HAO | CTL6: ACTIF CIRCULANT HAO | CTT6: ACTIF CIRCULANT HAO | CUB6: ACTIF CIRCULANT HAO | CUJ6: ACTIF CIRCULANT HAO | CUR6: ACTIF CIRCULANT HAO | CUZ6: ACTIF CIRCULANT HAO | CVH6: ACTIF CIRCULANT HAO | CVP6: ACTIF CIRCULANT HAO | CVX6: ACTIF CIRCULANT HAO | CWF6: ACTIF CIRCULANT HAO | CWN6: ACTIF CIRCULANT HAO | CWV6: ACTIF CIRCULANT HAO | CXD6: ACTIF CIRCULANT HAO | CXL6: ACTIF CIRCULANT HAO | CXT6: ACTIF CIRCULANT HAO | CYB6: ACTIF CIRCULANT HAO | CYJ6: ACTIF CIRCULANT HAO | CYR6: ACTIF CIRCULANT HAO | CYZ6: ACTIF CIRCULANT HAO | CZH6: ACTIF CIRCULANT HAO | CZP6: ACTIF CIRCULANT HAO | CZX6: ACTIF CIRCULANT HAO | DAF6: ACTIF CIRCULANT HAO | DAN6: ACTIF CIRCULANT HAO | DAV6: ACTIF CIRCULANT HAO | DBD6: ACTIF CIRCULANT HAO | DBL6: ACTIF CIRCULANT HAO | DBT6: ACTIF CIRCULANT HAO | DCB6: ACTIF CIRCULANT HAO | DCJ6: ACTIF CIRCULANT HAO | DCR6: ACTIF CIRCULANT HAO | DCZ6: ACTIF CIRCULANT HAO | DDH6: ACTIF CIRCULANT HAO | DDP6: ACTIF CIRCULANT HAO | DDX6: ACTIF CIRCULANT HAO | DEF6: ACTIF CIRCULANT HAO | DEN6: ACTIF CIRCULANT HAO | DEV6: ACTIF CIRCULANT HAO | DFD6: ACTIF CIRCULANT HAO | DFL6: ACTIF CIRCULANT HAO | DFT6: ACTIF CIRCULANT HAO | DGB6: ACTIF CIRCULANT HAO | DGJ6: ACTIF CIRCULANT HAO | DGR6: ACTIF CIRCULANT HAO | DGZ6: ACTIF CIRCULANT HAO | DHH6: ACTIF CIRCULANT HAO | DHP6: ACTIF CIRCULANT HAO | DHX6: ACTIF CIRCULANT HAO | DIF6: ACTIF CIRCULANT HAO | DIN6: ACTIF CIRCULANT HAO | DIV6: ACTIF CIRCULANT HAO | DJD6: ACTIF CIRCULANT HAO | DJL6: ACTIF CIRCULANT HAO | DJT6: ACTIF CIRCULANT HAO | DKB6: ACTIF CIRCULANT HAO | DKJ6: ACTIF CIRCULANT HAO | DKR6: ACTIF CIRCULANT HAO | DKZ6: ACTIF CIRCULANT HAO | DLH6: ACTIF CIRCULANT HAO | DLP6: ACTIF CIRCULANT HAO | DLX6: ACTIF CIRCULANT HAO | DMF6: ACTIF CIRCULANT HAO | DMN6: ACTIF CIRCULANT HAO | DMV6: ACTIF CIRCULANT HAO | DND6: ACTIF CIRCULANT HAO | DNL6: ACTIF CIRCULANT HAO | DNT6: ACTIF CIRCULANT HAO | DOB6: ACTIF CIRCULANT HAO | DOJ6: ACTIF CIRCULANT HAO | DOR6: ACTIF CIRCULANT HAO | DOZ6: ACTIF CIRCULANT HAO | DPH6: ACTIF CIRCULANT HAO | DPP6: ACTIF CIRCULANT HAO | DPX6: ACTIF CIRCULANT HAO | DQF6: ACTIF CIRCULANT HAO | DQN6: ACTIF CIRCULANT HAO | DQV6: ACTIF CIRCULANT HAO | DRD6: ACTIF CIRCULANT HAO | DRL6: ACTIF CIRCULANT HAO | DRT6: ACTIF CIRCULANT HAO | DSB6: ACTIF CIRCULANT HAO | DSJ6: ACTIF CIRCULANT HAO | DSR6: ACTIF CIRCULANT HAO | DSZ6: ACTIF CIRCULANT HAO | DTH6: ACTIF CIRCULANT HAO | DTP6: ACTIF CIRCULANT HAO | DTX6: ACTIF CIRCULANT HAO | DUF6: ACTIF CIRCULANT HAO | DUN6: ACTIF CIRCULANT HAO | DUV6: ACTIF CIRCULANT HAO | DVD6: ACTIF CIRCULANT HAO | DVL6: ACTIF CIRCULANT HAO | DVT6: ACTIF CIRCULANT HAO | DWB6: ACTIF CIRCULANT HAO | DWJ6: ACTIF CIRCULANT HAO | DWR6: ACTIF CIRCULANT HAO | DWZ6: ACTIF CIRCULANT HAO | DXH6: ACTIF CIRCULANT HAO | DXP6: ACTIF CIRCULANT HAO | DXX6: ACTIF CIRCULANT HAO | DYF6: ACTIF CIRCULANT HAO | DYN6: ACTIF CIRCULANT HAO | DYV6: ACTIF CIRCULANT HAO | DZD6: ACTIF CIRCULANT HAO | DZL6: ACTIF CIRCULANT HAO | DZT6: ACTIF CIRCULANT HAO | EAB6: ACTIF CIRCULANT HAO | EAJ6: ACTIF CIRCULANT HAO | EAR6: ACTIF CIRCULANT HAO | EAZ6: ACTIF CIRCULANT HAO | EBH6: ACTIF CIRCULANT HAO | EBP6: ACTIF CIRCULANT HAO | EBX6: ACTIF CIRCULANT HAO | ECF6: ACTIF CIRCULANT HAO | ECN6: ACTIF CIRCULANT HAO | ECV6: ACTIF CIRCULANT HAO | EDD6: ACTIF CIRCULANT HAO | EDL6: ACTIF CIRCULANT HAO | EDT6: ACTIF CIRCULANT HAO | EEB6: ACTIF CIRCULANT HAO | EEJ6: ACTIF CIRCULANT HAO | EER6: ACTIF CIRCULANT HAO | EEZ6: ACTIF CIRCULANT HAO | EFH6: ACTIF CIRCULANT HAO | EFP6: ACTIF CIRCULANT HAO | EFX6: ACTIF CIRCULANT HAO | EGF6: ACTIF CIRCULANT HAO | EGN6: ACTIF CIRCULANT HAO | EGV6: ACTIF CIRCULANT HAO | EHD6: ACTIF CIRCULANT HAO | EHL6: ACTIF CIRCULANT HAO | EHT6: ACTIF CIRCULANT HAO | EIB6: ACTIF CIRCULANT HAO | EIJ6: ACTIF CIRCULANT HAO | EIR6: ACTIF CIRCULANT HAO | EIZ6: ACTIF CIRCULANT HAO | EJH6: ACTIF CIRCULANT HAO | EJP6: ACTIF CIRCULANT HAO | EJX6: ACTIF CIRCULANT HAO | EKF6: ACTIF CIRCULANT HAO | EKN6: ACTIF CIRCULANT HAO | EKV6: ACTIF CIRCULANT HAO | ELD6: ACTIF CIRCULANT HAO | ELL6: ACTIF CIRCULANT HAO | ELT6: ACTIF CIRCULANT HAO | EMB6: ACTIF CIRCULANT HAO | EMJ6: ACTIF CIRCULANT HAO | EMR6: ACTIF CIRCULANT HAO | EMZ6: ACTIF CIRCULANT HAO | ENH6: ACTIF CIRCULANT HAO | ENP6: ACTIF CIRCULANT HAO | ENX6: ACTIF CIRCULANT HAO | EOF6: ACTIF CIRCULANT HAO | EON6: ACTIF CIRCULANT HAO | EOV6: ACTIF CIRCULANT HAO | EPD6: ACTIF CIRCULANT HAO | EPL6: ACTIF CIRCULANT HAO | EPT6: ACTIF CIRCULANT HAO | EQB6: ACTIF CIRCULANT HAO | EQJ6: ACTIF CIRCULANT HAO | EQR6: ACTIF CIRCULANT HAO | EQZ6: ACTIF CIRCULANT HAO | ERH6: ACTIF CIRCULANT HAO | ERP6: ACTIF CIRCULANT HAO | ERX6: ACTIF CIRCULANT HAO | ESF6: ACTIF CIRCULANT HAO | ESN6: ACTIF CIRCULANT HAO | ESV6: ACTIF CIRCULANT HAO | ETD6: ACTIF CIRCULANT HAO | ETL6: ACTIF CIRCULANT HAO | ETT6: ACTIF CIRCULANT HAO | EUB6: ACTIF CIRCULANT HAO | EUJ6: ACTIF CIRCULANT HAO | EUR6: ACTIF CIRCULANT HAO | EUZ6: ACTIF CIRCULANT HAO | EVH6: ACTIF CIRCULANT HAO | EVP6: ACTIF CIRCULANT HAO | EVX6: ACTIF CIRCULANT HAO | EWF6: ACTIF CIRCULANT HAO | EWN6: ACTIF CIRCULANT HAO | EWV6: ACTIF CIRCULANT HAO | EXD6: ACTIF CIRCULANT HAO | EXL6: ACTIF CIRCULANT HAO | EXT6: ACTIF CIRCULANT HAO | EYB6: ACTIF CIRCULANT HAO | EYJ6: ACTIF CIRCULANT HAO | EYR6: ACTIF CIRCULANT HAO | EYZ6: ACTIF CIRCULANT HAO | EZH6: ACTIF CIRCULANT HAO | EZP6: ACTIF CIRCULANT HAO | EZX6: ACTIF CIRCULANT HAO | FAF6: ACTIF CIRCULANT HAO | FAN6: ACTIF CIRCULANT HAO | FAV6: ACTIF CIRCULANT HAO | FBD6: ACTIF CIRCULANT HAO | FBL6: ACTIF CIRCULANT HAO | FBT6: ACTIF CIRCULANT HAO | FCB6: ACTIF CIRCULANT HAO | FCJ6: ACTIF CIRCULANT HAO | FCR6: ACTIF CIRCULANT HAO | FCZ6: ACTIF CIRCULANT HAO | FDH6: ACTIF CIRCULANT HAO | FDP6: ACTIF CIRCULANT HAO | FDX6: ACTIF CIRCULANT HAO | FEF6: ACTIF CIRCULANT HAO | FEN6: ACTIF CIRCULANT HAO | FEV6: ACTIF CIRCULANT HAO | FFD6: ACTIF CIRCULANT HAO | FFL6: ACTIF CIRCULANT HAO | FFT6: ACTIF CIRCULANT HAO | FGB6: ACTIF CIRCULANT HAO | FGJ6: ACTIF CIRCULANT HAO | FGR6: ACTIF CIRCULANT HAO | FGZ6: ACTIF CIRCULANT HAO | FHH6: ACTIF CIRCULANT HAO | FHP6: ACTIF CIRCULANT HAO | FHX6: ACTIF CIRCULANT HAO | FIF6: ACTIF CIRCULANT HAO | FIN6: ACTIF CIRCULANT HAO | FIV6: ACTIF CIRCULANT HAO | FJD6: ACTIF CIRCULANT HAO | FJL6: ACTIF CIRCULANT HAO | FJT6: ACTIF CIRCULANT HAO | FKB6: ACTIF CIRCULANT HAO | FKJ6: ACTIF CIRCULANT HAO | FKR6: ACTIF CIRCULANT HAO | FKZ6: ACTIF CIRCULANT HAO | FLH6: ACTIF CIRCULANT HAO | FLP6: ACTIF CIRCULANT HAO | FLX6: ACTIF CIRCULANT HAO | FMF6: ACTIF CIRCULANT HAO | FMN6: ACTIF CIRCULANT HAO | FMV6: ACTIF CIRCULANT HAO | FND6: ACTIF CIRCULANT HAO | FNL6: ACTIF CIRCULANT HAO | FNT6: ACTIF CIRCULANT HAO | FOB6: ACTIF CIRCULANT HAO | FOJ6: ACTIF CIRCULANT HAO | FOR6: ACTIF CIRCULANT HAO | FOZ6: ACTIF CIRCULANT HAO | FPH6: ACTIF CIRCULANT HAO | FPP6: ACTIF CIRCULANT HAO | FPX6: ACTIF CIRCULANT HAO | FQF6: ACTIF CIRCULANT HAO | FQN6: ACTIF CIRCULANT HAO | FQV6: ACTIF CIRCULANT HAO | FRD6: ACTIF CIRCULANT HAO | FRL6: ACTIF CIRCULANT HAO | FRT6: ACTIF CIRCULANT HAO | FSB6: ACTIF CIRCULANT HAO | FSJ6: ACTIF CIRCULANT HAO | FSR6: ACTIF CIRCULANT HAO | FSZ6: ACTIF CIRCULANT HAO | FTH6: ACTIF CIRCULANT HAO | FTP6: ACTIF CIRCULANT HAO | FTX6: ACTIF CIRCULANT HAO | FUF6: ACTIF CIRCULANT HAO | FUN6: ACTIF CIRCULANT HAO | FUV6: ACTIF CIRCULANT HAO | FVD6: ACTIF CIRCULANT HAO | FVL6: ACTIF CIRCULANT HAO | FVT6: ACTIF CIRCULANT HAO | FWB6: ACTIF CIRCULANT HAO | FWJ6: ACTIF CIRCULANT HAO | FWR6: ACTIF CIRCULANT HAO | FWZ6: ACTIF CIRCULANT HAO | FXH6: ACTIF CIRCULANT HAO | FXP6: ACTIF CIRCULANT HAO | FXX6: ACTIF CIRCULANT HAO | FYF6: ACTIF CIRCULANT HAO | FYN6: ACTIF CIRCULANT HAO | FYV6: ACTIF CIRCULANT HAO | FZD6: ACTIF CIRCULANT HAO | FZL6: ACTIF CIRCULANT HAO | FZT6: ACTIF CIRCULANT HAO | GAB6: ACTIF CIRCULANT HAO | GAJ6: ACTIF CIRCULANT HAO | GAR6: ACTIF CIRCULANT HAO | GAZ6: ACTIF CIRCULANT HAO | GBH6: ACTIF CIRCULANT HAO | GBP6: ACTIF CIRCULANT HAO | GBX6: ACTIF CIRCULANT HAO | GCF6: ACTIF CIRCULANT HAO | GCN6: ACTIF CIRCULANT HAO | GCV6: ACTIF CIRCULANT HAO | GDD6: ACTIF CIRCULANT HAO | GDL6: ACTIF CIRCULANT HAO | GDT6: ACTIF CIRCULANT HAO | GEB6: ACTIF CIRCULANT HAO | GEJ6: ACTIF CIRCULANT HAO | GER6: ACTIF CIRCULANT HAO | GEZ6: ACTIF CIRCULANT HAO | GFH6: ACTIF CIRCULANT HAO | GFP6: ACTIF CIRCULANT HAO | GFX6: ACTIF CIRCULANT HAO | GGF6: ACTIF CIRCULANT HAO | GGN6: ACTIF CIRCULANT HAO | GGV6: ACTIF CIRCULANT HAO | GHD6: ACTIF CIRCULANT HAO | GHL6: ACTIF CIRCULANT HAO | GHT6: ACTIF CIRCULANT HAO | GIB6: ACTIF CIRCULANT HAO | GIJ6: ACTIF CIRCULANT HAO | GIR6: ACTIF CIRCULANT HAO | GIZ6: ACTIF CIRCULANT HAO | GJH6: ACTIF CIRCULANT HAO | GJP6: ACTIF CIRCULANT HAO | GJX6: ACTIF CIRCULANT HAO | GKF6: ACTIF CIRCULANT HAO | GKN6: ACTIF CIRCULANT HAO | GKV6: ACTIF CIRCULANT HAO | GLD6: ACTIF CIRCULANT HAO | GLL6: ACTIF CIRCULANT HAO | GLT6: ACTIF CIRCULANT HAO | GMB6: ACTIF CIRCULANT HAO | GMJ6: ACTIF CIRCULANT HAO | GMR6: ACTIF CIRCULANT HAO | GMZ6: ACTIF CIRCULANT HAO | GNH6: ACTIF CIRCULANT HAO | GNP6: ACTIF CIRCULANT HAO | GNX6: ACTIF CIRCULANT HAO | GOF6: ACTIF CIRCULANT HAO | GON6: ACTIF CIRCULANT HAO | GOV6: ACTIF CIRCULANT HAO | GPD6: ACTIF CIRCULANT HAO | GPL6: ACTIF CIRCULANT HAO | GPT6: ACTIF CIRCULANT HAO | GQB6: ACTIF CIRCULANT HAO | GQJ6: ACTIF CIRCULANT HAO | GQR6: ACTIF CIRCULANT HAO | GQZ6: ACTIF CIRCULANT HAO | GRH6: ACTIF CIRCULANT HAO | GRP6: ACTIF CIRCULANT HAO | GRX6: ACTIF CIRCULANT HAO | GSF6: ACTIF CIRCULANT HAO | GSN6: ACTIF CIRCULANT HAO | GSV6: ACTIF CIRCULANT HAO | GTD6: ACTIF CIRCULANT HAO | GTL6: ACTIF CIRCULANT HAO | GTT6: ACTIF CIRCULANT HAO | GUB6: ACTIF CIRCULANT HAO | GUJ6: ACTIF CIRCULANT HAO | GUR6: ACTIF CIRCULANT HAO | GUZ6: ACTIF CIRCULANT HAO | GVH6: ACTIF CIRCULANT HAO | GVP6: ACTIF CIRCULANT HAO | GVX6: ACTIF CIRCULANT HAO | GWF6: ACTIF CIRCULANT HAO | GWN6: ACTIF CIRCULANT HAO | GWV6: ACTIF CIRCULANT HAO | GXD6: ACTIF CIRCULANT HAO | GXL6: ACTIF CIRCULANT HAO | GXT6: ACTIF CIRCULANT HAO | GYB6: ACTIF CIRCULANT HAO | GYJ6: ACTIF CIRCULANT HAO | GYR6: ACTIF CIRCULANT HAO | GYZ6: ACTIF CIRCULANT HAO | GZH6: ACTIF CIRCULANT HAO | GZP6: ACTIF CIRCULANT HAO | GZX6: ACTIF CIRCULANT HAO | HAF6: ACTIF CIRCULANT HAO | HAN6: ACTIF CIRCULANT HAO | HAV6: ACTIF CIRCULANT HAO | HBD6: ACTIF CIRCULANT HAO | HBL6: ACTIF CIRCULANT HAO | HBT6: ACTIF CIRCULANT HAO | HCB6: ACTIF CIRCULANT HAO | HCJ6: ACTIF CIRCULANT HAO | HCR6: ACTIF CIRCULANT HAO | HCZ6: ACTIF CIRCULANT HAO | HDH6: ACTIF CIRCULANT HAO | HDP6: ACTIF CIRCULANT HAO | HDX6: ACTIF CIRCULANT HAO | HEF6: ACTIF CIRCULANT HAO | HEN6: ACTIF CIRCULANT HAO | HEV6: ACTIF CIRCULANT HAO | HFD6: ACTIF CIRCULANT HAO | HFL6: ACTIF CIRCULANT HAO | HFT6: ACTIF CIRCULANT HAO | HGB6: ACTIF CIRCULANT HAO | HGJ6: ACTIF CIRCULANT HAO | HGR6: ACTIF CIRCULANT HAO | HGZ6: ACTIF CIRCULANT HAO | HHH6: ACTIF CIRCULANT HAO | HHP6: ACTIF CIRCULANT HAO | HHX6: ACTIF CIRCULANT HAO | HIF6: ACTIF CIRCULANT HAO | HIN6: ACTIF CIRCULANT HAO | HIV6: ACTIF CIRCULANT HAO | HJD6: ACTIF CIRCULANT HAO | HJL6: ACTIF CIRCULANT HAO | HJT6: ACTIF CIRCULANT HAO | HKB6: ACTIF CIRCULANT HAO | HKJ6: ACTIF CIRCULANT HAO | HKR6: ACTIF CIRCULANT HAO | HKZ6: ACTIF CIRCULANT HAO | HLH6: ACTIF CIRCULANT HAO | HLP6: ACTIF CIRCULANT HAO | HLX6: ACTIF CIRCULANT HAO | HMF6: ACTIF CIRCULANT HAO | HMN6: ACTIF CIRCULANT HAO | HMV6: ACTIF CIRCULANT HAO | HND6: ACTIF CIRCULANT HAO | HNL6: ACTIF CIRCULANT HAO | HNT6: ACTIF CIRCULANT HAO | HOB6: ACTIF CIRCULANT HAO | HOJ6: ACTIF CIRCULANT HAO | HOR6: ACTIF CIRCULANT HAO | HOZ6: ACTIF CIRCULANT HAO | HPH6: ACTIF CIRCULANT HAO | HPP6: ACTIF CIRCULANT HAO | HPX6: ACTIF CIRCULANT HAO | HQF6: ACTIF CIRCULANT HAO | HQN6: ACTIF CIRCULANT HAO | HQV6: ACTIF CIRCULANT HAO | HRD6: ACTIF CIRCULANT HAO | HRL6: ACTIF CIRCULANT HAO | HRT6: ACTIF CIRCULANT HAO | HSB6: ACTIF CIRCULANT HAO | HSJ6: ACTIF CIRCULANT HAO | HSR6: ACTIF CIRCULANT HAO | HSZ6: ACTIF CIRCULANT HAO | HTH6: ACTIF CIRCULANT HAO | HTP6: ACTIF CIRCULANT HAO | HTX6: ACTIF CIRCULANT HAO | HUF6: ACTIF CIRCULANT HAO | HUN6: ACTIF CIRCULANT HAO | HUV6: ACTIF CIRCULANT HAO | HVD6: ACTIF CIRCULANT HAO | HVL6: ACTIF CIRCULANT HAO | HVT6: ACTIF CIRCULANT HAO | HWB6: ACTIF CIRCULANT HAO | HWJ6: ACTIF CIRCULANT HAO | HWR6: ACTIF CIRCULANT HAO | HWZ6: ACTIF CIRCULANT HAO | HXH6: ACTIF CIRCULANT HAO | HXP6: ACTIF CIRCULANT HAO | HXX6: ACTIF CIRCULANT HAO | HYF6: ACTIF CIRCULANT HAO | HYN6: ACTIF CIRCULANT HAO | HYV6: ACTIF CIRCULANT HAO | HZD6: ACTIF CIRCULANT HAO | HZL6: ACTIF CIRCULANT HAO | HZT6: ACTIF CIRCULANT HAO | IAB6: ACTIF CIRCULANT HAO | IAJ6: ACTIF CIRCULANT HAO | IAR6: ACTIF CIRCULANT HAO | IAZ6: ACTIF CIRCULANT HAO | IBH6: ACTIF CIRCULANT HAO | IBP6: ACTIF CIRCULANT HAO | IBX6: ACTIF CIRCULANT HAO | ICF6: ACTIF CIRCULANT HAO | ICN6: ACTIF CIRCULANT HAO | ICV6: ACTIF CIRCULANT HAO | IDD6: ACTIF CIRCULANT HAO | IDL6: ACTIF CIRCULANT HAO | IDT6: ACTIF CIRCULANT HAO | IEB6: ACTIF CIRCULANT HAO | IEJ6: ACTIF CIRCULANT HAO | IER6: ACTIF CIRCULANT HAO | IEZ6: ACTIF CIRCULANT HAO | IFH6: ACTIF CIRCULANT HAO | IFP6: ACTIF CIRCULANT HAO | IFX6: ACTIF CIRCULANT HAO | IGF6: ACTIF CIRCULANT HAO | IGN6: ACTIF CIRCULANT HAO | IGV6: ACTIF CIRCULANT HAO | IHD6: ACTIF CIRCULANT HAO | IHL6: ACTIF CIRCULANT HAO | IHT6: ACTIF CIRCULANT HAO | IIB6: ACTIF CIRCULANT HAO | IIJ6: ACTIF CIRCULANT HAO | IIR6: ACTIF CIRCULANT HAO | IIZ6: ACTIF CIRCULANT HAO | IJH6: ACTIF CIRCULANT HAO | IJP6: ACTIF CIRCULANT HAO | IJX6: ACTIF CIRCULANT HAO | IKF6: ACTIF CIRCULANT HAO | IKN6: ACTIF CIRCULANT HAO | IKV6: ACTIF CIRCULANT HAO | ILD6: ACTIF CIRCULANT HAO | ILL6: ACTIF CIRCULANT HAO | ILT6: ACTIF CIRCULANT HAO | IMB6: ACTIF CIRCULANT HAO | IMJ6: ACTIF CIRCULANT HAO | IMR6: ACTIF CIRCULANT HAO | IMZ6: ACTIF CIRCULANT HAO | INH6: ACTIF CIRCULANT HAO | INP6: ACTIF CIRCULANT HAO | INX6: ACTIF CIRCULANT HAO | IOF6: ACTIF CIRCULANT HAO | ION6: ACTIF CIRCULANT HAO | IOV6: ACTIF CIRCULANT HAO | IPD6: ACTIF CIRCULANT HAO | IPL6: ACTIF CIRCULANT HAO | IPT6: ACTIF CIRCULANT HAO | IQB6: ACTIF CIRCULANT HAO | IQJ6: ACTIF CIRCULANT HAO | IQR6: ACTIF CIRCULANT HAO | IQZ6: ACTIF CIRCULANT HAO | IRH6: ACTIF CIRCULANT HAO | IRP6: ACTIF CIRCULANT HAO | IRX6: ACTIF CIRCULANT HAO | ISF6: ACTIF CIRCULANT HAO | ISN6: ACTIF CIRCULANT HAO | ISV6: ACTIF CIRCULANT HAO | ITD6: ACTIF CIRCULANT HAO | ITL6: ACTIF CIRCULANT HAO | ITT6: ACTIF CIRCULANT HAO | IUB6: ACTIF CIRCULANT HAO | IUJ6: ACTIF CIRCULANT HAO | IUR6: ACTIF CIRCULANT HAO | IUZ6: ACTIF CIRCULANT HAO | IVH6: ACTIF CIRCULANT HAO | IVP6: ACTIF CIRCULANT HAO | IVX6: ACTIF CIRCULANT HAO | IWF6: ACTIF CIRCULANT HAO | IWN6: ACTIF CIRCULANT HAO | IWV6: ACTIF CIRCULANT HAO | IXD6: ACTIF CIRCULANT HAO | IXL6: ACTIF CIRCULANT HAO | IXT6: ACTIF CIRCULANT HAO | IYB6: ACTIF CIRCULANT HAO | IYJ6: ACTIF CIRCULANT HAO | IYR6: ACTIF CIRCULANT HAO | IYZ6: ACTIF CIRCULANT HAO | IZH6: ACTIF CIRCULANT HAO | IZP6: ACTIF CIRCULANT HAO | IZX6: ACTIF CIRCULANT HAO | JAF6: ACTIF CIRCULANT HAO | JAN6: ACTIF CIRCULANT HAO | JAV6: ACTIF CIRCULANT HAO | JBD6: ACTIF CIRCULANT HAO | JBL6: ACTIF CIRCULANT HAO | JBT6: ACTIF CIRCULANT HAO | JCB6: ACTIF CIRCULANT HAO | JCJ6: ACTIF CIRCULANT HAO | JCR6: ACTIF CIRCULANT HAO | JCZ6: ACTIF CIRCULANT HAO | JDH6: ACTIF CIRCULANT HAO | JDP6: ACTIF CIRCULANT HAO | JDX6: ACTIF CIRCULANT HAO | JEF6: ACTIF CIRCULANT HAO | JEN6: ACTIF CIRCULANT HAO | JEV6: ACTIF CIRCULANT HAO | JFD6: ACTIF CIRCULANT HAO | JFL6: ACTIF CIRCULANT HAO | JFT6: ACTIF CIRCULANT HAO | JGB6: ACTIF CIRCULANT HAO | JGJ6: ACTIF CIRCULANT HAO | JGR6: ACTIF CIRCULANT HAO | JGZ6: ACTIF CIRCULANT HAO | JHH6: ACTIF CIRCULANT HAO | JHP6: ACTIF CIRCULANT HAO | JHX6: ACTIF CIRCULANT HAO | JIF6: ACTIF CIRCULANT HAO | JIN6: ACTIF CIRCULANT HAO | JIV6: ACTIF CIRCULANT HAO | JJD6: ACTIF CIRCULANT HAO | JJL6: ACTIF CIRCULANT HAO | JJT6: ACTIF CIRCULANT HAO | JKB6: ACTIF CIRCULANT HAO | JKJ6: ACTIF CIRCULANT HAO | JKR6: ACTIF CIRCULANT HAO | JKZ6: ACTIF CIRCULANT HAO | JLH6: ACTIF CIRCULANT HAO | JLP6: ACTIF CIRCULANT HAO | JLX6: ACTIF CIRCULANT HAO | JMF6: ACTIF CIRCULANT HAO | JMN6: ACTIF CIRCULANT HAO | JMV6: ACTIF CIRCULANT HAO | JND6: ACTIF CIRCULANT HAO | JNL6: ACTIF CIRCULANT HAO | JNT6: ACTIF CIRCULANT HAO | JOB6: ACTIF CIRCULANT HAO | JOJ6: ACTIF CIRCULANT HAO | JOR6: ACTIF CIRCULANT HAO | JOZ6: ACTIF CIRCULANT HAO | JPH6: ACTIF CIRCULANT HAO | JPP6: ACTIF CIRCULANT HAO | JPX6: ACTIF CIRCULANT HAO | JQF6: ACTIF CIRCULANT HAO | JQN6: ACTIF CIRCULANT HAO | JQV6: ACTIF CIRCULANT HAO | JRD6: ACTIF CIRCULANT HAO | JRL6: ACTIF CIRCULANT HAO | JRT6: ACTIF CIRCULANT HAO | JSB6: ACTIF CIRCULANT HAO | JSJ6: ACTIF CIRCULANT HAO | JSR6: ACTIF CIRCULANT HAO | JSZ6: ACTIF CIRCULANT HAO | JTH6: ACTIF CIRCULANT HAO | JTP6: ACTIF CIRCULANT HAO | JTX6: ACTIF CIRCULANT HAO | JUF6: ACTIF CIRCULANT HAO | JUN6: ACTIF CIRCULANT HAO | JUV6: ACTIF CIRCULANT HAO | JVD6: ACTIF CIRCULANT HAO | JVL6: ACTIF CIRCULANT HAO | JVT6: ACTIF CIRCULANT HAO | JWB6: ACTIF CIRCULANT HAO | JWJ6: ACTIF CIRCULANT HAO | JWR6: ACTIF CIRCULANT HAO | JWZ6: ACTIF CIRCULANT HAO | JXH6: ACTIF CIRCULANT HAO | JXP6: ACTIF CIRCULANT HAO | JXX6: ACTIF CIRCULANT HAO | JYF6: ACTIF CIRCULANT HAO | JYN6: ACTIF CIRCULANT HAO | JYV6: ACTIF CIRCULANT HAO | JZD6: ACTIF CIRCULANT HAO | JZL6: ACTIF CIRCULANT HAO | JZT6: ACTIF CIRCULANT HAO | KAB6: ACTIF CIRCULANT HAO | KAJ6: ACTIF CIRCULANT HAO | KAR6: ACTIF CIRCULANT HAO | KAZ6: ACTIF CIRCULANT HAO | KBH6: ACTIF CIRCULANT HAO | KBP6: ACTIF CIRCULANT HAO | KBX6: ACTIF CIRCULANT HAO | KCF6: ACTIF CIRCULANT HAO | KCN6: ACTIF CIRCULANT HAO | KCV6: ACTIF CIRCULANT HAO | KDD6: ACTIF CIRCULANT HAO | KDL6: ACTIF CIRCULANT HAO | KDT6: ACTIF CIRCULANT HAO | KEB6: ACTIF CIRCULANT HAO | KEJ6: ACTIF CIRCULANT HAO | KER6: ACTIF CIRCULANT HAO | KEZ6: ACTIF CIRCULANT HAO | KFH6: ACTIF CIRCULANT HAO | KFP6: ACTIF CIRCULANT HAO | KFX6: ACTIF CIRCULANT HAO | KGF6: ACTIF CIRCULANT HAO | KGN6: ACTIF CIRCULANT HAO | KGV6: ACTIF CIRCULANT HAO | KHD6: ACTIF CIRCULANT HAO | KHL6: ACTIF CIRCULANT HAO | KHT6: ACTIF CIRCULANT HAO | KIB6: ACTIF CIRCULANT HAO | KIJ6: ACTIF CIRCULANT HAO | KIR6: ACTIF CIRCULANT HAO | KIZ6: ACTIF CIRCULANT HAO | KJH6: ACTIF CIRCULANT HAO | KJP6: ACTIF CIRCULANT HAO | KJX6: ACTIF CIRCULANT HAO | KKF6: ACTIF CIRCULANT HAO | KKN6: ACTIF CIRCULANT HAO | KKV6: ACTIF CIRCULANT HAO | KLD6: ACTIF CIRCULANT HAO | KLL6: ACTIF CIRCULANT HAO | KLT6: ACTIF CIRCULANT HAO | KMB6: ACTIF CIRCULANT HAO | KMJ6: ACTIF CIRCULANT HAO | KMR6: ACTIF CIRCULANT HAO | KMZ6: ACTIF CIRCULANT HAO | KNH6: ACTIF CIRCULANT HAO | KNP6: ACTIF CIRCULANT HAO | KNX6: ACTIF CIRCULANT HAO | KOF6: ACTIF CIRCULANT HAO | KON6: ACTIF CIRCULANT HAO | KOV6: ACTIF CIRCULANT HAO | KPD6: ACTIF CIRCULANT HAO | KPL6: ACTIF CIRCULANT HAO | KPT6: ACTIF CIRCULANT HAO | KQB6: ACTIF CIRCULANT HAO | KQJ6: ACTIF CIRCULANT HAO | KQR6: ACTIF CIRCULANT HAO | KQZ6: ACTIF CIRCULANT HAO | KRH6: ACTIF CIRCULANT HAO | KRP6: ACTIF CIRCULANT HAO | KRX6: ACTIF CIRCULANT HAO | KSF6: ACTIF CIRCULANT HAO | KSN6: ACTIF CIRCULANT HAO | KSV6: ACTIF CIRCULANT HAO | KTD6: ACTIF CIRCULANT HAO | KTL6: ACTIF CIRCULANT HAO | KTT6: ACTIF CIRCULANT HAO | KUB6: ACTIF CIRCULANT HAO | KUJ6: ACTIF CIRCULANT HAO | KUR6: ACTIF CIRCULANT HAO | KUZ6: ACTIF CIRCULANT HAO | KVH6: ACTIF CIRCULANT HAO | KVP6: ACTIF CIRCULANT HAO | KVX6: ACTIF CIRCULANT HAO | KWF6: ACTIF CIRCULANT HAO | KWN6: ACTIF CIRCULANT HAO | KWV6: ACTIF CIRCULANT HAO | KXD6: ACTIF CIRCULANT HAO | KXL6: ACTIF CIRCULANT HAO | KXT6: ACTIF CIRCULANT HAO | KYB6: ACTIF CIRCULANT HAO | KYJ6: ACTIF CIRCULANT HAO | KYR6: ACTIF CIRCULANT HAO | KYZ6: ACTIF CIRCULANT HAO | KZH6: ACTIF CIRCULANT HAO | KZP6: ACTIF CIRCULANT HAO | KZX6: ACTIF CIRCULANT HAO | LAF6: ACTIF CIRCULANT HAO | LAN6: ACTIF CIRCULANT HAO | LAV6: ACTIF CIRCULANT HAO | LBD6: ACTIF CIRCULANT HAO | LBL6: ACTIF CIRCULANT HAO | LBT6: ACTIF CIRCULANT HAO | LCB6: ACTIF CIRCULANT HAO | LCJ6: ACTIF CIRCULANT HAO | LCR6: ACTIF CIRCULANT HAO | LCZ6: ACTIF CIRCULANT HAO | LDH6: ACTIF CIRCULANT HAO | LDP6: ACTIF CIRCULANT HAO | LDX6: ACTIF CIRCULANT HAO | LEF6: ACTIF CIRCULANT HAO | LEN6: ACTIF CIRCULANT HAO | LEV6: ACTIF CIRCULANT HAO | LFD6: ACTIF CIRCULANT HAO | LFL6: ACTIF CIRCULANT HAO | LFT6: ACTIF CIRCULANT HAO | LGB6: ACTIF CIRCULANT HAO | LGJ6: ACTIF CIRCULANT HAO | LGR6: ACTIF CIRCULANT HAO | LGZ6: ACTIF CIRCULANT HAO | LHH6: ACTIF CIRCULANT HAO | LHP6: ACTIF CIRCULANT HAO | LHX6: ACTIF CIRCULANT HAO | LIF6: ACTIF CIRCULANT HAO | LIN6: ACTIF CIRCULANT HAO | LIV6: ACTIF CIRCULANT HAO | LJD6: ACTIF CIRCULANT HAO | LJL6: ACTIF CIRCULANT HAO | LJT6: ACTIF CIRCULANT HAO | LKB6: ACTIF CIRCULANT HAO | LKJ6: ACTIF CIRCULANT HAO | LKR6: ACTIF CIRCULANT HAO | LKZ6: ACTIF CIRCULANT HAO | LLH6: ACTIF CIRCULANT HAO | LLP6: ACTIF CIRCULANT HAO | LLX6: ACTIF CIRCULANT HAO | LMF6: ACTIF CIRCULANT HAO | LMN6: ACTIF CIRCULANT HAO | LMV6: ACTIF CIRCULANT HAO | LND6: ACTIF CIRCULANT HAO | LNL6: ACTIF CIRCULANT HAO | LNT6: ACTIF CIRCULANT HAO | LOB6: ACTIF CIRCULANT HAO | LOJ6: ACTIF CIRCULANT HAO | LOR6: ACTIF CIRCULANT HAO | LOZ6: ACTIF CIRCULANT HAO | LPH6: ACTIF CIRCULANT HAO | LPP6: ACTIF CIRCULANT HAO | LPX6: ACTIF CIRCULANT HAO | LQF6: ACTIF CIRCULANT HAO | LQN6: ACTIF CIRCULANT HAO | LQV6: ACTIF CIRCULANT HAO | LRD6: ACTIF CIRCULANT HAO | LRL6: ACTIF CIRCULANT HAO | LRT6: ACTIF CIRCULANT HAO | LSB6: ACTIF CIRCULANT HAO | LSJ6: ACTIF CIRCULANT HAO | LSR6: ACTIF CIRCULANT HAO | LSZ6: ACTIF CIRCULANT HAO | LTH6: ACTIF CIRCULANT HAO | LTP6: ACTIF CIRCULANT HAO | LTX6: ACTIF CIRCULANT HAO | LUF6: ACTIF CIRCULANT HAO | LUN6: ACTIF CIRCULANT HAO | LUV6: ACTIF CIRCULANT HAO | LVD6: ACTIF CIRCULANT HAO | LVL6: ACTIF CIRCULANT HAO | LVT6: ACTIF CIRCULANT HAO | LWB6: ACTIF CIRCULANT HAO | LWJ6: ACTIF CIRCULANT HAO | LWR6: ACTIF CIRCULANT HAO | LWZ6: ACTIF CIRCULANT HAO | LXH6: ACTIF CIRCULANT HAO | LXP6: ACTIF CIRCULANT HAO | LXX6: ACTIF CIRCULANT HAO | LYF6: ACTIF CIRCULANT HAO | LYN6: ACTIF CIRCULANT HAO | LYV6: ACTIF CIRCULANT HAO | LZD6: ACTIF CIRCULANT HAO | LZL6: ACTIF CIRCULANT HAO | LZT6: ACTIF CIRCULANT HAO | MAB6: ACTIF CIRCULANT HAO | MAJ6: ACTIF CIRCULANT HAO | MAR6: ACTIF CIRCULANT HAO | MAZ6: ACTIF CIRCULANT HAO | MBH6: ACTIF CIRCULANT HAO | MBP6: ACTIF CIRCULANT HAO | MBX6: ACTIF CIRCULANT HAO | MCF6: ACTIF CIRCULANT HAO | MCN6: ACTIF CIRCULANT HAO | MCV6: ACTIF CIRCULANT HAO | MDD6: ACTIF CIRCULANT HAO | MDL6: ACTIF CIRCULANT HAO | MDT6: ACTIF CIRCULANT HAO | MEB6: ACTIF CIRCULANT HAO | MEJ6: ACTIF CIRCULANT HAO | MER6: ACTIF CIRCULANT HAO | MEZ6: ACTIF CIRCULANT HAO | MFH6: ACTIF CIRCULANT HAO | MFP6: ACTIF CIRCULANT HAO | MFX6: ACTIF CIRCULANT HAO | MGF6: ACTIF CIRCULANT HAO | MGN6: ACTIF CIRCULANT HAO | MGV6: ACTIF CIRCULANT HAO | MHD6: ACTIF CIRCULANT HAO | MHL6: ACTIF CIRCULANT HAO | MHT6: ACTIF CIRCULANT HAO | MIB6: ACTIF CIRCULANT HAO | MIJ6: ACTIF CIRCULANT HAO | MIR6: ACTIF CIRCULANT HAO | MIZ6: ACTIF CIRCULANT HAO | MJH6: ACTIF CIRCULANT HAO | MJP6: ACTIF CIRCULANT HAO | MJX6: ACTIF CIRCULANT HAO | MKF6: ACTIF CIRCULANT HAO | MKN6: ACTIF CIRCULANT HAO | MKV6: ACTIF CIRCULANT HAO | MLD6: ACTIF CIRCULANT HAO | MLL6: ACTIF CIRCULANT HAO | MLT6: ACTIF CIRCULANT HAO | MMB6: ACTIF CIRCULANT HAO | MMJ6: ACTIF CIRCULANT HAO | MMR6: ACTIF CIRCULANT HAO | MMZ6: ACTIF CIRCULANT HAO | MNH6: ACTIF CIRCULANT HAO | MNP6: ACTIF CIRCULANT HAO | MNX6: ACTIF CIRCULANT HAO | MOF6: ACTIF CIRCULANT HAO | MON6: ACTIF CIRCULANT HAO | MOV6: ACTIF CIRCULANT HAO | MPD6: ACTIF CIRCULANT HAO | MPL6: ACTIF CIRCULANT HAO | MPT6: ACTIF CIRCULANT HAO | MQB6: ACTIF CIRCULANT HAO | MQJ6: ACTIF CIRCULANT HAO | MQR6: ACTIF CIRCULANT HAO | MQZ6: ACTIF CIRCULANT HAO | MRH6: ACTIF CIRCULANT HAO | MRP6: ACTIF CIRCULANT HAO | MRX6: ACTIF CIRCULANT HAO | MSF6: ACTIF CIRCULANT HAO | MSN6: ACTIF CIRCULANT HAO | MSV6: ACTIF CIRCULANT HAO | MTD6: ACTIF CIRCULANT HAO | MTL6: ACTIF CIRCULANT HAO | MTT6: ACTIF CIRCULANT HAO | MUB6: ACTIF CIRCULANT HAO | MUJ6: ACTIF CIRCULANT HAO | MUR6: ACTIF CIRCULANT HAO | MUZ6: ACTIF CIRCULANT HAO | MVH6: ACTIF CIRCULANT HAO | MVP6: ACTIF CIRCULANT HAO | MVX6: ACTIF CIRCULANT HAO | MWF6: ACTIF CIRCULANT HAO | MWN6: ACTIF CIRCULANT HAO | MWV6: ACTIF CIRCULANT HAO | MXD6: ACTIF CIRCULANT HAO | MXL6: ACTIF CIRCULANT HAO | MXT6: ACTIF CIRCULANT HAO | MYB6: ACTIF CIRCULANT HAO | MYJ6: ACTIF CIRCULANT HAO | MYR6: ACTIF CIRCULANT HAO | MYZ6: ACTIF CIRCULANT HAO | MZH6: ACTIF CIRCULANT HAO | MZP6: ACTIF CIRCULANT HAO | MZX6: ACTIF CIRCULANT HAO | NAF6: ACTIF CIRCULANT HAO | NAN6: ACTIF CIRCULANT HAO | NAV6: ACTIF CIRCULANT HAO | NBD6: ACTIF CIRCULANT HAO | NBL6: ACTIF CIRCULANT HAO | NBT6: ACTIF CIRCULANT HAO | NCB6: ACTIF CIRCULANT HAO | NCJ6: ACTIF CIRCULANT HAO | NCR6: ACTIF CIRCULANT HAO | NCZ6: ACTIF CIRCULANT HAO | NDH6: ACTIF CIRCULANT HAO | NDP6: ACTIF CIRCULANT HAO | NDX6: ACTIF CIRCULANT HAO | NEF6: ACTIF CIRCULANT HAO | NEN6: ACTIF CIRCULANT HAO | NEV6: ACTIF CIRCULANT HAO | NFD6: ACTIF CIRCULANT HAO | NFL6: ACTIF CIRCULANT HAO | NFT6: ACTIF CIRCULANT HAO | NGB6: ACTIF CIRCULANT HAO | NGJ6: ACTIF CIRCULANT HAO | NGR6: ACTIF CIRCULANT HAO | NGZ6: ACTIF CIRCULANT HAO | NHH6: ACTIF CIRCULANT HAO | NHP6: ACTIF CIRCULANT HAO | NHX6: ACTIF CIRCULANT HAO | NIF6: ACTIF CIRCULANT HAO | NIN6: ACTIF CIRCULANT HAO | NIV6: ACTIF CIRCULANT HAO | NJD6: ACTIF CIRCULANT HAO | NJL6: ACTIF CIRCULANT HAO | NJT6: ACTIF CIRCULANT HAO | NKB6: ACTIF CIRCULANT HAO | NKJ6: ACTIF CIRCULANT HAO | NKR6: ACTIF CIRCULANT HAO | NKZ6: ACTIF CIRCULANT HAO | NLH6: ACTIF CIRCULANT HAO | NLP6: ACTIF CIRCULANT HAO | NLX6: ACTIF CIRCULANT HAO | NMF6: ACTIF CIRCULANT HAO | NMN6: ACTIF CIRCULANT HAO | NMV6: ACTIF CIRCULANT HAO | NND6: ACTIF CIRCULANT HAO | NNL6: ACTIF CIRCULANT HAO | NNT6: ACTIF CIRCULANT HAO | NOB6: ACTIF CIRCULANT HAO | NOJ6: ACTIF CIRCULANT HAO | NOR6: ACTIF CIRCULANT HAO | NOZ6: ACTIF CIRCULANT HAO | NPH6: ACTIF CIRCULANT HAO | NPP6: ACTIF CIRCULANT HAO | NPX6: ACTIF CIRCULANT HAO | NQF6: ACTIF CIRCULANT HAO | NQN6: ACTIF CIRCULANT HAO | NQV6: ACTIF CIRCULANT HAO | NRD6: ACTIF CIRCULANT HAO | NRL6: ACTIF CIRCULANT HAO | NRT6: ACTIF CIRCULANT HAO | NSB6: ACTIF CIRCULANT HAO | NSJ6: ACTIF CIRCULANT HAO | NSR6: ACTIF CIRCULANT HAO | NSZ6: ACTIF CIRCULANT HAO | NTH6: ACTIF CIRCULANT HAO | NTP6: ACTIF CIRCULANT HAO | NTX6: ACTIF CIRCULANT HAO | NUF6: ACTIF CIRCULANT HAO | NUN6: ACTIF CIRCULANT HAO | NUV6: ACTIF CIRCULANT HAO | NVD6: ACTIF CIRCULANT HAO | NVL6: ACTIF CIRCULANT HAO | NVT6: ACTIF CIRCULANT HAO | NWB6: ACTIF CIRCULANT HAO | NWJ6: ACTIF CIRCULANT HAO | NWR6: ACTIF CIRCULANT HAO | NWZ6: ACTIF CIRCULANT HAO | NXH6: ACTIF CIRCULANT HAO | NXP6: ACTIF CIRCULANT HAO | NXX6: ACTIF CIRCULANT HAO | NYF6: ACTIF CIRCULANT HAO | NYN6: ACTIF CIRCULANT HAO | NYV6: ACTIF CIRCULANT HAO | NZD6: ACTIF CIRCULANT HAO | NZL6: ACTIF CIRCULANT HAO | NZT6: ACTIF CIRCULANT HAO | OAB6: ACTIF CIRCULANT HAO | OAJ6: ACTIF CIRCULANT HAO | OAR6: ACTIF CIRCULANT HAO | OAZ6: ACTIF CIRCULANT HAO | OBH6: ACTIF CIRCULANT HAO | OBP6: ACTIF CIRCULANT HAO | OBX6: ACTIF CIRCULANT HAO | OCF6: ACTIF CIRCULANT HAO | OCN6: ACTIF CIRCULANT HAO | OCV6: ACTIF CIRCULANT HAO | ODD6: ACTIF CIRCULANT HAO | ODL6: ACTIF CIRCULANT HAO | ODT6: ACTIF CIRCULANT HAO | OEB6: ACTIF CIRCULANT HAO | OEJ6: ACTIF CIRCULANT HAO | OER6: ACTIF CIRCULANT HAO | OEZ6: ACTIF CIRCULANT HAO | OFH6: ACTIF CIRCULANT HAO | OFP6: ACTIF CIRCULANT HAO | OFX6: ACTIF CIRCULANT HAO | OGF6: ACTIF CIRCULANT HAO | OGN6: ACTIF CIRCULANT HAO | OGV6: ACTIF CIRCULANT HAO | OHD6: ACTIF CIRCULANT HAO | OHL6: ACTIF CIRCULANT HAO | OHT6: ACTIF CIRCULANT HAO | OIB6: ACTIF CIRCULANT HAO | OIJ6: ACTIF CIRCULANT HAO | OIR6: ACTIF CIRCULANT HAO | OIZ6: ACTIF CIRCULANT HAO | OJH6: ACTIF CIRCULANT HAO | OJP6: ACTIF CIRCULANT HAO | OJX6: ACTIF CIRCULANT HAO | OKF6: ACTIF CIRCULANT HAO | OKN6: ACTIF CIRCULANT HAO | OKV6: ACTIF CIRCULANT HAO | OLD6: ACTIF CIRCULANT HAO | OLL6: ACTIF CIRCULANT HAO | OLT6: ACTIF CIRCULANT HAO | OMB6: ACTIF CIRCULANT HAO | OMJ6: ACTIF CIRCULANT HAO | OMR6: ACTIF CIRCULANT HAO | OMZ6: ACTIF CIRCULANT HAO | ONH6: ACTIF CIRCULANT HAO | ONP6: ACTIF CIRCULANT HAO | ONX6: ACTIF CIRCULANT HAO | OOF6: ACTIF CIRCULANT HAO | OON6: ACTIF CIRCULANT HAO | OOV6: ACTIF CIRCULANT HAO | OPD6: ACTIF CIRCULANT HAO | OPL6: ACTIF CIRCULANT HAO | OPT6: ACTIF CIRCULANT HAO | OQB6: ACTIF CIRCULANT HAO | OQJ6: ACTIF CIRCULANT HAO | OQR6: ACTIF CIRCULANT HAO | OQZ6: ACTIF CIRCULANT HAO | ORH6: ACTIF CIRCULANT HAO | ORP6: ACTIF CIRCULANT HAO | ORX6: ACTIF CIRCULANT HAO | OSF6: ACTIF CIRCULANT HAO | OSN6: ACTIF CIRCULANT HAO | OSV6: ACTIF CIRCULANT HAO | OTD6: ACTIF CIRCULANT HAO | OTL6: ACTIF CIRCULANT HAO | OTT6: ACTIF CIRCULANT HAO | OUB6: ACTIF CIRCULANT HAO | OUJ6: ACTIF CIRCULANT HAO | OUR6: ACTIF CIRCULANT HAO | OUZ6: ACTIF CIRCULANT HAO | OVH6: ACTIF CIRCULANT HAO | OVP6: ACTIF CIRCULANT HAO | OVX6: ACTIF CIRCULANT HAO | OWF6: ACTIF CIRCULANT HAO | OWN6: ACTIF CIRCULANT HAO | OWV6: ACTIF CIRCULANT HAO | OXD6: ACTIF CIRCULANT HAO | OXL6: ACTIF CIRCULANT HAO | OXT6: ACTIF CIRCULANT HAO | OYB6: ACTIF CIRCULANT HAO | OYJ6: ACTIF CIRCULANT HAO | OYR6: ACTIF CIRCULANT HAO | OYZ6: ACTIF CIRCULANT HAO | OZH6: ACTIF CIRCULANT HAO | OZP6: ACTIF CIRCULANT HAO | OZX6: ACTIF CIRCULANT HAO | PAF6: ACTIF CIRCULANT HAO | PAN6: ACTIF CIRCULANT HAO | PAV6: ACTIF CIRCULANT HAO | PBD6: ACTIF CIRCULANT HAO | PBL6: ACTIF CIRCULANT HAO | PBT6: ACTIF CIRCULANT HAO | PCB6: ACTIF CIRCULANT HAO | PCJ6: ACTIF CIRCULANT HAO | PCR6: ACTIF CIRCULANT HAO | PCZ6: ACTIF CIRCULANT HAO | PDH6: ACTIF CIRCULANT HAO | PDP6: ACTIF CIRCULANT HAO | PDX6: ACTIF CIRCULANT HAO | PEF6: ACTIF CIRCULANT HAO | PEN6: ACTIF CIRCULANT HAO | PEV6: ACTIF CIRCULANT HAO | PFD6: ACTIF CIRCULANT HAO | PFL6: ACTIF CIRCULANT HAO | PFT6: ACTIF CIRCULANT HAO | PGB6: ACTIF CIRCULANT HAO | PGJ6: ACTIF CIRCULANT HAO | PGR6: ACTIF CIRCULANT HAO | PGZ6: ACTIF CIRCULANT HAO | PHH6: ACTIF CIRCULANT HAO | PHP6: ACTIF CIRCULANT HAO | PHX6: ACTIF CIRCULANT HAO | PIF6: ACTIF CIRCULANT HAO | PIN6: ACTIF CIRCULANT HAO | PIV6: ACTIF CIRCULANT HAO | PJD6: ACTIF CIRCULANT HAO | PJL6: ACTIF CIRCULANT HAO | PJT6: ACTIF CIRCULANT HAO | PKB6: ACTIF CIRCULANT HAO | PKJ6: ACTIF CIRCULANT HAO | PKR6: ACTIF CIRCULANT HAO | PKZ6: ACTIF CIRCULANT HAO | PLH6: ACTIF CIRCULANT HAO | PLP6: ACTIF CIRCULANT HAO | PLX6: ACTIF CIRCULANT HAO | PMF6: ACTIF CIRCULANT HAO | PMN6: ACTIF CIRCULANT HAO | PMV6: ACTIF CIRCULANT HAO | PND6: ACTIF CIRCULANT HAO | PNL6: ACTIF CIRCULANT HAO | PNT6: ACTIF CIRCULANT HAO | POB6: ACTIF CIRCULANT HAO | POJ6: ACTIF CIRCULANT HAO | POR6: ACTIF CIRCULANT HAO | POZ6: ACTIF CIRCULANT HAO | PPH6: ACTIF CIRCULANT HAO | PPP6: ACTIF CIRCULANT HAO | PPX6: ACTIF CIRCULANT HAO | PQF6: ACTIF CIRCULANT HAO | PQN6: ACTIF CIRCULANT HAO | PQV6: ACTIF CIRCULANT HAO | PRD6: ACTIF CIRCULANT HAO | PRL6: ACTIF CIRCULANT HAO | PRT6: ACTIF CIRCULANT HAO | PSB6: ACTIF CIRCULANT HAO | PSJ6: ACTIF CIRCULANT HAO | PSR6: ACTIF CIRCULANT HAO | PSZ6: ACTIF CIRCULANT HAO | PTH6: ACTIF CIRCULANT HAO | PTP6: ACTIF CIRCULANT HAO | PTX6: ACTIF CIRCULANT HAO | PUF6: ACTIF CIRCULANT HAO | PUN6: ACTIF CIRCULANT HAO | PUV6: ACTIF CIRCULANT HAO | PVD6: ACTIF CIRCULANT HAO | PVL6: ACTIF CIRCULANT HAO | PVT6: ACTIF CIRCULANT HAO | PWB6: ACTIF CIRCULANT HAO | PWJ6: ACTIF CIRCULANT HAO | PWR6: ACTIF CIRCULANT HAO | PWZ6: ACTIF CIRCULANT HAO | PXH6: ACTIF CIRCULANT HAO | PXP6: ACTIF CIRCULANT HAO | PXX6: ACTIF CIRCULANT HAO | PYF6: ACTIF CIRCULANT HAO | PYN6: ACTIF CIRCULANT HAO | PYV6: ACTIF CIRCULANT HAO | PZD6: ACTIF CIRCULANT HAO | PZL6: ACTIF CIRCULANT HAO | PZT6: ACTIF CIRCULANT HAO | QAB6: ACTIF CIRCULANT HAO | QAJ6: ACTIF CIRCULANT HAO | QAR6: ACTIF CIRCULANT HAO | QAZ6: ACTIF CIRCULANT HAO | QBH6: ACTIF CIRCULANT HAO | QBP6: ACTIF CIRCULANT HAO | QBX6: ACTIF CIRCULANT HAO | QCF6: ACTIF CIRCULANT HAO | QCN6: ACTIF CIRCULANT HAO | QCV6: ACTIF CIRCULANT HAO | QDD6: ACTIF CIRCULANT HAO | QDL6: ACTIF CIRCULANT HAO | QDT6: ACTIF CIRCULANT HAO | QEB6: ACTIF CIRCULANT HAO | QEJ6: ACTIF CIRCULANT HAO | QER6: ACTIF CIRCULANT HAO | QEZ6: ACTIF CIRCULANT HAO | QFH6: ACTIF CIRCULANT HAO | QFP6: ACTIF CIRCULANT HAO | QFX6: ACTIF CIRCULANT HAO | QGF6: ACTIF CIRCULANT HAO | QGN6: ACTIF CIRCULANT HAO | QGV6: ACTIF CIRCULANT HAO | QHD6: ACTIF CIRCULANT HAO | QHL6: ACTIF CIRCULANT HAO | QHT6: ACTIF CIRCULANT HAO | QIB6: ACTIF CIRCULANT HAO | QIJ6: ACTIF CIRCULANT HAO | QIR6: ACTIF CIRCULANT HAO | QIZ6: ACTIF CIRCULANT HAO | QJH6: ACTIF CIRCULANT HAO | QJP6: ACTIF CIRCULANT HAO | QJX6: ACTIF CIRCULANT HAO | QKF6: ACTIF CIRCULANT HAO | QKN6: ACTIF CIRCULANT HAO | QKV6: ACTIF CIRCULANT HAO | QLD6: ACTIF CIRCULANT HAO | QLL6: ACTIF CIRCULANT HAO | QLT6: ACTIF CIRCULANT HAO | QMB6: ACTIF CIRCULANT HAO | QMJ6: ACTIF CIRCULANT HAO | QMR6: ACTIF CIRCULANT HAO | QMZ6: ACTIF CIRCULANT HAO | QNH6: ACTIF CIRCULANT HAO | QNP6: ACTIF CIRCULANT HAO | QNX6: ACTIF CIRCULANT HAO | QOF6: ACTIF CIRCULANT HAO | QON6: ACTIF CIRCULANT HAO | QOV6: ACTIF CIRCULANT HAO | QPD6: ACTIF CIRCULANT HAO | QPL6: ACTIF CIRCULANT HAO | QPT6: ACTIF CIRCULANT HAO | QQB6: ACTIF CIRCULANT HAO | QQJ6: ACTIF CIRCULANT HAO | QQR6: ACTIF CIRCULANT HAO | QQZ6: ACTIF CIRCULANT HAO | QRH6: ACTIF CIRCULANT HAO | QRP6: ACTIF CIRCULANT HAO | QRX6: ACTIF CIRCULANT HAO | QSF6: ACTIF CIRCULANT HAO | QSN6: ACTIF CIRCULANT HAO | QSV6: ACTIF CIRCULANT HAO | QTD6: ACTIF CIRCULANT HAO | QTL6: ACTIF CIRCULANT HAO | QTT6: ACTIF CIRCULANT HAO | QUB6: ACTIF CIRCULANT HAO | QUJ6: ACTIF CIRCULANT HAO | QUR6: ACTIF CIRCULANT HAO | QUZ6: ACTIF CIRCULANT HAO | QVH6: ACTIF CIRCULANT HAO | QVP6: ACTIF CIRCULANT HAO | QVX6: ACTIF CIRCULANT HAO | QWF6: ACTIF CIRCULANT HAO | QWN6: ACTIF CIRCULANT HAO | QWV6: ACTIF CIRCULANT HAO | QXD6: ACTIF CIRCULANT HAO | QXL6: ACTIF CIRCULANT HAO | QXT6: ACTIF CIRCULANT HAO | QYB6: ACTIF CIRCULANT HAO | QYJ6: ACTIF CIRCULANT HAO | QYR6: ACTIF CIRCULANT HAO | QYZ6: ACTIF CIRCULANT HAO | QZH6: ACTIF CIRCULANT HAO | QZP6: ACTIF CIRCULANT HAO | QZX6: ACTIF CIRCULANT HAO | RAF6: ACTIF CIRCULANT HAO | RAN6: ACTIF CIRCULANT HAO | RAV6: ACTIF CIRCULANT HAO | RBD6: ACTIF CIRCULANT HAO | RBL6: ACTIF CIRCULANT HAO | RBT6: ACTIF CIRCULANT HAO | RCB6: ACTIF CIRCULANT HAO | RCJ6: ACTIF CIRCULANT HAO | RCR6: ACTIF CIRCULANT HAO | RCZ6: ACTIF CIRCULANT HAO | RDH6: ACTIF CIRCULANT HAO | RDP6: ACTIF CIRCULANT HAO | RDX6: ACTIF CIRCULANT HAO | REF6: ACTIF CIRCULANT HAO | REN6: ACTIF CIRCULANT HAO | REV6: ACTIF CIRCULANT HAO | RFD6: ACTIF CIRCULANT HAO | RFL6: ACTIF CIRCULANT HAO | RFT6: ACTIF CIRCULANT HAO | RGB6: ACTIF CIRCULANT HAO | RGJ6: ACTIF CIRCULANT HAO | RGR6: ACTIF CIRCULANT HAO | RGZ6: ACTIF CIRCULANT HAO | RHH6: ACTIF CIRCULANT HAO | RHP6: ACTIF CIRCULANT HAO | RHX6: ACTIF CIRCULANT HAO | RIF6: ACTIF CIRCULANT HAO | RIN6: ACTIF CIRCULANT HAO | RIV6: ACTIF CIRCULANT HAO | RJD6: ACTIF CIRCULANT HAO | RJL6: ACTIF CIRCULANT HAO | RJT6: ACTIF CIRCULANT HAO | RKB6: ACTIF CIRCULANT HAO | RKJ6: ACTIF CIRCULANT HAO | RKR6: ACTIF CIRCULANT HAO | RKZ6: ACTIF CIRCULANT HAO | RLH6: ACTIF CIRCULANT HAO | RLP6: ACTIF CIRCULANT HAO | RLX6: ACTIF CIRCULANT HAO | RMF6: ACTIF CIRCULANT HAO | RMN6: ACTIF CIRCULANT HAO | RMV6: ACTIF CIRCULANT HAO | RND6: ACTIF CIRCULANT HAO | RNL6: ACTIF CIRCULANT HAO | RNT6: ACTIF CIRCULANT HAO | ROB6: ACTIF CIRCULANT HAO | ROJ6: ACTIF CIRCULANT HAO | ROR6: ACTIF CIRCULANT HAO | ROZ6: ACTIF CIRCULANT HAO | RPH6: ACTIF CIRCULANT HAO | RPP6: ACTIF CIRCULANT HAO | RPX6: ACTIF CIRCULANT HAO | RQF6: ACTIF CIRCULANT HAO | RQN6: ACTIF CIRCULANT HAO | RQV6: ACTIF CIRCULANT HAO | RRD6: ACTIF CIRCULANT HAO | RRL6: ACTIF CIRCULANT HAO | RRT6: ACTIF CIRCULANT HAO | RSB6: ACTIF CIRCULANT HAO | RSJ6: ACTIF CIRCULANT HAO | RSR6: ACTIF CIRCULANT HAO | RSZ6: ACTIF CIRCULANT HAO | RTH6: ACTIF CIRCULANT HAO | RTP6: ACTIF CIRCULANT HAO | RTX6: ACTIF CIRCULANT HAO | RUF6: ACTIF CIRCULANT HAO | RUN6: ACTIF CIRCULANT HAO | RUV6: ACTIF CIRCULANT HAO | RVD6: ACTIF CIRCULANT HAO | RVL6: ACTIF CIRCULANT HAO | RVT6: ACTIF CIRCULANT HAO | RWB6: ACTIF CIRCULANT HAO | RWJ6: ACTIF CIRCULANT HAO | RWR6: ACTIF CIRCULANT HAO | RWZ6: ACTIF CIRCULANT HAO | RXH6: ACTIF CIRCULANT HAO | RXP6: ACTIF CIRCULANT HAO | RXX6: ACTIF CIRCULANT HAO | RYF6: ACTIF CIRCULANT HAO | RYN6: ACTIF CIRCULANT HAO | RYV6: ACTIF CIRCULANT HAO | RZD6: ACTIF CIRCULANT HAO | RZL6: ACTIF CIRCULANT HAO | RZT6: ACTIF CIRCULANT HAO | SAB6: ACTIF CIRCULANT HAO | SAJ6: ACTIF CIRCULANT HAO | SAR6: ACTIF CIRCULANT HAO | SAZ6: ACTIF CIRCULANT HAO | SBH6: ACTIF CIRCULANT HAO | SBP6: ACTIF CIRCULANT HAO | SBX6: ACTIF CIRCULANT HAO | SCF6: ACTIF CIRCULANT HAO | SCN6: ACTIF CIRCULANT HAO | SCV6: ACTIF CIRCULANT HAO | SDD6: ACTIF CIRCULANT HAO | SDL6: ACTIF CIRCULANT HAO | SDT6: ACTIF CIRCULANT HAO | SEB6: ACTIF CIRCULANT HAO | SEJ6: ACTIF CIRCULANT HAO | SER6: ACTIF CIRCULANT HAO | SEZ6: ACTIF CIRCULANT HAO | SFH6: ACTIF CIRCULANT HAO | SFP6: ACTIF CIRCULANT HAO | SFX6: ACTIF CIRCULANT HAO | SGF6: ACTIF CIRCULANT HAO | SGN6: ACTIF CIRCULANT HAO | SGV6: ACTIF CIRCULANT HAO | SHD6: ACTIF CIRCULANT HAO | SHL6: ACTIF CIRCULANT HAO | SHT6: ACTIF CIRCULANT HAO | SIB6: ACTIF CIRCULANT HAO | SIJ6: ACTIF CIRCULANT HAO | SIR6: ACTIF CIRCULANT HAO | SIZ6: ACTIF CIRCULANT HAO | SJH6: ACTIF CIRCULANT HAO | SJP6: ACTIF CIRCULANT HAO | SJX6: ACTIF CIRCULANT HAO | SKF6: ACTIF CIRCULANT HAO | SKN6: ACTIF CIRCULANT HAO | SKV6: ACTIF CIRCULANT HAO | SLD6: ACTIF CIRCULANT HAO | SLL6: ACTIF CIRCULANT HAO | SLT6: ACTIF CIRCULANT HAO | SMB6: ACTIF CIRCULANT HAO | SMJ6: ACTIF CIRCULANT HAO | SMR6: ACTIF CIRCULANT HAO | SMZ6: ACTIF CIRCULANT HAO | SNH6: ACTIF CIRCULANT HAO | SNP6: ACTIF CIRCULANT HAO | SNX6: ACTIF CIRCULANT HAO | SOF6: ACTIF CIRCULANT HAO | SON6: ACTIF CIRCULANT HAO | SOV6: ACTIF CIRCULANT HAO | SPD6: ACTIF CIRCULANT HAO | SPL6: ACTIF CIRCULANT HAO | SPT6: ACTIF CIRCULANT HAO | SQB6: ACTIF CIRCULANT HAO | SQJ6: ACTIF CIRCULANT HAO | SQR6: ACTIF CIRCULANT HAO | SQZ6: ACTIF CIRCULANT HAO | SRH6: ACTIF CIRCULANT HAO | SRP6: ACTIF CIRCULANT HAO | SRX6: ACTIF CIRCULANT HAO | SSF6: ACTIF CIRCULANT HAO | SSN6: ACTIF CIRCULANT HAO | SSV6: ACTIF CIRCULANT HAO | STD6: ACTIF CIRCULANT HAO | STL6: ACTIF CIRCULANT HAO | STT6: ACTIF CIRCULANT HAO | SUB6: ACTIF CIRCULANT HAO | SUJ6: ACTIF CIRCULANT HAO | SUR6: ACTIF CIRCULANT HAO | SUZ6: ACTIF CIRCULANT HAO | SVH6: ACTIF CIRCULANT HAO | SVP6: ACTIF CIRCULANT HAO | SVX6: ACTIF CIRCULANT HAO | SWF6: ACTIF CIRCULANT HAO | SWN6: ACTIF CIRCULANT HAO | SWV6: ACTIF CIRCULANT HAO | SXD6: ACTIF CIRCULANT HAO | SXL6: ACTIF CIRCULANT HAO | SXT6: ACTIF CIRCULANT HAO | SYB6: ACTIF CIRCULANT HAO | SYJ6: ACTIF CIRCULANT HAO | SYR6: ACTIF CIRCULANT HAO | SYZ6: ACTIF CIRCULANT HAO | SZH6: ACTIF CIRCULANT HAO | SZP6: ACTIF CIRCULANT HAO | SZX6: ACTIF CIRCULANT HAO | TAF6: ACTIF CIRCULANT HAO | TAN6: ACTIF CIRCULANT HAO | TAV6: ACTIF CIRCULANT HAO | TBD6: ACTIF CIRCULANT HAO | TBL6: ACTIF CIRCULANT HAO | TBT6: ACTIF CIRCULANT HAO | TCB6: ACTIF CIRCULANT HAO | TCJ6: ACTIF CIRCULANT HAO | TCR6: ACTIF CIRCULANT HAO | TCZ6: ACTIF CIRCULANT HAO | TDH6: ACTIF CIRCULANT HAO | TDP6: ACTIF CIRCULANT HAO | TDX6: ACTIF CIRCULANT HAO | TEF6: ACTIF CIRCULANT HAO | TEN6: ACTIF CIRCULANT HAO | TEV6: ACTIF CIRCULANT HAO | TFD6: ACTIF CIRCULANT HAO | TFL6: ACTIF CIRCULANT HAO | TFT6: ACTIF CIRCULANT HAO | TGB6: ACTIF CIRCULANT HAO | TGJ6: ACTIF CIRCULANT HAO | TGR6: ACTIF CIRCULANT HAO | TGZ6: ACTIF CIRCULANT HAO | THH6: ACTIF CIRCULANT HAO | THP6: ACTIF CIRCULANT HAO | THX6: ACTIF CIRCULANT HAO | TIF6: ACTIF CIRCULANT HAO | TIN6: ACTIF CIRCULANT HAO | TIV6: ACTIF CIRCULANT HAO | TJD6: ACTIF CIRCULANT HAO | TJL6: ACTIF CIRCULANT HAO | TJT6: ACTIF CIRCULANT HAO | TKB6: ACTIF CIRCULANT HAO | TKJ6: ACTIF CIRCULANT HAO | TKR6: ACTIF CIRCULANT HAO | TKZ6: ACTIF CIRCULANT HAO | TLH6: ACTIF CIRCULANT HAO | TLP6: ACTIF CIRCULANT HAO | TLX6: ACTIF CIRCULANT HAO | TMF6: ACTIF CIRCULANT HAO | TMN6: ACTIF CIRCULANT HAO | TMV6: ACTIF CIRCULANT HAO | TND6: ACTIF CIRCULANT HAO | TNL6: ACTIF CIRCULANT HAO | TNT6: ACTIF CIRCULANT HAO | TOB6: ACTIF CIRCULANT HAO | TOJ6: ACTIF CIRCULANT HAO | TOR6: ACTIF CIRCULANT HAO | TOZ6: ACTIF CIRCULANT HAO | TPH6: ACTIF CIRCULANT HAO | TPP6: ACTIF CIRCULANT HAO | TPX6: ACTIF CIRCULANT HAO | TQF6: ACTIF CIRCULANT HAO | TQN6: ACTIF CIRCULANT HAO | TQV6: ACTIF CIRCULANT HAO | TRD6: ACTIF CIRCULANT HAO | TRL6: ACTIF CIRCULANT HAO | TRT6: ACTIF CIRCULANT HAO | TSB6: ACTIF CIRCULANT HAO | TSJ6: ACTIF CIRCULANT HAO | TSR6: ACTIF CIRCULANT HAO | TSZ6: ACTIF CIRCULANT HAO | TTH6: ACTIF CIRCULANT HAO | TTP6: ACTIF CIRCULANT HAO | TTX6: ACTIF CIRCULANT HAO | TUF6: ACTIF CIRCULANT HAO | TUN6: ACTIF CIRCULANT HAO | TUV6: ACTIF CIRCULANT HAO | TVD6: ACTIF CIRCULANT HAO | TVL6: ACTIF CIRCULANT HAO | TVT6: ACTIF CIRCULANT HAO | TWB6: ACTIF CIRCULANT HAO | TWJ6: ACTIF CIRCULANT HAO | TWR6: ACTIF CIRCULANT HAO | TWZ6: ACTIF CIRCULANT HAO | TXH6: ACTIF CIRCULANT HAO | TXP6: ACTIF CIRCULANT HAO | TXX6: ACTIF CIRCULANT HAO | TYF6: ACTIF CIRCULANT HAO | TYN6: ACTIF CIRCULANT HAO | TYV6: ACTIF CIRCULANT HAO | TZD6: ACTIF CIRCULANT HAO | TZL6: ACTIF CIRCULANT HAO | TZT6: ACTIF CIRCULANT HAO | UAB6: ACTIF CIRCULANT HAO | UAJ6: ACTIF CIRCULANT HAO | UAR6: ACTIF CIRCULANT HAO | UAZ6: ACTIF CIRCULANT HAO | UBH6: ACTIF CIRCULANT HAO | UBP6: ACTIF CIRCULANT HAO | UBX6: ACTIF CIRCULANT HAO | UCF6: ACTIF CIRCULANT HAO | UCN6: ACTIF CIRCULANT HAO | UCV6: ACTIF CIRCULANT HAO | UDD6: ACTIF CIRCULANT HAO | UDL6: ACTIF CIRCULANT HAO | UDT6: ACTIF CIRCULANT HAO | UEB6: ACTIF CIRCULANT HAO | UEJ6: ACTIF CIRCULANT HAO | UER6: ACTIF CIRCULANT HAO | UEZ6: ACTIF CIRCULANT HAO | UFH6: ACTIF CIRCULANT HAO | UFP6: ACTIF CIRCULANT HAO | UFX6: ACTIF CIRCULANT HAO | UGF6: ACTIF CIRCULANT HAO | UGN6: ACTIF CIRCULANT HAO | UGV6: ACTIF CIRCULANT HAO | UHD6: ACTIF CIRCULANT HAO | UHL6: ACTIF CIRCULANT HAO | UHT6: ACTIF CIRCULANT HAO | UIB6: ACTIF CIRCULANT HAO | UIJ6: ACTIF CIRCULANT HAO | UIR6: ACTIF CIRCULANT HAO | UIZ6: ACTIF CIRCULANT HAO | UJH6: ACTIF CIRCULANT HAO | UJP6: ACTIF CIRCULANT HAO | UJX6: ACTIF CIRCULANT HAO | UKF6: ACTIF CIRCULANT HAO | UKN6: ACTIF CIRCULANT HAO | UKV6: ACTIF CIRCULANT HAO | ULD6: ACTIF CIRCULANT HAO | ULL6: ACTIF CIRCULANT HAO | ULT6: ACTIF CIRCULANT HAO | UMB6: ACTIF CIRCULANT HAO | UMJ6: ACTIF CIRCULANT HAO | UMR6: ACTIF CIRCULANT HAO | UMZ6: ACTIF CIRCULANT HAO | UNH6: ACTIF CIRCULANT HAO | UNP6: ACTIF CIRCULANT HAO | UNX6: ACTIF CIRCULANT HAO | UOF6: ACTIF CIRCULANT HAO | UON6: ACTIF CIRCULANT HAO | UOV6: ACTIF CIRCULANT HAO | UPD6: ACTIF CIRCULANT HAO | UPL6: ACTIF CIRCULANT HAO | UPT6: ACTIF CIRCULANT HAO | UQB6: ACTIF CIRCULANT HAO | UQJ6: ACTIF CIRCULANT HAO | UQR6: ACTIF CIRCULANT HAO | UQZ6: ACTIF CIRCULANT HAO | URH6: ACTIF CIRCULANT HAO | URP6: ACTIF CIRCULANT HAO | URX6: ACTIF CIRCULANT HAO | USF6: ACTIF CIRCULANT HAO | USN6: ACTIF CIRCULANT HAO | USV6: ACTIF CIRCULANT HAO | UTD6: ACTIF CIRCULANT HAO | UTL6: ACTIF CIRCULANT HAO | UTT6: ACTIF CIRCULANT HAO | UUB6: ACTIF CIRCULANT HAO | UUJ6: ACTIF CIRCULANT HAO | UUR6: ACTIF CIRCULANT HAO | UUZ6: ACTIF CIRCULANT HAO | UVH6: ACTIF CIRCULANT HAO | UVP6: ACTIF CIRCULANT HAO | UVX6: ACTIF CIRCULANT HAO | UWF6: ACTIF CIRCULANT HAO | UWN6: ACTIF CIRCULANT HAO | UWV6: ACTIF CIRCULANT HAO | UXD6: ACTIF CIRCULANT HAO | UXL6: ACTIF CIRCULANT HAO | UXT6: ACTIF CIRCULANT HAO | UYB6: ACTIF CIRCULANT HAO | UYJ6: ACTIF CIRCULANT HAO | UYR6: ACTIF CIRCULANT HAO | UYZ6: ACTIF CIRCULANT HAO | UZH6: ACTIF CIRCULANT HAO | UZP6: ACTIF CIRCULANT HAO | UZX6: ACTIF CIRCULANT HAO | VAF6: ACTIF CIRCULANT HAO | VAN6: ACTIF CIRCULANT HAO | VAV6: ACTIF CIRCULANT HAO | VBD6: ACTIF CIRCULANT HAO | VBL6: ACTIF CIRCULANT HAO | VBT6: ACTIF CIRCULANT HAO | VCB6: ACTIF CIRCULANT HAO | VCJ6: ACTIF CIRCULANT HAO | VCR6: ACTIF CIRCULANT HAO | VCZ6: ACTIF CIRCULANT HAO | VDH6: ACTIF CIRCULANT HAO | VDP6: ACTIF CIRCULANT HAO | VDX6: ACTIF CIRCULANT HAO | VEF6: ACTIF CIRCULANT HAO | VEN6: ACTIF CIRCULANT HAO | VEV6: ACTIF CIRCULANT HAO | VFD6: ACTIF CIRCULANT HAO | VFL6: ACTIF CIRCULANT HAO | VFT6: ACTIF CIRCULANT HAO | VGB6: ACTIF CIRCULANT HAO | VGJ6: ACTIF CIRCULANT HAO | VGR6: ACTIF CIRCULANT HAO | VGZ6: ACTIF CIRCULANT HAO | VHH6: ACTIF CIRCULANT HAO | VHP6: ACTIF CIRCULANT HAO | VHX6: ACTIF CIRCULANT HAO | VIF6: ACTIF CIRCULANT HAO | VIN6: ACTIF CIRCULANT HAO | VIV6: ACTIF CIRCULANT HAO | VJD6: ACTIF CIRCULANT HAO | VJL6: ACTIF CIRCULANT HAO | VJT6: ACTIF CIRCULANT HAO | VKB6: ACTIF CIRCULANT HAO | VKJ6: ACTIF CIRCULANT HAO | VKR6: ACTIF CIRCULANT HAO | VKZ6: ACTIF CIRCULANT HAO | VLH6: ACTIF CIRCULANT HAO | VLP6: ACTIF CIRCULANT HAO | VLX6: ACTIF CIRCULANT HAO | VMF6: ACTIF CIRCULANT HAO | VMN6: ACTIF CIRCULANT HAO | VMV6: ACTIF CIRCULANT HAO | VND6: ACTIF CIRCULANT HAO | VNL6: ACTIF CIRCULANT HAO | VNT6: ACTIF CIRCULANT HAO | VOB6: ACTIF CIRCULANT HAO | VOJ6: ACTIF CIRCULANT HAO | VOR6: ACTIF CIRCULANT HAO | VOZ6: ACTIF CIRCULANT HAO | VPH6: ACTIF CIRCULANT HAO | VPP6: ACTIF CIRCULANT HAO | VPX6: ACTIF CIRCULANT HAO | VQF6: ACTIF CIRCULANT HAO | VQN6: ACTIF CIRCULANT HAO | VQV6: ACTIF CIRCULANT HAO | VRD6: ACTIF CIRCULANT HAO | VRL6: ACTIF CIRCULANT HAO | VRT6: ACTIF CIRCULANT HAO | VSB6: ACTIF CIRCULANT HAO | VSJ6: ACTIF CIRCULANT HAO | VSR6: ACTIF CIRCULANT HAO | VSZ6: ACTIF CIRCULANT HAO | VTH6: ACTIF CIRCULANT HAO | VTP6: ACTIF CIRCULANT HAO | VTX6: ACTIF CIRCULANT HAO | VUF6: ACTIF CIRCULANT HAO | VUN6: ACTIF CIRCULANT HAO | VUV6: ACTIF CIRCULANT HAO | VVD6: ACTIF CIRCULANT HAO | VVL6: ACTIF CIRCULANT HAO | VVT6: ACTIF CIRCULANT HAO | VWB6: ACTIF CIRCULANT HAO | VWJ6: ACTIF CIRCULANT HAO | VWR6: ACTIF CIRCULANT HAO | VWZ6: ACTIF CIRCULANT HAO | VXH6: ACTIF CIRCULANT HAO | VXP6: ACTIF CIRCULANT HAO | VXX6: ACTIF CIRCULANT HAO | VYF6: ACTIF CIRCULANT HAO | VYN6: ACTIF CIRCULANT HAO | VYV6: ACTIF CIRCULANT HAO | VZD6: ACTIF CIRCULANT HAO | VZL6: ACTIF CIRCULANT HAO | VZT6: ACTIF CIRCULANT HAO | WAB6: ACTIF CIRCULANT HAO | WAJ6: ACTIF CIRCULANT HAO | WAR6: ACTIF CIRCULANT HAO | WAZ6: ACTIF CIRCULANT HAO | WBH6: ACTIF CIRCULANT HAO | WBP6: ACTIF CIRCULANT HAO | WBX6: ACTIF CIRCULANT HAO | WCF6: ACTIF CIRCULANT HAO | WCN6: ACTIF CIRCULANT HAO | WCV6: ACTIF CIRCULANT HAO | WDD6: ACTIF CIRCULANT HAO | WDL6: ACTIF CIRCULANT HAO | WDT6: ACTIF CIRCULANT HAO | WEB6: ACTIF CIRCULANT HAO | WEJ6: ACTIF CIRCULANT HAO | WER6: ACTIF CIRCULANT HAO | WEZ6: ACTIF CIRCULANT HAO | WFH6: ACTIF CIRCULANT HAO | WFP6: ACTIF CIRCULANT HAO | WFX6: ACTIF CIRCULANT HAO | WGF6: ACTIF CIRCULANT HAO | WGN6: ACTIF CIRCULANT HAO | WGV6: ACTIF CIRCULANT HAO | WHD6: ACTIF CIRCULANT HAO | WHL6: ACTIF CIRCULANT HAO | WHT6: ACTIF CIRCULANT HAO | WIB6: ACTIF CIRCULANT HAO | WIJ6: ACTIF CIRCULANT HAO | WIR6: ACTIF CIRCULANT HAO | WIZ6: ACTIF CIRCULANT HAO | WJH6: ACTIF CIRCULANT HAO | WJP6: ACTIF CIRCULANT HAO | WJX6: ACTIF CIRCULANT HAO | WKF6: ACTIF CIRCULANT HAO | WKN6: ACTIF CIRCULANT HAO | WKV6: ACTIF CIRCULANT HAO | WLD6: ACTIF CIRCULANT HAO | WLL6: ACTIF CIRCULANT HAO | WLT6: ACTIF CIRCULANT HAO | WMB6: ACTIF CIRCULANT HAO | WMJ6: ACTIF CIRCULANT HAO | WMR6: ACTIF CIRCULANT HAO | WMZ6: ACTIF CIRCULANT HAO | WNH6: ACTIF CIRCULANT HAO | WNP6: ACTIF CIRCULANT HAO | WNX6: ACTIF CIRCULANT HAO | WOF6: ACTIF CIRCULANT HAO | WON6: ACTIF CIRCULANT HAO | WOV6: ACTIF CIRCULANT HAO | WPD6: ACTIF CIRCULANT HAO | WPL6: ACTIF CIRCULANT HAO | WPT6: ACTIF CIRCULANT HAO | WQB6: ACTIF CIRCULANT HAO | WQJ6: ACTIF CIRCULANT HAO | WQR6: ACTIF CIRCULANT HAO | WQZ6: ACTIF CIRCULANT HAO | WRH6: ACTIF CIRCULANT HAO | WRP6: ACTIF CIRCULANT HAO | WRX6: ACTIF CIRCULANT HAO | WSF6: ACTIF CIRCULANT HAO | WSN6: ACTIF CIRCULANT HAO | WSV6: ACTIF CIRCULANT HAO | WTD6: ACTIF CIRCULANT HAO | WTL6: ACTIF CIRCULANT HAO | WTT6: ACTIF CIRCULANT HAO | WUB6: ACTIF CIRCULANT HAO | WUJ6: ACTIF CIRCULANT HAO | WUR6: ACTIF CIRCULANT HAO | WUZ6: ACTIF CIRCULANT HAO | WVH6: ACTIF CIRCULANT HAO | WVP6: ACTIF CIRCULANT HAO | WVX6: ACTIF CIRCULANT HAO | WWF6: ACTIF CIRCULANT HAO | WWN6: ACTIF CIRCULANT HAO | WWV6: ACTIF CIRCULANT HAO | WXD6: ACTIF CIRCULANT HAO | WXL6: ACTIF CIRCULANT HAO | WXT6: ACTIF CIRCULANT HAO | WYB6: ACTIF CIRCULANT HAO | WYJ6: ACTIF CIRCULANT HAO | WYR6: ACTIF CIRCULANT HAO | WYZ6: ACTIF CIRCULANT HAO | WZH6: ACTIF CIRCULANT HAO | WZP6: ACTIF CIRCULANT HAO | WZX6: ACTIF CIRCULANT HAO | XAF6: ACTIF CIRCULANT HAO | XAN6: ACTIF CIRCULANT HAO | XAV6: ACTIF CIRCULANT HAO | XBD6: ACTIF CIRCULANT HAO | XBL6: ACTIF CIRCULANT HAO | XBT6: ACTIF CIRCULANT HAO | XCB6: ACTIF CIRCULANT HAO | XCJ6: ACTIF CIRCULANT HAO | XCR6: ACTIF CIRCULANT HAO | XCZ6: ACTIF CIRCULANT HAO | XDH6: ACTIF CIRCULANT HAO | XDP6: ACTIF CIRCULANT HAO | XDX6: ACTIF CIRCULANT HAO | XEF6: ACTIF CIRCULANT HAO | XEN6: ACTIF CIRCULANT HAO | XEV6: ACTIF CIRCULANT HAO
A8: LIBELLES | B8: =IFERROR(YEAR('Fiche de renseignement R1'!V10),"Annee N") -> 1900 | D8: =IFERROR(YEAR('Fiche de renseignement R1'!Q20),"Annee N-1") -> 2020 | F8: Variation en %
A10: Créances sur cessions d'immobilisations | B10: =+SUMIF('BAL N'!J:J,"=485",'BAL N'!G:G) -> 0 | D10: =+SUMIF('BAL N'!J:J,"=485",'BAL N'!C:C) -> 0 | F10: =IFERROR((B10-D10)/B10,0) -> 0
A11: Autres créances hors activités ordinaires | B11: =+SUMIF('BAL N'!J:J,"=488",'BAL N'!G:G) -> 0 | D11: =+SUMIF('BAL N'!J:J,"=488",'BAL N'!C:C) -> 0 | F11: =IFERROR((B11-D11)/B11,0) -> 0
A12: TOTAL BRUT | B12: =SUM(B10:C11) -> 0 | D12: =SUM(D10:E11) -> 0 | F12: =SUM(F10:G11) -> 0
A13: Dépréciations des créances HAO
A14: TOTAL NET DE DEPRECIATION
A15: Commentaire :
A16: · Commenter touter variation significative
A17: · Dépréciation : indiquer les évènements et les circonstances qui ont motivé
A18: la dépréciation ou la reprise
A20: DETTES CIRCULANTES HAO
A22: LIBELLES | B22: =IFERROR(YEAR('Fiche de renseignement R1'!V10),"Annee N") -> 1900 | D22: =IFERROR(YEAR('Fiche de renseignement R1'!Q20),"Annee N-1") -> 2020 | F22: VARIATION EN %
A24: Fournisseurs d'investissements
A25: Fournisseurs d'investissements effets à payer
A26: Versements restant à effectuer sur titres de participation et titres immobilisés non libérés
A27: Autres dettes hors activités ordinaires
A28: TOTAL
A29: Commentaire :
A30: · Indiquer la date de cession et la nature de l'immobilisation achétée et/ou cédée
A31: · Expliquer toute variation significative

Sheet Note 6
A1: NOTE 6 : STOCKS ET ENCOURS(1)
A3: Désignation entité : | B3: ='Fiche de renseignement R1'!$J$4 -> 0 | C3: Excercice clos le : | D3: =+'Note 1'!E3 -> 0
A4: Numéro d'identification : | B4: =+'Note 1'!B4 -> 0 | C4: Durée en mois : | D4: =+'Note 1'!E4 -> 12
A6: LIBELLES | B6: =IFERROR(YEAR('Fiche de renseignement R1'!V10),"Annee N") -> 1900 | C6: =IFERROR(YEAR('Fiche de renseignement R1'!Q20),"Annee N-1") -> 2020 | D6: VARIATION EN %
A8: Marchandises | B8: =+SUMIF('BAL N'!I:I,"=31",'BAL N'!G:G) -> 0 | C8: =+SUMIF('BAL N'!I:I,"=31",'BAL N'!C:C) -> 0 | D8: =IFERROR((B8-C8)/B8,0) -> 0
A9: Matières premières et fournitures liées | B9: =+SUMIF('BAL N'!I:I,"=32",'BAL N'!G:G) -> 365270359 | C9: =+SUMIF('BAL N'!I:I,"=32",'BAL N'!C:C) -> 433749204 | D9: =IFERROR((B9-C9)/B9,0) -> -0.18747441
A10: Autres approvisionnements | B10: =+SUMIF('BAL N'!I:I,"=33",'BAL N'!G:G) -> 0 | C10: =+SUMIF('BAL N'!I:I,"=33",'BAL N'!C:C) -> 0 | D10: =IFERROR((B10-C10)/B10,0) -> 0
A11: Produits en cours | B11: =+SUMIF('BAL N'!I:I,"=34",'BAL N'!G:G) -> 0 | C11: =+SUMIF('BAL N'!I:I,"=34",'BAL N'!C:C) -> 0 | D11: =IFERROR((B11-C11)/B11,0) -> 0
A12: Services en cours | B12: =+SUMIF('BAL N'!I:I,"=35",'BAL N'!G:G) -> 0 | C12: =+SUMIF('BAL N'!I:I,"=35",'BAL N'!C:C) -> 0 | D12: =IFERROR((B12-C12)/B12,0) -> 0
A13: Produits finis | B13: =+SUMIF('BAL N'!I:I,"=36",'BAL N'!G:G) -> 0 | C13: =+SUMIF('BAL N'!I:I,"=36",'BAL N'!C:C) -> 0 | D13: =IFERROR((B13-C13)/B13,0) -> 0
A14: Produits intermédiaires | B14: =+SUMIF('BAL N'!I:I,"=37",'BAL N'!G:G) -> 0 | C14: =+SUMIF('BAL N'!I:I,"=37",'BAL N'!C:C) -> 0 | D14: =IFERROR((B14-C14)/B14,0) -> 0
A15: Stocks en cours de route, en consignation ou en dépôt | B15: =+SUMIF('BAL N'!I:I,"=38",'BAL N'!G:G) -> 0 | C15: =+SUMIF('BAL N'!I:I,"=38",'BAL N'!C:C) -> 0 | D15: =IFERROR((B15-C15)/B15,0) -> 0
A16: TOTAL BRUT STOCKS ET EN COURS | B16: =SUM(B8:B15) -> 365270359 | C16: =SUM(C8:C15) -> 433749204 | D16: =IFERROR((B16-C16)/B16,0) -> -0.18747441
A17: Dépréciations des stocks | B17: =+SUMIF('BAL N'!I:I,"=39",'BAL N'!H:H) -> 0 | C17: =+SUMIF('BAL N'!I:I,"=39",'BAL N'!D:D) -> 0 | D17: =IFERROR((B17-C17)/B17,0) -> 0
D18: =IFERROR((B18-C18)/B18,0) -> 0
A19: Total net de dépréciation | B19: =SUM(B17) -> 0 | C19: =SUM(C17) -> 0 | D19: =IFERROR((B19-C19)/B19,0) -> 0
A20: (1) : Les stocks HAO seront inscrits dans l'actif circulant HAO que lorsque leur montant total est significatif
A21: (supérieur à 5% du total de l'actif circulant)
A22: Commentaire :
A23: · Indiquer la date de prise d'inventaire et décrire brièvement la procédure, les méthodes comptables adoptées
A24: pour évaluer le stock
A25: · Commenter toute variation significative des stocks
A26: · Indiquer le détail des stocks dépréciés et les évènements et circonstances qui ont conduit à la dépréciation
A27: et à la reprise

Sheet Note 7
A1: NOTE 7 : CLIENTS
A3: Désignation entité : | B3: ='Fiche de renseignement R1'!$J$4 -> 0 | E3: Excercice clos le : | F3: =+'Note 1'!E3 -> 0
A4: Numéro d'identification : | B4: =+'Note 1'!B4 -> 0 | E4: Durée en mois : | F4: =+'Note 1'!E4 -> 12
A7: LIBELLES | B7: =IFERROR(YEAR('Fiche de renseignement R1'!V10),"Annee N") -> 1900 | C7: =IFERROR(YEAR('Fiche de renseignement R1'!Q20),"Annee N-1") -> 2020 | D7: Variation en % | E7: Créances à un an au plus | F7: Créances à plus d'un an et à deux ans au plus | G7: Créances à plus de deux ans
A9: Clients (hors réserves de propriété Groupe) | B9: =+SUMIF('BAL N'!J:J,"=411",'BAL N'!G:G)-SUMIF('BAL N'!K:K,"=4116",'BAL N'!G:G) -> 33496906640 | C9: =+SUMIF('BAL N'!J:J,"=411",'BAL N'!C:C)-SUMIF('BAL N'!K:K,"=4116",'BAL N'!C:C) -> 28210518525 | D9: =IFERROR((B9-C9)/B9,0) -> 0.1578172
A10: Clients effets à recevoir (hors réserves de propriété Groupe) | B10: =+SUMIF('BAL N'!J:J,"=412",'BAL N'!G:G)-SUMIF('BAL N'!K:K,"=4126",'BAL N'!G:G) -> 0 | C10: =+SUMIF('BAL N'!J:J,"=412",'BAL N'!C:C)-SUMIF('BAL N'!K:K,"=4122",'BAL N'!C:C) -> 0 | D10: =IFERROR((B10-C10)/B10,0) -> 0
A11: Clients effets à recevoir avec réserves de propriété | B11: =+SUMIF('BAL N'!K:K,"=4116",'BAL N'!G:G)+SUMIF('BAL N'!K:K,"=4126",'BAL N'!G:G) -> 0 | C11: =+SUMIF('BAL N'!J:J,"=412",'BAL N'!C:C) -> 0 | D11: =IFERROR((B11-C11)/B11,0) -> 0
A12: Clients et effets à recevoir Groupe | B12: =+SUMIF('BAL N'!K:K,"=4122",'BAL N'!G:G) -> 0 | C12: =+SUMIF('BAL N'!K:K,"=4122",'BAL N'!C:C) -> 0 | D12: =IFERROR((B12-C12)/B12,0) -> 0
A13: Créances sur cession d'immobilisations | B13: =+SUMIF('BAL N'!J:J,"=414",'BAL N'!G:G) -> 0 | C13: =+SUMIF('BAL N'!J:J,"=485",'BAL N'!C:C) -> 0 | D13: =IFERROR((B13-C13)/B13,0) -> 0
A14: Clients effets escomptés et non échus | B14: =+SUMIF('BAL N'!J:J,"=415",'BAL N'!G:G) -> 0 | C14: =+SUMIF('BAL N'!J:J,"=415",'BAL N'!C:C) -> 0 | D14: =IFERROR((B14-C14)/B14,0) -> 0
A15: Créances litigieuses ou douteuses | B15: =+SUMIF('BAL N'!J:J,"=416",'BAL N'!G:G) -> 0 | C15: =+SUMIF('BAL N'!J:J,"=416",'BAL N'!C:C) -> 0 | D15: =IFERROR((B15-C15)/B15,0) -> 0
A16: Clients produits à recevoir | B16: =+SUMIF('BAL N'!J:J,"=482",'BAL N'!G:G) -> 0 | C16: =+SUMIF('BAL N'!J:J,"=482",'BAL N'!C:C) -> 0 | D16: =IFERROR((B16-C16)/B16,0) -> 0
A17: TOTAL BRUT CLIENTS | B17: =SUM(B9:B16) -> 33496906640 | C17: =SUM(C9:C16) -> 28210518525 | D17: =IFERROR((B17-C17)/B17,0) -> 0.1578172
A18: Dépréciations des comptes clients | B18: =+SUMIF('BAL N'!J:J,"=491",'BAL N'!H:H) -> 0 | D18: =IFERROR((B18-C18)/B18,0) -> 0
A19: TOTAL NET DE DEPRECIATION | B19: =SUM(B18) -> 0 | C19: =SUM(C18) -> 0 | D19: =IFERROR((B19-C19)/B19,0) -> 0
A20: Clients, avances reçues hors groupe | B20: =+SUMIF('BAL N'!K:K,"=4191",'BAL N'!H:H)+SUMIF('BAL N'!J:J,"=419",'BAL N'!H:H) -> 68775383546 | C20: =+SUMIF('BAL N'!K:K,"=4191",'BAL N'!D:D) -> 29055421827 | D20: =IFERROR((B20-C20)/B20,0) -> 0.57753166
A21: Clients, avances reçues groupe | B21: =+SUMIF('BAL N'!K:K,"=4192",'BAL N'!H:H) -> 0 | C21: =+SUMIF('BAL N'!K:K,"=4192",'BAL N'!D:D) -> 0 | D21: =IFERROR((B21-C21)/B21,0) -> 0
A22: Autres clients créditeurs | B22: =+SUMIF('BAL N'!K:K,"=4193",'BAL N'!H:H)+SUMIF('BAL N'!K:K,"=4194",'BAL N'!H:H)+SUMIF('BAL N'!K:K,"=4195",'BAL N'!H:H)+SUMIF('BAL N'!K:K,"=4196",'BAL N'!H:H) -> 0 | C22: =+SUMIF('BAL N'!K:K,"=4192",'BAL N'!D:D)+SUMIF('BAL N'!K:K,"=4193",'BAL N'!D:D)+SUMIF('BAL N'!K:K,"=4194",'BAL N'!D:D)+SUMIF('BAL N'!K:K,"=4195",'BAL N'!D:D) -> 0 | D22: =IFERROR((B22-C22)/B22,0) -> 0
A23: TOTAL CLIENTS CREDITEURS | B23: =SUM(B20:B22) -> 68775383546 | C23: =SUM(C20:C22) -> 29055421827 | D23: =IFERROR((B23-C23)/B23,0) -> 0.57753166
A24: Commentaire :
A25: · Commenter toutes variations significatives
A26: · Indiquer pour les créances du groupe, le nom de la société du groupe et le % de titres détenues
A27: · Commenter toutes les créances anciennes
A28: · Indiquer les évènements et les circonstances qui ont conduit à la dépréciation et à la reprise

Sheet Note 8
A1: NOTE 8 : AUTRES CREANCES
A3: Désignation entité : | B3: ='Fiche de renseignement R1'!$J$4 -> 0 | E3: Excercice clos le : | F3: =+'Note 1'!E3 -> 0
A4: Numéro d'identification : | B4: =+'Note 1'!B4 -> 0 | E4: Durée en mois : | F4: =+'Note 1'!E4 -> 12
A7: LIBELLES | B7: =IFERROR(YEAR('Fiche de renseignement R1'!V10),"Annee N") -> 1900 | C7: =IFERROR(YEAR('Fiche de renseignement R1'!Q20),"Annee N-1") -> 2020 | D7: Variation en % | E7: Créances à un an au plus | F7: Créances à plus d'un an et à deux ans au plus | G7: Créances à plus de deux ans
A9: Personnel | B9: =SUMIF('BAL N'!J:J,"=421",'BAL N'!G:G) -> 18407185 | C9: =+SUMIF('BAL N'!J:J,"=421",'BAL N'!C:C) -> 29887116 | D9: =IFERROR((B9-C9)/B9,0) -> -0.62366576
A10: Organismes sociaux | B10: =+SUMIF('BAL N'!I:I,"=43",'BAL N'!G:G) -> 0 | C10: =+SUMIF('BAL N'!I:I,"=43",'BAL N'!C:C) -> 0 | D10: =IFERROR((B10-C10)/B10,0) -> 0
A11: Etat et collectivités publiques | B11: =+SUMIF('BAL N'!I:I,"=44",'BAL N'!G:G) -> 6433903 | C11: =+SUMIF('BAL N'!I:I,"=44",'BAL N'!C:C) -> 6234339 | D11: =IFERROR((B11-C11)/B11,0) -> 0.031017564
A12: Organismes internationaux | B12: =+SUMIF('BAL N'!I:I,"=45",'BAL N'!G:G) -> 0 | C12: =+SUMIF('BAL N'!I:I,"=45",'BAL N'!C:C) -> 0 | D12: =IFERROR((B12-C12)/B12,0) -> 0
A13: Apporteurs, associés et Groupe | B13: =+SUMIF('BAL N'!I:I,"=46",'BAL N'!G:G) -> 0 | C13: =+SUMIF('BAL N'!I:I,"=46",'BAL N'!C:C) -> 0 | D13: =IFERROR((B13-C13)/B13,0) -> 0
A14: Compte transitoire ajustement spécial lié à la révision du SYSCOHADA | B14: =+SUMIF('BAL N'!J:J,"=475",'BAL N'!G:G) -> 0 | C14: =+SUMIF('BAL N'!J:J,"=475",'BAL N'!C:C) -> 0 | D14: =IFERROR((B14-C14)/B14,0) -> 0
A15: Autres débiteurs divers | B15: =+SUMIF('BAL N'!I:I,"=47",'BAL N'!G:G)-SUMIF('BAL N'!J:J,"=475",'BAL N'!G:G) -> 0 | C15: =+SUMIF('BAL N'!I:I,"=47",'BAL N'!C:C)-SUMIF('BAL N'!J:J,"=475",'BAL N'!C:C) -> 0 | D15: =IFERROR((B15-C15)/B15,0) -> 0
A16: Comptes permanents non bloqués des établissements et des succursales | D16: =IFERROR((B16-C16)/B16,0) -> 0
A17: Comptes de liaison charges et produits | D17: =IFERROR((B17-C17)/B17,0) -> 0
A18: Comptes de liaison des sociétés en participation | D18: =IFERROR((B18-C18)/B18,0) -> 0
A19: TOTAL BRUT AUTRES CREANCES | B19: =SUM(B9:B18) -> 24841088 | C19: =SUM(C9:C18) -> 36121455 | D19: =IFERROR((B19-C19)/B19,0) -> -0.45410116
A20: Dépréciations des autres créances | B20: =+SUMIF('BAL N'!J:J,"=497",'BAL N'!H:H) -> 0 | C20: =+SUMIF('BAL N'!J:J,"=497",'BAL N'!D:D) -> 0 | D20: =IFERROR((B20-C20)/B20,0) -> 0
A21: TOTAL NET DE DEPRECIATION | B21: =+B19-B20 -> 24841088 | C21: =+C19-C20 -> 36121455 | D21: =IFERROR((B21-C21)/B21,0) -> -0.45410116
A22: Commentaire :
A23: · Justifier toute variation significative
A24: · Détailler les créances dont le montant est significatif
A25: · Justifier les créances anciennes
A26: · Indiquer les évènements et les circonstances qui ont conduit à la dépréciation et à la reprise
A27: · Compte transitoire ajustement spécial, indiquer le détail du compte et la durée restant pour l'apurement

Sheet Note 8A
A1: NOTE 8 A: TABLEAU D'ETALEMENT DES CHARGES IMMOBILISEES
A3: Désignation entité : | B3: ='Fiche de renseignement R1'!$J$4 -> 0 | E3: Excercice clos le : | F3: =+'Note 1'!E3 -> 0
A4: Numéro d'identification : | B4: =+'Note 1'!B4 -> 0 | E4: Durée en mois : | F4: =+'Note 1'!E4 -> 12
A6: LIBELLES | B6: Frais d'établissement | D6: Charges à répartir sur plusiers exercices | F6: Primes de remboursement des obligations
A8: Montant global à étaler au 1er janvier 2018
A9: Durée d'étalement retenue
B10: Comptes | C10: Montants | D10: Comptes | E10: Montants | F10: Comptes | G10: Montants
A11: Exercice 2018 | B11: 60… | D11: 60… | F11: 6714
B12: 61… | D12: 61…
B13: 62… | D13: 62…
B14: 63… | D14: 63…
B15: … | D15: …
A16: Total exercice 2018
A17: Total exercice 2019
A18: Total exercice 2020
A19: Total exercice 2021
A20: Total exercice 2022
A21: TOTAL GENERAL

Sheet Note 9
A1: NOTE 9 : TITRES DE PLACEMENT
A3: Désignation entité : | B3: ='Fiche de renseignement R1'!$J$4 -> 0 | C3: Excercice clos le : | D3: =+'Note 1'!E3 -> 0
A4: Numéro d'identification : | B4: =+'Note 1'!B4 -> 0 | C4: Durée en mois : | D4: =+'Note 1'!E4 -> 12
A6: LIBELLES | B6: =IFERROR(YEAR('Fiche de renseignement R1'!V10),"Annee N") -> 1900 | C6: =IFERROR(YEAR('Fiche de renseignement R1'!Q20),"Annee N-1") -> 2020 | D6: VARIATION EN %
A8: Titres de trésor et bons de caisse à court terme | B8: =+SUMIF('BAL N'!K:K,"5011",'BAL N'!G:G)+SUMIF('BAL N'!K:K,"5013",'BAL N'!G:G) -> 0 | C8: =+SUMIF('BAL N'!K:K,"5011",'BAL N'!C:C)+SUMIF('BAL N'!K:K,"5013",'BAL N'!C:C) -> 0 | D8: =IFERROR((B8-C8)/B8,0) -> 0
A9: Actions | B9: =+SUMIF('BAL N'!K:K,"502",'BAL N'!G:G) -> 0 | C9: =+SUMIF('BAL N'!J:J,"502",'BAL N'!C:C) -> 0 | D9: =IFERROR((B9-C9)/B9,0) -> 0
A10: Obligations | B10: =+SUMIF('BAL N'!K:K,"503",'BAL N'!G:G) -> 0 | C10: =+SUMIF('BAL N'!J:J,"503",'BAL N'!C:C) -> 0 | D10: =IFERROR((B10-C10)/B10,0) -> 0
A11: Bons de souscription | B11: =+SUMIF('BAL N'!K:K,"504",'BAL N'!G:G) -> 0 | C11: =+SUMIF('BAL N'!J:J,"504",'BAL N'!C:C) -> 0 | D11: =IFERROR((B11-C11)/B11,0) -> 0
A12: Titres négociables hors régions | B12: =+SUMIF('BAL N'!K:K,"505",'BAL N'!G:G) -> 0 | C12: =+SUMIF('BAL N'!J:J,"505",'BAL N'!C:C) -> 0 | D12: =IFERROR((B12-C12)/B12,0) -> 0
A13: Intérêts courus | B13: =+SUMIF('BAL N'!K:K,"506",'BAL N'!G:G) -> 0 | C13: =+SUMIF('BAL N'!J:J,"506",'BAL N'!C:C) -> 0 | D13: =IFERROR((B13-C13)/B13,0) -> 0
A14: Autres valeurs assimilées | B14: =+SUMIF('BAL N'!K:K,"508",'BAL N'!G:G) -> 0 | C14: =+SUMIF('BAL N'!J:J,"508",'BAL N'!C:C) -> 0 | D14: =IFERROR((B14-C14)/B14,0) -> 0
A15: TOTAL BRUT TITRES | B15: =SUM(B8:B14) -> 0 | C15: =SUM(C8:C14) -> 0 | D15: =IFERROR((B15-C15)/B15,0) -> 0
A16: Dépréciations des titres | B16: =+SUMIF('BAL N'!K:K,"590",'BAL N'!H:H) -> 0 | C16: =+SUMIF('BAL N'!J:J,"590",'BAL N'!C:C) -> 0 | D16: =IFERROR((B16-C16)/B16,0) -> 0
A18: TOTAL NET DE DEPRECIATION | B18: =SUM(B16) -> 0 | C18: =SUM(C16) -> 0 | D18: =IFERROR((B18-C18)/B18,0) -> 0
A19: Commentaire :
A20: · Justifier toutes variations significatives
A21: · Pour les titres côtés à une bourse de valeur : indiquer le nombre, le prix unitaire d'acquisition et le cours de
A22: la bourse au 31 décembre
A23: · Faire ressortir les actions ou parts propres et indiquer la date d'acquisition et le nombre de titres détenus
A24: · Indiquer les évènements et les circonstances qui ont conduit à la dépréciation et à la reprise

Sheet Note 10
A1: NOTE 10 : VALEURS A ENCAISSER
A3: Désignation entité : | B3: ='Fiche de renseignement R1'!$J$4 -> 0 | C3: Excercice clos le : | D3: =+'Note 1'!E3 -> 0
A4: Numéro d'identification : | B4: =+'Note 1'!B4 -> 0 | C4: Durée en mois : | D4: =+'Note 1'!E4 -> 12
A6: LIBELLES | B6: =IFERROR(YEAR('Fiche de renseignement R1'!V10),"Annee N") -> 1900 | C6: =IFERROR(YEAR('Fiche de renseignement R1'!Q20),"Annee N-1") -> 2020 | D6: VARIATION EN %
A8: Effets à encaisser | B8: =+SUMIF('BAL N'!J:J,"=511",'BAL N'!G:G) -> 0 | C8: =+SUMIF('BAL N'!J:J,"=511",'BAL N'!C:C) -> 0 | D8: =IFERROR((B8-C8)/B8,0) -> 0
A9: Effets à l'encaissement | B9: =+SUMIF('BAL N'!J:J,"=512",'BAL N'!G:G) -> 0 | C9: =+SUMIF('BAL N'!J:J,"=512",'BAL N'!C:C) -> 0 | D9: =IFERROR((B9-C9)/B9,0) -> 0
A10: Chèques à encaisser | B10: =+SUMIF('BAL N'!J:J,"=513",'BAL N'!G:G) -> 0 | C10: =+SUMIF('BAL N'!J:J,"=513",'BAL N'!C:C) -> 0 | D10: =IFERROR((B10-C10)/B10,0) -> 0
A11: Chèques à l'encaissement | B11: =+SUMIF('BAL N'!J:J,"=514",'BAL N'!G:G) -> 0 | C11: =+SUMIF('BAL N'!J:J,"=514",'BAL N'!C:C) -> 0 | D11: =IFERROR((B11-C11)/B11,0) -> 0
A12: Cartes de crédit à encaisser | B12: =+SUMIF('BAL N'!J:J,"=515",'BAL N'!G:G) -> 0 | C12: =+SUMIF('BAL N'!J:J,"=515",'BAL N'!C:C) -> 0 | D12: =IFERROR((B12-C12)/B12,0) -> 0
A13: Autres valeurs à encaisser | B13: =+SUMIF('BAL N'!J:J,"=518",'BAL N'!G:G) -> 0 | C13: =+SUMIF('BAL N'!J:J,"=518",'BAL N'!C:C) -> 0 | D13: =IFERROR((B13-C13)/B13,0) -> 0
A14: TOTAL BRUT VALEURS A ENCAISSER | B14: =SUM(B8:B13) -> 0 | C14: =SUM(C8:C13) -> 0 | D14: =IFERROR((B14-C14)/B14,0) -> 0
A15: Dépréciations des valeurs à encaisser | B15: =+SUMIF('BAL N'!J:J,"=591",'BAL N'!H:H) -> 0 | C15: =+SUMIF('BAL N'!J:J,"=591",'BAL N'!D:D) -> 0 | D15: =IFERROR((B15-C15)/B15,0) -> 0
A17: TOTAL NET DE DEPRECIATION | B17: =SUM(B15) -> 0 | C17: =SUM(C15) -> 0 | D17: =IFERROR((B17-C17)/B17,0) -> 0
A18: Commentaire :
A19: · Commenter toute variation significative
A20: · Indiquer les évènements et les circonstances qui ont conduit à la dépréciation et à la reprise

Sheet Note 11
A1: NOTE 11 : DISPONIBILITES
A3: Désignation entité : | B3: ='Fiche de renseignement R1'!$J$4 -> 0 | C3: Excercice clos le : | D3: =+'Note 1'!E3 -> 0
A4: Numéro d'identification : | B4: =+'Note 1'!B4 -> 0 | C4: Durée en mois : | D4: =+'Note 1'!E4 -> 12
A6: LIBELLES | B6: =IFERROR(YEAR('Fiche de renseignement R1'!V10),"Annee N") -> 1900 | C6: =IFERROR(YEAR('Fiche de renseignement R1'!Q20),"Annee N-1") -> 2020 | D6: VARIATION EN %
A8: Banques locales | B8: =+SUMIF('BAL N'!J:J,"=521",'BAL N'!G:G) -> 180980696 | C8: =+SUMIF('BAL N'!J:J,"=521",'BAL N'!C:C) -> 89238509 | D8: =IFERROR((B8-C8)/B8,0) -> 0.50691698
A9: Banques autres états région | B9: =+SUMIF('BAL N'!J:J,"=522",'BAL N'!G:G) -> 0 | C9: =+SUMIF('BAL N'!J:J,"=522",'BAL N'!C:C) -> 0 | D9: =IFERROR((B9-C9)/B9,0) -> 0
A10: Banques, dépôt à terme | B10: =+SUMIF('BAL N'!J:J,"=525",'BAL N'!G:G) -> 0 | C10: =+SUMIF('BAL N'!J:J,"=525",'BAL N'!C:C) -> 0 | D10: =IFERROR((B10-C10)/B10,0) -> 0
A11: Autres banques | B11: =+SUMIF('BAL N'!J:J,"=523",'BAL N'!G:G)+SUMIF('BAL N'!J:J,"=524",'BAL N'!G:G) -> 0 | C11: =+SUMIF('BAL N'!J:J,"=523",'BAL N'!C:C)+SUMIF('BAL N'!J:J,"=524",'BAL N'!C:C) -> 0 | D11: =IFERROR((B11-C11)/B11,0) -> 0
A12: Banques, intérêts courus | B12: =+SUMIF('BAL N'!J:J,"=526",'BAL N'!G:G) -> 0 | C12: =+SUMIF('BAL N'!J:J,"=526",'BAL N'!C:C) -> 0 | D12: =IFERROR((B12-C12)/B12,0) -> 0
A13: Chèques postaux | B13: =+SUMIF('BAL N'!J:J,"=531",'BAL N'!G:G) -> 0 | C13: =+SUMIF('BAL N'!J:J,"=531",'BAL N'!C:C) -> 0 | D13: =IFERROR((B13-C13)/B13,0) -> 0
A14: Autres établissements financiers | B14: =+SUMIF('BAL N'!J:J,"=532",'BAL N'!G:G)+SUMIF('BAL N'!J:J,"=533",'BAL N'!G:G)+SUMIF('BAL N'!J:J,"=538",'BAL N'!G:G) -> 0 | C14: =+SUMIF('BAL N'!J:J,"=532",'BAL N'!C:C)+SUMIF('BAL N'!J:J,"=533",'BAL N'!C:C)+SUMIF('BAL N'!J:J,"=538",'BAL N'!C:C) -> 0 | D14: =IFERROR((B14-C14)/B14,0) -> 0
A15: Etablissements financiers intérêts courus | B15: =+SUMIF('BAL N'!J:J,"=536",'BAL N'!G:G) -> 0 | C15: =+SUMIF('BAL N'!J:J,"=536",'BAL N'!C:C) -> 0 | D15: =IFERROR((B15-C15)/B15,0) -> 0
A16: Instruments de trésorerie | B16: =+SUMIF('BAL N'!I:I,"=54",'BAL N'!G:G) -> 0 | C16: =+SUMIF('BAL N'!I:I,"=54",'BAL N'!C:C) -> 0 | D16: =IFERROR((B16-C16)/B16,0) -> 0
A17: Caisse | B17: =+SUMIF('BAL N'!J:J,"=571",'BAL N'!G:G) -> 39972194 | C17: =+SUMIF('BAL N'!J:J,"=571",'BAL N'!C:C) -> 3179782 | D17: =IFERROR((B17-C17)/B17,0) -> 0.92045015
A18: Casse électronique mobile | B18: =+SUMIF('BAL N'!I:I,"=55",'BAL N'!G:G) -> 0 | C18: =+SUMIF('BAL N'!I:I,"=55",'BAL N'!C:C) -> 0 | D18: =IFERROR((B18-C18)/B18,0) -> 0
A19: Régies d'avances et virements accréditifs | B19: =+SUMIF('BAL N'!I:I,"=58",'BAL N'!G:G) -> 0 | C19: =+SUMIF('BAL N'!I:I,"=58",'BAL N'!C:C) -> 0 | D19: =IFERROR((B19-C19)/B19,0) -> 0
A20: TOTAL BRUT DISPONIBILITES | B20: =SUM(B8:B19) -> 220952890 | C20: =SUM(C8:C19) -> 92418291 | D20: =IFERROR((B20-C20)/B20,0) -> 0.58172853
A21: Dépréciations | B21: =+SUMIF('BAL N'!I:I,"=59",'BAL N'!H:H) -> 0 | C21: =+SUMIF('BAL N'!I:I,"=59",'BAL N'!D:D) -> 0 | D21: =IFERROR((B21-C21)/B21,0) -> 0
A23: TOTAL NET DE DEPRECIATIONS | B23: =SUM(B21) -> 0 | C23: =SUM(C21) -> 0 | D23: =IFERROR((B23-C23)/B23,0) -> 0
A24: Commentaire :
A25: · Indiquer la date de rapprochement des comptes bancaires
A26: · Indiquer la date d'inventaire de la caisse et des instruments de monnaie électronique
A27: · Justifier toute variation significative
A28: · Détailler les instruments de monnaie électronique si le montant est significatif
A29: · Indiquer les évènements et les circonstances qui ont conduit à la dépréciation et à la reprise
A31: NB : Banques et intérêts courus et Etablissement financiers intérêts courus figurent dans cette rubrique
A32: en négatif si le compte principal est débiteur

Sheet Note 12
A1: NOTE 12 : ECARTS DE CONVERSION
A3: Désignation entité : | B3: ='Fiche de renseignement R1'!$J$4 -> 0 | E3: Excercice clos le : | F3: =+'Note 1'!E3 -> 0
A4: Numéro d'identification : | B4: =+'Note 1'!B4 -> 0 | E4: Durée en mois : | F4: =+'Note 1'!E4 -> 12
A6: LIBELLES | B6: Devises | C6: Montant en devises | E6: Cours UML année acquisition | F6: Cours UML 31/12 | G6: Variation en valeur absolue
A8: Ecarts de conversion actif : Détailler les créances et dettes concernées
A11: Ecarts de conversion passif : Détailler les créances et dettes concernées
A16: Commentaire :
A17: · Faire un commentaire
A21: TRANSFERTS DE CHARGES
A23: LIBELLES | B23: ANNEE N | D23: ANNEE N-1 | F23: VARIATION EN %
A25: Transferts de charges d'exploitation : Détailler la nature des charges transférées
A28: Transferts de charges financières : Détailler la nature des charges transférées
A33: Commentaire :
A34: · Faire un commentaire

Sheet Note 13
A1: NOTE 13 : CAPITAL
A3: Désignation entité : | B3: ='Fiche de renseignement R1'!$J$4 -> 0 | E3: Excercice clos le : | F3: =+'Note 1'!E3 -> 0
A4: Numéro d'identification : | B4: =+'Note 1'!B4 -> 0 | E4: Durée en mois : | F4: =+'Note 1'!E4 -> 12
E7: Valeur nominale des actions ou parts : | G7: 10000
A8: NOMS ET PRENOMS | B8: Nationalité | C8: Nature des actions ou parts (ordinaires ou préférences) | E8: Montant total | F8: Nombre | G8: Cessions ou remboursements en cours d'exercice
F10: =IFERROR(E10/G7,0) -> 0
F11: =IFERROR(E11/G7,0) -> 0
F12: =IFERROR(E12/G7,0) -> 0
F13: =IFERROR(E13/G7,0) -> 0
F14: =IFERROR(E14/G7,0) -> 0
F15: =IFERROR(E15/G7,0) -> 0
F16: =IFERROR(E16/G7,0) -> 0
F17: =IFERROR(E17/G7,0) -> 0
A18: Apporteurs, capital non appelé
C19: TOTAL | E19: =SUM(E10:E17) -> 0 | F19: =SUM(F10:F17) -> 0
A20: Commentaire :
A21: · Indiquer si possible le montant du capital à la constitution
A22: · Indiquer si possible les dates des AGE et le montant du capital augmenté en cas d'augmentation de capital
A23: · Indiquer si possible les dates des AGE et le montant du capital diminué en cas de réduction de capital
A24: · Indiquer les avantages accordés aux actions de préférence
A25: · Apporteurs, capital non appelé : indiquer le délai restant pour appeler le capital

Sheet Note 14
A1: NOTE 14 : PRIMES ET RESERVES
A3: Désignation entité : | B3: ='Fiche de renseignement R1'!$J$4 -> 0 | E3: Excercice clos le : | F3: =+'Note 1'!E3 -> 0
A4: Numéro d'identification : | B4: =+'Note 1'!B4 -> 0 | E4: Durée en mois : | F4: =+'Note 1'!E4 -> 12
A7: LIBELLES | B7: =IFERROR(YEAR('Fiche de renseignement R1'!V10),"Annee N") -> 1900 | D7: =IFERROR(YEAR('Fiche de renseignement R1'!Q20),"Annee N-1") -> 2020 | F7: VARIATION EN VALEUR ABSOLUE
A9: Prime d'apport | B9: =+SUMIF('BAL N'!K:K,"=1051",'BAL N'!H:H) -> 0 | D9: =+SUMIF('BAL N'!K:K,"=1051",'BAL N'!D:D) -> 0 | F9: =+B9-D9 -> 0
A10: Primes d'émission | B10: =+SUMIF('BAL N'!J:J,"=1052",'BAL N'!H:H) -> 0 | D10: =+SUMIF('BAL N'!K:K,"=1052",'BAL N'!D:D) -> 0 | F10: =+B10-D10 -> 0
A11: Prime de fusion | B11: =+SUMIF('BAL N'!K:K,"=1053",'BAL N'!H:H) -> 0 | D11: =+SUMIF('BAL N'!K:K,"=1053",'BAL N'!D:D) -> 0 | F11: =+B11-D11 -> 0
A12: Primes de conversion | B12: =+SUMIF('BAL N'!K:K,"=1054",'BAL N'!H:H) -> 0 | D12: =+SUMIF('BAL N'!K:K,"=1054",'BAL N'!D:D) -> 0 | F12: =+B12-D12 -> 0
A13: Autres primes | B13: =+SUMIF('BAL N'!K:K,"=1058",'BAL N'!H:H) -> 0 | D13: =+SUMIF('BAL N'!K:K,"=1058",'BAL N'!D:D) -> 0 | F13: =+B13-D13 -> 0
A14: TOTAL PRIMES | B14: =SUM(B9:C13) -> 0 | D14: =SUM(D9:E13) -> 0 | F14: =+B14-D14 -> 0
A16: Réserves légales | B16: =+SUMIF('BAL N'!J:J,"=111",'BAL N'!H:H) -> 200000 | D16: =+SUMIF('BAL N'!J:J,"=111",'BAL N'!D:D) -> 200000 | F16: =+B16-D16 -> 0
A17: Réserves statutaires | B17: =+SUMIF('BAL N'!J:J,"=112",'BAL N'!H:H) -> 0 | D17: =+SUMIF('BAL N'!J:J,"=112",'BAL N'!D:D) -> 0 | F17: =+B17-D17 -> 0
A18: Réserves de plus-values nettes à long terme | B18: =+SUMIF('BAL N'!K:K,"=1131",'BAL N'!H:H) -> 0 | D18: =+SUMIF('BAL N'!K:K,"=1131",'BAL N'!D:D) -> 0 | F18: =+B18-D18 -> 0
A19: Réserves d'attribution gratuite d'actions au personnel salarié et aux dirigeants | B19: =+SUMIF('BAL N'!K:K,"=1132",'BAL N'!H:H) -> 0 | D19: =+SUMIF('BAL N'!K:K,"=1132",'BAL N'!D:D) -> 0 | F19: =+B19-D19 -> 0
A20: Autres réserves réglementées | B20: =+SUMIF('BAL N'!J:J,"=118",'BAL N'!H:H) -> 118365583 | D20: =+SUMIF('BAL N'!J:J,"=118",'BAL N'!D:D) -> 118365583 | F20: =+B20-D20 -> 0
A21: TOTAL RESERVES INDISPONIBLES | B21: =SUM(B15:C20) -> 118565583 | D21: =SUM(D15:E20) -> 118565583 | F21: =+B21-D21 -> 0
A22: Réserves libres | B22: =+SUMIF('BAL N'!J:J,"=118",'BAL N'!H:H) -> 118365583 | D22: =+SUMIF('BAL N'!J:J,"=118",'BAL N'!D:D) -> 118365583 | F22: =+B22-D22 -> 0
A23: Report à nouveau | B23: =+SUMIF('BAL N'!I:I,"=12",'BAL N'!H:H)-SUMIF('BAL N'!I:I,"=12",'BAL N'!G:G) -> 0 | D23: =+SUMIF('BAL N'!I:I,"=12",'BAL N'!D:D)-SUMIF('BAL N'!I:I,"=12",'BAL N'!C:C) -> 0 | F23: =+B23-D23 -> 0
A25: Commentaire :
A26: · Indiquer les dates de l'AGE qui a décidé des primes d'apport, d'émission de fusion
A27: · Indiquer le détail des réserves libres
A28: · Indiquer le montant restant à doter et le taux de dotation de la réserve légale
A29: · Indiquer la date de l'AGO qui justifie la variation des réserves et du report à nouveau

Sheet Note 15A
A1: NOTE 15A : SUBVENTIONS ET PROVISIONS REGLEMENTEES
A3: Désignation entité : | B3: ='Fiche de renseignement R1'!$J$4 -> 0 | E3: Excercice clos le : | G3: =+'Note 1'!E3 -> 0
A4: Numéro d'identification : | B4: =+'Note 1'!B4 -> 0 | E4: Durée en mois : | G4: =+'Note 1'!E4 -> 12
A7: LIBELLES | B7: NOTE | C7: =IFERROR(YEAR('Fiche de renseignement R1'!V10),"Annee N") -> 1900 | D7: =IFERROR(YEAR('Fiche de renseignement R1'!Q20),"Annee N-1") -> 2020 | E7: Variation en valeur absolue | F7: Variation en % | G7: Régime fiscal | H7: Échéances
A9: Etat | C9: =+SUMIF('BAL N'!K:K,"=1411",'BAL N'!H:H) -> 0 | D9: =+SUMIF('BAL N'!K:K,"=1411",'BAL N'!D:D) -> 0 | F9: =IFERROR((C9-D9)/C9,0) -> 0
A10: Régions | C10: =+SUMIF('BAL N'!K:K,"=1412",'BAL N'!H:H) -> 0 | D10: =+SUMIF('BAL N'!K:K,"=1412",'BAL N'!D:D) -> 0 | F10: =IFERROR((C10-D10)/C10,0) -> 0
A11: Départements | C11: =+SUMIF('BAL N'!K:K,"=1413",'BAL N'!H:H) -> 0 | D11: =+SUMIF('BAL N'!K:K,"=1413",'BAL N'!D:D) -> 0 | F11: =IFERROR((C11-D11)/C11,0) -> 0
A12: Communes et collectivités publiques décentralisées | C12: =+SUMIF('BAL N'!K:K,"=1414",'BAL N'!H:H) -> 0 | D12: =+SUMIF('BAL N'!K:K,"=1414",'BAL N'!D:D) -> 0 | F12: =IFERROR((C12-D12)/C12,0) -> 0
A13: Entités publiques ou mixtes | C13: =+SUMIF('BAL N'!K:K,"=1415",'BAL N'!H:H) -> 0 | D13: =+SUMIF('BAL N'!K:K,"=1415",'BAL N'!D:D) -> 0 | F13: =IFERROR((C13-D13)/C13,0) -> 0
A14: Entités et organismes privés | C14: =+SUMIF('BAL N'!K:K,"=1416",'BAL N'!H:H) -> 0 | D14: =+SUMIF('BAL N'!K:K,"=1416",'BAL N'!D:D) -> 0 | F14: =IFERROR((C14-D14)/C14,0) -> 0
A15: Organismes internationaux | C15: =+SUMIF('BAL N'!K:K,"=1417",'BAL N'!H:H) -> 0 | D15: =+SUMIF('BAL N'!K:K,"=1417",'BAL N'!D:D) -> 0 | F15: =IFERROR((C15-D15)/C15,0) -> 0
A16: Autres | C16: =+SUMIF('BAL N'!K:K,"=1418",'BAL N'!H:H) -> 0 | D16: =+SUMIF('BAL N'!K:K,"=1418",'BAL N'!D:D) -> 0 | F16: =IFERROR((C16-D16)/C16,0) -> 0
A17: TOTAL SUBVENTIONS | C17: =SUM(C9:C16) -> 0 | D17: =SUM(D9:D16) -> 0 | F17: =IFERROR((C17-D17)/C17,0) -> 0
F18: =IFERROR((C18-D18)/C18,0) -> 0
A19: Amortissements dérogatoires | C19: =+SUMIF('BAL N'!J:J,"=151",'BAL N'!H:H) -> 0 | D19: =+SUMIF('BAL N'!J:J,"=151",'BAL N'!D:D) -> 0 | F19: =IFERROR((C19-D19)/C19,0) -> 0
A20: Plus-values de cession à réinvestir | C20: =+SUMIF('BAL N'!J:J,"=152",'BAL N'!H:H) -> 0 | D20: =+SUMIF('BAL N'!J:J,"=152",'BAL N'!D:D) -> 0 | F20: =IFERROR((C20-D20)/C20,0) -> 0
A21: Provision spéciale de réévaluation | C21: =+SUMIF('BAL N'!J:J,"=154",'BAL N'!H:H) -> 0 | D21: =+SUMIF('BAL N'!J:J,"=154",'BAL N'!D:D) -> 0 | F21: =IFERROR((C21-D21)/C21,0) -> 0
A22: Provisions réglementées relatives aux immobilisations | C22: =+SUMIF('BAL N'!J:J,"=155",'BAL N'!H:H) -> 0 | D22: =+SUMIF('BAL N'!J:J,"=155",'BAL N'!D:D) -> 0 | F22: =IFERROR((C22-D22)/C22,0) -> 0
A23: Provisions réglementées relatives aux stocks | C23: =+SUMIF('BAL N'!J:J,"=156",'BAL N'!H:H) -> 0 | D23: =+SUMIF('BAL N'!J:J,"=156",'BAL N'!D:D) -> 0 | F23: =IFERROR((C23-D23)/C23,0) -> 0
A24: Provisions pour investissement | C24: =+SUMIF('BAL N'!J:J,"=157",'BAL N'!H:H) -> 0 | D24: =+SUMIF('BAL N'!J:J,"=157",'BAL N'!D:D) -> 0 | F24: =IFERROR((C24-D24)/C24,0) -> 0
A25: Autres provisions et fonds réglementés | C25: =+SUMIF('BAL N'!J:J,"=158",'BAL N'!H:H) -> 0 | D25: =+SUMIF('BAL N'!J:J,"=158",'BAL N'!D:D) -> 0 | F25: =IFERROR((C25-D25)/C25,0) -> 0
A26: TOTAL PROVISIONS REGLEMENTEES | C26: =SUM(C18:C25) -> 0 | D26: =SUM(D18:D25) -> 0 | F26: =IFERROR((C26-D26)/C26,0) -> 0
A28: TOTAL SUBVENTIONS ET PROVISIONS REGLEMENTEES | C28: =C17+C26 -> 0 | D28: =D17+D26 -> 0 | F28: =IFERROR((C28-D28)/C28,0) -> 0
A30: Commentaire :
A31: Indiquer pour la subvention la date d'octroi, la nature, les obligations éventuelles.
A32: Pour les provisions réglementées, indiquer le texte de référence, les obligations.
A33: Commenter toute variation significative.

Sheet Note 15B
A1: NOTE 15B : AUTRES FONDS PROPRES(1)
A3: Désignation entité : | B3: ='Fiche de renseignement R1'!$J$4 -> 0 | E3: Excercice clos le : | F3: =+'Note 1'!E3 -> 0
A4: Numéro d'identification : | B4: =+'Note 1'!B4 -> 0 | E4: Durée en mois : | F4: =+'Note 1'!E4 -> 12
A7: LIBELLES | B7: NOTE | C7: =IFERROR(YEAR('Fiche de renseignement R1'!V10),"Annee N") -> 1900 | D7: =IFERROR(YEAR('Fiche de renseignement R1'!Q20),"Annee N-1") -> 2020 | E7: Variation en valeur absolue | F7: Variation en % | G7: Échéances
A9: Titres participatifs | C9: =+SUMIF('BAL N'!K:K,"=2742",'BAL N'!G:G) -> 0 | D9: =+SUMIF('BAL N'!K:K,"=2742",'BAL N'!C:C) -> 0 | F9: =IFERROR((C9-D9)/C9,0) -> 0
A10: Avances conditionnées | C10: =+SUMIF('BAL N'!K:K,"=2743",'BAL N'!G:G) -> 0 | D10: =+SUMIF('BAL N'!K:K,"=2743",'BAL N'!C:C) -> 0 | F10: =IFERROR((C10-D10)/C10,0) -> 0
A11: Titres subordonnés à durée indéterminée (TSDI) | C11: =+SUMIF('BAL N'!K:K,"=2744",'BAL N'!G:G) -> 0 | D11: =+SUMIF('BAL N'!K:K,"=2744",'BAL N'!C:C) -> 0 | F11: =IFERROR((C11-D11)/C11,0) -> 0
A12: Obligations remboursables en actions (ORA) | C12: =+SUMIF('BAL N'!K:K,"=2745",'BAL N'!G:G) -> 0 | D12: =+SUMIF('BAL N'!K:K,"=2745",'BAL N'!C:C) -> 0 | F12: =IFERROR((C12-D12)/C12,0) -> 0
A13: Autres | C13: =+SUMIF('BAL N'!K:K,"=2748",'BAL N'!G:G) -> 0 | D13: =+SUMIF('BAL N'!K:K,"=2748",'BAL N'!C:C) -> 0 | F13: =IFERROR((C13-D13)/C13,0) -> 0
A14: TOTAL AUTRES FONDS PROPRES | C14: =SUM(C9:C13) -> 0 | D14: =SUM(D9:D13) -> 0 | F14: =IFERROR((C14-D14)/C14,0) -> 0
A16: (1) : Le cas échéant, une rubrique "Autres fonds propres" (montant des émissions de titres participatifs,
A17: avances conditionnées,…) sur une ligne séparée est intercalée entre les rubriques
A18: "TOTAL CAPTAUX PROPRES ET RESSOURCES ASSIMILEES" et "EMPRUNTS ET DETTES FINANCIERES" si le
A19: montant des autres fonds propres est significatif.
A21: Commentaire :
A22: · Justifier l'inscription de ces dettes dans une rubrique spécifique du passif du bilan "autres fonds
A23: propres" (faible probabilité de remboursement, absence d'échéancier…)
A24: · Justifier le caractère significatif du montant total de cette rubrique
A25: · Commenter toute variation significative

Sheet Note 16A
A1: NOTE 16A : DETTES FINANCIERES ET RESSOURCES ASSIMILEES
A3: Désignation entité : | B3: ='Fiche de renseignement R1'!$J$4 -> 0 | E3: Excercice clos le : | G3: =+'Note 1'!E3 -> 0
A4: Numéro d'identification : | B4: =+'Note 1'!B4 -> 0 | E4: Durée en mois : | G4: =+'Note 1'!E4 -> 12
A6: LIBELLES | B6: =IFERROR(YEAR('Fiche de renseignement R1'!V10),"Annee N") -> 1900 | C6: =IFERROR(YEAR('Fiche de renseignement R1'!Q20),"Annee N-1") -> 2020 | D6: Variation en valeur absolue | E6: Variation en % | F6: Dettes à un an au plus | G6: Dettes à plus d'un an et à deux ans au plus | H6: Dettes à plus de deux ans
A8: Emprunts obligataires | B8: =+SUMIF('BAL N'!J:J,"=161",'BAL N'!H:H) -> 0 | C8: =+SUMIF('BAL N'!J:J,"=161",'BAL N'!D:D) -> 0 | E8: =IFERROR((B8-C8)/B8,0) -> 0
A9: Emprunts et dettes auprès des établissements de crédit | B9: =+SUMIF('BAL N'!J:J,"=162",'BAL N'!H:H) -> 0 | C9: =+SUMIF('BAL N'!J:J,"=162",'BAL N'!D:D) -> 0 | E9: =IFERROR((B9-C9)/B9,0) -> 0
A10: Avances reçues de l'Etat | B10: =+SUMIF('BAL N'!J:J,"=163",'BAL N'!H:H) -> 0 | C10: =+SUMIF('BAL N'!J:J,"=163",'BAL N'!D:D) -> 0 | E10: =IFERROR((B10-C10)/B10,0) -> 0
A11: Avances reçues et comptes courants bloqués | B11: =+SUMIF('BAL N'!J:J,"=164",'BAL N'!H:H) -> 0 | C11: =+SUMIF('BAL N'!J:J,"=164",'BAL N'!D:D) -> 0 | E11: =IFERROR((B11-C11)/B11,0) -> 0
A12: Dépôts et cautionnements reçus | B12: =+SUMIF('BAL N'!J:J,"=165",'BAL N'!H:H) -> 0 | C12: =+SUMIF('BAL N'!J:J,"=165",'BAL N'!D:D) -> 0 | E12: =IFERROR((B12-C12)/B12,0) -> 0
A13: Intérêts courus | B13: =+SUMIF('BAL N'!J:J,"=166",'BAL N'!H:H) -> 0 | C13: =+SUMIF('BAL N'!J:J,"=166",'BAL N'!D:D) -> 0 | E13: =IFERROR((B13-C13)/B13,0) -> 0
A14: Avances assorties de conditions particulières | B14: =+SUMIF('BAL N'!J:J,"=167",'BAL N'!H:H) -> 0 | C14: =+SUMIF('BAL N'!J:J,"=167",'BAL N'!D:D) -> 0 | E14: =IFERROR((B14-C14)/B14,0) -> 0
A15: Autres emprunts et dettes | B15: =+SUMIF('BAL N'!J:J,"=168",'BAL N'!H:H) -> 0 | C15: =+SUMIF('BAL N'!J:J,"=1683",'BAL N'!D:D) -> 0 | E15: =IFERROR((B15-C15)/B15,0) -> 0
A16: Dettes liées à des participations | B16: =+SUMIF('BAL N'!I:I,"=18",'BAL N'!H:H) -> 0 | C16: =+SUMIF('BAL N'!K:K,"=18",'BAL N'!I:I) -> 0 | E16: =IFERROR((B16-C16)/B16,0) -> 0
A17: Comptes permanents bloqués des établissements et succursales | E17: =IFERROR((B17-C17)/B17,0) -> 0
A18: TOTAL EMPRUNTS ET DETTES FINANCIERES | B18: =SUM(B8:B17) -> 0 | C18: =SUM(C8:C17) -> 0 | E18: =IFERROR((B18-C18)/B18,0) -> 0
A20: Crédit bail immobilier | B20: =+SUMIF('BAL N'!J:J,"=172",'BAL N'!H:H) -> 0 | C20: =+SUMIF('BAL N'!J:J,"=172",'BAL N'!D:D) -> 0 | E20: =IFERROR((B20-C20)/B20,0) -> 0
A21: Crédit bail mobilier | B21: =+SUMIF('BAL N'!J:J,"=173",'BAL N'!H:H) -> 0 | C21: =+SUMIF('BAL N'!J:J,"=173",'BAL N'!D:D) -> 0 | E21: =IFERROR((B21-C21)/B21,0) -> 0
A22: Location vente | B22: =+SUMIF('BAL N'!J:J,"=174",'BAL N'!H:H) -> 0 | C22: =+SUMIF('BAL N'!J:J,"=174",'BAL N'!D:D) -> 0 | E22: =IFERROR((B22-C22)/B22,0) -> 0
A23: Intérêts courus | B23: =+SUMIF('BAL N'!J:J,"=176",'BAL N'!H:H) -> 0 | C23: =+SUMIF('BAL N'!J:J,"=176",'BAL N'!D:D) -> 0 | E23: =IFERROR((B23-C23)/B23,0) -> 0
A24: Autres dettes de location acquisition | B24: =+SUMIF('BAL N'!J:J,"=178",'BAL N'!H:H) -> 0 | C24: =+SUMIF('BAL N'!J:J,"=178",'BAL N'!D:D) -> 0 | E24: =IFERROR((B24-C24)/B24,0) -> 0
A25: TOTAL DETTES DE LOCATION ACQUISITION | B25: =SUM(B20:B24) -> 0 | C25: =SUM(C20:C24) -> 0 | E25: =IFERROR((B25-C25)/B25,0) -> 0
A27: Provisions pour litiges | B27: =+SUMIF('BAL N'!J:J,"=191",'BAL N'!H:H) -> 0 | C27: =+SUMIF('BAL N'!J:J,"=191",'BAL N'!D:D) -> 0 | E27: =IFERROR((B27-C27)/B27,0) -> 0
A28: Provisions pour garantie donnés aux clients | B28: =+SUMIF('BAL N'!J:J,"=192",'BAL N'!H:H) -> 0 | C28: =+SUMIF('BAL N'!J:J,"=192",'BAL N'!D:D) -> 0 | E28: =IFERROR((B28-C28)/B28,0) -> 0
A29: Provisions pour pertes sur marchés à achèvement futur | B29: =+SUMIF('BAL N'!J:J,"=193",'BAL N'!H:H) -> 0 | C29: =+SUMIF('BAL N'!J:J,"=193",'BAL N'!D:D) -> 0 | E29: =IFERROR((B29-C29)/B29,0) -> 0
A30: Provisions pour pertes de change | B30: =+SUMIF('BAL N'!J:J,"=194",'BAL N'!H:H) -> 0 | C30: =+SUMIF('BAL N'!J:J,"=194",'BAL N'!D:D) -> 0 | E30: =IFERROR((B30-C30)/B30,0) -> 0
A31: Provisions pour impôts | B31: =+SUMIF('BAL N'!J:J,"=195",'BAL N'!H:H) -> 0 | C31: =+SUMIF('BAL N'!J:J,"=195",'BAL N'!D:D) -> 0 | E31: =IFERROR((B31-C31)/B31,0) -> 0
